Workbook

Sheet Producto No. 1 Plana
A5: ANEXO No. 1. Oferta Producto No. 1 Curva Plana Convocatoria Pública DISPAC S.A. E.S.P.
A8: PROPONENTE
A10: MES | B10: DEMANDA REQUERIDA DISPAC KWh | C10: DEMANDA PERIODO REQUERIDA DISPAC KWh | D10: PORCENTAJE (%) OFERTADO DE LA DEMANDA REQUERIDA | E10: DEMANDA OFERTADA KWh - MES | F10: DEMANDA PERIODO OFERTADA KWh | G10: PRECIO OFERTADO $ kWh (0.00)
A11: 46023 | B11: =+'General Productos No. 1 Plana'!AD2 -> 10118400 | C11: =SUM(B11:B22) -> 92016000 | D11: 0 | E11: =+B11*D11 -> 0 | F11: =SUM(E11:E22) -> 0
A12: 46054 | B12: =+'General Productos No. 1 Plana'!AD5 -> 10416000 | D12: 0 | E12: =+B12*D12 -> 0
A13: 46082 | B13: =+'General Productos No. 1 Plana'!AD8 -> 12573600 | D13: 0 | E13: =+B13*D13 -> 0
A14: 46113 | B14: =+'General Productos No. 1 Plana'!AD11 -> 8640000 | D14: 0 | E14: =+B14*D14 -> 0
A15: 46143 | B15: =+'General Productos No. 1 Plana'!AD14 -> 9672000 | D15: 0 | E15: =+B15*D15 -> 0
A16: 46174 | B16: =+'General Productos No. 1 Plana'!AD17 -> 6120000 | D16: 0 | E16: =+B16*D16 -> 0
A17: 46204 | B17: =+'General Productos No. 1 Plana'!AD20 -> 11904000 | D17: 0 | E17: =+B17*D17 -> 0
A18: 46235 | B18: =+'General Productos No. 1 Plana'!AD23 -> 9672000 | D18: 0 | E18: =+B18*D18 -> 0
A19: 46266 | B19: =+'General Productos No. 1 Plana'!AD26 -> 1800000 | D19: 0 | E19: =+B19*D19 -> 0
A20: 46296 | B20: =+'General Productos No. 1 Plana'!AD29 -> 1860000 | D20: 0 | E20: =+B20*D20 -> 0
A21: 46327 | B21: =+'General Productos No. 1 Plana'!AD32 -> 1800000 | D21: 0 | E21: =+B21*D21 -> 0
A22: 46357 | B22: =+'General Productos No. 1 Plana'!AD35 -> 7440000 | D22: 0 | E22: =+B22*D22 -> 0
A23: 46388 | B23: =+'General Productos No. 1 Plana'!AD38 -> 13392000 | C23: =SUM(B23:B34) -> 93072000 | D23: 0 | E23: =+B23*D23 -> 0 | F23: =SUM(E23:E34) -> 0
A24: 46419 | B24: =+'General Productos No. 1 Plana'!AD41 -> 12096000 | D24: 0 | E24: =+B24*D24 -> 0
A25: 46447 | B25: =+'General Productos No. 1 Plana'!AD44 -> 7440000 | D25: 0 | E25: =+B25*D25 -> 0
A26: 46478 | B26: =+'General Productos No. 1 Plana'!AD47 -> 12960000 | D26: 0 | E26: =+B26*D26 -> 0
A27: 46508 | B27: =+'General Productos No. 1 Plana'!AD50 -> 6696000 | D27: 0 | E27: =+B27*D27 -> 0
A28: 46539 | B28: =+'General Productos No. 1 Plana'!AD53 -> 10080000 | D28: 0 | E28: =+B28*D28 -> 0
A29: 46569 | B29: =+'General Productos No. 1 Plana'!AD56 -> 8928000 | D29: 0 | E29: =+B29*D29 -> 0
A30: 46600 | B30: =+'General Productos No. 1 Plana'!AD59 -> 9672000 | D30: 0 | E30: =+B30*D30 -> 0
A31: 46631 | B31: =+'General Productos No. 1 Plana'!AD62 -> 1440000 | D31: 0 | E31: =+B31*D31 -> 0
A32: 46661 | B32: =+'General Productos No. 1 Plana'!AD65 -> 1488000 | D32: 0 | E32: =+B32*D32 -> 0
A33: 46692 | B33: =+'General Productos No. 1 Plana'!AD68 -> 1440000 | D33: 0 | E33: =+B33*D33 -> 0
A34: 46722 | B34: =+'General Productos No. 1 Plana'!AD71 -> 7440000 | D34: 0 | E34: =+B34*D34 -> 0
A35: 46753 | B35: =+'General Productos No. 1 Plana'!AD74 -> 12276000 | C35: =SUM(B35:B46) -> 78528000 | D35: 0 | E35: =+B35*D35 -> 0 | F35: =SUM(E35:E46) -> 0
A36: 46784 | B36: =+'General Productos No. 1 Plana'!AD77 -> 10788000 | D36: 0 | E36: =+B36*D36 -> 0
A37: 46813 | B37: =+'General Productos No. 1 Plana'!AD80 -> 11904000 | D37: 0 | E37: =+B37*D37 -> 0
A38: 46844 | B38: =+'General Productos No. 1 Plana'!AD83 -> 8280000 | D38: 0 | E38: =+B38*D38 -> 0
A39: 46874 | B39: =+'General Productos No. 1 Plana'!AD86 -> 2232000 | D39: 0 | E39: =+B39*D39 -> 0
A40: 46905 | B40: =+'General Productos No. 1 Plana'!AD89 -> 2160000 | D40: 0 | E40: =+B40*D40 -> 0
A41: 46935 | B41: =+'General Productos No. 1 Plana'!AD92 -> 2232000 | D41: 0 | E41: =+B41*D41 -> 0
A42: 46966 | B42: =+'General Productos No. 1 Plana'!AD95 -> 2976000 | D42: 0 | E42: =+B42*D42 -> 0
A43: 46997 | B43: =+'General Productos No. 1 Plana'!AD98 -> 5400000 | D43: 0 | E43: =+B43*D43 -> 0
A44: 47027 | B44: =+'General Productos No. 1 Plana'!AD101 -> 7440000 | D44: 0 | E44: =+B44*D44 -> 0
A45: 47058 | B45: =+'General Productos No. 1 Plana'!AD104 -> 5400000 | D45: 0 | E45: =+B45*D45 -> 0
A46: 47088 | B46: =+'General Productos No. 1 Plana'!AD107 -> 7440000 | D46: 0 | E46: =+B46*D46 -> 0
A47: TOTALES | B47: =SUM(B11:B46) -> 263616000 | C47: =SUM(C11:C46) -> 263616000 | E47: =SUM(E11:E22) -> 0 | F47: =SUM(F11:F22) -> 0 | G47: =IFERROR(SUMPRODUCT(F11:F22,G11:G22)/SUM(F11:F22),"")
A49: NOTAS:
A50: (1) Oferta válida para la modalidad Pague lo Contratado.
A51: (2) Las cantidades de energía se despacharan de acuerdo a la curva del Despacho Horario producto.
A52: (3) El oferente presentará propuesta correspondiente a un porcentaje (%) para el producto que sea de su interés de la curva descrita en el numeral 19 “Cantidad demandada” de los presentes pliegos
A53: (4) El oferente deberá garantizar una cobertura mínima de demanda de: Treinta y cinco por ciento (35%) para los meses de enero, febrero, marzo, abril y diciembre y Setenta por ciento (70%) para los meses restantes del año.
A54: (5) Esta oferta podrá cubrir hasta el 100% de cada uno de los meses correspondientes a la demanda requerida por DISPAC S.A. E.S.P. de acuerdo a la curva del Despacho
A55: (6) Los precios ofertados incluyen todos los pagos, cargos, impuestos, estampillas, etc., que el Proponente deba realizar ante cualquier entidad gubernamental, o empresa pública, privada o mixta para entregar la energía en la (s) frontera (s) con el Sistema de Transmisión Nacional – STN.
A56: (7) Los precios ofertados serán a precios de septiembre de 2025 y este será indexado mes a mes con el Índice de Precios al Productor Provisional expedido por el DANE.
A57: (8) El precio máximo a adjudicar estará por debajo al precio que presente DISPAC S.A. E.S.P. en su oferta de reserva.
A58: (9) Las ofertas presentadas y remitidas por el ASIC para cada uno de los productos, serán objeto de evaluación si estás son inferiores al precio de reserva presentado por DISPAC.
A59: (10) El precio ofertado debe ser anual
A62: Oferente
... A66: Calidad del firmante

Sheet General Productos No. 1 Plana
A1: Año | B1: Mes | C1: # días | D1: TPD | E1: HORA 01 | F1: HORA 02 | G1: HORA 03 | H1: HORA 04 | I1: HORA 05 | J1: HORA 06 | K1: HORA 07 | L1: HORA 08 | M1: HORA 09 | N1: HORA 10 | O1: HORA 11 | P1: HORA 12 | Q1: HORA 13 | R1: HORA 14 | S1: HORA 15 | T1: HORA 16 | U1: HORA 17 | V1: HORA 18 | W1: HORA 19 | X1: HORA 20 | Y1: HORA 21 | Z1: HORA 22 | AA1: HORA 23 | AB1: HORA 24 | AC1: kWh/d | AD1: kWh/mes (plano)
A2: 2026 | B2: 1 | C2: 6 | D2: Festivo | E2: 13600 | F2: 13600 | G2: 13600 | H2: 13600 | I2: 13600 | J2: 13600 | K2: 13600 | L2: 13600 | M2: 13600 | N2: 13600 | O2: 13600 | P2: 13600 | Q2: 13600 | R2: 13600 | S2: 13600 | T2: 13600 | U2: 13600 | V2: 13600 | W2: 13600 | X2: 13600 | Y2: 13600 | Z2: 13600 | AA2: 13600 | AB2: 13600 | AC2: =SUM(E2:AB2) -> 326400 | AD2: =+SUMPRODUCT(AC2:AC4,C2:C4) -> 10118400 | AE2: =+SUM(AD2:AD37) -> 92016000
A3: 2026 | B3: 1 | C3: 20 | D3: Ordinario | E3: 13600 | F3: 13600 | G3: 13600 | H3: 13600 | I3: 13600 | J3: 13600 | K3: 13600 | L3: 13600 | M3: 13600 | N3: 13600 | O3: 13600 | P3: 13600 | Q3: 13600 | R3: 13600 | S3: 13600 | T3: 13600 | U3: 13600 | V3: 13600 | W3: 13600 | X3: 13600 | Y3: 13600 | Z3: 13600 | AA3: 13600 | AB3: 13600 | AC3: =SUM(E3:AB3) -> 326400
A4: 2026 | B4: 1 | C4: 5 | D4: Sábado | E4: 13600 | F4: 13600 | G4: 13600 | H4: 13600 | I4: 13600 | J4: 13600 | K4: 13600 | L4: 13600 | M4: 13600 | N4: 13600 | O4: 13600 | P4: 13600 | Q4: 13600 | R4: 13600 | S4: 13600 | T4: 13600 | U4: 13600 | V4: 13600 | W4: 13600 | X4: 13600 | Y4: 13600 | Z4: 13600 | AA4: 13600 | AB4: 13600 | AC4: =SUM(E4:AB4) -> 326400
A5: 2026 | B5: 2 | C5: 4 | D5: Festivo | E5: 15500 | F5: 15500 | G5: 15500 | H5: 15500 | I5: 15500 | J5: 15500 | K5: 15500 | L5: 15500 | M5: 15500 | N5: 15500 | O5: 15500 | P5: 15500 | Q5: 15500 | R5: 15500 | S5: 15500 | T5: 15500 | U5: 15500 | V5: 15500 | W5: 15500 | X5: 15500 | Y5: 15500 | Z5: 15500 | AA5: 15500 | AB5: 15500 | AC5: =SUM(E5:AB5) -> 372000 | AD5: =+SUMPRODUCT(AC5:AC7,C5:C7) -> 10416000
A6: 2026 | B6: 2 | C6: 20 | D6: Ordinario | E6: 15500 | F6: 15500 | G6: 15500 | H6: 15500 | I6: 15500 | J6: 15500 | K6: 15500 | L6: 15500 | M6: 15500 | N6: 15500 | O6: 15500 | P6: 15500 | Q6: 15500 | R6: 15500 | S6: 15500 | T6: 15500 | U6: 15500 | V6: 15500 | W6: 15500 | X6: 15500 | Y6: 15500 | Z6: 15500 | AA6: 15500 | AB6: 15500 | AC6: =SUM(E6:AB6) -> 372000
A7: 2026 | B7: 2 | C7: 4 | D7: Sábado | E7: 15500 | F7: 15500 | G7: 15500 | H7: 15500 | I7: 15500 | J7: 15500 | K7: 15500 | L7: 15500 | M7: 15500 | N7: 15500 | O7: 15500 | P7: 15500 | Q7: 15500 | R7: 15500 | S7: 15500 | T7: 15500 | U7: 15500 | V7: 15500 | W7: 15500 | X7: 15500 | Y7: 15500 | Z7: 15500 | AA7: 15500 | AB7: 15500 | AC7: =SUM(E7:AB7) -> 372000
A8: 2026 | B8: 3 | C8: 6 | D8: Festivo | E8: 16900 | F8: 16900 | G8: 16900 | H8: 16900 | I8: 16900 | J8: 16900 | K8: 16900 | L8: 16900 | M8: 16900 | N8: 16900 | O8: 16900 | P8: 16900 | Q8: 16900 | R8: 16900 | S8: 16900 | T8: 16900 | U8: 16900 | V8: 16900 | W8: 16900 | X8: 16900 | Y8: 16900 | Z8: 16900 | AA8: 16900 | AB8: 16900 | AC8: =SUM(E8:AB8) -> 405600 | AD8: =+SUMPRODUCT(AC8:AC10,C8:C10) -> 12573600
A9: 2026 | B9: 3 | C9: 21 | D9: Ordinario | E9: 16900 | F9: 16900 | G9: 16900 | H9: 16900 | I9: 16900 | J9: 16900 | K9: 16900 | L9: 16900 | M9: 16900 | N9: 16900 | O9: 16900 | P9: 16900 | Q9: 16900 | R9: 16900 | S9: 16900 | T9: 16900 | U9: 16900 | V9: 16900 | W9: 16900 | X9: 16900 | Y9: 16900 | Z9: 16900 | AA9: 16900 | AB9: 16900 | AC9: =SUM(E9:AB9) -> 405600
A10: 2026 | B10: 3 | C10: 4 | D10: Sábado | E10: 16900 | F10: 16900 | G10: 16900 | H10: 16900 | I10: 16900 | J10: 16900 | K10: 16900 | L10: 16900 | M10: 16900 | N10: 16900 | O10: 16900 | P10: 16900 | Q10: 16900 | R10: 16900 | S10: 16900 | T10: 16900 | U10: 16900 | V10: 16900 | W10: 16900 | X10: 16900 | Y10: 16900 | Z10: 16900 | AA10: 16900 | AB10: 16900 | AC10: =SUM(E10:AB10) -> 405600
A11: 2026 | B11: 4 | C11: 6 | D11: Festivo | E11: 12000 | F11: 12000 | G11: 12000 | H11: 12000 | I11: 12000 | J11: 12000 | K11: 12000 | L11: 12000 | M11: 12000 | N11: 12000 | O11: 12000 | P11: 12000 | Q11: 12000 | R11: 12000 | S11: 12000 | T11: 12000 | U11: 12000 | V11: 12000 | W11: 12000 | X11: 12000 | Y11: 12000 | Z11: 12000 | AA11: 12000 | AB11: 12000 | AC11: =SUM(E11:AB11) -> 288000 | AD11: =+SUMPRODUCT(AC11:AC13,C11:C13) -> 8640000
A12: 2026 | B12: 4 | C12: 20 | D12: Ordinario | E12: 12000 | F12: 12000 | G12: 12000 | H12: 12000 | I12: 12000 | J12: 12000 | K12: 12000 | L12: 12000 | M12: 12000 | N12: 12000 | O12: 12000 | P12: 12000 | Q12: 12000 | R12: 12000 | S12: 12000 | T12: 12000 | U12: 12000 | V12: 12000 | W12: 12000 | X12: 12000 | Y12: 12000 | Z12: 12000 | AA12: 12000 | AB12: 12000 | AC12: =SUM(E12:AB12) -> 288000
A13: 2026 | B13: 4 | C13: 4 | D13: Sábado | E13: 12000 | F13: 12000 | G13: 12000 | H13: 12000 | I13: 12000 | J13: 12000 | K13: 12000 | L13: 12000 | M13: 12000 | N13: 12000 | O13: 12000 | P13: 12000 | Q13: 12000 | R13: 12000 | S13: 12000 | T13: 12000 | U13: 12000 | V13: 12000 | W13: 12000 | X13: 12000 | Y13: 12000 | Z13: 12000 | AA13: 12000 | AB13: 12000 | AC13: =SUM(E13:AB13) -> 288000
A14: 2026 | B14: 5 | C14: 7 | D14: Festivo | E14: 13000 | F14: 13000 | G14: 13000 | H14: 13000 | I14: 13000 | J14: 13000 | K14: 13000 | L14: 13000 | M14: 13000 | N14: 13000 | O14: 13000 | P14: 13000 | Q14: 13000 | R14: 13000 | S14: 13000 | T14: 13000 | U14: 13000 | V14: 13000 | W14: 13000 | X14: 13000 | Y14: 13000 | Z14: 13000 | AA14: 13000 | AB14: 13000 | AC14: =SUM(E14:AB14) -> 312000 | AD14: =+SUMPRODUCT(AC14:AC16,C14:C16) -> 9672000
A15: 2026 | B15: 5 | C15: 19 | D15: Ordinario | E15: 13000 | F15: 13000 | G15: 13000 | H15: 13000 | I15: 13000 | J15: 13000 | K15: 13000 | L15: 13000 | M15: 13000 | N15: 13000 | O15: 13000 | P15: 13000 | Q15: 13000 | R15: 13000 | S15: 13000 | T15: 13000 | U15: 13000 | V15: 13000 | W15: 13000 | X15: 13000 | Y15: 13000 | Z15: 13000 | AA15: 13000 | AB15: 13000 | AC15: =SUM(E15:AB15) -> 312000
A16: 2026 | B16: 5 | C16: 5 | D16: Sábado | E16: 13000 | F16: 13000 | G16: 13000 | H16: 13000 | I16: 13000 | J16: 13000 | K16: 13000 | L16: 13000 | M16: 13000 | N16: 13000 | O16: 13000 | P16: 13000 | Q16: 13000 | R16: 13000 | S16: 13000 | T16: 13000 | U16: 13000 | V16: 13000 | W16: 13000 | X16: 13000 | Y16: 13000 | Z16: 13000 | AA16: 13000 | AB16: 13000 | AC16: =SUM(E16:AB16) -> 312000
A17: 2026 | B17: 6 | C17: 7 | D17: Festivo | E17: 8500 | F17: 8500 | G17: 8500 | H17: 8500 | I17: 8500 | J17: 8500 | K17: 8500 | L17: 8500 | M17: 8500 | N17: 8500 | O17: 8500 | P17: 8500 | Q17: 8500 | R17: 8500 | S17: 8500 | T17: 8500 | U17: 8500 | V17: 8500 | W17: 8500 | X17: 8500 | Y17: 8500 | Z17: 8500 | AA17: 8500 | AB17: 8500 | AC17: =SUM(E17:AB17) -> 204000 | AD17: =+SUMPRODUCT(AC17:AC19,C17:C19) -> 6120000
A18: 2026 | B18: 6 | C18: 19 | D18: Ordinario | E18: 8500 | F18: 8500 | G18: 8500 | H18: 8500 | I18: 8500 | J18: 8500 | K18: 8500 | L18: 8500 | M18: 8500 | N18: 8500 | O18: 8500 | P18: 8500 | Q18: 8500 | R18: 8500 | S18: 8500 | T18: 8500 | U18: 8500 | V18: 8500 | W18: 8500 | X18: 8500 | Y18: 8500 | Z18: 8500 | AA18: 8500 | AB18: 8500 | AC18: =SUM(E18:AB18) -> 204000
A19: 2026 | B19: 6 | C19: 4 | D19: Sábado | E19: 8500 | F19: 8500 | G19: 8500 | H19: 8500 | I19: 8500 | J19: 8500 | K19: 8500 | L19: 8500 | M19: 8500 | N19: 8500 | O19: 8500 | P19: 8500 | Q19: 8500 | R19: 8500 | S19: 8500 | T19: 8500 | U19: 8500 | V19: 8500 | W19: 8500 | X19: 8500 | Y19: 8500 | Z19: 8500 | AA19: 8500 | AB19: 8500 | AC19: =SUM(E19:AB19) -> 204000
A20: 2026 | B20: 7 | C20: 5 | D20: Festivo | E20: 16000 | F20: 16000 | G20: 16000 | H20: 16000 | I20: 16000 | J20: 16000 | K20: 16000 | L20: 16000 | M20: 16000 | N20: 16000 | O20: 16000 | P20: 16000 | Q20: 16000 | R20: 16000 | S20: 16000 | T20: 16000 | U20: 16000 | V20: 16000 | W20: 16000 | X20: 16000 | Y20: 16000 | Z20: 16000 | AA20: 16000 | AB20: 16000 | AC20: =SUM(E20:AB20) -> 384000 | AD20: =+SUMPRODUCT(AC20:AC22,C20:C22) -> 11904000
A21: 2026 | B21: 7 | C21: 22 | D21: Ordinario | E21: 16000 | F21: 16000 | G21: 16000 | H21: 16000 | I21: 16000 | J21: 16000 | K21: 16000 | L21: 16000 | M21: 16000 | N21: 16000 | O21: 16000 | P21: 16000 | Q21: 16000 | R21: 16000 | S21: 16000 | T21: 16000 | U21: 16000 | V21: 16000 | W21: 16000 | X21: 16000 | Y21: 16000 | Z21: 16000 | AA21: 16000 | AB21: 16000 | AC21: =SUM(E21:AB21) -> 384000
A22: 2026 | B22: 7 | C22: 4 | D22: Sábado | E22: 16000 | F22: 16000 | G22: 16000 | H22: 16000 | I22: 16000 | J22: 16000 | K22: 16000 | L22: 16000 | M22: 16000 | N22: 16000 | O22: 16000 | P22: 16000 | Q22: 16000 | R22: 16000 | S22: 16000 | T22: 16000 | U22: 16000 | V22: 16000 | W22: 16000 | X22: 16000 | Y22: 16000 | Z22: 16000 | AA22: 16000 | AB22: 16000 | AC22: =SUM(E22:AB22) -> 384000
A23: 2026 | B23: 8 | C23: 7 | D23: Festivo | E23: 13000 | F23: 13000 | G23: 13000 | H23: 13000 | I23: 13000 | J23: 13000 | K23: 13000 | L23: 13000 | M23: 13000 | N23: 13000 | O23: 13000 | P23: 13000 | Q23: 13000 | R23: 13000 | S23: 13000 | T23: 13000 | U23: 13000 | V23: 13000 | W23: 13000 | X23: 13000 | Y23: 13000 | Z23: 13000 | AA23: 13000 | AB23: 13000 | AC23: =SUM(E23:AB23) -> 312000 | AD23: =+SUMPRODUCT(AC23:AC25,C23:C25) -> 9672000
A24: 2026 | B24: 8 | C24: 19 | D24: Ordinario | E24: 13000 | F24: 13000 | G24: 13000 | H24: 13000 | I24: 13000 | J24: 13000 | K24: 13000 | L24: 13000 | M24: 13000 | N24: 13000 | O24: 13000 | P24: 13000 | Q24: 13000 | R24: 13000 | S24: 13000 | T24: 13000 | U24: 13000 | V24: 13000 | W24: 13000 | X24: 13000 | Y24: 13000 | Z24: 13000 | AA24: 13000 | AB24: 13000 | AC24: =SUM(E24:AB24) -> 312000
A25: 2026 | B25: 8 | C25: 5 | D25: Sábado | E25: 13000 | F25: 13000 | G25: 13000 | H25: 13000 | I25: 13000 | J25: 13000 | K25: 13000 | L25: 13000 | M25: 13000 | N25: 13000 | O25: 13000 | P25: 13000 | Q25: 13000 | R25: 13000 | S25: 13000 | T25: 13000 | U25: 13000 | V25: 13000 | W25: 13000 | X25: 13000 | Y25: 13000 | Z25: 13000 | AA25: 13000 | AB25: 13000 | AC25: =SUM(E25:AB25) -> 312000
A26: 2026 | B26: 9 | C26: 4 | D26: Festivo | E26: 2500 | F26: 2500 | G26: 2500 | H26: 2500 | I26: 2500 | J26: 2500 | K26: 2500 | L26: 2500 | M26: 2500 | N26: 2500 | O26: 2500 | P26: 2500 | Q26: 2500 | R26: 2500 | S26: 2500 | T26: 2500 | U26: 2500 | V26: 2500 | W26: 2500 | X26: 2500 | Y26: 2500 | Z26: 2500 | AA26: 2500 | AB26: 2500 | AC26: =SUM(E26:AB26) -> 60000 | AD26: =+SUMPRODUCT(AC26:AC28,C26:C28) -> 1800000
A27: 2026 | B27: 9 | C27: 22 | D27: Ordinario | E27: 2500 | F27: 2500 | G27: 2500 | H27: 2500 | I27: 2500 | J27: 2500 | K27: 2500 | L27: 2500 | M27: 2500 | N27: 2500 | O27: 2500 | P27: 2500 | Q27: 2500 | R27: 2500 | S27: 2500 | T27: 2500 | U27: 2500 | V27: 2500 | W27: 2500 | X27: 2500 | Y27: 2500 | Z27: 2500 | AA27: 2500 | AB27: 2500 | AC27: =SUM(E27:AB27) -> 60000
A28: 2026 | B28: 9 | C28: 4 | D28: Sábado | E28: 2500 | F28: 2500 | G28: 2500 | H28: 2500 | I28: 2500 | J28: 2500 | K28: 2500 | L28: 2500 | M28: 2500 | N28: 2500 | O28: 2500 | P28: 2500 | Q28: 2500 | R28: 2500 | S28: 2500 | T28: 2500 | U28: 2500 | V28: 2500 | W28: 2500 | X28: 2500 | Y28: 2500 | Z28: 2500 | AA28: 2500 | AB28: 2500 | AC28: =SUM(E28:AB28) -> 60000
A29: 2026 | B29: 10 | C29: 5 | D29: Festivo | E29: 2500 | F29: 2500 | G29: 2500 | H29: 2500 | I29: 2500 | J29: 2500 | K29: 2500 | L29: 2500 | M29: 2500 | N29: 2500 | O29: 2500 | P29: 2500 | Q29: 2500 | R29: 2500 | S29: 2500 | T29: 2500 | U29: 2500 | V29: 2500 | W29: 2500 | X29: 2500 | Y29: 2500 | Z29: 2500 | AA29: 2500 | AB29: 2500 | AC29: =SUM(E29:AB29) -> 60000 | AD29: =+SUMPRODUCT(AC29:AC31,C29:C31) -> 1860000
A30: 2026 | B30: 10 | C30: 21 | D30: Ordinario | E30: 2500 | F30: 2500 | G30: 2500 | H30: 2500 | I30: 2500 | J30: 2500 | K30: 2500 | L30: 2500 | M30: 2500 | N30: 2500 | O30: 2500 | P30: 2500 | Q30: 2500 | R30: 2500 | S30: 2500 | T30: 2500 | U30: 2500 | V30: 2500 | W30: 2500 | X30: 2500 | Y30: 2500 | Z30: 2500 | AA30: 2500 | AB30: 2500 | AC30: =SUM(E30:AB30) -> 60000
A31: 2026 | B31: 10 | C31: 5 | D31: Sábado | E31: 2500 | F31: 2500 | G31: 2500 | H31: 2500 | I31: 2500 | J31: 2500 | K31: 2500 | L31: 2500 | M31: 2500 | N31: 2500 | O31: 2500 | P31: 2500 | Q31: 2500 | R31: 2500 | S31: 2500 | T31: 2500 | U31: 2500 | V31: 2500 | W31: 2500 | X31: 2500 | Y31: 2500 | Z31: 2500 | AA31: 2500 | AB31: 2500 | AC31: =SUM(E31:AB31) -> 60000
A32: 2026 | B32: 11 | C32: 7 | D32: Festivo | E32: 2500 | F32: 2500 | G32: 2500 | H32: 2500 | I32: 2500 | J32: 2500 | K32: 2500 | L32: 2500 | M32: 2500 | N32: 2500 | O32: 2500 | P32: 2500 | Q32: 2500 | R32: 2500 | S32: 2500 | T32: 2500 | U32: 2500 | V32: 2500 | W32: 2500 | X32: 2500 | Y32: 2500 | Z32: 2500 | AA32: 2500 | AB32: 2500 | AC32: =SUM(E32:AB32) -> 60000 | AD32: =+SUMPRODUCT(AC32:AC34,C32:C34) -> 1800000
A33: 2026 | B33: 11 | C33: 19 | D33: Ordinario | E33: 2500 | F33: 2500 | G33: 2500 | H33: 2500 | I33: 2500 | J33: 2500 | K33: 2500 | L33: 2500 | M33: 2500 | N33: 2500 | O33: 2500 | P33: 2500 | Q33: 2500 | R33: 2500 | S33: 2500 | T33: 2500 | U33: 2500 | V33: 2500 | W33: 2500 | X33: 2500 | Y33: 2500 | Z33: 2500 | AA33: 2500 | AB33: 2500 | AC33: =SUM(E33:AB33) -> 60000
A34: 2026 | B34: 11 | C34: 4 | D34: Sábado | E34: 2500 | F34: 2500 | G34: 2500 | H34: 2500 | I34: 2500 | J34: 2500 | K34: 2500 | L34: 2500 | M34: 2500 | N34: 2500 | O34: 2500 | P34: 2500 | Q34: 2500 | R34: 2500 | S34: 2500 | T34: 2500 | U34: 2500 | V34: 2500 | W34: 2500 | X34: 2500 | Y34: 2500 | Z34: 2500 | AA34: 2500 | AB34: 2500 | AC34: =SUM(E34:AB34) -> 60000
A35: 2026 | B35: 12 | C35: 6 | D35: Festivo | E35: 10000 | F35: 10000 | G35: 10000 | H35: 10000 | I35: 10000 | J35: 10000 | K35: 10000 | L35: 10000 | M35: 10000 | N35: 10000 | O35: 10000 | P35: 10000 | Q35: 10000 | R35: 10000 | S35: 10000 | T35: 10000 | U35: 10000 | V35: 10000 | W35: 10000 | X35: 10000 | Y35: 10000 | Z35: 10000 | AA35: 10000 | AB35: 10000 | AC35: =SUM(E35:AB35) -> 240000 | AD35: =+SUMPRODUCT(AC35:AC37,C35:C37) -> 7440000
A36: 2026 | B36: 12 | C36: 21 | D36: Ordinario | E36: 10000 | F36: 10000 | G36: 10000 | H36: 10000 | I36: 10000 | J36: 10000 | K36: 10000 | L36: 10000 | M36: 10000 | N36: 10000 | O36: 10000 | P36: 10000 | Q36: 10000 | R36: 10000 | S36: 10000 | T36: 10000 | U36: 10000 | V36: 10000 | W36: 10000 | X36: 10000 | Y36: 10000 | Z36: 10000 | AA36: 10000 | AB36: 10000 | AC36: =SUM(E36:AB36) -> 240000
A37: 2026 | B37: 12 | C37: 4 | D37: Sábado | E37: 10000 | F37: 10000 | G37: 10000 | H37: 10000 | I37: 10000 | J37: 10000 | K37: 10000 | L37: 10000 | M37: 10000 | N37: 10000 | O37: 10000 | P37: 10000 | Q37: 10000 | R37: 10000 | S37: 10000 | T37: 10000 | U37: 10000 | V37: 10000 | W37: 10000 | X37: 10000 | Y37: 10000 | Z37: 10000 | AA37: 10000 | AB37: 10000 | AC37: =SUM(E37:AB37) -> 240000
A38: 2027 | B38: 1 | C38: 7 | D38: Festivo | E38: 18000 | F38: 18000 | G38: 18000 | H38: 18000 | I38: 18000 | J38: 18000 | K38: 18000 | L38: 18000 | M38: 18000 | N38: 18000 | O38: 18000 | P38: 18000 | Q38: 18000 | R38: 18000 | S38: 18000 | T38: 18000 | U38: 18000 | V38: 18000 | W38: 18000 | X38: 18000 | Y38: 18000 | Z38: 18000 | AA38: 18000 | AB38: 18000 | AC38: =SUM(E38:AB38) -> 432000 | AD38: =+SUMPRODUCT(AC38:AC40,C38:C40) -> 13392000 | AE38: =+SUM(AD38:AD73) -> 93072000
A39: 2027 | B39: 1 | C39: 19 | D39: Ordinario | E39: 18000 | F39: 18000 | G39: 18000 | H39: 18000 | I39: 18000 | J39: 18000 | K39: 18000 | L39: 18000 | M39: 18000 | N39: 18000 | O39: 18000 | P39: 18000 | Q39: 18000 | R39: 18000 | S39: 18000 | T39: 18000 | U39: 18000 | V39: 18000 | W39: 18000 | X39: 18000 | Y39: 18000 | Z39: 18000 | AA39: 18000 | AB39: 18000 | AC39: =SUM(E39:AB39) -> 432000
A40: 2027 | B40: 1 | C40: 5 | D40: Sábado | E40: 18000 | F40: 18000 | G40: 18000 | H40: 18000 | I40: 18000 | J40: 18000 | K40: 18000 | L40: 18000 | M40: 18000 | N40: 18000 | O40: 18000 | P40: 18000 | Q40: 18000 | R40: 18000 | S40: 18000 | T40: 18000 | U40: 18000 | V40: 18000 | W40: 18000 | X40: 18000 | Y40: 18000 | Z40: 18000 | AA40: 18000 | AB40: 18000 | AC40: =SUM(E40:AB40) -> 432000
A41: 2027 | B41: 2 | C41: 4 | D41: Festivo | E41: 18000 | F41: 18000 | G41: 18000 | H41: 18000 | I41: 18000 | J41: 18000 | K41: 18000 | L41: 18000 | M41: 18000 | N41: 18000 | O41: 18000 | P41: 18000 | Q41: 18000 | R41: 18000 | S41: 18000 | T41: 18000 | U41: 18000 | V41: 18000 | W41: 18000 | X41: 18000 | Y41: 18000 | Z41: 18000 | AA41: 18000 | AB41: 18000 | AC41: =SUM(E41:AB41) -> 432000 | AD41: =+SUMPRODUCT(AC41:AC43,C41:C43) -> 12096000
A42: 2027 | B42: 2 | C42: 20 | D42: Ordinario | E42: 18000 | F42: 18000 | G42: 18000 | H42: 18000 | I42: 18000 | J42: 18000 | K42: 18000 | L42: 18000 | M42: 18000 | N42: 18000 | O42: 18000 | P42: 18000 | Q42: 18000 | R42: 18000 | S42: 18000 | T42: 18000 | U42: 18000 | V42: 18000 | W42: 18000 | X42: 18000 | Y42: 18000 | Z42: 18000 | AA42: 18000 | AB42: 18000 | AC42: =SUM(E42:AB42) -> 432000
A43: 2027 | B43: 2 | C43: 4 | D43: Sábado | E43: 18000 | F43: 18000 | G43: 18000 | H43: 18000 | I43: 18000 | J43: 18000 | K43: 18000 | L43: 18000 | M43: 18000 | N43: 18000 | O43: 18000 | P43: 18000 | Q43: 18000 | R43: 18000 | S43: 18000 | T43: 18000 | U43: 18000 | V43: 18000 | W43: 18000 | X43: 18000 | Y43: 18000 | Z43: 18000 | AA43: 18000 | AB43: 18000 | AC43: =SUM(E43:AB43) -> 432000
A44: 2027 | B44: 3 | C44: 7 | D44: Festivo | E44: 10000 | F44: 10000 | G44: 10000 | H44: 10000 | I44: 10000 | J44: 10000 | K44: 10000 | L44: 10000 | M44: 10000 | N44: 10000 | O44: 10000 | P44: 10000 | Q44: 10000 | R44: 10000 | S44: 10000 | T44: 10000 | U44: 10000 | V44: 10000 | W44: 10000 | X44: 10000 | Y44: 10000 | Z44: 10000 | AA44: 10000 | AB44: 10000 | AC44: =SUM(E44:AB44) -> 240000 | AD44: =+SUMPRODUCT(AC44:AC46,C44:C46) -> 7440000
A45: 2027 | B45: 3 | C45: 20 | D45: Ordinario | E45: 10000 | F45: 10000 | G45: 10000 | H45: 10000 | I45: 10000 | J45: 10000 | K45: 10000 | L45: 10000 | M45: 10000 | N45: 10000 | O45: 10000 | P45: 10000 | Q45: 10000 | R45: 10000 | S45: 10000 | T45: 10000 | U45: 10000 | V45: 10000 | W45: 10000 | X45: 10000 | Y45: 10000 | Z45: 10000 | AA45: 10000 | AB45: 10000 | AC45: =SUM(E45:AB45) -> 240000
A46: 2027 | B46: 3 | C46: 4 | D46: Sábado | E46: 10000 | F46: 10000 | G46: 10000 | H46: 10000 | I46: 10000 | J46: 10000 | K46: 10000 | L46: 10000 | M46: 10000 | N46: 10000 | O46: 10000 | P46: 10000 | Q46: 10000 | R46: 10000 | S46: 10000 | T46: 10000 | U46: 10000 | V46: 10000 | W46: 10000 | X46: 10000 | Y46: 10000 | Z46: 10000 | AA46: 10000 | AB46: 10000 | AC46: =SUM(E46:AB46) -> 240000
A47: 2027 | B47: 4 | C47: 4 | D47: Festivo | E47: 18000 | F47: 18000 | G47: 18000 | H47: 18000 | I47: 18000 | J47: 18000 | K47: 18000 | L47: 18000 | M47: 18000 | N47: 18000 | O47: 18000 | P47: 18000 | Q47: 18000 | R47: 18000 | S47: 18000 | T47: 18000 | U47: 18000 | V47: 18000 | W47: 18000 | X47: 18000 | Y47: 18000 | Z47: 18000 | AA47: 18000 | AB47: 18000 | AC47: =SUM(E47:AB47) -> 432000 | AD47: =+SUMPRODUCT(AC47:AC49,C47:C49) -> 12960000
A48: 2027 | B48: 4 | C48: 22 | D48: Ordinario | E48: 18000 | F48: 18000 | G48: 18000 | H48: 18000 | I48: 18000 | J48: 18000 | K48: 18000 | L48: 18000 | M48: 18000 | N48: 18000 | O48: 18000 | P48: 18000 | Q48: 18000 | R48: 18000 | S48: 18000 | T48: 18000 | U48: 18000 | V48: 18000 | W48: 18000 | X48: 18000 | Y48: 18000 | Z48: 18000 | AA48: 18000 | AB48: 18000 | AC48: =SUM(E48:AB48) -> 432000
A49: 2027 | B49: 4 | C49: 4 | D49: Sábado | E49: 18000 | F49: 18000 | G49: 18000 | H49: 18000 | I49: 18000 | J49: 18000 | K49: 18000 | L49: 18000 | M49: 18000 | N49: 18000 | O49: 18000 | P49: 18000 | Q49: 18000 | R49: 18000 | S49: 18000 | T49: 18000 | U49: 18000 | V49: 18000 | W49: 18000 | X49: 18000 | Y49: 18000 | Z49: 18000 | AA49: 18000 | AB49: 18000 | AC49: =SUM(E49:AB49) -> 432000
A50: 2027 | B50: 5 | C50: 8 | D50: Festivo | E50: 9000 | F50: 9000 | G50: 9000 | H50: 9000 | I50: 9000 | J50: 9000 | K50: 9000 | L50: 9000 | M50: 9000 | N50: 9000 | O50: 9000 | P50: 9000 | Q50: 9000 | R50: 9000 | S50: 9000 | T50: 9000 | U50: 9000 | V50: 9000 | W50: 9000 | X50: 9000 | Y50: 9000 | Z50: 9000 | AA50: 9000 | AB50: 9000 | AC50: =SUM(E50:AB50) -> 216000 | AD50: =+SUMPRODUCT(AC50:AC52,C50:C52) -> 6696000
A51: 2027 | B51: 5 | C51: 19 | D51: Ordinario | E51: 9000 | F51: 9000 | G51: 9000 | H51: 9000 | I51: 9000 | J51: 9000 | K51: 9000 | L51: 9000 | M51: 9000 | N51: 9000 | O51: 9000 | P51: 9000 | Q51: 9000 | R51: 9000 | S51: 9000 | T51: 9000 | U51: 9000 | V51: 9000 | W51: 9000 | X51: 9000 | Y51: 9000 | Z51: 9000 | AA51: 9000 | AB51: 9000 | AC51: =SUM(E51:AB51) -> 216000
A52: 2027 | B52: 5 | C52: 4 | D52: Sábado | E52: 9000 | F52: 9000 | G52: 9000 | H52: 9000 | I52: 9000 | J52: 9000 | K52: 9000 | L52: 9000 | M52: 9000 | N52: 9000 | O52: 9000 | P52: 9000 | Q52: 9000 | R52: 9000 | S52: 9000 | T52: 9000 | U52: 9000 | V52: 9000 | W52: 9000 | X52: 9000 | Y52: 9000 | Z52: 9000 | AA52: 9000 | AB52: 9000 | AC52: =SUM(E52:AB52) -> 216000
A53: 2027 | B53: 6 | C53: 5 | D53: Festivo | E53: 14000 | F53: 14000 | G53: 14000 | H53: 14000 | I53: 14000 | J53: 14000 | K53: 14000 | L53: 14000 | M53: 14000 | N53: 14000 | O53: 14000 | P53: 14000 | Q53: 14000 | R53: 14000 | S53: 14000 | T53: 14000 | U53: 14000 | V53: 14000 | W53: 14000 | X53: 14000 | Y53: 14000 | Z53: 14000 | AA53: 14000 | AB53: 14000 | AC53: =SUM(E53:AB53) -> 336000 | AD53: =+SUMPRODUCT(AC53:AC55,C53:C55) -> 10080000
A54: 2027 | B54: 6 | C54: 21 | D54: Ordinario | E54: 14000 | F54: 14000 | G54: 14000 | H54: 14000 | I54: 14000 | J54: 14000 | K54: 14000 | L54: 14000 | M54: 14000 | N54: 14000 | O54: 14000 | P54: 14000 | Q54: 14000 | R54: 14000 | S54: 14000 | T54: 14000 | U54: 14000 | V54: 14000 | W54: 14000 | X54: 14000 | Y54: 14000 | Z54: 14000 | AA54: 14000 | AB54: 14000 | AC54: =SUM(E54:AB54) -> 336000
A55: 2027 | B55: 6 | C55: 4 | D55: Sábado | E55: 14000 | F55: 14000 | G55: 14000 | H55: 14000 | I55: 14000 | J55: 14000 | K55: 14000 | L55: 14000 | M55: 14000 | N55: 14000 | O55: 14000 | P55: 14000 | Q55: 14000 | R55: 14000 | S55: 14000 | T55: 14000 | U55: 14000 | V55: 14000 | W55: 14000 | X55: 14000 | Y55: 14000 | Z55: 14000 | AA55: 14000 | AB55: 14000 | AC55: =SUM(E55:AB55) -> 336000
A56: 2027 | B56: 7 | C56: 6 | D56: Festivo | E56: 12000 | F56: 12000 | G56: 12000 | H56: 12000 | I56: 12000 | J56: 12000 | K56: 12000 | L56: 12000 | M56: 12000 | N56: 12000 | O56: 12000 | P56: 12000 | Q56: 12000 | R56: 12000 | S56: 12000 | T56: 12000 | U56: 12000 | V56: 12000 | W56: 12000 | X56: 12000 | Y56: 12000 | Z56: 12000 | AA56: 12000 | AB56: 12000 | AC56: =SUM(E56:AB56) -> 288000 | AD56: =+SUMPRODUCT(AC56:AC58,C56:C58) -> 8928000
A57: 2027 | B57: 7 | C57: 20 | D57: Ordinario | E57: 12000 | F57: 12000 | G57: 12000 | H57: 12000 | I57: 12000 | J57: 12000 | K57: 12000 | L57: 12000 | M57: 12000 | N57: 12000 | O57: 12000 | P57: 12000 | Q57: 12000 | R57: 12000 | S57: 12000 | T57: 12000 | U57: 12000 | V57: 12000 | W57: 12000 | X57: 12000 | Y57: 12000 | Z57: 12000 | AA57: 12000 | AB57: 12000 | AC57: =SUM(E57:AB57) -> 288000
A58: 2027 | B58: 7 | C58: 5 | D58: Sábado | E58: 12000 | F58: 12000 | G58: 12000 | H58: 12000 | I58: 12000 | J58: 12000 | K58: 12000 | L58: 12000 | M58: 12000 | N58: 12000 | O58: 12000 | P58: 12000 | Q58: 12000 | R58: 12000 | S58: 12000 | T58: 12000 | U58: 12000 | V58: 12000 | W58: 12000 | X58: 12000 | Y58: 12000 | Z58: 12000 | AA58: 12000 | AB58: 12000 | AC58: =SUM(E58:AB58) -> 288000
A59: 2027 | B59: 8 | C59: 7 | D59: Festivo | E59: 13000 | F59: 13000 | G59: 13000 | H59: 13000 | I59: 13000 | J59: 13000 | K59: 13000 | L59: 13000 | M59: 13000 | N59: 13000 | O59: 13000 | P59: 13000 | Q59: 13000 | R59: 13000 | S59: 13000 | T59: 13000 | U59: 13000 | V59: 13000 | W59: 13000 | X59: 13000 | Y59: 13000 | Z59: 13000 | AA59: 13000 | AB59: 13000 | AC59: =SUM(E59:AB59) -> 312000 | AD59: =+SUMPRODUCT(AC59:AC61,C59:C61) -> 9672000
A60: 2027 | B60: 8 | C60: 21 | D60: Ordinario | E60: 13000 | F60: 13000 | G60: 13000 | H60: 13000 | I60: 13000 | J60: 13000 | K60: 13000 | L60: 13000 | M60: 13000 | N60: 13000 | O60: 13000 | P60: 13000 | Q60: 13000 | R60: 13000 | S60: 13000 | T60: 13000 | U60: 13000 | V60: 13000 | W60: 13000 | X60: 13000 | Y60: 13000 | Z60: 13000 | AA60: 13000 | AB60: 13000 | AC60: =SUM(E60:AB60) -> 312000
A61: 2027 | B61: 8 | C61: 3 | D61: Sábado | E61: 13000 | F61: 13000 | G61: 13000 | H61: 13000 | I61: 13000 | J61: 13000 | K61: 13000 | L61: 13000 | M61: 13000 | N61: 13000 | O61: 13000 | P61: 13000 | Q61: 13000 | R61: 13000 | S61: 13000 | T61: 13000 | U61: 13000 | V61: 13000 | W61: 13000 | X61: 13000 | Y61: 13000 | Z61: 13000 | AA61: 13000 | AB61: 13000 | AC61: =SUM(E61:AB61) -> 312000
A62: 2027 | B62: 9 | C62: 4 | D62: Festivo | E62: 2000 | F62: 2000 | G62: 2000 | H62: 2000 | I62: 2000 | J62: 2000 | K62: 2000 | L62: 2000 | M62: 2000 | N62: 2000 | O62: 2000 | P62: 2000 | Q62: 2000 | R62: 2000 | S62: 2000 | T62: 2000 | U62: 2000 | V62: 2000 | W62: 2000 | X62: 2000 | Y62: 2000 | Z62: 2000 | AA62: 2000 | AB62: 2000 | AC62: =SUM(E62:AB62) -> 48000 | AD62: =+SUMPRODUCT(AC62:AC64,C62:C64) -> 1440000
A63: 2027 | B63: 9 | C63: 22 | D63: Ordinario | E63: 2000 | F63: 2000 | G63: 2000 | H63: 2000 | I63: 2000 | J63: 2000 | K63: 2000 | L63: 2000 | M63: 2000 | N63: 2000 | O63: 2000 | P63: 2000 | Q63: 2000 | R63: 2000 | S63: 2000 | T63: 2000 | U63: 2000 | V63: 2000 | W63: 2000 | X63: 2000 | Y63: 2000 | Z63: 2000 | AA63: 2000 | AB63: 2000 | AC63: =SUM(E63:AB63) -> 48000
A64: 2027 | B64: 9 | C64: 4 | D64: Sábado | E64: 2000 | F64: 2000 | G64: 2000 | H64: 2000 | I64: 2000 | J64: 2000 | K64: 2000 | L64: 2000 | M64: 2000 | N64: 2000 | O64: 2000 | P64: 2000 | Q64: 2000 | R64: 2000 | S64: 2000 | T64: 2000 | U64: 2000 | V64: 2000 | W64: 2000 | X64: 2000 | Y64: 2000 | Z64: 2000 | AA64: 2000 | AB64: 2000 | AC64: =SUM(E64:AB64) -> 48000
A65: 2027 | B65: 10 | C65: 6 | D65: Festivo | E65: 2000 | F65: 2000 | G65: 2000 | H65: 2000 | I65: 2000 | J65: 2000 | K65: 2000 | L65: 2000 | M65: 2000 | N65: 2000 | O65: 2000 | P65: 2000 | Q65: 2000 | R65: 2000 | S65: 2000 | T65: 2000 | U65: 2000 | V65: 2000 | W65: 2000 | X65: 2000 | Y65: 2000 | Z65: 2000 | AA65: 2000 | AB65: 2000 | AC65: =SUM(E65:AB65) -> 48000 | AD65: =+SUMPRODUCT(AC65:AC67,C65:C67) -> 1488000
A66: 2027 | B66: 10 | C66: 20 | D66: Ordinario | E66: 2000 | F66: 2000 | G66: 2000 | H66: 2000 | I66: 2000 | J66: 2000 | K66: 2000 | L66: 2000 | M66: 2000 | N66: 2000 | O66: 2000 | P66: 2000 | Q66: 2000 | R66: 2000 | S66: 2000 | T66: 2000 | U66: 2000 | V66: 2000 | W66: 2000 | X66: 2000 | Y66: 2000 | Z66: 2000 | AA66: 2000 | AB66: 2000 | AC66: =SUM(E66:AB66) -> 48000
A67: 2027 | B67: 10 | C67: 5 | D67: Sábado | E67: 2000 | F67: 2000 | G67: 2000 | H67: 2000 | I67: 2000 | J67: 2000 | K67: 2000 | L67: 2000 | M67: 2000 | N67: 2000 | O67: 2000 | P67: 2000 | Q67: 2000 | R67: 2000 | S67: 2000 | T67: 2000 | U67: 2000 | V67: 2000 | W67: 2000 | X67: 2000 | Y67: 2000 | Z67: 2000 | AA67: 2000 | AB67: 2000 | AC67: =SUM(E67:AB67) -> 48000
A68: 2027 | B68: 11 | C68: 6 | D68: Festivo | E68: 2000 | F68: 2000 | G68: 2000 | H68: 2000 | I68: 2000 | J68: 2000 | K68: 2000 | L68: 2000 | M68: 2000 | N68: 2000 | O68: 2000 | P68: 2000 | Q68: 2000 | R68: 2000 | S68: 2000 | T68: 2000 | U68: 2000 | V68: 2000 | W68: 2000 | X68: 2000 | Y68: 2000 | Z68: 2000 | AA68: 2000 | AB68: 2000 | AC68: =SUM(E68:AB68) -> 48000 | AD68: =+SUMPRODUCT(AC68:AC70,C68:C70) -> 1440000
A69: 2027 | B69: 11 | C69: 20 | D69: Ordinario | E69: 2000 | F69: 2000 | G69: 2000 | H69: 2000 | I69: 2000 | J69: 2000 | K69: 2000 | L69: 2000 | M69: 2000 | N69: 2000 | O69: 2000 | P69: 2000 | Q69: 2000 | R69: 2000 | S69: 2000 | T69: 2000 | U69: 2000 | V69: 2000 | W69: 2000 | X69: 2000 | Y69: 2000 | Z69: 2000 | AA69: 2000 | AB69: 2000 | AC69: =SUM(E69:AB69) -> 48000
A70: 2027 | B70: 11 | C70: 4 | D70: Sábado | E70: 2000 | F70: 2000 | G70: 2000 | H70: 2000 | I70: 2000 | J70: 2000 | K70: 2000 | L70: 2000 | M70: 2000 | N70: 2000 | O70: 2000 | P70: 2000 | Q70: 2000 | R70: 2000 | S70: 2000 | T70: 2000 | U70: 2000 | V70: 2000 | W70: 2000 | X70: 2000 | Y70: 2000 | Z70: 2000 | AA70: 2000 | AB70: 2000 | AC70: =SUM(E70:AB70) -> 48000
A71: 2027 | B71: 12 | C71: 6 | D71: Festivo | E71: 10000 | F71: 10000 | G71: 10000 | H71: 10000 | I71: 10000 | J71: 10000 | K71: 10000 | L71: 10000 | M71: 10000 | N71: 10000 | O71: 10000 | P71: 10000 | Q71: 10000 | R71: 10000 | S71: 10000 | T71: 10000 | U71: 10000 | V71: 10000 | W71: 10000 | X71: 10000 | Y71: 10000 | Z71: 10000 | AA71: 10000 | AB71: 10000 | AC71: =SUM(E71:AB71) -> 240000 | AD71: =+SUMPRODUCT(AC71:AC73,C71:C73) -> 7440000
A72: 2027 | B72: 12 | C72: 22 | D72: Ordinario | E72: 10000 | F72: 10000 | G72: 10000 | H72: 10000 | I72: 10000 | J72: 10000 | K72: 10000 | L72: 10000 | M72: 10000 | N72: 10000 | O72: 10000 | P72: 10000 | Q72: 10000 | R72: 10000 | S72: 10000 | T72: 10000 | U72: 10000 | V72: 10000 | W72: 10000 | X72: 10000 | Y72: 10000 | Z72: 10000 | AA72: 10000 | AB72: 10000 | AC72: =SUM(E72:AB72) -> 240000
A73: 2027 | B73: 12 | C73: 3 | D73: Sábado | E73: 10000 | F73: 10000 | G73: 10000 | H73: 10000 | I73: 10000 | J73: 10000 | K73: 10000 | L73: 10000 | M73: 10000 | N73: 10000 | O73: 10000 | P73: 10000 | Q73: 10000 | R73: 10000 | S73: 10000 | T73: 10000 | U73: 10000 | V73: 10000 | W73: 10000 | X73: 10000 | Y73: 10000 | Z73: 10000 | AA73: 10000 | AB73: 10000 | AC73: =SUM(E73:AB73) -> 240000
A74: 2028 | B74: 1 | C74: 7 | D74: Festivo | E74: 16500 | F74: 16500 | G74: 16500 | H74: 16500 | I74: 16500 | J74: 16500 | K74: 16500 | L74: 16500 | M74: 16500 | N74: 16500 | O74: 16500 | P74: 16500 | Q74: 16500 | R74: 16500 | S74: 16500 | T74: 16500 | U74: 16500 | V74: 16500 | W74: 16500 | X74: 16500 | Y74: 16500 | Z74: 16500 | AA74: 16500 | AB74: 16500 | AC74: =SUM(E74:AB74) -> 396000 | AD74: =+SUMPRODUCT(AC74:AC76,C74:C76) -> 12276000 | AE74: =+SUM(AD74:AD109) -> 78528000
A75: 2028 | B75: 1 | C75: 20 | D75: Ordinario | E75: 16500 | F75: 16500 | G75: 16500 | H75: 16500 | I75: 16500 | J75: 16500 | K75: 16500 | L75: 16500 | M75: 16500 | N75: 16500 | O75: 16500 | P75: 16500 | Q75: 16500 | R75: 16500 | S75: 16500 | T75: 16500 | U75: 16500 | V75: 16500 | W75: 16500 | X75: 16500 | Y75: 16500 | Z75: 16500 | AA75: 16500 | AB75: 16500 | AC75: =SUM(E75:AB75) -> 396000
A76: 2028 | B76: 1 | C76: 4 | D76: Sábado | E76: 16500 | F76: 16500 | G76: 16500 | H76: 16500 | I76: 16500 | J76: 16500 | K76: 16500 | L76: 16500 | M76: 16500 | N76: 16500 | O76: 16500 | P76: 16500 | Q76: 16500 | R76: 16500 | S76: 16500 | T76: 16500 | U76: 16500 | V76: 16500 | W76: 16500 | X76: 16500 | Y76: 16500 | Z76: 16500 | AA76: 16500 | AB76: 16500 | AC76: =SUM(E76:AB76) -> 396000
A77: 2028 | B77: 2 | C77: 4 | D77: Festivo | E77: 15500 | F77: 15500 | G77: 15500 | H77: 15500 | I77: 15500 | J77: 15500 | K77: 15500 | L77: 15500 | M77: 15500 | N77: 15500 | O77: 15500 | P77: 15500 | Q77: 15500 | R77: 15500 | S77: 15500 | T77: 15500 | U77: 15500 | V77: 15500 | W77: 15500 | X77: 15500 | Y77: 15500 | Z77: 15500 | AA77: 15500 | AB77: 15500 | AC77: =SUM(E77:AB77) -> 372000 | AD77: =+SUMPRODUCT(AC77:AC79,C77:C79) -> 10788000
A78: 2028 | B78: 2 | C78: 21 | D78: Ordinario | E78: 15500 | F78: 15500 | G78: 15500 | H78: 15500 | I78: 15500 | J78: 15500 | K78: 15500 | L78: 15500 | M78: 15500 | N78: 15500 | O78: 15500 | P78: 15500 | Q78: 15500 | R78: 15500 | S78: 15500 | T78: 15500 | U78: 15500 | V78: 15500 | W78: 15500 | X78: 15500 | Y78: 15500 | Z78: 15500 | AA78: 15500 | AB78: 15500 | AC78: =SUM(E78:AB78) -> 372000
A79: 2028 | B79: 2 | C79: 4 | D79: Sábado | E79: 15500 | F79: 15500 | G79: 15500 | H79: 15500 | I79: 15500 | J79: 15500 | K79: 15500 | L79: 15500 | M79: 15500 | N79: 15500 | O79: 15500 | P79: 15500 | Q79: 15500 | R79: 15500 | S79: 15500 | T79: 15500 | U79: 15500 | V79: 15500 | W79: 15500 | X79: 15500 | Y79: 15500 | Z79: 15500 | AA79: 15500 | AB79: 15500 | AC79: =SUM(E79:AB79) -> 372000
A80: 2028 | B80: 3 | C80: 5 | D80: Festivo | E80: 16000 | F80: 16000 | G80: 16000 | H80: 16000 | I80: 16000 | J80: 16000 | K80: 16000 | L80: 16000 | M80: 16000 | N80: 16000 | O80: 16000 | P80: 16000 | Q80: 16000 | R80: 16000 | S80: 16000 | T80: 16000 | U80: 16000 | V80: 16000 | W80: 16000 | X80: 16000 | Y80: 16000 | Z80: 16000 | AA80: 16000 | AB80: 16000 | AC80: =SUM(E80:AB80) -> 384000 | AD80: =+SUMPRODUCT(AC80:AC82,C80:C82) -> 11904000
A81: 2028 | B81: 3 | C81: 22 | D81: Ordinario | E81: 16000 | F81: 16000 | G81: 16000 | H81: 16000 | I81: 16000 | J81: 16000 | K81: 16000 | L81: 16000 | M81: 16000 | N81: 16000 | O81: 16000 | P81: 16000 | Q81: 16000 | R81: 16000 | S81: 16000 | T81: 16000 | U81: 16000 | V81: 16000 | W81: 16000 | X81: 16000 | Y81: 16000 | Z81: 16000 | AA81: 16000 | AB81: 16000 | AC81: =SUM(E81:AB81) -> 384000
A82: 2028 | B82: 3 | C82: 4 | D82: Sábado | E82: 16000 | F82: 16000 | G82: 16000 | H82: 16000 | I82: 16000 | J82: 16000 | K82: 16000 | L82: 16000 | M82: 16000 | N82: 16000 | O82: 16000 | P82: 16000 | Q82: 16000 | R82: 16000 | S82: 16000 | T82: 16000 | U82: 16000 | V82: 16000 | W82: 16000 | X82: 16000 | Y82: 16000 | Z82: 16000 | AA82: 16000 | AB82: 16000 | AC82: =SUM(E82:AB82) -> 384000
A83: 2028 | B83: 4 | C83: 7 | D83: Festivo | E83: 11500 | F83: 11500 | G83: 11500 | H83: 11500 | I83: 11500 | J83: 11500 | K83: 11500 | L83: 11500 | M83: 11500 | N83: 11500 | O83: 11500 | P83: 11500 | Q83: 11500 | R83: 11500 | S83: 11500 | T83: 11500 | U83: 11500 | V83: 11500 | W83: 11500 | X83: 11500 | Y83: 11500 | Z83: 11500 | AA83: 11500 | AB83: 11500 | AC83: =SUM(E83:AB83) -> 276000 | AD83: =+SUMPRODUCT(AC83:AC85,C83:C85) -> 8280000
A84: 2028 | B84: 4 | C84: 18 | D84: Ordinario | E84: 11500 | F84: 11500 | G84: 11500 | H84: 11500 | I84: 11500 | J84: 11500 | K84: 11500 | L84: 11500 | M84: 11500 | N84: 11500 | O84: 11500 | P84: 11500 | Q84: 11500 | R84: 11500 | S84: 11500 | T84: 11500 | U84: 11500 | V84: 11500 | W84: 11500 | X84: 11500 | Y84: 11500 | Z84: 11500 | AA84: 11500 | AB84: 11500 | AC84: =SUM(E84:AB84) -> 276000
A85: 2028 | B85: 4 | C85: 5 | D85: Sábado | E85: 11500 | F85: 11500 | G85: 11500 | H85: 11500 | I85: 11500 | J85: 11500 | K85: 11500 | L85: 11500 | M85: 11500 | N85: 11500 | O85: 11500 | P85: 11500 | Q85: 11500 | R85: 11500 | S85: 11500 | T85: 11500 | U85: 11500 | V85: 11500 | W85: 11500 | X85: 11500 | Y85: 11500 | Z85: 11500 | AA85: 11500 | AB85: 11500 | AC85: =SUM(E85:AB85) -> 276000
A86: 2028 | B86: 5 | C86: 6 | D86: Festivo | E86: 3000 | F86: 3000 | G86: 3000 | H86: 3000 | I86: 3000 | J86: 3000 | K86: 3000 | L86: 3000 | M86: 3000 | N86: 3000 | O86: 3000 | P86: 3000 | Q86: 3000 | R86: 3000 | S86: 3000 | T86: 3000 | U86: 3000 | V86: 3000 | W86: 3000 | X86: 3000 | Y86: 3000 | Z86: 3000 | AA86: 3000 | AB86: 3000 | AC86: =SUM(E86:AB86) -> 72000 | AD86: =+SUMPRODUCT(AC86:AC88,C86:C88) -> 2232000
A87: 2028 | B87: 5 | C87: 21 | D87: Ordinario | E87: 3000 | F87: 3000 | G87: 3000 | H87: 3000 | I87: 3000 | J87: 3000 | K87: 3000 | L87: 3000 | M87: 3000 | N87: 3000 | O87: 3000 | P87: 3000 | Q87: 3000 | R87: 3000 | S87: 3000 | T87: 3000 | U87: 3000 | V87: 3000 | W87: 3000 | X87: 3000 | Y87: 3000 | Z87: 3000 | AA87: 3000 | AB87: 3000 | AC87: =SUM(E87:AB87) -> 72000
A88: 2028 | B88: 5 | C88: 4 | D88: Sábado | E88: 3000 | F88: 3000 | G88: 3000 | H88: 3000 | I88: 3000 | J88: 3000 | K88: 3000 | L88: 3000 | M88: 3000 | N88: 3000 | O88: 3000 | P88: 3000 | Q88: 3000 | R88: 3000 | S88: 3000 | T88: 3000 | U88: 3000 | V88: 3000 | W88: 3000 | X88: 3000 | Y88: 3000 | Z88: 3000 | AA88: 3000 | AB88: 3000 | AC88: =SUM(E88:AB88) -> 72000
A89: 2028 | B89: 6 | C89: 6 | D89: Festivo | E89: 3000 | F89: 3000 | G89: 3000 | H89: 3000 | I89: 3000 | J89: 3000 | K89: 3000 | L89: 3000 | M89: 3000 | N89: 3000 | O89: 3000 | P89: 3000 | Q89: 3000 | R89: 3000 | S89: 3000 | T89: 3000 | U89: 3000 | V89: 3000 | W89: 3000 | X89: 3000 | Y89: 3000 | Z89: 3000 | AA89: 3000 | AB89: 3000 | AC89: =SUM(E89:AB89) -> 72000 | AD89: =+SUMPRODUCT(AC89:AC91,C89:C91) -> 2160000
A90: 2028 | B90: 6 | C90: 20 | D90: Ordinario | E90: 3000 | F90: 3000 | G90: 3000 | H90: 3000 | I90: 3000 | J90: 3000 | K90: 3000 | L90: 3000 | M90: 3000 | N90: 3000 | O90: 3000 | P90: 3000 | Q90: 3000 | R90: 3000 | S90: 3000 | T90: 3000 | U90: 3000 | V90: 3000 | W90: 3000 | X90: 3000 | Y90: 3000 | Z90: 3000 | AA90: 3000 | AB90: 3000 | AC90: =SUM(E90:AB90) -> 72000
A91: 2028 | B91: 6 | C91: 4 | D91: Sábado | E91: 3000 | F91: 3000 | G91: 3000 | H91: 3000 | I91: 3000 | J91: 3000 | K91: 3000 | L91: 3000 | M91: 3000 | N91: 3000 | O91: 3000 | P91: 3000 | Q91: 3000 | R91: 3000 | S91: 3000 | T91: 3000 | U91: 3000 | V91: 3000 | W91: 3000 | X91: 3000 | Y91: 3000 | Z91: 3000 | AA91: 3000 | AB91: 3000 | AC91: =SUM(E91:AB91) -> 72000
A92: 2028 | B92: 7 | C92: 7 | D92: Festivo | E92: 3000 | F92: 3000 | G92: 3000 | H92: 3000 | I92: 3000 | J92: 3000 | K92: 3000 | L92: 3000 | M92: 3000 | N92: 3000 | O92: 3000 | P92: 3000 | Q92: 3000 | R92: 3000 | S92: 3000 | T92: 3000 | U92: 3000 | V92: 3000 | W92: 3000 | X92: 3000 | Y92: 3000 | Z92: 3000 | AA92: 3000 | AB92: 3000 | AC92: =SUM(E92:AB92) -> 72000 | AD92: =+SUMPRODUCT(AC92:AC94,C92:C94) -> 2232000
A93: 2028 | B93: 7 | C93: 19 | D93: Ordinario | E93: 3000 | F93: 3000 | G93: 3000 | H93: 3000 | I93: 3000 | J93: 3000 | K93: 3000 | L93: 3000 | M93: 3000 | N93: 3000 | O93: 3000 | P93: 3000 | Q93: 3000 | R93: 3000 | S93: 3000 | T93: 3000 | U93: 3000 | V93: 3000 | W93: 3000 | X93: 3000 | Y93: 3000 | Z93: 3000 | AA93: 3000 | AB93: 3000 | AC93: =SUM(E93:AB93) -> 72000
A94: 2028 | B94: 7 | C94: 5 | D94: Sábado | E94: 3000 | F94: 3000 | G94: 3000 | H94: 3000 | I94: 3000 | J94: 3000 | K94: 3000 | L94: 3000 | M94: 3000 | N94: 3000 | O94: 3000 | P94: 3000 | Q94: 3000 | R94: 3000 | S94: 3000 | T94: 3000 | U94: 3000 | V94: 3000 | W94: 3000 | X94: 3000 | Y94: 3000 | Z94: 3000 | AA94: 3000 | AB94: 3000 | AC94: =SUM(E94:AB94) -> 72000
A95: 2028 | B95: 8 | C95: 6 | D95: Festivo | E95: 4000 | F95: 4000 | G95: 4000 | H95: 4000 | I95: 4000 | J95: 4000 | K95: 4000 | L95: 4000 | M95: 4000 | N95: 4000 | O95: 4000 | P95: 4000 | Q95: 4000 | R95: 4000 | S95: 4000 | T95: 4000 | U95: 4000 | V95: 4000 | W95: 4000 | X95: 4000 | Y95: 4000 | Z95: 4000 | AA95: 4000 | AB95: 4000 | AC95: =SUM(E95:AB95) -> 96000 | AD95: =+SUMPRODUCT(AC95:AC97,C95:C97) -> 2976000
A96: 2028 | B96: 8 | C96: 21 | D96: Ordinario | E96: 4000 | F96: 4000 | G96: 4000 | H96: 4000 | I96: 4000 | J96: 4000 | K96: 4000 | L96: 4000 | M96: 4000 | N96: 4000 | O96: 4000 | P96: 4000 | Q96: 4000 | R96: 4000 | S96: 4000 | T96: 4000 | U96: 4000 | V96: 4000 | W96: 4000 | X96: 4000 | Y96: 4000 | Z96: 4000 | AA96: 4000 | AB96: 4000 | AC96: =SUM(E96:AB96) -> 96000
A97: 2028 | B97: 8 | C97: 4 | D97: Sábado | E97: 4000 | F97: 4000 | G97: 4000 | H97: 4000 | I97: 4000 | J97: 4000 | K97: 4000 | L97: 4000 | M97: 4000 | N97: 4000 | O97: 4000 | P97: 4000 | Q97: 4000 | R97: 4000 | S97: 4000 | T97: 4000 | U97: 4000 | V97: 4000 | W97: 4000 | X97: 4000 | Y97: 4000 | Z97: 4000 | AA97: 4000 | AB97: 4000 | AC97: =SUM(E97:AB97) -> 96000
A98: 2028 | B98: 9 | C98: 4 | D98: Festivo | E98: 7500 | F98: 7500 | G98: 7500 | H98: 7500 | I98: 7500 | J98: 7500 | K98: 7500 | L98: 7500 | M98: 7500 | N98: 7500 | O98: 7500 | P98: 7500 | Q98: 7500 | R98: 7500 | S98: 7500 | T98: 7500 | U98: 7500 | V98: 7500 | W98: 7500 | X98: 7500 | Y98: 7500 | Z98: 7500 | AA98: 7500 | AB98: 7500 | AC98: =SUM(E98:AB98) -> 180000 | AD98: =+SUMPRODUCT(AC98:AC100,C98:C100) -> 5400000
A99: 2028 | B99: 9 | C99: 21 | D99: Ordinario | E99: 7500 | F99: 7500 | G99: 7500 | H99: 7500 | I99: 7500 | J99: 7500 | K99: 7500 | L99: 7500 | M99: 7500 | N99: 7500 | O99: 7500 | P99: 7500 | Q99: 7500 | R99: 7500 | S99: 7500 | T99: 7500 | U99: 7500 | V99: 7500 | W99: 7500 | X99: 7500 | Y99: 7500 | Z99: 7500 | AA99: 7500 | AB99: 7500 | AC99: =SUM(E99:AB99) -> 180000
A100: 2028 | B100: 9 | C100: 5 | D100: Sábado | E100: 7500 | F100: 7500 | G100: 7500 | H100: 7500 | I100: 7500 | J100: 7500 | K100: 7500 | L100: 7500 | M100: 7500 | N100: 7500 | O100: 7500 | P100: 7500 | Q100: 7500 | R100: 7500 | S100: 7500 | T100: 7500 | U100: 7500 | V100: 7500 | W100: 7500 | X100: 7500 | Y100: 7500 | Z100: 7500 | AA100: 7500 | AB100: 7500 | AC100: =SUM(E100:AB100) -> 180000
...

Sheet Producto No. 2 Curva
A5: ANEXO No. 1. Oferta Producto No. 2 Curva Plana Convocatoria Pública DISPAC S.A. E.S.P.
A8: PROPONENTE
A10: MES | B10: DEMANDA REQUERIDA DISPAC KWh | C10: DEMANDA PERIODO REQUERIDA DISPAC KWh | D10: PORCENTAJE (%) OFERTADO DE LA DEMANDA REQUERIDA | E10: DEMANDA OFERTADA KWh - MES | F10: DEMANDA PERIODO OFERTADA KWh | G10: PRECIO OFERTADO $ kWh (0.00)
A11: 46023 | B11: =+'Producto No. 2 (Curva)'!AD2 -> 3731047 | C11: =SUM(B11:B22) -> 63783813 | D11: 0 | E11: =+B11*D11 -> 0 | F11: =SUM(E11:E22) -> 0
A12: 46054 | B12: =+'Producto No. 2 (Curva)'!AD5 -> 3372840 | D12: 0 | E12: =+B12*D12 -> 0
A13: 46082 | B13: =+'Producto No. 2 (Curva)'!AD8 -> 4477313 | D13: 0 | E13: 0
A14: 46113 | B14: =+'Producto No. 2 (Curva)'!AD11 -> 7876062 | D14: 0 | E14: =+B14*D14 -> 0
A15: 46143 | B15: =+'Producto No. 2 (Curva)'!AD14 -> 6714696 | D15: 0 | E15: =+B15*D15 -> 0
A16: 46174 | B16: =+'Producto No. 2 (Curva)'!AD17 -> 9456276 | D16: 0 | E16: =+B16*D16 -> 0
A17: 46204 | B17: =+'Producto No. 2 (Curva)'!AD20 -> 4460345 | D17: 0 | E17: =+B17*D17 -> 0
A18: 46235 | B18: =+'Producto No. 2 (Curva)'!AD23 -> 6255842 | D18: 0 | E18: =+B18*D18 -> 0
A19: 46266 | B19: =+'Producto No. 2 (Curva)'!AD26 -> 2553138 | D19: 0 | E19: =+B19*D19 -> 0
A20: 46296 | B20: =+'Producto No. 2 (Curva)'!AD29 -> 2398451 | D20: 0 | E20: =+B20*D20 -> 0
A21: 46327 | B21: =+'Producto No. 2 (Curva)'!AD32 -> 2758031 | D21: 0 | E21: =+B21*D21 -> 0
A22: 46357 | B22: =+'Producto No. 2 (Curva)'!AD35 -> 9729772 | D22: 0 | E22: =+B22*D22 -> 0
A23: 46388 | B23: =+'Producto No. 2 (Curva)'!AD38 -> 3913842 | C23: =SUM(B23:B34) -> 67871522 | D23: 0 | E23: =+B23*D23 -> 0 | F23: =SUM(E23:E34) -> 0
A24: 46419 | B24: =+'Producto No. 2 (Curva)'!AD41 -> 3319492 | D24: 0 | E24: =+B24*D24 -> 0
A25: 46447 | B25: =+'Producto No. 2 (Curva)'!AD44 -> 10019614 | D25: 0 | E25: =+B25*D25 -> 0
A26: 46478 | B26: =+'Producto No. 2 (Curva)'!AD47 -> 4096284 | D26: 0 | E26: =+B26*D26 -> 0
A27: 46508 | B27: =+'Producto No. 2 (Curva)'!AD50 -> 9564657 | D27: 0 | E27: =+B27*D27 -> 0
A28: 46539 | B28: =+'Producto No. 2 (Curva)'!AD53 -> 4633932 | D28: 0 | E28: =+B28*D28 -> 0
A29: 46569 | B29: =+'Producto No. 2 (Curva)'!AD56 -> 7973639 | D29: 0 | E29: =+B29*D29 -> 0
A30: 46600 | B30: =+'Producto No. 2 (Curva)'!AD59 -> 6832722 | D30: 0 | E30: =+B30*D30 -> 0
A31: 46631 | B31: =+'Producto No. 2 (Curva)'!AD62 -> 2528108 | D31: 0 | E31: =+B31*D31 -> 0
A32: 46661 | B32: =+'Producto No. 2 (Curva)'!AD65 -> 2320125 | D32: 0 | E32: =+B32*D32 -> 0
A33: 46692 | B33: =+'Producto No. 2 (Curva)'!AD68 -> 2665816 | D33: 0 | E33: =+B33*D33 -> 0
A34: 46722 | B34: =+'Producto No. 2 (Curva)'!AD71 -> 10003291 | D34: 0 | E34: =+B34*D34 -> 0
A35: 46753 | B35: =+'Producto No. 2 (Curva)'!AD74 -> 3774561 | C35: =SUM(B35:B46) -> 63351821 | D35: 0 | E35: =+B35*D35 -> 0 | F35: =SUM(E35:E46) -> 0
A36: 46784 | B36: =+'Producto No. 2 (Curva)'!AD77 -> 3526018 | D36: 0 | E36: =+B36*D36 -> 0
A37: 46813 | B37: =+'Producto No. 2 (Curva)'!AD80 -> 4012629 | D37: 0 | E37: =+B37*D37 -> 0
A38: 46844 | B38: =+'Producto No. 2 (Curva)'!AD83 -> 7226259 | D38: 0 | E38: =+B38*D38 -> 0
A39: 46874 | B39: =+'Producto No. 2 (Curva)'!AD86 -> 5462581 | D39: 0 | E39: =+B39*D39 -> 0
A40: 46905 | B40: =+'Producto No. 2 (Curva)'!AD89 -> 4678440 | D40: 0 | E40: =+B40*D40 -> 0
A41: 46935 | B41: =+'Producto No. 2 (Curva)'!AD92 -> 4746122 | D41: 0 | E41: =+B41*D41 -> 0
A42: 46966 | B42: =+'Producto No. 2 (Curva)'!AD95 -> 6365062 | D42: 0 | E42: =+B42*D42 -> 0
A43: 46997 | B43: =+'Producto No. 2 (Curva)'!AD98 -> 4241430 | D43: 0 | E43: =+B43*D43 -> 0
A44: 47027 | B44: =+'Producto No. 2 (Curva)'!AD101 -> 4590692 | D44: 0 | E44: =+B44*D44 -> 0
A45: 47058 | B45: =+'Producto No. 2 (Curva)'!AD104 -> 6281282 | D45: 0 | E45: =+B45*D45 -> 0
A46: 47088 | B46: =+'Producto No. 2 (Curva)'!AD107 -> 8446745 | D46: 0 | E46: =+B46*D46 -> 0
A47: TOTALES | B47: =SUM(B11:B46) -> 195007156 | C47: =SUM(C11:C46) -> 195007156 | E47: =SUM(E11:E22) -> 0 | F47: =SUM(F11:F22) -> 0 | G47: =IFERROR(SUMPRODUCT(F11:F22,G11:G22)/SUM(F11:F22),"")
A49: NOTAS:
A50: (1) Oferta válida para la modalidad Pague lo Contratado.
A51: (2) Las cantidades de energía se despacharan de acuerdo a la curva del Despacho Horario producto.
A52: (3) El oferente presentará propuesta correspondiente a un porcentaje (%) para el producto que sea de su interés de la curva descrita en el numeral 19 “Cantidad demandada” de los presentes pliegos.
A53: (4) El oferente deberá garantizar una cobertura mínima de demanda de: Treinta y cinco por ciento (35%) para los meses de enero, febrero, marzo, abril y diciembre y Setenta por ciento (70%) para los meses restantes del año.
A54: (5) Esta oferta podrá cubrir hasta el 100% de cada uno de los meses correspondientes a la demanda requerida por DISPAC S.A. E.S.P. de acuerdo a la curva del Despacho
A55: (6) Los precios ofertados incluyen todos los pagos, cargos, impuestos, estampillas, etc., que el Proponente deba realizar ante cualquier entidad gubernamental, o empresa pública, privada o mixta para entregar la energía en la (s) frontera (s) con el Sistema de Transmisión Nacional – STN.
A56: (7) Los precios ofertados serán a precios de septiembre de 2025 y este será indexado mes a mes con el Índice de Precios al Productor Provisional expedido por el DANE.
A57: (8) El precio máximo a adjudicar estará por debajo al precio que presente DISPAC S.A. E.S.P. en su oferta de reserva.
A58: (9) Las ofertas presentadas y remitidas por el ASIC para cada uno de los productos, serán objeto de evaluación si estás son inferiores al precio de reserva presentado por DISPAC.
A59: (10) El precio ofertado debe ser anual
A61: Oferente
... A65: Calidad del firmante

Sheet Producto No. 2 (Curva)
A1: Año | B1: Mes | C1: # días | D1: TPD | E1: HORA 01 | F1: HORA 02 | G1: HORA 03 | H1: HORA 04 | I1: HORA 05 | J1: HORA 06 | K1: HORA 07 | L1: HORA 08 | M1: HORA 09 | N1: HORA 10 | O1: HORA 11 | P1: HORA 12 | Q1: HORA 13 | R1: HORA 14 | S1: HORA 15 | T1: HORA 16 | U1: HORA 17 | V1: HORA 18 | W1: HORA 19 | X1: HORA 20 | Y1: HORA 21 | Z1: HORA 22 | AA1: HORA 23 | AB1: HORA 24 | AC1: kWh/d | AD1: kWh/mes
A2: 2026 | B2: 1 | C2: 6 | D2: Festivo | E2: =VLOOKUP(E$1,'[1]Demanda requerida 2026'!$CB$74:$DL$97,MATCH(_xlfn.CONCAT(TEXT(DATE($A2,$B2,1),"mmm-yy"),$D2),'[1]Demanda requerida 2026'!$CB$39:$DL$39,0),FALSE) -> 359 | F2: =VLOOKUP(F$1,'[1]Demanda requerida 2026'!$CB$74:$DL$97,MATCH(_xlfn.CONCAT(TEXT(DATE($A2,$B2,1),"mmm-yy"),$D2),'[1]Demanda requerida 2026'!$CB$39:$DL$39,0),FALSE) -> 200 | G2: =VLOOKUP(G$1,'[1]Demanda requerida 2026'!$CB$74:$DL$97,MATCH(_xlfn.CONCAT(TEXT(DATE($A2,$B2,1),"mmm-yy"),$D2),'[1]Demanda requerida 2026'!$CB$39:$DL$39,0),FALSE) -> 200 | H2: =VLOOKUP(H$1,'[1]Demanda requerida 2026'!$CB$74:$DL$97,MATCH(_xlfn.CONCAT(TEXT(DATE($A2,$B2,1),"mmm-yy"),$D2),'[1]Demanda requerida 2026'!$CB$39:$DL$39,0),FALSE) -> 200 | I2: =VLOOKUP(I$1,'[1]Demanda requerida 2026'!$CB$74:$DL$97,MATCH(_xlfn.CONCAT(TEXT(DATE($A2,$B2,1),"mmm-yy"),$D2),'[1]Demanda requerida 2026'!$CB$39:$DL$39,0),FALSE) -> 200 | J2: =VLOOKUP(J$1,'[1]Demanda requerida 2026'!$CB$74:$DL$97,MATCH(_xlfn.CONCAT(TEXT(DATE($A2,$B2,1),"mmm-yy"),$D2),'[1]Demanda requerida 2026'!$CB$39:$DL$39,0),FALSE) -> 200 | K2: =VLOOKUP(K$1,'[1]Demanda requerida 2026'!$CB$74:$DL$97,MATCH(_xlfn.CONCAT(TEXT(DATE($A2,$B2,1),"mmm-yy"),$D2),'[1]Demanda requerida 2026'!$CB$39:$DL$39,0),FALSE) -> 200 | L2: =VLOOKUP(L$1,'[1]Demanda requerida 2026'!$CB$74:$DL$97,MATCH(_xlfn.CONCAT(TEXT(DATE($A2,$B2,1),"mmm-yy"),$D2),'[1]Demanda requerida 2026'!$CB$39:$DL$39,0),FALSE) -> 200 | ... AB2: =VLOOKUP(AB$1,'[1]Demanda requerida 2026'!$CB$74:$DL$97,MATCH(_xlfn.CONCAT(TEXT(DATE($A2,$B2,1),"mmm-yy"),$D2),'[1]Demanda requerida 2026'!$CB$39:$DL$39,0),FALSE) -> 2077 | AC2: =SUM(E2:AB2) -> 75547 | AD2: =+SUMPRODUCT(AC2:AC4,C2:C4) -> 3731047 | AE2: =+SUM(AD2:AD37) -> 63783813
A3: 2026 | B3: 1 | C3: 20 | D3: Ordinario | E3: =VLOOKUP(E$1,'[1]Demanda requerida 2026'!$CB$74:$DL$97,MATCH(_xlfn.CONCAT(TEXT(DATE($A3,$B3,1),"mmm-yy"),$D3),'[1]Demanda requerida 2026'!$CB$39:$DL$39,0),FALSE) -> 370 | F3: =VLOOKUP(F$1,'[1]Demanda requerida 2026'!$CB$74:$DL$97,MATCH(_xlfn.CONCAT(TEXT(DATE($A3,$B3,1),"mmm-yy"),$D3),'[1]Demanda requerida 2026'!$CB$39:$DL$39,0),FALSE) -> 200 | G3: =VLOOKUP(G$1,'[1]Demanda requerida 2026'!$CB$74:$DL$97,MATCH(_xlfn.CONCAT(TEXT(DATE($A3,$B3,1),"mmm-yy"),$D3),'[1]Demanda requerida 2026'!$CB$39:$DL$39,0),FALSE) -> 200 | H3: =VLOOKUP(H$1,'[1]Demanda requerida 2026'!$CB$74:$DL$97,MATCH(_xlfn.CONCAT(TEXT(DATE($A3,$B3,1),"mmm-yy"),$D3),'[1]Demanda requerida 2026'!$CB$39:$DL$39,0),FALSE) -> 200 | I3: =VLOOKUP(I$1,'[1]Demanda requerida 2026'!$CB$74:$DL$97,MATCH(_xlfn.CONCAT(TEXT(DATE($A3,$B3,1),"mmm-yy"),$D3),'[1]Demanda requerida 2026'!$CB$39:$DL$39,0),FALSE) -> 200 | J3: =VLOOKUP(J$1,'[1]Demanda requerida 2026'!$CB$74:$DL$97,MATCH(_xlfn.CONCAT(TEXT(DATE($A3,$B3,1),"mmm-yy"),$D3),'[1]Demanda requerida 2026'!$CB$39:$DL$39,0),FALSE) -> 200 | K3: =VLOOKUP(K$1,'[1]Demanda requerida 2026'!$CB$74:$DL$97,MATCH(_xlfn.CONCAT(TEXT(DATE($A3,$B3,1),"mmm-yy"),$D3),'[1]Demanda requerida 2026'!$CB$39:$DL$39,0),FALSE) -> 200 | L3: =VLOOKUP(L$1,'[1]Demanda requerida 2026'!$CB$74:$DL$97,MATCH(_xlfn.CONCAT(TEXT(DATE($A3,$B3,1),"mmm-yy"),$D3),'[1]Demanda requerida 2026'!$CB$39:$DL$39,0),FALSE) -> 1129 | ... AB3: =VLOOKUP(AB$1,'[1]Demanda requerida 2026'!$CB$74:$DL$97,MATCH(_xlfn.CONCAT(TEXT(DATE($A3,$B3,1),"mmm-yy"),$D3),'[1]Demanda requerida 2026'!$CB$39:$DL$39,0),FALSE) -> 3695 | AC3: =SUM(E3:AB3) -> 132574
A4: 2026 | B4: 1 | C4: 5 | D4: Sábado | E4: =VLOOKUP(E$1,'[1]Demanda requerida 2026'!$CB$74:$DL$97,MATCH(_xlfn.CONCAT(TEXT(DATE($A4,$B4,1),"mmm-yy"),$D4),'[1]Demanda requerida 2026'!$CB$39:$DL$39,0),FALSE) -> 320 | F4: =VLOOKUP(F$1,'[1]Demanda requerida 2026'!$CB$74:$DL$97,MATCH(_xlfn.CONCAT(TEXT(DATE($A4,$B4,1),"mmm-yy"),$D4),'[1]Demanda requerida 2026'!$CB$39:$DL$39,0),FALSE) -> 200 | G4: =VLOOKUP(G$1,'[1]Demanda requerida 2026'!$CB$74:$DL$97,MATCH(_xlfn.CONCAT(TEXT(DATE($A4,$B4,1),"mmm-yy"),$D4),'[1]Demanda requerida 2026'!$CB$39:$DL$39,0),FALSE) -> 200 | H4: =VLOOKUP(H$1,'[1]Demanda requerida 2026'!$CB$74:$DL$97,MATCH(_xlfn.CONCAT(TEXT(DATE($A4,$B4,1),"mmm-yy"),$D4),'[1]Demanda requerida 2026'!$CB$39:$DL$39,0),FALSE) -> 200 | I4: =VLOOKUP(I$1,'[1]Demanda requerida 2026'!$CB$74:$DL$97,MATCH(_xlfn.CONCAT(TEXT(DATE($A4,$B4,1),"mmm-yy"),$D4),'[1]Demanda requerida 2026'!$CB$39:$DL$39,0),FALSE) -> 200 | J4: =VLOOKUP(J$1,'[1]Demanda requerida 2026'!$CB$74:$DL$97,MATCH(_xlfn.CONCAT(TEXT(DATE($A4,$B4,1),"mmm-yy"),$D4),'[1]Demanda requerida 2026'!$CB$39:$DL$39,0),FALSE) -> 200 | K4: =VLOOKUP(K$1,'[1]Demanda requerida 2026'!$CB$74:$DL$97,MATCH(_xlfn.CONCAT(TEXT(DATE($A4,$B4,1),"mmm-yy"),$D4),'[1]Demanda requerida 2026'!$CB$39:$DL$39,0),FALSE) -> 200 | L4: =VLOOKUP(L$1,'[1]Demanda requerida 2026'!$CB$74:$DL$97,MATCH(_xlfn.CONCAT(TEXT(DATE($A4,$B4,1),"mmm-yy"),$D4),'[1]Demanda requerida 2026'!$CB$39:$DL$39,0),FALSE) -> 293 | ... AB4: =VLOOKUP(AB$1,'[1]Demanda requerida 2026'!$CB$74:$DL$97,MATCH(_xlfn.CONCAT(TEXT(DATE($A4,$B4,1),"mmm-yy"),$D4),'[1]Demanda requerida 2026'!$CB$39:$DL$39,0),FALSE) -> 3943 | AC4: =SUM(E4:AB4) -> 125257
A5: 2026 | B5: 2 | C5: 4 | D5: Festivo | E5: =VLOOKUP(E$1,'[1]Demanda requerida 2026'!$CB$74:$DL$97,MATCH(_xlfn.CONCAT(TEXT(DATE($A5,$B5,1),"mmm-yy"),$D5),'[1]Demanda requerida 2026'!$CB$39:$DL$39,0),FALSE) -> 363 | F5: =VLOOKUP(F$1,'[1]Demanda requerida 2026'!$CB$74:$DL$97,MATCH(_xlfn.CONCAT(TEXT(DATE($A5,$B5,1),"mmm-yy"),$D5),'[1]Demanda requerida 2026'!$CB$39:$DL$39,0),FALSE) -> 200 | G5: =VLOOKUP(G$1,'[1]Demanda requerida 2026'!$CB$74:$DL$97,MATCH(_xlfn.CONCAT(TEXT(DATE($A5,$B5,1),"mmm-yy"),$D5),'[1]Demanda requerida 2026'!$CB$39:$DL$39,0),FALSE) -> 200 | H5: =VLOOKUP(H$1,'[1]Demanda requerida 2026'!$CB$74:$DL$97,MATCH(_xlfn.CONCAT(TEXT(DATE($A5,$B5,1),"mmm-yy"),$D5),'[1]Demanda requerida 2026'!$CB$39:$DL$39,0),FALSE) -> 200 | I5: =VLOOKUP(I$1,'[1]Demanda requerida 2026'!$CB$74:$DL$97,MATCH(_xlfn.CONCAT(TEXT(DATE($A5,$B5,1),"mmm-yy"),$D5),'[1]Demanda requerida 2026'!$CB$39:$DL$39,0),FALSE) -> 200 | J5: =VLOOKUP(J$1,'[1]Demanda requerida 2026'!$CB$74:$DL$97,MATCH(_xlfn.CONCAT(TEXT(DATE($A5,$B5,1),"mmm-yy"),$D5),'[1]Demanda requerida 2026'!$CB$39:$DL$39,0),FALSE) -> 200 | K5: =VLOOKUP(K$1,'[1]Demanda requerida 2026'!$CB$74:$DL$97,MATCH(_xlfn.CONCAT(TEXT(DATE($A5,$B5,1),"mmm-yy"),$D5),'[1]Demanda requerida 2026'!$CB$39:$DL$39,0),FALSE) -> 200 | L5: =VLOOKUP(L$1,'[1]Demanda requerida 2026'!$CB$74:$DL$97,MATCH(_xlfn.CONCAT(TEXT(DATE($A5,$B5,1),"mmm-yy"),$D5),'[1]Demanda requerida 2026'!$CB$39:$DL$39,0),FALSE) -> 200 | ... AB5: =VLOOKUP(AB$1,'[1]Demanda requerida 2026'!$CB$74:$DL$97,MATCH(_xlfn.CONCAT(TEXT(DATE($A5,$B5,1),"mmm-yy"),$D5),'[1]Demanda requerida 2026'!$CB$39:$DL$39,0),FALSE) -> 2335 | AC5: =SUM(E5:AB5) -> 91958 | AD5: =+SUMPRODUCT(AC5:AC7,C5:C7) -> 3372840
A6: 2026 | B6: 2 | C6: 20 | D6: Ordinario | E6: =VLOOKUP(E$1,'[1]Demanda requerida 2026'!$CB$74:$DL$97,MATCH(_xlfn.CONCAT(TEXT(DATE($A6,$B6,1),"mmm-yy"),$D6),'[1]Demanda requerida 2026'!$CB$39:$DL$39,0),FALSE) -> 200 | F6: =VLOOKUP(F$1,'[1]Demanda requerida 2026'!$CB$74:$DL$97,MATCH(_xlfn.CONCAT(TEXT(DATE($A6,$B6,1),"mmm-yy"),$D6),'[1]Demanda requerida 2026'!$CB$39:$DL$39,0),FALSE) -> 200 | G6: =VLOOKUP(G$1,'[1]Demanda requerida 2026'!$CB$74:$DL$97,MATCH(_xlfn.CONCAT(TEXT(DATE($A6,$B6,1),"mmm-yy"),$D6),'[1]Demanda requerida 2026'!$CB$39:$DL$39,0),FALSE) -> 200 | H6: =VLOOKUP(H$1,'[1]Demanda requerida 2026'!$CB$74:$DL$97,MATCH(_xlfn.CONCAT(TEXT(DATE($A6,$B6,1),"mmm-yy"),$D6),'[1]Demanda requerida 2026'!$CB$39:$DL$39,0),FALSE) -> 200 | I6: =VLOOKUP(I$1,'[1]Demanda requerida 2026'!$CB$74:$DL$97,MATCH(_xlfn.CONCAT(TEXT(DATE($A6,$B6,1),"mmm-yy"),$D6),'[1]Demanda requerida 2026'!$CB$39:$DL$39,0),FALSE) -> 200 | J6: =VLOOKUP(J$1,'[1]Demanda requerida 2026'!$CB$74:$DL$97,MATCH(_xlfn.CONCAT(TEXT(DATE($A6,$B6,1),"mmm-yy"),$D6),'[1]Demanda requerida 2026'!$CB$39:$DL$39,0),FALSE) -> 200 | K6: =VLOOKUP(K$1,'[1]Demanda requerida 2026'!$CB$74:$DL$97,MATCH(_xlfn.CONCAT(TEXT(DATE($A6,$B6,1),"mmm-yy"),$D6),'[1]Demanda requerida 2026'!$CB$39:$DL$39,0),FALSE) -> 731 | L6: =VLOOKUP(L$1,'[1]Demanda requerida 2026'!$CB$74:$DL$97,MATCH(_xlfn.CONCAT(TEXT(DATE($A6,$B6,1),"mmm-yy"),$D6),'[1]Demanda requerida 2026'!$CB$39:$DL$39,0),FALSE) -> 1701 | ... AB6: =VLOOKUP(AB$1,'[1]Demanda requerida 2026'!$CB$74:$DL$97,MATCH(_xlfn.CONCAT(TEXT(DATE($A6,$B6,1),"mmm-yy"),$D6),'[1]Demanda requerida 2026'!$CB$39:$DL$39,0),FALSE) -> 2489 | AC6: =SUM(E6:AB6) -> 127959
A7: 2026 | B7: 2 | C7: 4 | D7: Sábado | E7: =VLOOKUP(E$1,'[1]Demanda requerida 2026'!$CB$74:$DL$97,MATCH(_xlfn.CONCAT(TEXT(DATE($A7,$B7,1),"mmm-yy"),$D7),'[1]Demanda requerida 2026'!$CB$39:$DL$39,0),FALSE) -> 200 | F7: =VLOOKUP(F$1,'[1]Demanda requerida 2026'!$CB$74:$DL$97,MATCH(_xlfn.CONCAT(TEXT(DATE($A7,$B7,1),"mmm-yy"),$D7),'[1]Demanda requerida 2026'!$CB$39:$DL$39,0),FALSE) -> 200 | G7: =VLOOKUP(G$1,'[1]Demanda requerida 2026'!$CB$74:$DL$97,MATCH(_xlfn.CONCAT(TEXT(DATE($A7,$B7,1),"mmm-yy"),$D7),'[1]Demanda requerida 2026'!$CB$39:$DL$39,0),FALSE) -> 200 | H7: =VLOOKUP(H$1,'[1]Demanda requerida 2026'!$CB$74:$DL$97,MATCH(_xlfn.CONCAT(TEXT(DATE($A7,$B7,1),"mmm-yy"),$D7),'[1]Demanda requerida 2026'!$CB$39:$DL$39,0),FALSE) -> 200 | I7: =VLOOKUP(I$1,'[1]Demanda requerida 2026'!$CB$74:$DL$97,MATCH(_xlfn.CONCAT(TEXT(DATE($A7,$B7,1),"mmm-yy"),$D7),'[1]Demanda requerida 2026'!$CB$39:$DL$39,0),FALSE) -> 200 | J7: =VLOOKUP(J$1,'[1]Demanda requerida 2026'!$CB$74:$DL$97,MATCH(_xlfn.CONCAT(TEXT(DATE($A7,$B7,1),"mmm-yy"),$D7),'[1]Demanda requerida 2026'!$CB$39:$DL$39,0),FALSE) -> 200 | K7: =VLOOKUP(K$1,'[1]Demanda requerida 2026'!$CB$74:$DL$97,MATCH(_xlfn.CONCAT(TEXT(DATE($A7,$B7,1),"mmm-yy"),$D7),'[1]Demanda requerida 2026'!$CB$39:$DL$39,0),FALSE) -> 200 | L7: =VLOOKUP(L$1,'[1]Demanda requerida 2026'!$CB$74:$DL$97,MATCH(_xlfn.CONCAT(TEXT(DATE($A7,$B7,1),"mmm-yy"),$D7),'[1]Demanda requerida 2026'!$CB$39:$DL$39,0),FALSE) -> 83 | ... AB7: =VLOOKUP(AB$1,'[1]Demanda requerida 2026'!$CB$74:$DL$97,MATCH(_xlfn.CONCAT(TEXT(DATE($A7,$B7,1),"mmm-yy"),$D7),'[1]Demanda requerida 2026'!$CB$39:$DL$39,0),FALSE) -> 3233 | AC7: =SUM(E7:AB7) -> 111457
A8: 2026 | B8: 3 | C8: 6 | D8: Festivo | E8: =VLOOKUP(E$1,'[1]Demanda requerida 2026'!$CB$74:$DL$97,MATCH(_xlfn.CONCAT(TEXT(DATE($A8,$B8,1),"mmm-yy"),$D8),'[1]Demanda requerida 2026'!$CB$39:$DL$39,0),FALSE) -> 200 | F8: =VLOOKUP(F$1,'[1]Demanda requerida 2026'!$CB$74:$DL$97,MATCH(_xlfn.CONCAT(TEXT(DATE($A8,$B8,1),"mmm-yy"),$D8),'[1]Demanda requerida 2026'!$CB$39:$DL$39,0),FALSE) -> 200 | G8: =VLOOKUP(G$1,'[1]Demanda requerida 2026'!$CB$74:$DL$97,MATCH(_xlfn.CONCAT(TEXT(DATE($A8,$B8,1),"mmm-yy"),$D8),'[1]Demanda requerida 2026'!$CB$39:$DL$39,0),FALSE) -> 200 | H8: =VLOOKUP(H$1,'[1]Demanda requerida 2026'!$CB$74:$DL$97,MATCH(_xlfn.CONCAT(TEXT(DATE($A8,$B8,1),"mmm-yy"),$D8),'[1]Demanda requerida 2026'!$CB$39:$DL$39,0),FALSE) -> 200 | I8: =VLOOKUP(I$1,'[1]Demanda requerida 2026'!$CB$74:$DL$97,MATCH(_xlfn.CONCAT(TEXT(DATE($A8,$B8,1),"mmm-yy"),$D8),'[1]Demanda requerida 2026'!$CB$39:$DL$39,0),FALSE) -> 200 | J8: =VLOOKUP(J$1,'[1]Demanda requerida 2026'!$CB$74:$DL$97,MATCH(_xlfn.CONCAT(TEXT(DATE($A8,$B8,1),"mmm-yy"),$D8),'[1]Demanda requerida 2026'!$CB$39:$DL$39,0),FALSE) -> 200 | K8: =VLOOKUP(K$1,'[1]Demanda requerida 2026'!$CB$74:$DL$97,MATCH(_xlfn.CONCAT(TEXT(DATE($A8,$B8,1),"mmm-yy"),$D8),'[1]Demanda requerida 2026'!$CB$39:$DL$39,0),FALSE) -> 200 | L8: =VLOOKUP(L$1,'[1]Demanda requerida 2026'!$CB$74:$DL$97,MATCH(_xlfn.CONCAT(TEXT(DATE($A8,$B8,1),"mmm-yy"),$D8),'[1]Demanda requerida 2026'!$CB$39:$DL$39,0),FALSE) -> 200 | ... AB8: =VLOOKUP(AB$1,'[1]Demanda requerida 2026'!$CB$74:$DL$97,MATCH(_xlfn.CONCAT(TEXT(DATE($A8,$B8,1),"mmm-yy"),$D8),'[1]Demanda requerida 2026'!$CB$39:$DL$39,0),FALSE) -> 200 | AC8: =SUM(E8:AB8) -> 25913 | AD8: =+SUMPRODUCT(AC8:AC10,C8:C10) -> 4477313
A9: 2026 | B9: 3 | C9: 21 | D9: Ordinario | E9: =VLOOKUP(E$1,'[1]Demanda requerida 2026'!$CB$74:$DL$97,MATCH(_xlfn.CONCAT(TEXT(DATE($A9,$B9,1),"mmm-yy"),$D9),'[1]Demanda requerida 2026'!$CB$39:$DL$39,0),FALSE) -> 1777 | F9: =VLOOKUP(F$1,'[1]Demanda requerida 2026'!$CB$74:$DL$97,MATCH(_xlfn.CONCAT(TEXT(DATE($A9,$B9,1),"mmm-yy"),$D9),'[1]Demanda requerida 2026'!$CB$39:$DL$39,0),FALSE) -> 709 | G9: =VLOOKUP(G$1,'[1]Demanda requerida 2026'!$CB$74:$DL$97,MATCH(_xlfn.CONCAT(TEXT(DATE($A9,$B9,1),"mmm-yy"),$D9),'[1]Demanda requerida 2026'!$CB$39:$DL$39,0),FALSE) -> 200 | H9: =VLOOKUP(H$1,'[1]Demanda requerida 2026'!$CB$74:$DL$97,MATCH(_xlfn.CONCAT(TEXT(DATE($A9,$B9,1),"mmm-yy"),$D9),'[1]Demanda requerida 2026'!$CB$39:$DL$39,0),FALSE) -> 200 | I9: =VLOOKUP(I$1,'[1]Demanda requerida 2026'!$CB$74:$DL$97,MATCH(_xlfn.CONCAT(TEXT(DATE($A9,$B9,1),"mmm-yy"),$D9),'[1]Demanda requerida 2026'!$CB$39:$DL$39,0),FALSE) -> 200 | J9: =VLOOKUP(J$1,'[1]Demanda requerida 2026'!$CB$74:$DL$97,MATCH(_xlfn.CONCAT(TEXT(DATE($A9,$B9,1),"mmm-yy"),$D9),'[1]Demanda requerida 2026'!$CB$39:$DL$39,0),FALSE) -> 938 | K9: =VLOOKUP(K$1,'[1]Demanda requerida 2026'!$CB$74:$DL$97,MATCH(_xlfn.CONCAT(TEXT(DATE($A9,$B9,1),"mmm-yy"),$D9),'[1]Demanda requerida 2026'!$CB$39:$DL$39,0),FALSE) -> 2484 | L9: =VLOOKUP(L$1,'[1]Demanda requerida 2026'!$CB$74:$DL$97,MATCH(_xlfn.CONCAT(TEXT(DATE($A9,$B9,1),"mmm-yy"),$D9),'[1]Demanda requerida 2026'!$CB$39:$DL$39,0),FALSE) -> 3865 | ... AB9: =VLOOKUP(AB$1,'[1]Demanda requerida 2026'!$CB$74:$DL$97,MATCH(_xlfn.CONCAT(TEXT(DATE($A9,$B9,1),"mmm-yy"),$D9),'[1]Demanda requerida 2026'!$CB$39:$DL$39,0),FALSE) -> 5081 | AC9: =SUM(E9:AB9) -> 178963
A10: 2026 | B10: 3 | C10: 4 | D10: Sábado | E10: =VLOOKUP(E$1,'[1]Demanda requerida 2026'!$CB$74:$DL$97,MATCH(_xlfn.CONCAT(TEXT(DATE($A10,$B10,1),"mmm-yy"),$D10),'[1]Demanda requerida 2026'!$CB$39:$DL$39,0),FALSE) -> 424 | F10: =VLOOKUP(F$1,'[1]Demanda requerida 2026'!$CB$74:$DL$97,MATCH(_xlfn.CONCAT(TEXT(DATE($A10,$B10,1),"mmm-yy"),$D10),'[1]Demanda requerida 2026'!$CB$39:$DL$39,0),FALSE) -> 200 | G10: =VLOOKUP(G$1,'[1]Demanda requerida 2026'!$CB$74:$DL$97,MATCH(_xlfn.CONCAT(TEXT(DATE($A10,$B10,1),"mmm-yy"),$D10),'[1]Demanda requerida 2026'!$CB$39:$DL$39,0),FALSE) -> 200 | H10: =VLOOKUP(H$1,'[1]Demanda requerida 2026'!$CB$74:$DL$97,MATCH(_xlfn.CONCAT(TEXT(DATE($A10,$B10,1),"mmm-yy"),$D10),'[1]Demanda requerida 2026'!$CB$39:$DL$39,0),FALSE) -> 200 | I10: =VLOOKUP(I$1,'[1]Demanda requerida 2026'!$CB$74:$DL$97,MATCH(_xlfn.CONCAT(TEXT(DATE($A10,$B10,1),"mmm-yy"),$D10),'[1]Demanda requerida 2026'!$CB$39:$DL$39,0),FALSE) -> 200 | J10: =VLOOKUP(J$1,'[1]Demanda requerida 2026'!$CB$74:$DL$97,MATCH(_xlfn.CONCAT(TEXT(DATE($A10,$B10,1),"mmm-yy"),$D10),'[1]Demanda requerida 2026'!$CB$39:$DL$39,0),FALSE) -> 200 | K10: =VLOOKUP(K$1,'[1]Demanda requerida 2026'!$CB$74:$DL$97,MATCH(_xlfn.CONCAT(TEXT(DATE($A10,$B10,1),"mmm-yy"),$D10),'[1]Demanda requerida 2026'!$CB$39:$DL$39,0),FALSE) -> 200 | L10: =VLOOKUP(L$1,'[1]Demanda requerida 2026'!$CB$74:$DL$97,MATCH(_xlfn.CONCAT(TEXT(DATE($A10,$B10,1),"mmm-yy"),$D10),'[1]Demanda requerida 2026'!$CB$39:$DL$39,0),FALSE) -> 590 | ... AB10: =VLOOKUP(AB$1,'[1]Demanda requerida 2026'!$CB$74:$DL$97,MATCH(_xlfn.CONCAT(TEXT(DATE($A10,$B10,1),"mmm-yy"),$D10),'[1]Demanda requerida 2026'!$CB$39:$DL$39,0),FALSE) -> 5349 | AC10: =SUM(E10:AB10) -> 140903
A11: 2026 | B11: 4 | C11: 6 | D11: Festivo | E11: =VLOOKUP(E$1,'[1]Demanda requerida 2026'!$CB$74:$DL$97,MATCH(_xlfn.CONCAT(TEXT(DATE($A11,$B11,1),"mmm-yy"),$D11),'[1]Demanda requerida 2026'!$CB$39:$DL$39,0),FALSE) -> 200 | F11: =VLOOKUP(F$1,'[1]Demanda requerida 2026'!$CB$74:$DL$97,MATCH(_xlfn.CONCAT(TEXT(DATE($A11,$B11,1),"mmm-yy"),$D11),'[1]Demanda requerida 2026'!$CB$39:$DL$39,0),FALSE) -> 200 | G11: =VLOOKUP(G$1,'[1]Demanda requerida 2026'!$CB$74:$DL$97,MATCH(_xlfn.CONCAT(TEXT(DATE($A11,$B11,1),"mmm-yy"),$D11),'[1]Demanda requerida 2026'!$CB$39:$DL$39,0),FALSE) -> 200 | H11: =VLOOKUP(H$1,'[1]Demanda requerida 2026'!$CB$74:$DL$97,MATCH(_xlfn.CONCAT(TEXT(DATE($A11,$B11,1),"mmm-yy"),$D11),'[1]Demanda requerida 2026'!$CB$39:$DL$39,0),FALSE) -> 200 | I11: =VLOOKUP(I$1,'[1]Demanda requerida 2026'!$CB$74:$DL$97,MATCH(_xlfn.CONCAT(TEXT(DATE($A11,$B11,1),"mmm-yy"),$D11),'[1]Demanda requerida 2026'!$CB$39:$DL$39,0),FALSE) -> 200 | J11: =VLOOKUP(J$1,'[1]Demanda requerida 2026'!$CB$74:$DL$97,MATCH(_xlfn.CONCAT(TEXT(DATE($A11,$B11,1),"mmm-yy"),$D11),'[1]Demanda requerida 2026'!$CB$39:$DL$39,0),FALSE) -> 200 | K11: =VLOOKUP(K$1,'[1]Demanda requerida 2026'!$CB$74:$DL$97,MATCH(_xlfn.CONCAT(TEXT(DATE($A11,$B11,1),"mmm-yy"),$D11),'[1]Demanda requerida 2026'!$CB$39:$DL$39,0),FALSE) -> 200 | L11: =VLOOKUP(L$1,'[1]Demanda requerida 2026'!$CB$74:$DL$97,MATCH(_xlfn.CONCAT(TEXT(DATE($A11,$B11,1),"mmm-yy"),$D11),'[1]Demanda requerida 2026'!$CB$39:$DL$39,0),FALSE) -> 200 | ... AB11: =VLOOKUP(AB$1,'[1]Demanda requerida 2026'!$CB$74:$DL$97,MATCH(_xlfn.CONCAT(TEXT(DATE($A11,$B11,1),"mmm-yy"),$D11),'[1]Demanda requerida 2026'!$CB$39:$DL$39,0),FALSE) -> 200 | AC11: =SUM(E11:AB11) -> 13045 | AD11: =+SUMPRODUCT(AC11:AC13,C11:C13) -> 7876062
A12: 2026 | B12: 4 | C12: 20 | D12: Ordinario | E12: =VLOOKUP(E$1,'[1]Demanda requerida 2026'!$CB$74:$DL$97,MATCH(_xlfn.CONCAT(TEXT(DATE($A12,$B12,1),"mmm-yy"),$D12),'[1]Demanda requerida 2026'!$CB$39:$DL$39,0),FALSE) -> 8911 | F12: =VLOOKUP(F$1,'[1]Demanda requerida 2026'!$CB$74:$DL$97,MATCH(_xlfn.CONCAT(TEXT(DATE($A12,$B12,1),"mmm-yy"),$D12),'[1]Demanda requerida 2026'!$CB$39:$DL$39,0),FALSE) -> 7740 | G12: =VLOOKUP(G$1,'[1]Demanda requerida 2026'!$CB$74:$DL$97,MATCH(_xlfn.CONCAT(TEXT(DATE($A12,$B12,1),"mmm-yy"),$D12),'[1]Demanda requerida 2026'!$CB$39:$DL$39,0),FALSE) -> 6908 | H12: =VLOOKUP(H$1,'[1]Demanda requerida 2026'!$CB$74:$DL$97,MATCH(_xlfn.CONCAT(TEXT(DATE($A12,$B12,1),"mmm-yy"),$D12),'[1]Demanda requerida 2026'!$CB$39:$DL$39,0),FALSE) -> 6373 | I12: =VLOOKUP(I$1,'[1]Demanda requerida 2026'!$CB$74:$DL$97,MATCH(_xlfn.CONCAT(TEXT(DATE($A12,$B12,1),"mmm-yy"),$D12),'[1]Demanda requerida 2026'!$CB$39:$DL$39,0),FALSE) -> 6223 | J12: =VLOOKUP(J$1,'[1]Demanda requerida 2026'!$CB$74:$DL$97,MATCH(_xlfn.CONCAT(TEXT(DATE($A12,$B12,1),"mmm-yy"),$D12),'[1]Demanda requerida 2026'!$CB$39:$DL$39,0),FALSE) -> 7491 | K12: =VLOOKUP(K$1,'[1]Demanda requerida 2026'!$CB$74:$DL$97,MATCH(_xlfn.CONCAT(TEXT(DATE($A12,$B12,1),"mmm-yy"),$D12),'[1]Demanda requerida 2026'!$CB$39:$DL$39,0),FALSE) -> 8911 | L12: =VLOOKUP(L$1,'[1]Demanda requerida 2026'!$CB$74:$DL$97,MATCH(_xlfn.CONCAT(TEXT(DATE($A12,$B12,1),"mmm-yy"),$D12),'[1]Demanda requerida 2026'!$CB$39:$DL$39,0),FALSE) -> 10696 | ... AB12: =VLOOKUP(AB$1,'[1]Demanda requerida 2026'!$CB$74:$DL$97,MATCH(_xlfn.CONCAT(TEXT(DATE($A12,$B12,1),"mmm-yy"),$D12),'[1]Demanda requerida 2026'!$CB$39:$DL$39,0),FALSE) -> 11750 | AC12: =SUM(E12:AB12) -> 343087
A13: 2026 | B13: 4 | C13: 4 | D13: Sábado | E13: =VLOOKUP(E$1,'[1]Demanda requerida 2026'!$CB$74:$DL$97,MATCH(_xlfn.CONCAT(TEXT(DATE($A13,$B13,1),"mmm-yy"),$D13),'[1]Demanda requerida 2026'!$CB$39:$DL$39,0),FALSE) -> 5841 | F13: =VLOOKUP(F$1,'[1]Demanda requerida 2026'!$CB$74:$DL$97,MATCH(_xlfn.CONCAT(TEXT(DATE($A13,$B13,1),"mmm-yy"),$D13),'[1]Demanda requerida 2026'!$CB$39:$DL$39,0),FALSE) -> 4753 | G13: =VLOOKUP(G$1,'[1]Demanda requerida 2026'!$CB$74:$DL$97,MATCH(_xlfn.CONCAT(TEXT(DATE($A13,$B13,1),"mmm-yy"),$D13),'[1]Demanda requerida 2026'!$CB$39:$DL$39,0),FALSE) -> 3911 | H13: =VLOOKUP(H$1,'[1]Demanda requerida 2026'!$CB$74:$DL$97,MATCH(_xlfn.CONCAT(TEXT(DATE($A13,$B13,1),"mmm-yy"),$D13),'[1]Demanda requerida 2026'!$CB$39:$DL$39,0),FALSE) -> 3431 | I13: =VLOOKUP(I$1,'[1]Demanda requerida 2026'!$CB$74:$DL$97,MATCH(_xlfn.CONCAT(TEXT(DATE($A13,$B13,1),"mmm-yy"),$D13),'[1]Demanda requerida 2026'!$CB$39:$DL$39,0),FALSE) -> 3204 | J13: =VLOOKUP(J$1,'[1]Demanda requerida 2026'!$CB$74:$DL$97,MATCH(_xlfn.CONCAT(TEXT(DATE($A13,$B13,1),"mmm-yy"),$D13),'[1]Demanda requerida 2026'!$CB$39:$DL$39,0),FALSE) -> 3368 | K13: =VLOOKUP(K$1,'[1]Demanda requerida 2026'!$CB$74:$DL$97,MATCH(_xlfn.CONCAT(TEXT(DATE($A13,$B13,1),"mmm-yy"),$D13),'[1]Demanda requerida 2026'!$CB$39:$DL$39,0),FALSE) -> 2010 | L13: =VLOOKUP(L$1,'[1]Demanda requerida 2026'!$CB$74:$DL$97,MATCH(_xlfn.CONCAT(TEXT(DATE($A13,$B13,1),"mmm-yy"),$D13),'[1]Demanda requerida 2026'!$CB$39:$DL$39,0),FALSE) -> 6004 | ... AB13: =VLOOKUP(AB$1,'[1]Demanda requerida 2026'!$CB$74:$DL$97,MATCH(_xlfn.CONCAT(TEXT(DATE($A13,$B13,1),"mmm-yy"),$D13),'[1]Demanda requerida 2026'!$CB$39:$DL$39,0),FALSE) -> 9357 | AC13: =SUM(E13:AB13) -> 234013
A14: 2026 | B14: 5 | C14: 7 | D14: Festivo | E14: =VLOOKUP(E$1,'[1]Demanda requerida 2026'!$CB$74:$DL$97,MATCH(_xlfn.CONCAT(TEXT(DATE($A14,$B14,1),"mmm-yy"),$D14),'[1]Demanda requerida 2026'!$CB$39:$DL$39,0),FALSE) -> 200 | F14: =VLOOKUP(F$1,'[1]Demanda requerida 2026'!$CB$74:$DL$97,MATCH(_xlfn.CONCAT(TEXT(DATE($A14,$B14,1),"mmm-yy"),$D14),'[1]Demanda requerida 2026'!$CB$39:$DL$39,0),FALSE) -> 200 | G14: =VLOOKUP(G$1,'[1]Demanda requerida 2026'!$CB$74:$DL$97,MATCH(_xlfn.CONCAT(TEXT(DATE($A14,$B14,1),"mmm-yy"),$D14),'[1]Demanda requerida 2026'!$CB$39:$DL$39,0),FALSE) -> 200 | H14: =VLOOKUP(H$1,'[1]Demanda requerida 2026'!$CB$74:$DL$97,MATCH(_xlfn.CONCAT(TEXT(DATE($A14,$B14,1),"mmm-yy"),$D14),'[1]Demanda requerida 2026'!$CB$39:$DL$39,0),FALSE) -> 200 | I14: =VLOOKUP(I$1,'[1]Demanda requerida 2026'!$CB$74:$DL$97,MATCH(_xlfn.CONCAT(TEXT(DATE($A14,$B14,1),"mmm-yy"),$D14),'[1]Demanda requerida 2026'!$CB$39:$DL$39,0),FALSE) -> 200 | J14: =VLOOKUP(J$1,'[1]Demanda requerida 2026'!$CB$74:$DL$97,MATCH(_xlfn.CONCAT(TEXT(DATE($A14,$B14,1),"mmm-yy"),$D14),'[1]Demanda requerida 2026'!$CB$39:$DL$39,0),FALSE) -> 200 | K14: =VLOOKUP(K$1,'[1]Demanda requerida 2026'!$CB$74:$DL$97,MATCH(_xlfn.CONCAT(TEXT(DATE($A14,$B14,1),"mmm-yy"),$D14),'[1]Demanda requerida 2026'!$CB$39:$DL$39,0),FALSE) -> 200 | L14: =VLOOKUP(L$1,'[1]Demanda requerida 2026'!$CB$74:$DL$97,MATCH(_xlfn.CONCAT(TEXT(DATE($A14,$B14,1),"mmm-yy"),$D14),'[1]Demanda requerida 2026'!$CB$39:$DL$39,0),FALSE) -> 200 | ... AB14: =VLOOKUP(AB$1,'[1]Demanda requerida 2026'!$CB$74:$DL$97,MATCH(_xlfn.CONCAT(TEXT(DATE($A14,$B14,1),"mmm-yy"),$D14),'[1]Demanda requerida 2026'!$CB$39:$DL$39,0),FALSE) -> 200 | AC14: =SUM(E14:AB14) -> 17825 | AD14: =+SUMPRODUCT(AC14:AC16,C14:C16) -> 6714696
A15: 2026 | B15: 5 | C15: 19 | D15: Ordinario | E15: =VLOOKUP(E$1,'[1]Demanda requerida 2026'!$CB$74:$DL$97,MATCH(_xlfn.CONCAT(TEXT(DATE($A15,$B15,1),"mmm-yy"),$D15),'[1]Demanda requerida 2026'!$CB$39:$DL$39,0),FALSE) -> 6143 | F15: =VLOOKUP(F$1,'[1]Demanda requerida 2026'!$CB$74:$DL$97,MATCH(_xlfn.CONCAT(TEXT(DATE($A15,$B15,1),"mmm-yy"),$D15),'[1]Demanda requerida 2026'!$CB$39:$DL$39,0),FALSE) -> 4740 | G15: =VLOOKUP(G$1,'[1]Demanda requerida 2026'!$CB$74:$DL$97,MATCH(_xlfn.CONCAT(TEXT(DATE($A15,$B15,1),"mmm-yy"),$D15),'[1]Demanda requerida 2026'!$CB$39:$DL$39,0),FALSE) -> 3955 | H15: =VLOOKUP(H$1,'[1]Demanda requerida 2026'!$CB$74:$DL$97,MATCH(_xlfn.CONCAT(TEXT(DATE($A15,$B15,1),"mmm-yy"),$D15),'[1]Demanda requerida 2026'!$CB$39:$DL$39,0),FALSE) -> 3534 | I15: =VLOOKUP(I$1,'[1]Demanda requerida 2026'!$CB$74:$DL$97,MATCH(_xlfn.CONCAT(TEXT(DATE($A15,$B15,1),"mmm-yy"),$D15),'[1]Demanda requerida 2026'!$CB$39:$DL$39,0),FALSE) -> 3553 | J15: =VLOOKUP(J$1,'[1]Demanda requerida 2026'!$CB$74:$DL$97,MATCH(_xlfn.CONCAT(TEXT(DATE($A15,$B15,1),"mmm-yy"),$D15),'[1]Demanda requerida 2026'!$CB$39:$DL$39,0),FALSE) -> 4740 | K15: =VLOOKUP(K$1,'[1]Demanda requerida 2026'!$CB$74:$DL$97,MATCH(_xlfn.CONCAT(TEXT(DATE($A15,$B15,1),"mmm-yy"),$D15),'[1]Demanda requerida 2026'!$CB$39:$DL$39,0),FALSE) -> 6235 | L15: =VLOOKUP(L$1,'[1]Demanda requerida 2026'!$CB$74:$DL$97,MATCH(_xlfn.CONCAT(TEXT(DATE($A15,$B15,1),"mmm-yy"),$D15),'[1]Demanda requerida 2026'!$CB$39:$DL$39,0),FALSE) -> 7989 | ... AB15: =VLOOKUP(AB$1,'[1]Demanda requerida 2026'!$CB$74:$DL$97,MATCH(_xlfn.CONCAT(TEXT(DATE($A15,$B15,1),"mmm-yy"),$D15),'[1]Demanda requerida 2026'!$CB$39:$DL$39,0),FALSE) -> 9902 | AC15: =SUM(E15:AB15) -> 291344
A16: 2026 | B16: 5 | C16: 5 | D16: Sábado | E16: =VLOOKUP(E$1,'[1]Demanda requerida 2026'!$CB$74:$DL$97,MATCH(_xlfn.CONCAT(TEXT(DATE($A16,$B16,1),"mmm-yy"),$D16),'[1]Demanda requerida 2026'!$CB$39:$DL$39,0),FALSE) -> 4602 | F16: =VLOOKUP(F$1,'[1]Demanda requerida 2026'!$CB$74:$DL$97,MATCH(_xlfn.CONCAT(TEXT(DATE($A16,$B16,1),"mmm-yy"),$D16),'[1]Demanda requerida 2026'!$CB$39:$DL$39,0),FALSE) -> 3403 | G16: =VLOOKUP(G$1,'[1]Demanda requerida 2026'!$CB$74:$DL$97,MATCH(_xlfn.CONCAT(TEXT(DATE($A16,$B16,1),"mmm-yy"),$D16),'[1]Demanda requerida 2026'!$CB$39:$DL$39,0),FALSE) -> 2648 | H16: =VLOOKUP(H$1,'[1]Demanda requerida 2026'!$CB$74:$DL$97,MATCH(_xlfn.CONCAT(TEXT(DATE($A16,$B16,1),"mmm-yy"),$D16),'[1]Demanda requerida 2026'!$CB$39:$DL$39,0),FALSE) -> 2117 | I16: =VLOOKUP(I$1,'[1]Demanda requerida 2026'!$CB$74:$DL$97,MATCH(_xlfn.CONCAT(TEXT(DATE($A16,$B16,1),"mmm-yy"),$D16),'[1]Demanda requerida 2026'!$CB$39:$DL$39,0),FALSE) -> 1967 | J16: =VLOOKUP(J$1,'[1]Demanda requerida 2026'!$CB$74:$DL$97,MATCH(_xlfn.CONCAT(TEXT(DATE($A16,$B16,1),"mmm-yy"),$D16),'[1]Demanda requerida 2026'!$CB$39:$DL$39,0),FALSE) -> 2200 | K16: =VLOOKUP(K$1,'[1]Demanda requerida 2026'!$CB$74:$DL$97,MATCH(_xlfn.CONCAT(TEXT(DATE($A16,$B16,1),"mmm-yy"),$D16),'[1]Demanda requerida 2026'!$CB$39:$DL$39,0),FALSE) -> 2864 | L16: =VLOOKUP(L$1,'[1]Demanda requerida 2026'!$CB$74:$DL$97,MATCH(_xlfn.CONCAT(TEXT(DATE($A16,$B16,1),"mmm-yy"),$D16),'[1]Demanda requerida 2026'!$CB$39:$DL$39,0),FALSE) -> 4872 | ... AB16: =VLOOKUP(AB$1,'[1]Demanda requerida 2026'!$CB$74:$DL$97,MATCH(_xlfn.CONCAT(TEXT(DATE($A16,$B16,1),"mmm-yy"),$D16),'[1]Demanda requerida 2026'!$CB$39:$DL$39,0),FALSE) -> 7180 | AC16: =SUM(E16:AB16) -> 210877
A17: 2026 | B17: 6 | C17: 7 | D17: Festivo | E17: =VLOOKUP(E$1,'[1]Demanda requerida 2026'!$CB$74:$DL$97,MATCH(_xlfn.CONCAT(TEXT(DATE($A17,$B17,1),"mmm-yy"),$D17),'[1]Demanda requerida 2026'!$CB$39:$DL$39,0),FALSE) -> 200 | F17: =VLOOKUP(F$1,'[1]Demanda requerida 2026'!$CB$74:$DL$97,MATCH(_xlfn.CONCAT(TEXT(DATE($A17,$B17,1),"mmm-yy"),$D17),'[1]Demanda requerida 2026'!$CB$39:$DL$39,0),FALSE) -> 200 | G17: =VLOOKUP(G$1,'[1]Demanda requerida 2026'!$CB$74:$DL$97,MATCH(_xlfn.CONCAT(TEXT(DATE($A17,$B17,1),"mmm-yy"),$D17),'[1]Demanda requerida 2026'!$CB$39:$DL$39,0),FALSE) -> 200 | H17: =VLOOKUP(H$1,'[1]Demanda requerida 2026'!$CB$74:$DL$97,MATCH(_xlfn.CONCAT(TEXT(DATE($A17,$B17,1),"mmm-yy"),$D17),'[1]Demanda requerida 2026'!$CB$39:$DL$39,0),FALSE) -> 200 | I17: =VLOOKUP(I$1,'[1]Demanda requerida 2026'!$CB$74:$DL$97,MATCH(_xlfn.CONCAT(TEXT(DATE($A17,$B17,1),"mmm-yy"),$D17),'[1]Demanda requerida 2026'!$CB$39:$DL$39,0),FALSE) -> 200 | J17: =VLOOKUP(J$1,'[1]Demanda requerida 2026'!$CB$74:$DL$97,MATCH(_xlfn.CONCAT(TEXT(DATE($A17,$B17,1),"mmm-yy"),$D17),'[1]Demanda requerida 2026'!$CB$39:$DL$39,0),FALSE) -> 200 | K17: =VLOOKUP(K$1,'[1]Demanda requerida 2026'!$CB$74:$DL$97,MATCH(_xlfn.CONCAT(TEXT(DATE($A17,$B17,1),"mmm-yy"),$D17),'[1]Demanda requerida 2026'!$CB$39:$DL$39,0),FALSE) -> 200 | L17: =VLOOKUP(L$1,'[1]Demanda requerida 2026'!$CB$74:$DL$97,MATCH(_xlfn.CONCAT(TEXT(DATE($A17,$B17,1),"mmm-yy"),$D17),'[1]Demanda requerida 2026'!$CB$39:$DL$39,0),FALSE) -> 200 | ... AB17: =VLOOKUP(AB$1,'[1]Demanda requerida 2026'!$CB$74:$DL$97,MATCH(_xlfn.CONCAT(TEXT(DATE($A17,$B17,1),"mmm-yy"),$D17),'[1]Demanda requerida 2026'!$CB$39:$DL$39,0),FALSE) -> 200 | AC17: =SUM(E17:AB17) -> 10177 | AD17: =+SUMPRODUCT(AC17:AC19,C17:C19) -> 9456276
A18: 2026 | B18: 6 | C18: 19 | D18: Ordinario | E18: =VLOOKUP(E$1,'[1]Demanda requerida 2026'!$CB$74:$DL$97,MATCH(_xlfn.CONCAT(TEXT(DATE($A18,$B18,1),"mmm-yy"),$D18),'[1]Demanda requerida 2026'!$CB$39:$DL$39,0),FALSE) -> 11434 | F18: =VLOOKUP(F$1,'[1]Demanda requerida 2026'!$CB$74:$DL$97,MATCH(_xlfn.CONCAT(TEXT(DATE($A18,$B18,1),"mmm-yy"),$D18),'[1]Demanda requerida 2026'!$CB$39:$DL$39,0),FALSE) -> 10006 | G18: =VLOOKUP(G$1,'[1]Demanda requerida 2026'!$CB$74:$DL$97,MATCH(_xlfn.CONCAT(TEXT(DATE($A18,$B18,1),"mmm-yy"),$D18),'[1]Demanda requerida 2026'!$CB$39:$DL$39,0),FALSE) -> 9076 | H18: =VLOOKUP(H$1,'[1]Demanda requerida 2026'!$CB$74:$DL$97,MATCH(_xlfn.CONCAT(TEXT(DATE($A18,$B18,1),"mmm-yy"),$D18),'[1]Demanda requerida 2026'!$CB$39:$DL$39,0),FALSE) -> 8564 | I18: =VLOOKUP(I$1,'[1]Demanda requerida 2026'!$CB$74:$DL$97,MATCH(_xlfn.CONCAT(TEXT(DATE($A18,$B18,1),"mmm-yy"),$D18),'[1]Demanda requerida 2026'!$CB$39:$DL$39,0),FALSE) -> 8765 | J18: =VLOOKUP(J$1,'[1]Demanda requerida 2026'!$CB$74:$DL$97,MATCH(_xlfn.CONCAT(TEXT(DATE($A18,$B18,1),"mmm-yy"),$D18),'[1]Demanda requerida 2026'!$CB$39:$DL$39,0),FALSE) -> 9913 | K18: =VLOOKUP(K$1,'[1]Demanda requerida 2026'!$CB$74:$DL$97,MATCH(_xlfn.CONCAT(TEXT(DATE($A18,$B18,1),"mmm-yy"),$D18),'[1]Demanda requerida 2026'!$CB$39:$DL$39,0),FALSE) -> 11616 | L18: =VLOOKUP(L$1,'[1]Demanda requerida 2026'!$CB$74:$DL$97,MATCH(_xlfn.CONCAT(TEXT(DATE($A18,$B18,1),"mmm-yy"),$D18),'[1]Demanda requerida 2026'!$CB$39:$DL$39,0),FALSE) -> 14100 | ... AB18: =VLOOKUP(AB$1,'[1]Demanda requerida 2026'!$CB$74:$DL$97,MATCH(_xlfn.CONCAT(TEXT(DATE($A18,$B18,1),"mmm-yy"),$D18),'[1]Demanda requerida 2026'!$CB$39:$DL$39,0),FALSE) -> 15842 | AC18: =SUM(E18:AB18) -> 430231
A19: 2026 | B19: 6 | C19: 4 | D19: Sábado | E19: =VLOOKUP(E$1,'[1]Demanda requerida 2026'!$CB$74:$DL$97,MATCH(_xlfn.CONCAT(TEXT(DATE($A19,$B19,1),"mmm-yy"),$D19),'[1]Demanda requerida 2026'!$CB$39:$DL$39,0),FALSE) -> 6784 | F19: =VLOOKUP(F$1,'[1]Demanda requerida 2026'!$CB$74:$DL$97,MATCH(_xlfn.CONCAT(TEXT(DATE($A19,$B19,1),"mmm-yy"),$D19),'[1]Demanda requerida 2026'!$CB$39:$DL$39,0),FALSE) -> 6086 | G19: =VLOOKUP(G$1,'[1]Demanda requerida 2026'!$CB$74:$DL$97,MATCH(_xlfn.CONCAT(TEXT(DATE($A19,$B19,1),"mmm-yy"),$D19),'[1]Demanda requerida 2026'!$CB$39:$DL$39,0),FALSE) -> 5703 | H19: =VLOOKUP(H$1,'[1]Demanda requerida 2026'!$CB$74:$DL$97,MATCH(_xlfn.CONCAT(TEXT(DATE($A19,$B19,1),"mmm-yy"),$D19),'[1]Demanda requerida 2026'!$CB$39:$DL$39,0),FALSE) -> 5076 | I19: =VLOOKUP(I$1,'[1]Demanda requerida 2026'!$CB$74:$DL$97,MATCH(_xlfn.CONCAT(TEXT(DATE($A19,$B19,1),"mmm-yy"),$D19),'[1]Demanda requerida 2026'!$CB$39:$DL$39,0),FALSE) -> 4845 | J19: =VLOOKUP(J$1,'[1]Demanda requerida 2026'!$CB$74:$DL$97,MATCH(_xlfn.CONCAT(TEXT(DATE($A19,$B19,1),"mmm-yy"),$D19),'[1]Demanda requerida 2026'!$CB$39:$DL$39,0),FALSE) -> 5455 | K19: =VLOOKUP(K$1,'[1]Demanda requerida 2026'!$CB$74:$DL$97,MATCH(_xlfn.CONCAT(TEXT(DATE($A19,$B19,1),"mmm-yy"),$D19),'[1]Demanda requerida 2026'!$CB$39:$DL$39,0),FALSE) -> 6000 | L19: =VLOOKUP(L$1,'[1]Demanda requerida 2026'!$CB$74:$DL$97,MATCH(_xlfn.CONCAT(TEXT(DATE($A19,$B19,1),"mmm-yy"),$D19),'[1]Demanda requerida 2026'!$CB$39:$DL$39,0),FALSE) -> 8204 | ... AB19: =VLOOKUP(AB$1,'[1]Demanda requerida 2026'!$CB$74:$DL$97,MATCH(_xlfn.CONCAT(TEXT(DATE($A19,$B19,1),"mmm-yy"),$D19),'[1]Demanda requerida 2026'!$CB$39:$DL$39,0),FALSE) -> 13003 | AC19: =SUM(E19:AB19) -> 302662
A20: 2026 | B20: 7 | C20: 5 | D20: Festivo | E20: =VLOOKUP(E$1,'[1]Demanda requerida 2026'!$CB$74:$DL$97,MATCH(_xlfn.CONCAT(TEXT(DATE($A20,$B20,1),"mmm-yy"),$D20),'[1]Demanda requerida 2026'!$CB$39:$DL$39,0),FALSE) -> 200 | F20: =VLOOKUP(F$1,'[1]Demanda requerida 2026'!$CB$74:$DL$97,MATCH(_xlfn.CONCAT(TEXT(DATE($A20,$B20,1),"mmm-yy"),$D20),'[1]Demanda requerida 2026'!$CB$39:$DL$39,0),FALSE) -> 200 | G20: =VLOOKUP(G$1,'[1]Demanda requerida 2026'!$CB$74:$DL$97,MATCH(_xlfn.CONCAT(TEXT(DATE($A20,$B20,1),"mmm-yy"),$D20),'[1]Demanda requerida 2026'!$CB$39:$DL$39,0),FALSE) -> 200 | H20: =VLOOKUP(H$1,'[1]Demanda requerida 2026'!$CB$74:$DL$97,MATCH(_xlfn.CONCAT(TEXT(DATE($A20,$B20,1),"mmm-yy"),$D20),'[1]Demanda requerida 2026'!$CB$39:$DL$39,0),FALSE) -> 200 | I20: =VLOOKUP(I$1,'[1]Demanda requerida 2026'!$CB$74:$DL$97,MATCH(_xlfn.CONCAT(TEXT(DATE($A20,$B20,1),"mmm-yy"),$D20),'[1]Demanda requerida 2026'!$CB$39:$DL$39,0),FALSE) -> 200 | J20: =VLOOKUP(J$1,'[1]Demanda requerida 2026'!$CB$74:$DL$97,MATCH(_xlfn.CONCAT(TEXT(DATE($A20,$B20,1),"mmm-yy"),$D20),'[1]Demanda requerida 2026'!$CB$39:$DL$39,0),FALSE) -> 200 | K20: =VLOOKUP(K$1,'[1]Demanda requerida 2026'!$CB$74:$DL$97,MATCH(_xlfn.CONCAT(TEXT(DATE($A20,$B20,1),"mmm-yy"),$D20),'[1]Demanda requerida 2026'!$CB$39:$DL$39,0),FALSE) -> 200 | L20: =VLOOKUP(L$1,'[1]Demanda requerida 2026'!$CB$74:$DL$97,MATCH(_xlfn.CONCAT(TEXT(DATE($A20,$B20,1),"mmm-yy"),$D20),'[1]Demanda requerida 2026'!$CB$39:$DL$39,0),FALSE) -> 200 | ... AB20: =VLOOKUP(AB$1,'[1]Demanda requerida 2026'!$CB$74:$DL$97,MATCH(_xlfn.CONCAT(TEXT(DATE($A20,$B20,1),"mmm-yy"),$D20),'[1]Demanda requerida 2026'!$CB$39:$DL$39,0),FALSE) -> 200 | AC20: =SUM(E20:AB20) -> 17983 | AD20: =+SUMPRODUCT(AC20:AC22,C20:C22) -> 4460345
A21: 2026 | B21: 7 | C21: 22 | D21: Ordinario | E21: =VLOOKUP(E$1,'[1]Demanda requerida 2026'!$CB$74:$DL$97,MATCH(_xlfn.CONCAT(TEXT(DATE($A21,$B21,1),"mmm-yy"),$D21),'[1]Demanda requerida 2026'!$CB$39:$DL$39,0),FALSE) -> 1980 | F21: =VLOOKUP(F$1,'[1]Demanda requerida 2026'!$CB$74:$DL$97,MATCH(_xlfn.CONCAT(TEXT(DATE($A21,$B21,1),"mmm-yy"),$D21),'[1]Demanda requerida 2026'!$CB$39:$DL$39,0),FALSE) -> 782 | G21: =VLOOKUP(G$1,'[1]Demanda requerida 2026'!$CB$74:$DL$97,MATCH(_xlfn.CONCAT(TEXT(DATE($A21,$B21,1),"mmm-yy"),$D21),'[1]Demanda requerida 2026'!$CB$39:$DL$39,0),FALSE) -> 200 | H21: =VLOOKUP(H$1,'[1]Demanda requerida 2026'!$CB$74:$DL$97,MATCH(_xlfn.CONCAT(TEXT(DATE($A21,$B21,1),"mmm-yy"),$D21),'[1]Demanda requerida 2026'!$CB$39:$DL$39,0),FALSE) -> 200 | I21: =VLOOKUP(I$1,'[1]Demanda requerida 2026'!$CB$74:$DL$97,MATCH(_xlfn.CONCAT(TEXT(DATE($A21,$B21,1),"mmm-yy"),$D21),'[1]Demanda requerida 2026'!$CB$39:$DL$39,0),FALSE) -> 200 | J21: =VLOOKUP(J$1,'[1]Demanda requerida 2026'!$CB$74:$DL$97,MATCH(_xlfn.CONCAT(TEXT(DATE($A21,$B21,1),"mmm-yy"),$D21),'[1]Demanda requerida 2026'!$CB$39:$DL$39,0),FALSE) -> 684 | K21: =VLOOKUP(K$1,'[1]Demanda requerida 2026'!$CB$74:$DL$97,MATCH(_xlfn.CONCAT(TEXT(DATE($A21,$B21,1),"mmm-yy"),$D21),'[1]Demanda requerida 2026'!$CB$39:$DL$39,0),FALSE) -> 2185 | L21: =VLOOKUP(L$1,'[1]Demanda requerida 2026'!$CB$74:$DL$97,MATCH(_xlfn.CONCAT(TEXT(DATE($A21,$B21,1),"mmm-yy"),$D21),'[1]Demanda requerida 2026'!$CB$39:$DL$39,0),FALSE) -> 3769 | ... AB21: =VLOOKUP(AB$1,'[1]Demanda requerida 2026'!$CB$74:$DL$97,MATCH(_xlfn.CONCAT(TEXT(DATE($A21,$B21,1),"mmm-yy"),$D21),'[1]Demanda requerida 2026'!$CB$39:$DL$39,0),FALSE) -> 5126 | AC21: =SUM(E21:AB21) -> 175717
A22: 2026 | B22: 7 | C22: 4 | D22: Sábado | E22: =VLOOKUP(E$1,'[1]Demanda requerida 2026'!$CB$74:$DL$97,MATCH(_xlfn.CONCAT(TEXT(DATE($A22,$B22,1),"mmm-yy"),$D22),'[1]Demanda requerida 2026'!$CB$39:$DL$39,0),FALSE) -> 200 | F22: =VLOOKUP(F$1,'[1]Demanda requerida 2026'!$CB$74:$DL$97,MATCH(_xlfn.CONCAT(TEXT(DATE($A22,$B22,1),"mmm-yy"),$D22),'[1]Demanda requerida 2026'!$CB$39:$DL$39,0),FALSE) -> 200 | G22: =VLOOKUP(G$1,'[1]Demanda requerida 2026'!$CB$74:$DL$97,MATCH(_xlfn.CONCAT(TEXT(DATE($A22,$B22,1),"mmm-yy"),$D22),'[1]Demanda requerida 2026'!$CB$39:$DL$39,0),FALSE) -> 200 | H22: =VLOOKUP(H$1,'[1]Demanda requerida 2026'!$CB$74:$DL$97,MATCH(_xlfn.CONCAT(TEXT(DATE($A22,$B22,1),"mmm-yy"),$D22),'[1]Demanda requerida 2026'!$CB$39:$DL$39,0),FALSE) -> 200 | I22: =VLOOKUP(I$1,'[1]Demanda requerida 2026'!$CB$74:$DL$97,MATCH(_xlfn.CONCAT(TEXT(DATE($A22,$B22,1),"mmm-yy"),$D22),'[1]Demanda requerida 2026'!$CB$39:$DL$39,0),FALSE) -> 200 | J22: =VLOOKUP(J$1,'[1]Demanda requerida 2026'!$CB$74:$DL$97,MATCH(_xlfn.CONCAT(TEXT(DATE($A22,$B22,1),"mmm-yy"),$D22),'[1]Demanda requerida 2026'!$CB$39:$DL$39,0),FALSE) -> 200 | K22: =VLOOKUP(K$1,'[1]Demanda requerida 2026'!$CB$74:$DL$97,MATCH(_xlfn.CONCAT(TEXT(DATE($A22,$B22,1),"mmm-yy"),$D22),'[1]Demanda requerida 2026'!$CB$39:$DL$39,0),FALSE) -> 200 | L22: =VLOOKUP(L$1,'[1]Demanda requerida 2026'!$CB$74:$DL$97,MATCH(_xlfn.CONCAT(TEXT(DATE($A22,$B22,1),"mmm-yy"),$D22),'[1]Demanda requerida 2026'!$CB$39:$DL$39,0),FALSE) -> 632 | ... AB22: =VLOOKUP(AB$1,'[1]Demanda requerida 2026'!$CB$74:$DL$97,MATCH(_xlfn.CONCAT(TEXT(DATE($A22,$B22,1),"mmm-yy"),$D22),'[1]Demanda requerida 2026'!$CB$39:$DL$39,0),FALSE) -> 4120 | AC22: =SUM(E22:AB22) -> 126164
A23: 2026 | B23: 8 | C23: 7 | D23: Festivo | E23: =VLOOKUP(E$1,'[1]Demanda requerida 2026'!$CB$74:$DL$97,MATCH(_xlfn.CONCAT(TEXT(DATE($A23,$B23,1),"mmm-yy"),$D23),'[1]Demanda requerida 2026'!$CB$39:$DL$39,0),FALSE) -> 200 | F23: =VLOOKUP(F$1,'[1]Demanda requerida 2026'!$CB$74:$DL$97,MATCH(_xlfn.CONCAT(TEXT(DATE($A23,$B23,1),"mmm-yy"),$D23),'[1]Demanda requerida 2026'!$CB$39:$DL$39,0),FALSE) -> 200 | G23: =VLOOKUP(G$1,'[1]Demanda requerida 2026'!$CB$74:$DL$97,MATCH(_xlfn.CONCAT(TEXT(DATE($A23,$B23,1),"mmm-yy"),$D23),'[1]Demanda requerida 2026'!$CB$39:$DL$39,0),FALSE) -> 200 | H23: =VLOOKUP(H$1,'[1]Demanda requerida 2026'!$CB$74:$DL$97,MATCH(_xlfn.CONCAT(TEXT(DATE($A23,$B23,1),"mmm-yy"),$D23),'[1]Demanda requerida 2026'!$CB$39:$DL$39,0),FALSE) -> 200 | I23: =VLOOKUP(I$1,'[1]Demanda requerida 2026'!$CB$74:$DL$97,MATCH(_xlfn.CONCAT(TEXT(DATE($A23,$B23,1),"mmm-yy"),$D23),'[1]Demanda requerida 2026'!$CB$39:$DL$39,0),FALSE) -> 200 | J23: =VLOOKUP(J$1,'[1]Demanda requerida 2026'!$CB$74:$DL$97,MATCH(_xlfn.CONCAT(TEXT(DATE($A23,$B23,1),"mmm-yy"),$D23),'[1]Demanda requerida 2026'!$CB$39:$DL$39,0),FALSE) -> 200 | K23: =VLOOKUP(K$1,'[1]Demanda requerida 2026'!$CB$74:$DL$97,MATCH(_xlfn.CONCAT(TEXT(DATE($A23,$B23,1),"mmm-yy"),$D23),'[1]Demanda requerida 2026'!$CB$39:$DL$39,0),FALSE) -> 200 | L23: =VLOOKUP(L$1,'[1]Demanda requerida 2026'!$CB$74:$DL$97,MATCH(_xlfn.CONCAT(TEXT(DATE($A23,$B23,1),"mmm-yy"),$D23),'[1]Demanda requerida 2026'!$CB$39:$DL$39,0),FALSE) -> 200 | ... AB23: =VLOOKUP(AB$1,'[1]Demanda requerida 2026'!$CB$74:$DL$97,MATCH(_xlfn.CONCAT(TEXT(DATE($A23,$B23,1),"mmm-yy"),$D23),'[1]Demanda requerida 2026'!$CB$39:$DL$39,0),FALSE) -> 200 | AC23: =SUM(E23:AB23) -> 16832 | AD23: =+SUMPRODUCT(AC23:AC25,C23:C25) -> 6255842
A24: 2026 | B24: 8 | C24: 19 | D24: Ordinario | E24: =VLOOKUP(E$1,'[1]Demanda requerida 2026'!$CB$74:$DL$97,MATCH(_xlfn.CONCAT(TEXT(DATE($A24,$B24,1),"mmm-yy"),$D24),'[1]Demanda requerida 2026'!$CB$39:$DL$39,0),FALSE) -> 5203 | F24: =VLOOKUP(F$1,'[1]Demanda requerida 2026'!$CB$74:$DL$97,MATCH(_xlfn.CONCAT(TEXT(DATE($A24,$B24,1),"mmm-yy"),$D24),'[1]Demanda requerida 2026'!$CB$39:$DL$39,0),FALSE) -> 4253 | G24: =VLOOKUP(G$1,'[1]Demanda requerida 2026'!$CB$74:$DL$97,MATCH(_xlfn.CONCAT(TEXT(DATE($A24,$B24,1),"mmm-yy"),$D24),'[1]Demanda requerida 2026'!$CB$39:$DL$39,0),FALSE) -> 3532 | H24: =VLOOKUP(H$1,'[1]Demanda requerida 2026'!$CB$74:$DL$97,MATCH(_xlfn.CONCAT(TEXT(DATE($A24,$B24,1),"mmm-yy"),$D24),'[1]Demanda requerida 2026'!$CB$39:$DL$39,0),FALSE) -> 3010 | I24: =VLOOKUP(I$1,'[1]Demanda requerida 2026'!$CB$74:$DL$97,MATCH(_xlfn.CONCAT(TEXT(DATE($A24,$B24,1),"mmm-yy"),$D24),'[1]Demanda requerida 2026'!$CB$39:$DL$39,0),FALSE) -> 3009 | J24: =VLOOKUP(J$1,'[1]Demanda requerida 2026'!$CB$74:$DL$97,MATCH(_xlfn.CONCAT(TEXT(DATE($A24,$B24,1),"mmm-yy"),$D24),'[1]Demanda requerida 2026'!$CB$39:$DL$39,0),FALSE) -> 4426 | K24: =VLOOKUP(K$1,'[1]Demanda requerida 2026'!$CB$74:$DL$97,MATCH(_xlfn.CONCAT(TEXT(DATE($A24,$B24,1),"mmm-yy"),$D24),'[1]Demanda requerida 2026'!$CB$39:$DL$39,0),FALSE) -> 6080 | L24: =VLOOKUP(L$1,'[1]Demanda requerida 2026'!$CB$74:$DL$97,MATCH(_xlfn.CONCAT(TEXT(DATE($A24,$B24,1),"mmm-yy"),$D24),'[1]Demanda requerida 2026'!$CB$39:$DL$39,0),FALSE) -> 7640 | ... AB24: =VLOOKUP(AB$1,'[1]Demanda requerida 2026'!$CB$74:$DL$97,MATCH(_xlfn.CONCAT(TEXT(DATE($A24,$B24,1),"mmm-yy"),$D24),'[1]Demanda requerida 2026'!$CB$39:$DL$39,0),FALSE) -> 8183 | AC24: =SUM(E24:AB24) -> 275807
A25: 2026 | B25: 8 | C25: 5 | D25: Sábado | E25: =VLOOKUP(E$1,'[1]Demanda requerida 2026'!$CB$74:$DL$97,MATCH(_xlfn.CONCAT(TEXT(DATE($A25,$B25,1),"mmm-yy"),$D25),'[1]Demanda requerida 2026'!$CB$39:$DL$39,0),FALSE) -> 1634 | F25: =VLOOKUP(F$1,'[1]Demanda requerida 2026'!$CB$74:$DL$97,MATCH(_xlfn.CONCAT(TEXT(DATE($A25,$B25,1),"mmm-yy"),$D25),'[1]Demanda requerida 2026'!$CB$39:$DL$39,0),FALSE) -> 1378 | G25: =VLOOKUP(G$1,'[1]Demanda requerida 2026'!$CB$74:$DL$97,MATCH(_xlfn.CONCAT(TEXT(DATE($A25,$B25,1),"mmm-yy"),$D25),'[1]Demanda requerida 2026'!$CB$39:$DL$39,0),FALSE) -> 793 | H25: =VLOOKUP(H$1,'[1]Demanda requerida 2026'!$CB$74:$DL$97,MATCH(_xlfn.CONCAT(TEXT(DATE($A25,$B25,1),"mmm-yy"),$D25),'[1]Demanda requerida 2026'!$CB$39:$DL$39,0),FALSE) -> 198 | I25: =VLOOKUP(I$1,'[1]Demanda requerida 2026'!$CB$74:$DL$97,MATCH(_xlfn.CONCAT(TEXT(DATE($A25,$B25,1),"mmm-yy"),$D25),'[1]Demanda requerida 2026'!$CB$39:$DL$39,0),FALSE) -> 77 | J25: =VLOOKUP(J$1,'[1]Demanda requerida 2026'!$CB$74:$DL$97,MATCH(_xlfn.CONCAT(TEXT(DATE($A25,$B25,1),"mmm-yy"),$D25),'[1]Demanda requerida 2026'!$CB$39:$DL$39,0),FALSE) -> 369 | K25: =VLOOKUP(K$1,'[1]Demanda requerida 2026'!$CB$74:$DL$97,MATCH(_xlfn.CONCAT(TEXT(DATE($A25,$B25,1),"mmm-yy"),$D25),'[1]Demanda requerida 2026'!$CB$39:$DL$39,0),FALSE) -> 1248 | L25: =VLOOKUP(L$1,'[1]Demanda requerida 2026'!$CB$74:$DL$97,MATCH(_xlfn.CONCAT(TEXT(DATE($A25,$B25,1),"mmm-yy"),$D25),'[1]Demanda requerida 2026'!$CB$39:$DL$39,0),FALSE) -> 3437 | ... AB25: =VLOOKUP(AB$1,'[1]Demanda requerida 2026'!$CB$74:$DL$97,MATCH(_xlfn.CONCAT(TEXT(DATE($A25,$B25,1),"mmm-yy"),$D25),'[1]Demanda requerida 2026'!$CB$39:$DL$39,0),FALSE) -> 5987 | AC25: =SUM(E25:AB25) -> 179537
A26: 2026 | B26: 9 | C26: 4 | D26: Festivo | E26: =VLOOKUP(E$1,'[1]Demanda requerida 2026'!$CB$74:$DL$97,MATCH(_xlfn.CONCAT(TEXT(DATE($A26,$B26,1),"mmm-yy"),$D26),'[1]Demanda requerida 2026'!$CB$39:$DL$39,0),FALSE) -> 200 | F26: =VLOOKUP(F$1,'[1]Demanda requerida 2026'!$CB$74:$DL$97,MATCH(_xlfn.CONCAT(TEXT(DATE($A26,$B26,1),"mmm-yy"),$D26),'[1]Demanda requerida 2026'!$CB$39:$DL$39,0),FALSE) -> 200 | G26: =VLOOKUP(G$1,'[1]Demanda requerida 2026'!$CB$74:$DL$97,MATCH(_xlfn.CONCAT(TEXT(DATE($A26,$B26,1),"mmm-yy"),$D26),'[1]Demanda requerida 2026'!$CB$39:$DL$39,0),FALSE) -> 200 | H26: =VLOOKUP(H$1,'[1]Demanda requerida 2026'!$CB$74:$DL$97,MATCH(_xlfn.CONCAT(TEXT(DATE($A26,$B26,1),"mmm-yy"),$D26),'[1]Demanda requerida 2026'!$CB$39:$DL$39,0),FALSE) -> 200 | I26: =VLOOKUP(I$1,'[1]Demanda requerida 2026'!$CB$74:$DL$97,MATCH(_xlfn.CONCAT(TEXT(DATE($A26,$B26,1),"mmm-yy"),$D26),'[1]Demanda requerida 2026'!$CB$39:$DL$39,0),FALSE) -> 200 | J26: =VLOOKUP(J$1,'[1]Demanda requerida 2026'!$CB$74:$DL$97,MATCH(_xlfn.CONCAT(TEXT(DATE($A26,$B26,1),"mmm-yy"),$D26),'[1]Demanda requerida 2026'!$CB$39:$DL$39,0),FALSE) -> 200 | K26: =VLOOKUP(K$1,'[1]Demanda requerida 2026'!$CB$74:$DL$97,MATCH(_xlfn.CONCAT(TEXT(DATE($A26,$B26,1),"mmm-yy"),$D26),'[1]Demanda requerida 2026'!$CB$39:$DL$39,0),FALSE) -> 200 | L26: =VLOOKUP(L$1,'[1]Demanda requerida 2026'!$CB$74:$DL$97,MATCH(_xlfn.CONCAT(TEXT(DATE($A26,$B26,1),"mmm-yy"),$D26),'[1]Demanda requerida 2026'!$CB$39:$DL$39,0),FALSE) -> 200 | ... AB26: =VLOOKUP(AB$1,'[1]Demanda requerida 2026'!$CB$74:$DL$97,MATCH(_xlfn.CONCAT(TEXT(DATE($A26,$B26,1),"mmm-yy"),$D26),'[1]Demanda requerida 2026'!$CB$39:$DL$39,0),FALSE) -> 200 | AC26: =SUM(E26:AB26) -> 39367 | AD26: =+SUMPRODUCT(AC26:AC28,C26:C28) -> 2553138
A27: 2026 | B27: 9 | C27: 22 | D27: Ordinario | E27: =VLOOKUP(E$1,'[1]Demanda requerida 2026'!$CB$74:$DL$97,MATCH(_xlfn.CONCAT(TEXT(DATE($A27,$B27,1),"mmm-yy"),$D27),'[1]Demanda requerida 2026'!$CB$39:$DL$39,0),FALSE) -> 200 | F27: =VLOOKUP(F$1,'[1]Demanda requerida 2026'!$CB$74:$DL$97,MATCH(_xlfn.CONCAT(TEXT(DATE($A27,$B27,1),"mmm-yy"),$D27),'[1]Demanda requerida 2026'!$CB$39:$DL$39,0),FALSE) -> 200 | G27: =VLOOKUP(G$1,'[1]Demanda requerida 2026'!$CB$74:$DL$97,MATCH(_xlfn.CONCAT(TEXT(DATE($A27,$B27,1),"mmm-yy"),$D27),'[1]Demanda requerida 2026'!$CB$39:$DL$39,0),FALSE) -> 200 | H27: =VLOOKUP(H$1,'[1]Demanda requerida 2026'!$CB$74:$DL$97,MATCH(_xlfn.CONCAT(TEXT(DATE($A27,$B27,1),"mmm-yy"),$D27),'[1]Demanda requerida 2026'!$CB$39:$DL$39,0),FALSE) -> 200 | I27: =VLOOKUP(I$1,'[1]Demanda requerida 2026'!$CB$74:$DL$97,MATCH(_xlfn.CONCAT(TEXT(DATE($A27,$B27,1),"mmm-yy"),$D27),'[1]Demanda requerida 2026'!$CB$39:$DL$39,0),FALSE) -> 200 | J27: =VLOOKUP(J$1,'[1]Demanda requerida 2026'!$CB$74:$DL$97,MATCH(_xlfn.CONCAT(TEXT(DATE($A27,$B27,1),"mmm-yy"),$D27),'[1]Demanda requerida 2026'!$CB$39:$DL$39,0),FALSE) -> 200 | K27: =VLOOKUP(K$1,'[1]Demanda requerida 2026'!$CB$74:$DL$97,MATCH(_xlfn.CONCAT(TEXT(DATE($A27,$B27,1),"mmm-yy"),$D27),'[1]Demanda requerida 2026'!$CB$39:$DL$39,0),FALSE) -> 200 | L27: =VLOOKUP(L$1,'[1]Demanda requerida 2026'!$CB$74:$DL$97,MATCH(_xlfn.CONCAT(TEXT(DATE($A27,$B27,1),"mmm-yy"),$D27),'[1]Demanda requerida 2026'!$CB$39:$DL$39,0),FALSE) -> 200 | ... AB27: =VLOOKUP(AB$1,'[1]Demanda requerida 2026'!$CB$74:$DL$97,MATCH(_xlfn.CONCAT(TEXT(DATE($A27,$B27,1),"mmm-yy"),$D27),'[1]Demanda requerida 2026'!$CB$39:$DL$39,0),FALSE) -> 374 | AC27: =SUM(E27:AB27) -> 96785
A28: 2026 | B28: 9 | C28: 4 | D28: Sábado | E28: =VLOOKUP(E$1,'[1]Demanda requerida 2026'!$CB$74:$DL$97,MATCH(_xlfn.CONCAT(TEXT(DATE($A28,$B28,1),"mmm-yy"),$D28),'[1]Demanda requerida 2026'!$CB$39:$DL$39,0),FALSE) -> 200 | F28: =VLOOKUP(F$1,'[1]Demanda requerida 2026'!$CB$74:$DL$97,MATCH(_xlfn.CONCAT(TEXT(DATE($A28,$B28,1),"mmm-yy"),$D28),'[1]Demanda requerida 2026'!$CB$39:$DL$39,0),FALSE) -> 200 | G28: =VLOOKUP(G$1,'[1]Demanda requerida 2026'!$CB$74:$DL$97,MATCH(_xlfn.CONCAT(TEXT(DATE($A28,$B28,1),"mmm-yy"),$D28),'[1]Demanda requerida 2026'!$CB$39:$DL$39,0),FALSE) -> 200 | H28: =VLOOKUP(H$1,'[1]Demanda requerida 2026'!$CB$74:$DL$97,MATCH(_xlfn.CONCAT(TEXT(DATE($A28,$B28,1),"mmm-yy"),$D28),'[1]Demanda requerida 2026'!$CB$39:$DL$39,0),FALSE) -> 200 | I28: =VLOOKUP(I$1,'[1]Demanda requerida 2026'!$CB$74:$DL$97,MATCH(_xlfn.CONCAT(TEXT(DATE($A28,$B28,1),"mmm-yy"),$D28),'[1]Demanda requerida 2026'!$CB$39:$DL$39,0),FALSE) -> 200 | J28: =VLOOKUP(J$1,'[1]Demanda requerida 2026'!$CB$74:$DL$97,MATCH(_xlfn.CONCAT(TEXT(DATE($A28,$B28,1),"mmm-yy"),$D28),'[1]Demanda requerida 2026'!$CB$39:$DL$39,0),FALSE) -> 200 | K28: =VLOOKUP(K$1,'[1]Demanda requerida 2026'!$CB$74:$DL$97,MATCH(_xlfn.CONCAT(TEXT(DATE($A28,$B28,1),"mmm-yy"),$D28),'[1]Demanda requerida 2026'!$CB$39:$DL$39,0),FALSE) -> 200 | L28: =VLOOKUP(L$1,'[1]Demanda requerida 2026'!$CB$74:$DL$97,MATCH(_xlfn.CONCAT(TEXT(DATE($A28,$B28,1),"mmm-yy"),$D28),'[1]Demanda requerida 2026'!$CB$39:$DL$39,0),FALSE) -> 200 | ... AB28: =VLOOKUP(AB$1,'[1]Demanda requerida 2026'!$CB$74:$DL$97,MATCH(_xlfn.CONCAT(TEXT(DATE($A28,$B28,1),"mmm-yy"),$D28),'[1]Demanda requerida 2026'!$CB$39:$DL$39,0),FALSE) -> 200 | AC28: =SUM(E28:AB28) -> 66600
A29: 2026 | B29: 10 | C29: 5 | D29: Festivo | E29: =VLOOKUP(E$1,'[1]Demanda requerida 2026'!$CB$74:$DL$97,MATCH(_xlfn.CONCAT(TEXT(DATE($A29,$B29,1),"mmm-yy"),$D29),'[1]Demanda requerida 2026'!$CB$39:$DL$39,0),FALSE) -> 200 | F29: =VLOOKUP(F$1,'[1]Demanda requerida 2026'!$CB$74:$DL$97,MATCH(_xlfn.CONCAT(TEXT(DATE($A29,$B29,1),"mmm-yy"),$D29),'[1]Demanda requerida 2026'!$CB$39:$DL$39,0),FALSE) -> 200 | G29: =VLOOKUP(G$1,'[1]Demanda requerida 2026'!$CB$74:$DL$97,MATCH(_xlfn.CONCAT(TEXT(DATE($A29,$B29,1),"mmm-yy"),$D29),'[1]Demanda requerida 2026'!$CB$39:$DL$39,0),FALSE) -> 200 | H29: =VLOOKUP(H$1,'[1]Demanda requerida 2026'!$CB$74:$DL$97,MATCH(_xlfn.CONCAT(TEXT(DATE($A29,$B29,1),"mmm-yy"),$D29),'[1]Demanda requerida 2026'!$CB$39:$DL$39,0),FALSE) -> 200 | I29: =VLOOKUP(I$1,'[1]Demanda requerida 2026'!$CB$74:$DL$97,MATCH(_xlfn.CONCAT(TEXT(DATE($A29,$B29,1),"mmm-yy"),$D29),'[1]Demanda requerida 2026'!$CB$39:$DL$39,0),FALSE) -> 200 | J29: =VLOOKUP(J$1,'[1]Demanda requerida 2026'!$CB$74:$DL$97,MATCH(_xlfn.CONCAT(TEXT(DATE($A29,$B29,1),"mmm-yy"),$D29),'[1]Demanda requerida 2026'!$CB$39:$DL$39,0),FALSE) -> 200 | K29: =VLOOKUP(K$1,'[1]Demanda requerida 2026'!$CB$74:$DL$97,MATCH(_xlfn.CONCAT(TEXT(DATE($A29,$B29,1),"mmm-yy"),$D29),'[1]Demanda requerida 2026'!$CB$39:$DL$39,0),FALSE) -> 200 | L29: =VLOOKUP(L$1,'[1]Demanda requerida 2026'!$CB$74:$DL$97,MATCH(_xlfn.CONCAT(TEXT(DATE($A29,$B29,1),"mmm-yy"),$D29),'[1]Demanda requerida 2026'!$CB$39:$DL$39,0),FALSE) -> 200 | ... AB29: =VLOOKUP(AB$1,'[1]Demanda requerida 2026'!$CB$74:$DL$97,MATCH(_xlfn.CONCAT(TEXT(DATE($A29,$B29,1),"mmm-yy"),$D29),'[1]Demanda requerida 2026'!$CB$39:$DL$39,0),FALSE) -> 200 | AC29: =SUM(E29:AB29) -> 4800 | AD29: =+SUMPRODUCT(AC29:AC31,C29:C31) -> 2398451
A30: 2026 | B30: 10 | C30: 21 | D30: Ordinario | E30: =VLOOKUP(E$1,'[1]Demanda requerida 2026'!$CB$74:$DL$97,MATCH(_xlfn.CONCAT(TEXT(DATE($A30,$B30,1),"mmm-yy"),$D30),'[1]Demanda requerida 2026'!$CB$39:$DL$39,0),FALSE) -> 200 | F30: =VLOOKUP(F$1,'[1]Demanda requerida 2026'!$CB$74:$DL$97,MATCH(_xlfn.CONCAT(TEXT(DATE($A30,$B30,1),"mmm-yy"),$D30),'[1]Demanda requerida 2026'!$CB$39:$DL$39,0),FALSE) -> 200 | G30: =VLOOKUP(G$1,'[1]Demanda requerida 2026'!$CB$74:$DL$97,MATCH(_xlfn.CONCAT(TEXT(DATE($A30,$B30,1),"mmm-yy"),$D30),'[1]Demanda requerida 2026'!$CB$39:$DL$39,0),FALSE) -> 200 | H30: =VLOOKUP(H$1,'[1]Demanda requerida 2026'!$CB$74:$DL$97,MATCH(_xlfn.CONCAT(TEXT(DATE($A30,$B30,1),"mmm-yy"),$D30),'[1]Demanda requerida 2026'!$CB$39:$DL$39,0),FALSE) -> 200 | I30: =VLOOKUP(I$1,'[1]Demanda requerida 2026'!$CB$74:$DL$97,MATCH(_xlfn.CONCAT(TEXT(DATE($A30,$B30,1),"mmm-yy"),$D30),'[1]Demanda requerida 2026'!$CB$39:$DL$39,0),FALSE) -> 200 | J30: =VLOOKUP(J$1,'[1]Demanda requerida 2026'!$CB$74:$DL$97,MATCH(_xlfn.CONCAT(TEXT(DATE($A30,$B30,1),"mmm-yy"),$D30),'[1]Demanda requerida 2026'!$CB$39:$DL$39,0),FALSE) -> 200 | K30: =VLOOKUP(K$1,'[1]Demanda requerida 2026'!$CB$74:$DL$97,MATCH(_xlfn.CONCAT(TEXT(DATE($A30,$B30,1),"mmm-yy"),$D30),'[1]Demanda requerida 2026'!$CB$39:$DL$39,0),FALSE) -> 200 | L30: =VLOOKUP(L$1,'[1]Demanda requerida 2026'!$CB$74:$DL$97,MATCH(_xlfn.CONCAT(TEXT(DATE($A30,$B30,1),"mmm-yy"),$D30),'[1]Demanda requerida 2026'!$CB$39:$DL$39,0),FALSE) -> 200 | ... AB30: =VLOOKUP(AB$1,'[1]Demanda requerida 2026'!$CB$74:$DL$97,MATCH(_xlfn.CONCAT(TEXT(DATE($A30,$B30,1),"mmm-yy"),$D30),'[1]Demanda requerida 2026'!$CB$39:$DL$39,0),FALSE) -> 200 | AC30: =SUM(E30:AB30) -> 81316
A31: 2026 | B31: 10 | C31: 5 | D31: Sábado | E31: =VLOOKUP(E$1,'[1]Demanda requerida 2026'!$CB$74:$DL$97,MATCH(_xlfn.CONCAT(TEXT(DATE($A31,$B31,1),"mmm-yy"),$D31),'[1]Demanda requerida 2026'!$CB$39:$DL$39,0),FALSE) -> 164 | F31: =VLOOKUP(F$1,'[1]Demanda requerida 2026'!$CB$74:$DL$97,MATCH(_xlfn.CONCAT(TEXT(DATE($A31,$B31,1),"mmm-yy"),$D31),'[1]Demanda requerida 2026'!$CB$39:$DL$39,0),FALSE) -> 200 | G31: =VLOOKUP(G$1,'[1]Demanda requerida 2026'!$CB$74:$DL$97,MATCH(_xlfn.CONCAT(TEXT(DATE($A31,$B31,1),"mmm-yy"),$D31),'[1]Demanda requerida 2026'!$CB$39:$DL$39,0),FALSE) -> 200 | H31: =VLOOKUP(H$1,'[1]Demanda requerida 2026'!$CB$74:$DL$97,MATCH(_xlfn.CONCAT(TEXT(DATE($A31,$B31,1),"mmm-yy"),$D31),'[1]Demanda requerida 2026'!$CB$39:$DL$39,0),FALSE) -> 200 | I31: =VLOOKUP(I$1,'[1]Demanda requerida 2026'!$CB$74:$DL$97,MATCH(_xlfn.CONCAT(TEXT(DATE($A31,$B31,1),"mmm-yy"),$D31),'[1]Demanda requerida 2026'!$CB$39:$DL$39,0),FALSE) -> 200 | J31: =VLOOKUP(J$1,'[1]Demanda requerida 2026'!$CB$74:$DL$97,MATCH(_xlfn.CONCAT(TEXT(DATE($A31,$B31,1),"mmm-yy"),$D31),'[1]Demanda requerida 2026'!$CB$39:$DL$39,0),FALSE) -> 200 | K31: =VLOOKUP(K$1,'[1]Demanda requerida 2026'!$CB$74:$DL$97,MATCH(_xlfn.CONCAT(TEXT(DATE($A31,$B31,1),"mmm-yy"),$D31),'[1]Demanda requerida 2026'!$CB$39:$DL$39,0),FALSE) -> 200 | L31: =VLOOKUP(L$1,'[1]Demanda requerida 2026'!$CB$74:$DL$97,MATCH(_xlfn.CONCAT(TEXT(DATE($A31,$B31,1),"mmm-yy"),$D31),'[1]Demanda requerida 2026'!$CB$39:$DL$39,0),FALSE) -> 200 | ... AB31: =VLOOKUP(AB$1,'[1]Demanda requerida 2026'!$CB$74:$DL$97,MATCH(_xlfn.CONCAT(TEXT(DATE($A31,$B31,1),"mmm-yy"),$D31),'[1]Demanda requerida 2026'!$CB$39:$DL$39,0),FALSE) -> 2919 | AC31: =SUM(E31:AB31) -> 133363
A32: 2026 | B32: 11 | C32: 7 | D32: Festivo | E32: =VLOOKUP(E$1,'[1]Demanda requerida 2026'!$CB$74:$DL$97,MATCH(_xlfn.CONCAT(TEXT(DATE($A32,$B32,1),"mmm-yy"),$D32),'[1]Demanda requerida 2026'!$CB$39:$DL$39,0),FALSE) -> 200 | F32: =VLOOKUP(F$1,'[1]Demanda requerida 2026'!$CB$74:$DL$97,MATCH(_xlfn.CONCAT(TEXT(DATE($A32,$B32,1),"mmm-yy"),$D32),'[1]Demanda requerida 2026'!$CB$39:$DL$39,0),FALSE) -> 200 | G32: =VLOOKUP(G$1,'[1]Demanda requerida 2026'!$CB$74:$DL$97,MATCH(_xlfn.CONCAT(TEXT(DATE($A32,$B32,1),"mmm-yy"),$D32),'[1]Demanda requerida 2026'!$CB$39:$DL$39,0),FALSE) -> 200 | H32: =VLOOKUP(H$1,'[1]Demanda requerida 2026'!$CB$74:$DL$97,MATCH(_xlfn.CONCAT(TEXT(DATE($A32,$B32,1),"mmm-yy"),$D32),'[1]Demanda requerida 2026'!$CB$39:$DL$39,0),FALSE) -> 200 | I32: =VLOOKUP(I$1,'[1]Demanda requerida 2026'!$CB$74:$DL$97,MATCH(_xlfn.CONCAT(TEXT(DATE($A32,$B32,1),"mmm-yy"),$D32),'[1]Demanda requerida 2026'!$CB$39:$DL$39,0),FALSE) -> 200 | J32: =VLOOKUP(J$1,'[1]Demanda requerida 2026'!$CB$74:$DL$97,MATCH(_xlfn.CONCAT(TEXT(DATE($A32,$B32,1),"mmm-yy"),$D32),'[1]Demanda requerida 2026'!$CB$39:$DL$39,0),FALSE) -> 200 | K32: =VLOOKUP(K$1,'[1]Demanda requerida 2026'!$CB$74:$DL$97,MATCH(_xlfn.CONCAT(TEXT(DATE($A32,$B32,1),"mmm-yy"),$D32),'[1]Demanda requerida 2026'!$CB$39:$DL$39,0),FALSE) -> 200 | L32: =VLOOKUP(L$1,'[1]Demanda requerida 2026'!$CB$74:$DL$97,MATCH(_xlfn.CONCAT(TEXT(DATE($A32,$B32,1),"mmm-yy"),$D32),'[1]Demanda requerida 2026'!$CB$39:$DL$39,0),FALSE) -> 200 | ... AB32: =VLOOKUP(AB$1,'[1]Demanda requerida 2026'!$CB$74:$DL$97,MATCH(_xlfn.CONCAT(TEXT(DATE($A32,$B32,1),"mmm-yy"),$D32),'[1]Demanda requerida 2026'!$CB$39:$DL$39,0),FALSE) -> 200 | AC32: =SUM(E32:AB32) -> 4800 | AD32: =+SUMPRODUCT(AC32:AC34,C32:C34) -> 2758031
A33: 2026 | B33: 11 | C33: 19 | D33: Ordinario | E33: =VLOOKUP(E$1,'[1]Demanda requerida 2026'!$CB$74:$DL$97,MATCH(_xlfn.CONCAT(TEXT(DATE($A33,$B33,1),"mmm-yy"),$D33),'[1]Demanda requerida 2026'!$CB$39:$DL$39,0),FALSE) -> 200 | F33: =VLOOKUP(F$1,'[1]Demanda requerida 2026'!$CB$74:$DL$97,MATCH(_xlfn.CONCAT(TEXT(DATE($A33,$B33,1),"mmm-yy"),$D33),'[1]Demanda requerida 2026'!$CB$39:$DL$39,0),FALSE) -> 200 | G33: =VLOOKUP(G$1,'[1]Demanda requerida 2026'!$CB$74:$DL$97,MATCH(_xlfn.CONCAT(TEXT(DATE($A33,$B33,1),"mmm-yy"),$D33),'[1]Demanda requerida 2026'!$CB$39:$DL$39,0),FALSE) -> 200 | H33: =VLOOKUP(H$1,'[1]Demanda requerida 2026'!$CB$74:$DL$97,MATCH(_xlfn.CONCAT(TEXT(DATE($A33,$B33,1),"mmm-yy"),$D33),'[1]Demanda requerida 2026'!$CB$39:$DL$39,0),FALSE) -> 200 | I33: =VLOOKUP(I$1,'[1]Demanda requerida 2026'!$CB$74:$DL$97,MATCH(_xlfn.CONCAT(TEXT(DATE($A33,$B33,1),"mmm-yy"),$D33),'[1]Demanda requerida 2026'!$CB$39:$DL$39,0),FALSE) -> 200 | J33: =VLOOKUP(J$1,'[1]Demanda requerida 2026'!$CB$74:$DL$97,MATCH(_xlfn.CONCAT(TEXT(DATE($A33,$B33,1),"mmm-yy"),$D33),'[1]Demanda requerida 2026'!$CB$39:$DL$39,0),FALSE) -> 200 | K33: =VLOOKUP(K$1,'[1]Demanda requerida 2026'!$CB$74:$DL$97,MATCH(_xlfn.CONCAT(TEXT(DATE($A33,$B33,1),"mmm-yy"),$D33),'[1]Demanda requerida 2026'!$CB$39:$DL$39,0),FALSE) -> 200 | L33: =VLOOKUP(L$1,'[1]Demanda requerida 2026'!$CB$74:$DL$97,MATCH(_xlfn.CONCAT(TEXT(DATE($A33,$B33,1),"mmm-yy"),$D33),'[1]Demanda requerida 2026'!$CB$39:$DL$39,0),FALSE) -> 1869 | ... AB33: =VLOOKUP(AB$1,'[1]Demanda requerida 2026'!$CB$74:$DL$97,MATCH(_xlfn.CONCAT(TEXT(DATE($A33,$B33,1),"mmm-yy"),$D33),'[1]Demanda requerida 2026'!$CB$39:$DL$39,0),FALSE) -> 2742 | AC33: =SUM(E33:AB33) -> 141049
A34: 2026 | B34: 11 | C34: 4 | D34: Sábado | E34: =VLOOKUP(E$1,'[1]Demanda requerida 2026'!$CB$74:$DL$97,MATCH(_xlfn.CONCAT(TEXT(DATE($A34,$B34,1),"mmm-yy"),$D34),'[1]Demanda requerida 2026'!$CB$39:$DL$39,0),FALSE) -> 200 | F34: =VLOOKUP(F$1,'[1]Demanda requerida 2026'!$CB$74:$DL$97,MATCH(_xlfn.CONCAT(TEXT(DATE($A34,$B34,1),"mmm-yy"),$D34),'[1]Demanda requerida 2026'!$CB$39:$DL$39,0),FALSE) -> 200 | G34: =VLOOKUP(G$1,'[1]Demanda requerida 2026'!$CB$74:$DL$97,MATCH(_xlfn.CONCAT(TEXT(DATE($A34,$B34,1),"mmm-yy"),$D34),'[1]Demanda requerida 2026'!$CB$39:$DL$39,0),FALSE) -> 200 | H34: =VLOOKUP(H$1,'[1]Demanda requerida 2026'!$CB$74:$DL$97,MATCH(_xlfn.CONCAT(TEXT(DATE($A34,$B34,1),"mmm-yy"),$D34),'[1]Demanda requerida 2026'!$CB$39:$DL$39,0),FALSE) -> 200 | I34: =VLOOKUP(I$1,'[1]Demanda requerida 2026'!$CB$74:$DL$97,MATCH(_xlfn.CONCAT(TEXT(DATE($A34,$B34,1),"mmm-yy"),$D34),'[1]Demanda requerida 2026'!$CB$39:$DL$39,0),FALSE) -> 200 | J34: =VLOOKUP(J$1,'[1]Demanda requerida 2026'!$CB$74:$DL$97,MATCH(_xlfn.CONCAT(TEXT(DATE($A34,$B34,1),"mmm-yy"),$D34),'[1]Demanda requerida 2026'!$CB$39:$DL$39,0),FALSE) -> 200 | K34: =VLOOKUP(K$1,'[1]Demanda requerida 2026'!$CB$74:$DL$97,MATCH(_xlfn.CONCAT(TEXT(DATE($A34,$B34,1),"mmm-yy"),$D34),'[1]Demanda requerida 2026'!$CB$39:$DL$39,0),FALSE) -> 200 | L34: =VLOOKUP(L$1,'[1]Demanda requerida 2026'!$CB$74:$DL$97,MATCH(_xlfn.CONCAT(TEXT(DATE($A34,$B34,1),"mmm-yy"),$D34),'[1]Demanda requerida 2026'!$CB$39:$DL$39,0),FALSE) -> 200 | ... AB34: =VLOOKUP(AB$1,'[1]Demanda requerida 2026'!$CB$74:$DL$97,MATCH(_xlfn.CONCAT(TEXT(DATE($A34,$B34,1),"mmm-yy"),$D34),'[1]Demanda requerida 2026'!$CB$39:$DL$39,0),FALSE) -> 200 | AC34: =SUM(E34:AB34) -> 11125
A35: 2026 | B35: 12 | C35: 6 | D35: Festivo | E35: =VLOOKUP(E$1,'[1]Demanda requerida 2026'!$CB$74:$DL$97,MATCH(_xlfn.CONCAT(TEXT(DATE($A35,$B35,1),"mmm-yy"),$D35),'[1]Demanda requerida 2026'!$CB$39:$DL$39,0),FALSE) -> 200 | F35: =VLOOKUP(F$1,'[1]Demanda requerida 2026'!$CB$74:$DL$97,MATCH(_xlfn.CONCAT(TEXT(DATE($A35,$B35,1),"mmm-yy"),$D35),'[1]Demanda requerida 2026'!$CB$39:$DL$39,0),FALSE) -> 200 | G35: =VLOOKUP(G$1,'[1]Demanda requerida 2026'!$CB$74:$DL$97,MATCH(_xlfn.CONCAT(TEXT(DATE($A35,$B35,1),"mmm-yy"),$D35),'[1]Demanda requerida 2026'!$CB$39:$DL$39,0),FALSE) -> 200 | H35: =VLOOKUP(H$1,'[1]Demanda requerida 2026'!$CB$74:$DL$97,MATCH(_xlfn.CONCAT(TEXT(DATE($A35,$B35,1),"mmm-yy"),$D35),'[1]Demanda requerida 2026'!$CB$39:$DL$39,0),FALSE) -> 200 | I35: =VLOOKUP(I$1,'[1]Demanda requerida 2026'!$CB$74:$DL$97,MATCH(_xlfn.CONCAT(TEXT(DATE($A35,$B35,1),"mmm-yy"),$D35),'[1]Demanda requerida 2026'!$CB$39:$DL$39,0),FALSE) -> 200 | J35: =VLOOKUP(J$1,'[1]Demanda requerida 2026'!$CB$74:$DL$97,MATCH(_xlfn.CONCAT(TEXT(DATE($A35,$B35,1),"mmm-yy"),$D35),'[1]Demanda requerida 2026'!$CB$39:$DL$39,0),FALSE) -> 200 | K35: =VLOOKUP(K$1,'[1]Demanda requerida 2026'!$CB$74:$DL$97,MATCH(_xlfn.CONCAT(TEXT(DATE($A35,$B35,1),"mmm-yy"),$D35),'[1]Demanda requerida 2026'!$CB$39:$DL$39,0),FALSE) -> 200 | L35: =VLOOKUP(L$1,'[1]Demanda requerida 2026'!$CB$74:$DL$97,MATCH(_xlfn.CONCAT(TEXT(DATE($A35,$B35,1),"mmm-yy"),$D35),'[1]Demanda requerida 2026'!$CB$39:$DL$39,0),FALSE) -> 200 | ... AB35: =VLOOKUP(AB$1,'[1]Demanda requerida 2026'!$CB$74:$DL$97,MATCH(_xlfn.CONCAT(TEXT(DATE($A35,$B35,1),"mmm-yy"),$D35),'[1]Demanda requerida 2026'!$CB$39:$DL$39,0),FALSE) -> 200 | AC35: =SUM(E35:AB35) -> 9892 | AD35: =+SUMPRODUCT(AC35:AC37,C35:C37) -> 9729772
A36: 2026 | B36: 12 | C36: 21 | D36: Ordinario | E36: =VLOOKUP(E$1,'[1]Demanda requerida 2026'!$CB$74:$DL$97,MATCH(_xlfn.CONCAT(TEXT(DATE($A36,$B36,1),"mmm-yy"),$D36),'[1]Demanda requerida 2026'!$CB$39:$DL$39,0),FALSE) -> 12114 | F36: =VLOOKUP(F$1,'[1]Demanda requerida 2026'!$CB$74:$DL$97,MATCH(_xlfn.CONCAT(TEXT(DATE($A36,$B36,1),"mmm-yy"),$D36),'[1]Demanda requerida 2026'!$CB$39:$DL$39,0),FALSE) -> 10875 | G36: =VLOOKUP(G$1,'[1]Demanda requerida 2026'!$CB$74:$DL$97,MATCH(_xlfn.CONCAT(TEXT(DATE($A36,$B36,1),"mmm-yy"),$D36),'[1]Demanda requerida 2026'!$CB$39:$DL$39,0),FALSE) -> 9927 | H36: =VLOOKUP(H$1,'[1]Demanda requerida 2026'!$CB$74:$DL$97,MATCH(_xlfn.CONCAT(TEXT(DATE($A36,$B36,1),"mmm-yy"),$D36),'[1]Demanda requerida 2026'!$CB$39:$DL$39,0),FALSE) -> 9291 | I36: =VLOOKUP(I$1,'[1]Demanda requerida 2026'!$CB$74:$DL$97,MATCH(_xlfn.CONCAT(TEXT(DATE($A36,$B36,1),"mmm-yy"),$D36),'[1]Demanda requerida 2026'!$CB$39:$DL$39,0),FALSE) -> 9142 | J36: =VLOOKUP(J$1,'[1]Demanda requerida 2026'!$CB$74:$DL$97,MATCH(_xlfn.CONCAT(TEXT(DATE($A36,$B36,1),"mmm-yy"),$D36),'[1]Demanda requerida 2026'!$CB$39:$DL$39,0),FALSE) -> 9809 | K36: =VLOOKUP(K$1,'[1]Demanda requerida 2026'!$CB$74:$DL$97,MATCH(_xlfn.CONCAT(TEXT(DATE($A36,$B36,1),"mmm-yy"),$D36),'[1]Demanda requerida 2026'!$CB$39:$DL$39,0),FALSE) -> 11027 | L36: =VLOOKUP(L$1,'[1]Demanda requerida 2026'!$CB$74:$DL$97,MATCH(_xlfn.CONCAT(TEXT(DATE($A36,$B36,1),"mmm-yy"),$D36),'[1]Demanda requerida 2026'!$CB$39:$DL$39,0),FALSE) -> 13412 | ... AB36: =VLOOKUP(AB$1,'[1]Demanda requerida 2026'!$CB$74:$DL$97,MATCH(_xlfn.CONCAT(TEXT(DATE($A36,$B36,1),"mmm-yy"),$D36),'[1]Demanda requerida 2026'!$CB$39:$DL$39,0),FALSE) -> 15397 | AC36: =SUM(E36:AB36) -> 406288
A37: 2026 | B37: 12 | C37: 4 | D37: Sábado | E37: =VLOOKUP(E$1,'[1]Demanda requerida 2026'!$CB$74:$DL$97,MATCH(_xlfn.CONCAT(TEXT(DATE($A37,$B37,1),"mmm-yy"),$D37),'[1]Demanda requerida 2026'!$CB$39:$DL$39,0),FALSE) -> 7960 | F37: =VLOOKUP(F$1,'[1]Demanda requerida 2026'!$CB$74:$DL$97,MATCH(_xlfn.CONCAT(TEXT(DATE($A37,$B37,1),"mmm-yy"),$D37),'[1]Demanda requerida 2026'!$CB$39:$DL$39,0),FALSE) -> 6680 | G37: =VLOOKUP(G$1,'[1]Demanda requerida 2026'!$CB$74:$DL$97,MATCH(_xlfn.CONCAT(TEXT(DATE($A37,$B37,1),"mmm-yy"),$D37),'[1]Demanda requerida 2026'!$CB$39:$DL$39,0),FALSE) -> 5928 | H37: =VLOOKUP(H$1,'[1]Demanda requerida 2026'!$CB$74:$DL$97,MATCH(_xlfn.CONCAT(TEXT(DATE($A37,$B37,1),"mmm-yy"),$D37),'[1]Demanda requerida 2026'!$CB$39:$DL$39,0),FALSE) -> 5261 | I37: =VLOOKUP(I$1,'[1]Demanda requerida 2026'!$CB$74:$DL$97,MATCH(_xlfn.CONCAT(TEXT(DATE($A37,$B37,1),"mmm-yy"),$D37),'[1]Demanda requerida 2026'!$CB$39:$DL$39,0),FALSE) -> 4982 | J37: =VLOOKUP(J$1,'[1]Demanda requerida 2026'!$CB$74:$DL$97,MATCH(_xlfn.CONCAT(TEXT(DATE($A37,$B37,1),"mmm-yy"),$D37),'[1]Demanda requerida 2026'!$CB$39:$DL$39,0),FALSE) -> 5186 | K37: =VLOOKUP(K$1,'[1]Demanda requerida 2026'!$CB$74:$DL$97,MATCH(_xlfn.CONCAT(TEXT(DATE($A37,$B37,1),"mmm-yy"),$D37),'[1]Demanda requerida 2026'!$CB$39:$DL$39,0),FALSE) -> 6098 | L37: =VLOOKUP(L$1,'[1]Demanda requerida 2026'!$CB$74:$DL$97,MATCH(_xlfn.CONCAT(TEXT(DATE($A37,$B37,1),"mmm-yy"),$D37),'[1]Demanda requerida 2026'!$CB$39:$DL$39,0),FALSE) -> 7722 | ... AB37: =VLOOKUP(AB$1,'[1]Demanda requerida 2026'!$CB$74:$DL$97,MATCH(_xlfn.CONCAT(TEXT(DATE($A37,$B37,1),"mmm-yy"),$D37),'[1]Demanda requerida 2026'!$CB$39:$DL$39,0),FALSE) -> 11688 | AC37: =SUM(E37:AB37) -> 284593
A38: 2027 | B38: 1 | C38: 7 | D38: Festivo | E38: =VLOOKUP(E$1,'[1]Demanda requerida 2027'!$CI$74:$DS$97,MATCH(_xlfn.CONCAT(TEXT(DATE($A38,$B38,1),"mmm-yy"),$D38),'[1]Demanda requerida 2027'!$CI$70:$DS$70,0),FALSE) -> 637 | F38: =VLOOKUP(F$1,'[1]Demanda requerida 2027'!$CI$74:$DS$97,MATCH(_xlfn.CONCAT(TEXT(DATE($A38,$B38,1),"mmm-yy"),$D38),'[1]Demanda requerida 2027'!$CI$70:$DS$70,0),FALSE) -> 200 | G38: =VLOOKUP(G$1,'[1]Demanda requerida 2027'!$CI$74:$DS$97,MATCH(_xlfn.CONCAT(TEXT(DATE($A38,$B38,1),"mmm-yy"),$D38),'[1]Demanda requerida 2027'!$CI$70:$DS$70,0),FALSE) -> 200 | H38: =VLOOKUP(H$1,'[1]Demanda requerida 2027'!$CI$74:$DS$97,MATCH(_xlfn.CONCAT(TEXT(DATE($A38,$B38,1),"mmm-yy"),$D38),'[1]Demanda requerida 2027'!$CI$70:$DS$70,0),FALSE) -> 200 | I38: =VLOOKUP(I$1,'[1]Demanda requerida 2027'!$CI$74:$DS$97,MATCH(_xlfn.CONCAT(TEXT(DATE($A38,$B38,1),"mmm-yy"),$D38),'[1]Demanda requerida 2027'!$CI$70:$DS$70,0),FALSE) -> 200 | J38: =VLOOKUP(J$1,'[1]Demanda requerida 2027'!$CI$74:$DS$97,MATCH(_xlfn.CONCAT(TEXT(DATE($A38,$B38,1),"mmm-yy"),$D38),'[1]Demanda requerida 2027'!$CI$70:$DS$70,0),FALSE) -> 200 | K38: =VLOOKUP(K$1,'[1]Demanda requerida 2027'!$CI$74:$DS$97,MATCH(_xlfn.CONCAT(TEXT(DATE($A38,$B38,1),"mmm-yy"),$D38),'[1]Demanda requerida 2027'!$CI$70:$DS$70,0),FALSE) -> 200 | L38: =VLOOKUP(L$1,'[1]Demanda requerida 2027'!$CI$74:$DS$97,MATCH(_xlfn.CONCAT(TEXT(DATE($A38,$B38,1),"mmm-yy"),$D38),'[1]Demanda requerida 2027'!$CI$70:$DS$70,0),FALSE) -> 200 | ... AB38: =VLOOKUP(AB$1,'[1]Demanda requerida 2027'!$CI$74:$DS$97,MATCH(_xlfn.CONCAT(TEXT(DATE($A38,$B38,1),"mmm-yy"),$D38),'[1]Demanda requerida 2027'!$CI$70:$DS$70,0),FALSE) -> 2367 | AC38: =SUM(E38:AB38) -> 82040 | AD38: =+SUMPRODUCT(AC38:AC40,C38:C40) -> 3913842 | AE38: =+SUM(AD38:AD73) -> 67871522
A39: 2027 | B39: 1 | C39: 19 | D39: Ordinario | E39: =VLOOKUP(E$1,'[1]Demanda requerida 2027'!$CI$74:$DS$97,MATCH(_xlfn.CONCAT(TEXT(DATE($A39,$B39,1),"mmm-yy"),$D39),'[1]Demanda requerida 2027'!$CI$70:$DS$70,0),FALSE) -> 751 | F39: =VLOOKUP(F$1,'[1]Demanda requerida 2027'!$CI$74:$DS$97,MATCH(_xlfn.CONCAT(TEXT(DATE($A39,$B39,1),"mmm-yy"),$D39),'[1]Demanda requerida 2027'!$CI$70:$DS$70,0),FALSE) -> 200 | G39: =VLOOKUP(G$1,'[1]Demanda requerida 2027'!$CI$74:$DS$97,MATCH(_xlfn.CONCAT(TEXT(DATE($A39,$B39,1),"mmm-yy"),$D39),'[1]Demanda requerida 2027'!$CI$70:$DS$70,0),FALSE) -> 200 | H39: =VLOOKUP(H$1,'[1]Demanda requerida 2027'!$CI$74:$DS$97,MATCH(_xlfn.CONCAT(TEXT(DATE($A39,$B39,1),"mmm-yy"),$D39),'[1]Demanda requerida 2027'!$CI$70:$DS$70,0),FALSE) -> 200 | I39: =VLOOKUP(I$1,'[1]Demanda requerida 2027'!$CI$74:$DS$97,MATCH(_xlfn.CONCAT(TEXT(DATE($A39,$B39,1),"mmm-yy"),$D39),'[1]Demanda requerida 2027'!$CI$70:$DS$70,0),FALSE) -> 200 | J39: =VLOOKUP(J$1,'[1]Demanda requerida 2027'!$CI$74:$DS$97,MATCH(_xlfn.CONCAT(TEXT(DATE($A39,$B39,1),"mmm-yy"),$D39),'[1]Demanda requerida 2027'!$CI$70:$DS$70,0),FALSE) -> 200 | K39: =VLOOKUP(K$1,'[1]Demanda requerida 2027'!$CI$74:$DS$97,MATCH(_xlfn.CONCAT(TEXT(DATE($A39,$B39,1),"mmm-yy"),$D39),'[1]Demanda requerida 2027'!$CI$70:$DS$70,0),FALSE) -> 11 | L39: =VLOOKUP(L$1,'[1]Demanda requerida 2027'!$CI$74:$DS$97,MATCH(_xlfn.CONCAT(TEXT(DATE($A39,$B39,1),"mmm-yy"),$D39),'[1]Demanda requerida 2027'!$CI$70:$DS$70,0),FALSE) -> 1573 | ... AB39: =VLOOKUP(AB$1,'[1]Demanda requerida 2027'!$CI$74:$DS$97,MATCH(_xlfn.CONCAT(TEXT(DATE($A39,$B39,1),"mmm-yy"),$D39),'[1]Demanda requerida 2027'!$CI$70:$DS$70,0),FALSE) -> 4070 | AC39: =SUM(E39:AB39) -> 142433
A40: 2027 | B40: 1 | C40: 5 | D40: Sábado | E40: =VLOOKUP(E$1,'[1]Demanda requerida 2027'!$CI$74:$DS$97,MATCH(_xlfn.CONCAT(TEXT(DATE($A40,$B40,1),"mmm-yy"),$D40),'[1]Demanda requerida 2027'!$CI$70:$DS$70,0),FALSE) -> 183 | F40: =VLOOKUP(F$1,'[1]Demanda requerida 2027'!$CI$74:$DS$97,MATCH(_xlfn.CONCAT(TEXT(DATE($A40,$B40,1),"mmm-yy"),$D40),'[1]Demanda requerida 2027'!$CI$70:$DS$70,0),FALSE) -> 200 | G40: =VLOOKUP(G$1,'[1]Demanda requerida 2027'!$CI$74:$DS$97,MATCH(_xlfn.CONCAT(TEXT(DATE($A40,$B40,1),"mmm-yy"),$D40),'[1]Demanda requerida 2027'!$CI$70:$DS$70,0),FALSE) -> 200 | H40: =VLOOKUP(H$1,'[1]Demanda requerida 2027'!$CI$74:$DS$97,MATCH(_xlfn.CONCAT(TEXT(DATE($A40,$B40,1),"mmm-yy"),$D40),'[1]Demanda requerida 2027'!$CI$70:$DS$70,0),FALSE) -> 200 | I40: =VLOOKUP(I$1,'[1]Demanda requerida 2027'!$CI$74:$DS$97,MATCH(_xlfn.CONCAT(TEXT(DATE($A40,$B40,1),"mmm-yy"),$D40),'[1]Demanda requerida 2027'!$CI$70:$DS$70,0),FALSE) -> 200 | J40: =VLOOKUP(J$1,'[1]Demanda requerida 2027'!$CI$74:$DS$97,MATCH(_xlfn.CONCAT(TEXT(DATE($A40,$B40,1),"mmm-yy"),$D40),'[1]Demanda requerida 2027'!$CI$70:$DS$70,0),FALSE) -> 200 | K40: =VLOOKUP(K$1,'[1]Demanda requerida 2027'!$CI$74:$DS$97,MATCH(_xlfn.CONCAT(TEXT(DATE($A40,$B40,1),"mmm-yy"),$D40),'[1]Demanda requerida 2027'!$CI$70:$DS$70,0),FALSE) -> 200 | L40: =VLOOKUP(L$1,'[1]Demanda requerida 2027'!$CI$74:$DS$97,MATCH(_xlfn.CONCAT(TEXT(DATE($A40,$B40,1),"mmm-yy"),$D40),'[1]Demanda requerida 2027'!$CI$70:$DS$70,0),FALSE) -> 61 | ... AB40: =VLOOKUP(AB$1,'[1]Demanda requerida 2027'!$CI$74:$DS$97,MATCH(_xlfn.CONCAT(TEXT(DATE($A40,$B40,1),"mmm-yy"),$D40),'[1]Demanda requerida 2027'!$CI$70:$DS$70,0),FALSE) -> 4127 | AC40: =SUM(E40:AB40) -> 126667
A41: 2027 | B41: 2 | C41: 4 | D41: Festivo | E41: =VLOOKUP(E$1,'[1]Demanda requerida 2027'!$CI$74:$DS$97,MATCH(_xlfn.CONCAT(TEXT(DATE($A41,$B41,1),"mmm-yy"),$D41),'[1]Demanda requerida 2027'!$CI$70:$DS$70,0),FALSE) -> 81 | F41: =VLOOKUP(F$1,'[1]Demanda requerida 2027'!$CI$74:$DS$97,MATCH(_xlfn.CONCAT(TEXT(DATE($A41,$B41,1),"mmm-yy"),$D41),'[1]Demanda requerida 2027'!$CI$70:$DS$70,0),FALSE) -> 200 | G41: =VLOOKUP(G$1,'[1]Demanda requerida 2027'!$CI$74:$DS$97,MATCH(_xlfn.CONCAT(TEXT(DATE($A41,$B41,1),"mmm-yy"),$D41),'[1]Demanda requerida 2027'!$CI$70:$DS$70,0),FALSE) -> 200 | H41: =VLOOKUP(H$1,'[1]Demanda requerida 2027'!$CI$74:$DS$97,MATCH(_xlfn.CONCAT(TEXT(DATE($A41,$B41,1),"mmm-yy"),$D41),'[1]Demanda requerida 2027'!$CI$70:$DS$70,0),FALSE) -> 200 | I41: =VLOOKUP(I$1,'[1]Demanda requerida 2027'!$CI$74:$DS$97,MATCH(_xlfn.CONCAT(TEXT(DATE($A41,$B41,1),"mmm-yy"),$D41),'[1]Demanda requerida 2027'!$CI$70:$DS$70,0),FALSE) -> 200 | J41: =VLOOKUP(J$1,'[1]Demanda requerida 2027'!$CI$74:$DS$97,MATCH(_xlfn.CONCAT(TEXT(DATE($A41,$B41,1),"mmm-yy"),$D41),'[1]Demanda requerida 2027'!$CI$70:$DS$70,0),FALSE) -> 200 | K41: =VLOOKUP(K$1,'[1]Demanda requerida 2027'!$CI$74:$DS$97,MATCH(_xlfn.CONCAT(TEXT(DATE($A41,$B41,1),"mmm-yy"),$D41),'[1]Demanda requerida 2027'!$CI$70:$DS$70,0),FALSE) -> 200 | L41: =VLOOKUP(L$1,'[1]Demanda requerida 2027'!$CI$74:$DS$97,MATCH(_xlfn.CONCAT(TEXT(DATE($A41,$B41,1),"mmm-yy"),$D41),'[1]Demanda requerida 2027'!$CI$70:$DS$70,0),FALSE) -> 200 | ... AB41: =VLOOKUP(AB$1,'[1]Demanda requerida 2027'!$CI$74:$DS$97,MATCH(_xlfn.CONCAT(TEXT(DATE($A41,$B41,1),"mmm-yy"),$D41),'[1]Demanda requerida 2027'!$CI$70:$DS$70,0),FALSE) -> 2073 | AC41: =SUM(E41:AB41) -> 89401 | AD41: =+SUMPRODUCT(AC41:AC43,C41:C43) -> 3319492
A42: 2027 | B42: 2 | C42: 20 | D42: Ordinario | E42: =VLOOKUP(E$1,'[1]Demanda requerida 2027'!$CI$74:$DS$97,MATCH(_xlfn.CONCAT(TEXT(DATE($A42,$B42,1),"mmm-yy"),$D42),'[1]Demanda requerida 2027'!$CI$70:$DS$70,0),FALSE) -> 200 | F42: =VLOOKUP(F$1,'[1]Demanda requerida 2027'!$CI$74:$DS$97,MATCH(_xlfn.CONCAT(TEXT(DATE($A42,$B42,1),"mmm-yy"),$D42),'[1]Demanda requerida 2027'!$CI$70:$DS$70,0),FALSE) -> 200 | G42: =VLOOKUP(G$1,'[1]Demanda requerida 2027'!$CI$74:$DS$97,MATCH(_xlfn.CONCAT(TEXT(DATE($A42,$B42,1),"mmm-yy"),$D42),'[1]Demanda requerida 2027'!$CI$70:$DS$70,0),FALSE) -> 200 | H42: =VLOOKUP(H$1,'[1]Demanda requerida 2027'!$CI$74:$DS$97,MATCH(_xlfn.CONCAT(TEXT(DATE($A42,$B42,1),"mmm-yy"),$D42),'[1]Demanda requerida 2027'!$CI$70:$DS$70,0),FALSE) -> 200 | I42: =VLOOKUP(I$1,'[1]Demanda requerida 2027'!$CI$74:$DS$97,MATCH(_xlfn.CONCAT(TEXT(DATE($A42,$B42,1),"mmm-yy"),$D42),'[1]Demanda requerida 2027'!$CI$70:$DS$70,0),FALSE) -> 200 | J42: =VLOOKUP(J$1,'[1]Demanda requerida 2027'!$CI$74:$DS$97,MATCH(_xlfn.CONCAT(TEXT(DATE($A42,$B42,1),"mmm-yy"),$D42),'[1]Demanda requerida 2027'!$CI$70:$DS$70,0),FALSE) -> 200 | K42: =VLOOKUP(K$1,'[1]Demanda requerida 2027'!$CI$74:$DS$97,MATCH(_xlfn.CONCAT(TEXT(DATE($A42,$B42,1),"mmm-yy"),$D42),'[1]Demanda requerida 2027'!$CI$70:$DS$70,0),FALSE) -> 460 | L42: =VLOOKUP(L$1,'[1]Demanda requerida 2027'!$CI$74:$DS$97,MATCH(_xlfn.CONCAT(TEXT(DATE($A42,$B42,1),"mmm-yy"),$D42),'[1]Demanda requerida 2027'!$CI$70:$DS$70,0),FALSE) -> 1471 | ... AB42: =VLOOKUP(AB$1,'[1]Demanda requerida 2027'!$CI$74:$DS$97,MATCH(_xlfn.CONCAT(TEXT(DATE($A42,$B42,1),"mmm-yy"),$D42),'[1]Demanda requerida 2027'!$CI$70:$DS$70,0),FALSE) -> 2232 | AC42: =SUM(E42:AB42) -> 126126
A43: 2027 | B43: 2 | C43: 4 | D43: Sábado | E43: =VLOOKUP(E$1,'[1]Demanda requerida 2027'!$CI$74:$DS$97,MATCH(_xlfn.CONCAT(TEXT(DATE($A43,$B43,1),"mmm-yy"),$D43),'[1]Demanda requerida 2027'!$CI$70:$DS$70,0),FALSE) -> 200 | F43: =VLOOKUP(F$1,'[1]Demanda requerida 2027'!$CI$74:$DS$97,MATCH(_xlfn.CONCAT(TEXT(DATE($A43,$B43,1),"mmm-yy"),$D43),'[1]Demanda requerida 2027'!$CI$70:$DS$70,0),FALSE) -> 200 | G43: =VLOOKUP(G$1,'[1]Demanda requerida 2027'!$CI$74:$DS$97,MATCH(_xlfn.CONCAT(TEXT(DATE($A43,$B43,1),"mmm-yy"),$D43),'[1]Demanda requerida 2027'!$CI$70:$DS$70,0),FALSE) -> 200 | H43: =VLOOKUP(H$1,'[1]Demanda requerida 2027'!$CI$74:$DS$97,MATCH(_xlfn.CONCAT(TEXT(DATE($A43,$B43,1),"mmm-yy"),$D43),'[1]Demanda requerida 2027'!$CI$70:$DS$70,0),FALSE) -> 200 | I43: =VLOOKUP(I$1,'[1]Demanda requerida 2027'!$CI$74:$DS$97,MATCH(_xlfn.CONCAT(TEXT(DATE($A43,$B43,1),"mmm-yy"),$D43),'[1]Demanda requerida 2027'!$CI$70:$DS$70,0),FALSE) -> 200 | J43: =VLOOKUP(J$1,'[1]Demanda requerida 2027'!$CI$74:$DS$97,MATCH(_xlfn.CONCAT(TEXT(DATE($A43,$B43,1),"mmm-yy"),$D43),'[1]Demanda requerida 2027'!$CI$70:$DS$70,0),FALSE) -> 200 | K43: =VLOOKUP(K$1,'[1]Demanda requerida 2027'!$CI$74:$DS$97,MATCH(_xlfn.CONCAT(TEXT(DATE($A43,$B43,1),"mmm-yy"),$D43),'[1]Demanda requerida 2027'!$CI$70:$DS$70,0),FALSE) -> 200 | L43: =VLOOKUP(L$1,'[1]Demanda requerida 2027'!$CI$74:$DS$97,MATCH(_xlfn.CONCAT(TEXT(DATE($A43,$B43,1),"mmm-yy"),$D43),'[1]Demanda requerida 2027'!$CI$70:$DS$70,0),FALSE) -> 200 | ... AB43: =VLOOKUP(AB$1,'[1]Demanda requerida 2027'!$CI$74:$DS$97,MATCH(_xlfn.CONCAT(TEXT(DATE($A43,$B43,1),"mmm-yy"),$D43),'[1]Demanda requerida 2027'!$CI$70:$DS$70,0),FALSE) -> 2996 | AC43: =SUM(E43:AB43) -> 109842
A44: 2027 | B44: 3 | C44: 7 | D44: Festivo | E44: =VLOOKUP(E$1,'[1]Demanda requerida 2027'!$CI$74:$DS$97,MATCH(_xlfn.CONCAT(TEXT(DATE($A44,$B44,1),"mmm-yy"),$D44),'[1]Demanda requerida 2027'!$CI$70:$DS$70,0),FALSE) -> 200 | F44: =VLOOKUP(F$1,'[1]Demanda requerida 2027'!$CI$74:$DS$97,MATCH(_xlfn.CONCAT(TEXT(DATE($A44,$B44,1),"mmm-yy"),$D44),'[1]Demanda requerida 2027'!$CI$70:$DS$70,0),FALSE) -> 200 | G44: =VLOOKUP(G$1,'[1]Demanda requerida 2027'!$CI$74:$DS$97,MATCH(_xlfn.CONCAT(TEXT(DATE($A44,$B44,1),"mmm-yy"),$D44),'[1]Demanda requerida 2027'!$CI$70:$DS$70,0),FALSE) -> 200 | H44: =VLOOKUP(H$1,'[1]Demanda requerida 2027'!$CI$74:$DS$97,MATCH(_xlfn.CONCAT(TEXT(DATE($A44,$B44,1),"mmm-yy"),$D44),'[1]Demanda requerida 2027'!$CI$70:$DS$70,0),FALSE) -> 200 | I44: =VLOOKUP(I$1,'[1]Demanda requerida 2027'!$CI$74:$DS$97,MATCH(_xlfn.CONCAT(TEXT(DATE($A44,$B44,1),"mmm-yy"),$D44),'[1]Demanda requerida 2027'!$CI$70:$DS$70,0),FALSE) -> 200 | J44: =VLOOKUP(J$1,'[1]Demanda requerida 2027'!$CI$74:$DS$97,MATCH(_xlfn.CONCAT(TEXT(DATE($A44,$B44,1),"mmm-yy"),$D44),'[1]Demanda requerida 2027'!$CI$70:$DS$70,0),FALSE) -> 200 | K44: =VLOOKUP(K$1,'[1]Demanda requerida 2027'!$CI$74:$DS$97,MATCH(_xlfn.CONCAT(TEXT(DATE($A44,$B44,1),"mmm-yy"),$D44),'[1]Demanda requerida 2027'!$CI$70:$DS$70,0),FALSE) -> 200 | L44: =VLOOKUP(L$1,'[1]Demanda requerida 2027'!$CI$74:$DS$97,MATCH(_xlfn.CONCAT(TEXT(DATE($A44,$B44,1),"mmm-yy"),$D44),'[1]Demanda requerida 2027'!$CI$70:$DS$70,0),FALSE) -> 200 | ... AB44: =VLOOKUP(AB$1,'[1]Demanda requerida 2027'!$CI$74:$DS$97,MATCH(_xlfn.CONCAT(TEXT(DATE($A44,$B44,1),"mmm-yy"),$D44),'[1]Demanda requerida 2027'!$CI$70:$DS$70,0),FALSE) -> 200 | AC44: =SUM(E44:AB44) -> 11474 | AD44: =+SUMPRODUCT(AC44:AC46,C44:C46) -> 10019614
A45: 2027 | B45: 3 | C45: 20 | D45: Ordinario | E45: =VLOOKUP(E$1,'[1]Demanda requerida 2027'!$CI$74:$DS$97,MATCH(_xlfn.CONCAT(TEXT(DATE($A45,$B45,1),"mmm-yy"),$D45),'[1]Demanda requerida 2027'!$CI$70:$DS$70,0),FALSE) -> 11729 | F45: =VLOOKUP(F$1,'[1]Demanda requerida 2027'!$CI$74:$DS$97,MATCH(_xlfn.CONCAT(TEXT(DATE($A45,$B45,1),"mmm-yy"),$D45),'[1]Demanda requerida 2027'!$CI$70:$DS$70,0),FALSE) -> 10525 | G45: =VLOOKUP(G$1,'[1]Demanda requerida 2027'!$CI$74:$DS$97,MATCH(_xlfn.CONCAT(TEXT(DATE($A45,$B45,1),"mmm-yy"),$D45),'[1]Demanda requerida 2027'!$CI$70:$DS$70,0),FALSE) -> 9717 | H45: =VLOOKUP(H$1,'[1]Demanda requerida 2027'!$CI$74:$DS$97,MATCH(_xlfn.CONCAT(TEXT(DATE($A45,$B45,1),"mmm-yy"),$D45),'[1]Demanda requerida 2027'!$CI$70:$DS$70,0),FALSE) -> 9199 | I45: =VLOOKUP(I$1,'[1]Demanda requerida 2027'!$CI$74:$DS$97,MATCH(_xlfn.CONCAT(TEXT(DATE($A45,$B45,1),"mmm-yy"),$D45),'[1]Demanda requerida 2027'!$CI$70:$DS$70,0),FALSE) -> 9182 | J45: =VLOOKUP(J$1,'[1]Demanda requerida 2027'!$CI$74:$DS$97,MATCH(_xlfn.CONCAT(TEXT(DATE($A45,$B45,1),"mmm-yy"),$D45),'[1]Demanda requerida 2027'!$CI$70:$DS$70,0),FALSE) -> 10783 | K45: =VLOOKUP(K$1,'[1]Demanda requerida 2027'!$CI$74:$DS$97,MATCH(_xlfn.CONCAT(TEXT(DATE($A45,$B45,1),"mmm-yy"),$D45),'[1]Demanda requerida 2027'!$CI$70:$DS$70,0),FALSE) -> 12527 | L45: =VLOOKUP(L$1,'[1]Demanda requerida 2027'!$CI$74:$DS$97,MATCH(_xlfn.CONCAT(TEXT(DATE($A45,$B45,1),"mmm-yy"),$D45),'[1]Demanda requerida 2027'!$CI$70:$DS$70,0),FALSE) -> 14125 | ... AB45: =VLOOKUP(AB$1,'[1]Demanda requerida 2027'!$CI$74:$DS$97,MATCH(_xlfn.CONCAT(TEXT(DATE($A45,$B45,1),"mmm-yy"),$D45),'[1]Demanda requerida 2027'!$CI$70:$DS$70,0),FALSE) -> 15365 | AC45: =SUM(E45:AB45) -> 433288
A46: 2027 | B46: 3 | C46: 4 | D46: Sábado | E46: =VLOOKUP(E$1,'[1]Demanda requerida 2027'!$CI$74:$DS$97,MATCH(_xlfn.CONCAT(TEXT(DATE($A46,$B46,1),"mmm-yy"),$D46),'[1]Demanda requerida 2027'!$CI$70:$DS$70,0),FALSE) -> 8173 | F46: =VLOOKUP(F$1,'[1]Demanda requerida 2027'!$CI$74:$DS$97,MATCH(_xlfn.CONCAT(TEXT(DATE($A46,$B46,1),"mmm-yy"),$D46),'[1]Demanda requerida 2027'!$CI$70:$DS$70,0),FALSE) -> 6900 | G46: =VLOOKUP(G$1,'[1]Demanda requerida 2027'!$CI$74:$DS$97,MATCH(_xlfn.CONCAT(TEXT(DATE($A46,$B46,1),"mmm-yy"),$D46),'[1]Demanda requerida 2027'!$CI$70:$DS$70,0),FALSE) -> 6126 | H46: =VLOOKUP(H$1,'[1]Demanda requerida 2027'!$CI$74:$DS$97,MATCH(_xlfn.CONCAT(TEXT(DATE($A46,$B46,1),"mmm-yy"),$D46),'[1]Demanda requerida 2027'!$CI$70:$DS$70,0),FALSE) -> 5532 | I46: =VLOOKUP(I$1,'[1]Demanda requerida 2027'!$CI$74:$DS$97,MATCH(_xlfn.CONCAT(TEXT(DATE($A46,$B46,1),"mmm-yy"),$D46),'[1]Demanda requerida 2027'!$CI$70:$DS$70,0),FALSE) -> 5450 | J46: =VLOOKUP(J$1,'[1]Demanda requerida 2027'!$CI$74:$DS$97,MATCH(_xlfn.CONCAT(TEXT(DATE($A46,$B46,1),"mmm-yy"),$D46),'[1]Demanda requerida 2027'!$CI$70:$DS$70,0),FALSE) -> 5821 | K46: =VLOOKUP(K$1,'[1]Demanda requerida 2027'!$CI$74:$DS$97,MATCH(_xlfn.CONCAT(TEXT(DATE($A46,$B46,1),"mmm-yy"),$D46),'[1]Demanda requerida 2027'!$CI$70:$DS$70,0),FALSE) -> 6669 | L46: =VLOOKUP(L$1,'[1]Demanda requerida 2027'!$CI$74:$DS$97,MATCH(_xlfn.CONCAT(TEXT(DATE($A46,$B46,1),"mmm-yy"),$D46),'[1]Demanda requerida 2027'!$CI$70:$DS$70,0),FALSE) -> 8495 | ... AB46: =VLOOKUP(AB$1,'[1]Demanda requerida 2027'!$CI$74:$DS$97,MATCH(_xlfn.CONCAT(TEXT(DATE($A46,$B46,1),"mmm-yy"),$D46),'[1]Demanda requerida 2027'!$CI$70:$DS$70,0),FALSE) -> 12881 | AC46: =SUM(E46:AB46) -> 318384
A47: 2027 | B47: 4 | C47: 4 | D47: Festivo | E47: =VLOOKUP(E$1,'[1]Demanda requerida 2027'!$CI$74:$DS$97,MATCH(_xlfn.CONCAT(TEXT(DATE($A47,$B47,1),"mmm-yy"),$D47),'[1]Demanda requerida 2027'!$CI$70:$DS$70,0),FALSE) -> 200 | F47: =VLOOKUP(F$1,'[1]Demanda requerida 2027'!$CI$74:$DS$97,MATCH(_xlfn.CONCAT(TEXT(DATE($A47,$B47,1),"mmm-yy"),$D47),'[1]Demanda requerida 2027'!$CI$70:$DS$70,0),FALSE) -> 200 | G47: =VLOOKUP(G$1,'[1]Demanda requerida 2027'!$CI$74:$DS$97,MATCH(_xlfn.CONCAT(TEXT(DATE($A47,$B47,1),"mmm-yy"),$D47),'[1]Demanda requerida 2027'!$CI$70:$DS$70,0),FALSE) -> 200 | H47: =VLOOKUP(H$1,'[1]Demanda requerida 2027'!$CI$74:$DS$97,MATCH(_xlfn.CONCAT(TEXT(DATE($A47,$B47,1),"mmm-yy"),$D47),'[1]Demanda requerida 2027'!$CI$70:$DS$70,0),FALSE) -> 200 | I47: =VLOOKUP(I$1,'[1]Demanda requerida 2027'!$CI$74:$DS$97,MATCH(_xlfn.CONCAT(TEXT(DATE($A47,$B47,1),"mmm-yy"),$D47),'[1]Demanda requerida 2027'!$CI$70:$DS$70,0),FALSE) -> 200 | J47: =VLOOKUP(J$1,'[1]Demanda requerida 2027'!$CI$74:$DS$97,MATCH(_xlfn.CONCAT(TEXT(DATE($A47,$B47,1),"mmm-yy"),$D47),'[1]Demanda requerida 2027'!$CI$70:$DS$70,0),FALSE) -> 200 | K47: =VLOOKUP(K$1,'[1]Demanda requerida 2027'!$CI$74:$DS$97,MATCH(_xlfn.CONCAT(TEXT(DATE($A47,$B47,1),"mmm-yy"),$D47),'[1]Demanda requerida 2027'!$CI$70:$DS$70,0),FALSE) -> 200 | L47: =VLOOKUP(L$1,'[1]Demanda requerida 2027'!$CI$74:$DS$97,MATCH(_xlfn.CONCAT(TEXT(DATE($A47,$B47,1),"mmm-yy"),$D47),'[1]Demanda requerida 2027'!$CI$70:$DS$70,0),FALSE) -> 200 | ... AB47: =VLOOKUP(AB$1,'[1]Demanda requerida 2027'!$CI$74:$DS$97,MATCH(_xlfn.CONCAT(TEXT(DATE($A47,$B47,1),"mmm-yy"),$D47),'[1]Demanda requerida 2027'!$CI$70:$DS$70,0),FALSE) -> 3667 | AC47: =SUM(E47:AB47) -> 81382 | AD47: =+SUMPRODUCT(AC47:AC49,C47:C49) -> 4096284
A48: 2027 | B48: 4 | C48: 22 | D48: Ordinario | E48: =VLOOKUP(E$1,'[1]Demanda requerida 2027'!$CI$74:$DS$97,MATCH(_xlfn.CONCAT(TEXT(DATE($A48,$B48,1),"mmm-yy"),$D48),'[1]Demanda requerida 2027'!$CI$70:$DS$70,0),FALSE) -> 944 | F48: =VLOOKUP(F$1,'[1]Demanda requerida 2027'!$CI$74:$DS$97,MATCH(_xlfn.CONCAT(TEXT(DATE($A48,$B48,1),"mmm-yy"),$D48),'[1]Demanda requerida 2027'!$CI$70:$DS$70,0),FALSE) -> 200 | G48: =VLOOKUP(G$1,'[1]Demanda requerida 2027'!$CI$74:$DS$97,MATCH(_xlfn.CONCAT(TEXT(DATE($A48,$B48,1),"mmm-yy"),$D48),'[1]Demanda requerida 2027'!$CI$70:$DS$70,0),FALSE) -> 200 | H48: =VLOOKUP(H$1,'[1]Demanda requerida 2027'!$CI$74:$DS$97,MATCH(_xlfn.CONCAT(TEXT(DATE($A48,$B48,1),"mmm-yy"),$D48),'[1]Demanda requerida 2027'!$CI$70:$DS$70,0),FALSE) -> 200 | I48: =VLOOKUP(I$1,'[1]Demanda requerida 2027'!$CI$74:$DS$97,MATCH(_xlfn.CONCAT(TEXT(DATE($A48,$B48,1),"mmm-yy"),$D48),'[1]Demanda requerida 2027'!$CI$70:$DS$70,0),FALSE) -> 200 | J48: =VLOOKUP(J$1,'[1]Demanda requerida 2027'!$CI$74:$DS$97,MATCH(_xlfn.CONCAT(TEXT(DATE($A48,$B48,1),"mmm-yy"),$D48),'[1]Demanda requerida 2027'!$CI$70:$DS$70,0),FALSE) -> 200 | K48: =VLOOKUP(K$1,'[1]Demanda requerida 2027'!$CI$74:$DS$97,MATCH(_xlfn.CONCAT(TEXT(DATE($A48,$B48,1),"mmm-yy"),$D48),'[1]Demanda requerida 2027'!$CI$70:$DS$70,0),FALSE) -> 944 | L48: =VLOOKUP(L$1,'[1]Demanda requerida 2027'!$CI$74:$DS$97,MATCH(_xlfn.CONCAT(TEXT(DATE($A48,$B48,1),"mmm-yy"),$D48),'[1]Demanda requerida 2027'!$CI$70:$DS$70,0),FALSE) -> 2577 | ... AB48: =VLOOKUP(AB$1,'[1]Demanda requerida 2027'!$CI$74:$DS$97,MATCH(_xlfn.CONCAT(TEXT(DATE($A48,$B48,1),"mmm-yy"),$D48),'[1]Demanda requerida 2027'!$CI$70:$DS$70,0),FALSE) -> 3679 | AC48: =SUM(E48:AB48) -> 149066
A49: 2027 | B49: 4 | C49: 4 | D49: Sábado | E49: =VLOOKUP(E$1,'[1]Demanda requerida 2027'!$CI$74:$DS$97,MATCH(_xlfn.CONCAT(TEXT(DATE($A49,$B49,1),"mmm-yy"),$D49),'[1]Demanda requerida 2027'!$CI$70:$DS$70,0),FALSE) -> 585 | F49: =VLOOKUP(F$1,'[1]Demanda requerida 2027'!$CI$74:$DS$97,MATCH(_xlfn.CONCAT(TEXT(DATE($A49,$B49,1),"mmm-yy"),$D49),'[1]Demanda requerida 2027'!$CI$70:$DS$70,0),FALSE) -> 200 | G49: =VLOOKUP(G$1,'[1]Demanda requerida 2027'!$CI$74:$DS$97,MATCH(_xlfn.CONCAT(TEXT(DATE($A49,$B49,1),"mmm-yy"),$D49),'[1]Demanda requerida 2027'!$CI$70:$DS$70,0),FALSE) -> 200 | H49: =VLOOKUP(H$1,'[1]Demanda requerida 2027'!$CI$74:$DS$97,MATCH(_xlfn.CONCAT(TEXT(DATE($A49,$B49,1),"mmm-yy"),$D49),'[1]Demanda requerida 2027'!$CI$70:$DS$70,0),FALSE) -> 200 | I49: =VLOOKUP(I$1,'[1]Demanda requerida 2027'!$CI$74:$DS$97,MATCH(_xlfn.CONCAT(TEXT(DATE($A49,$B49,1),"mmm-yy"),$D49),'[1]Demanda requerida 2027'!$CI$70:$DS$70,0),FALSE) -> 200 | J49: =VLOOKUP(J$1,'[1]Demanda requerida 2027'!$CI$74:$DS$97,MATCH(_xlfn.CONCAT(TEXT(DATE($A49,$B49,1),"mmm-yy"),$D49),'[1]Demanda requerida 2027'!$CI$70:$DS$70,0),FALSE) -> 200 | K49: =VLOOKUP(K$1,'[1]Demanda requerida 2027'!$CI$74:$DS$97,MATCH(_xlfn.CONCAT(TEXT(DATE($A49,$B49,1),"mmm-yy"),$D49),'[1]Demanda requerida 2027'!$CI$70:$DS$70,0),FALSE) -> 200 | L49: =VLOOKUP(L$1,'[1]Demanda requerida 2027'!$CI$74:$DS$97,MATCH(_xlfn.CONCAT(TEXT(DATE($A49,$B49,1),"mmm-yy"),$D49),'[1]Demanda requerida 2027'!$CI$70:$DS$70,0),FALSE) -> 767 | ... AB49: =VLOOKUP(AB$1,'[1]Demanda requerida 2027'!$CI$74:$DS$97,MATCH(_xlfn.CONCAT(TEXT(DATE($A49,$B49,1),"mmm-yy"),$D49),'[1]Demanda requerida 2027'!$CI$70:$DS$70,0),FALSE) -> 4164 | AC49: =SUM(E49:AB49) -> 122826
A50: 2027 | B50: 5 | C50: 8 | D50: Festivo | E50: =VLOOKUP(E$1,'[1]Demanda requerida 2027'!$CI$74:$DS$97,MATCH(_xlfn.CONCAT(TEXT(DATE($A50,$B50,1),"mmm-yy"),$D50),'[1]Demanda requerida 2027'!$CI$70:$DS$70,0),FALSE) -> 200 | F50: =VLOOKUP(F$1,'[1]Demanda requerida 2027'!$CI$74:$DS$97,MATCH(_xlfn.CONCAT(TEXT(DATE($A50,$B50,1),"mmm-yy"),$D50),'[1]Demanda requerida 2027'!$CI$70:$DS$70,0),FALSE) -> 200 | G50: =VLOOKUP(G$1,'[1]Demanda requerida 2027'!$CI$74:$DS$97,MATCH(_xlfn.CONCAT(TEXT(DATE($A50,$B50,1),"mmm-yy"),$D50),'[1]Demanda requerida 2027'!$CI$70:$DS$70,0),FALSE) -> 200 | H50: =VLOOKUP(H$1,'[1]Demanda requerida 2027'!$CI$74:$DS$97,MATCH(_xlfn.CONCAT(TEXT(DATE($A50,$B50,1),"mmm-yy"),$D50),'[1]Demanda requerida 2027'!$CI$70:$DS$70,0),FALSE) -> 200 | I50: =VLOOKUP(I$1,'[1]Demanda requerida 2027'!$CI$74:$DS$97,MATCH(_xlfn.CONCAT(TEXT(DATE($A50,$B50,1),"mmm-yy"),$D50),'[1]Demanda requerida 2027'!$CI$70:$DS$70,0),FALSE) -> 200 | J50: =VLOOKUP(J$1,'[1]Demanda requerida 2027'!$CI$74:$DS$97,MATCH(_xlfn.CONCAT(TEXT(DATE($A50,$B50,1),"mmm-yy"),$D50),'[1]Demanda requerida 2027'!$CI$70:$DS$70,0),FALSE) -> 200 | K50: =VLOOKUP(K$1,'[1]Demanda requerida 2027'!$CI$74:$DS$97,MATCH(_xlfn.CONCAT(TEXT(DATE($A50,$B50,1),"mmm-yy"),$D50),'[1]Demanda requerida 2027'!$CI$70:$DS$70,0),FALSE) -> 200 | L50: =VLOOKUP(L$1,'[1]Demanda requerida 2027'!$CI$74:$DS$97,MATCH(_xlfn.CONCAT(TEXT(DATE($A50,$B50,1),"mmm-yy"),$D50),'[1]Demanda requerida 2027'!$CI$70:$DS$70,0),FALSE) -> 200 | ... AB50: =VLOOKUP(AB$1,'[1]Demanda requerida 2027'!$CI$74:$DS$97,MATCH(_xlfn.CONCAT(TEXT(DATE($A50,$B50,1),"mmm-yy"),$D50),'[1]Demanda requerida 2027'!$CI$70:$DS$70,0),FALSE) -> 200 | AC50: =SUM(E50:AB50) -> 18606 | AD50: =+SUMPRODUCT(AC50:AC52,C50:C52) -> 9564657
A51: 2027 | B51: 5 | C51: 19 | D51: Ordinario | E51: =VLOOKUP(E$1,'[1]Demanda requerida 2027'!$CI$74:$DS$97,MATCH(_xlfn.CONCAT(TEXT(DATE($A51,$B51,1),"mmm-yy"),$D51),'[1]Demanda requerida 2027'!$CI$70:$DS$70,0),FALSE) -> 10115 | F51: =VLOOKUP(F$1,'[1]Demanda requerida 2027'!$CI$74:$DS$97,MATCH(_xlfn.CONCAT(TEXT(DATE($A51,$B51,1),"mmm-yy"),$D51),'[1]Demanda requerida 2027'!$CI$70:$DS$70,0),FALSE) -> 8673 | G51: =VLOOKUP(G$1,'[1]Demanda requerida 2027'!$CI$74:$DS$97,MATCH(_xlfn.CONCAT(TEXT(DATE($A51,$B51,1),"mmm-yy"),$D51),'[1]Demanda requerida 2027'!$CI$70:$DS$70,0),FALSE) -> 7866 | H51: =VLOOKUP(H$1,'[1]Demanda requerida 2027'!$CI$74:$DS$97,MATCH(_xlfn.CONCAT(TEXT(DATE($A51,$B51,1),"mmm-yy"),$D51),'[1]Demanda requerida 2027'!$CI$70:$DS$70,0),FALSE) -> 7434 | I51: =VLOOKUP(I$1,'[1]Demanda requerida 2027'!$CI$74:$DS$97,MATCH(_xlfn.CONCAT(TEXT(DATE($A51,$B51,1),"mmm-yy"),$D51),'[1]Demanda requerida 2027'!$CI$70:$DS$70,0),FALSE) -> 7453 | J51: =VLOOKUP(J$1,'[1]Demanda requerida 2027'!$CI$74:$DS$97,MATCH(_xlfn.CONCAT(TEXT(DATE($A51,$B51,1),"mmm-yy"),$D51),'[1]Demanda requerida 2027'!$CI$70:$DS$70,0),FALSE) -> 8673 | K51: =VLOOKUP(K$1,'[1]Demanda requerida 2027'!$CI$74:$DS$97,MATCH(_xlfn.CONCAT(TEXT(DATE($A51,$B51,1),"mmm-yy"),$D51),'[1]Demanda requerida 2027'!$CI$70:$DS$70,0),FALSE) -> 10209 | L51: =VLOOKUP(L$1,'[1]Demanda requerida 2027'!$CI$74:$DS$97,MATCH(_xlfn.CONCAT(TEXT(DATE($A51,$B51,1),"mmm-yy"),$D51),'[1]Demanda requerida 2027'!$CI$70:$DS$70,0),FALSE) -> 12084 | ... AB51: =VLOOKUP(AB$1,'[1]Demanda requerida 2027'!$CI$74:$DS$97,MATCH(_xlfn.CONCAT(TEXT(DATE($A51,$B51,1),"mmm-yy"),$D51),'[1]Demanda requerida 2027'!$CI$70:$DS$70,0),FALSE) -> 13810 | AC51: =SUM(E51:AB51) -> 390195
A52: 2027 | B52: 5 | C52: 4 | D52: Sábado | E52: =VLOOKUP(E$1,'[1]Demanda requerida 2027'!$CI$74:$DS$97,MATCH(_xlfn.CONCAT(TEXT(DATE($A52,$B52,1),"mmm-yy"),$D52),'[1]Demanda requerida 2027'!$CI$70:$DS$70,0),FALSE) -> 15520 | F52: =VLOOKUP(F$1,'[1]Demanda requerida 2027'!$CI$74:$DS$97,MATCH(_xlfn.CONCAT(TEXT(DATE($A52,$B52,1),"mmm-yy"),$D52),'[1]Demanda requerida 2027'!$CI$70:$DS$70,0),FALSE) -> 13979 | G52: =VLOOKUP(G$1,'[1]Demanda requerida 2027'!$CI$74:$DS$97,MATCH(_xlfn.CONCAT(TEXT(DATE($A52,$B52,1),"mmm-yy"),$D52),'[1]Demanda requerida 2027'!$CI$70:$DS$70,0),FALSE) -> 13009 | H52: =VLOOKUP(H$1,'[1]Demanda requerida 2027'!$CI$74:$DS$97,MATCH(_xlfn.CONCAT(TEXT(DATE($A52,$B52,1),"mmm-yy"),$D52),'[1]Demanda requerida 2027'!$CI$70:$DS$70,0),FALSE) -> 12327 | I52: =VLOOKUP(I$1,'[1]Demanda requerida 2027'!$CI$74:$DS$97,MATCH(_xlfn.CONCAT(TEXT(DATE($A52,$B52,1),"mmm-yy"),$D52),'[1]Demanda requerida 2027'!$CI$70:$DS$70,0),FALSE) -> 12135 | J52: =VLOOKUP(J$1,'[1]Demanda requerida 2027'!$CI$74:$DS$97,MATCH(_xlfn.CONCAT(TEXT(DATE($A52,$B52,1),"mmm-yy"),$D52),'[1]Demanda requerida 2027'!$CI$70:$DS$70,0),FALSE) -> 12434 | K52: =VLOOKUP(K$1,'[1]Demanda requerida 2027'!$CI$74:$DS$97,MATCH(_xlfn.CONCAT(TEXT(DATE($A52,$B52,1),"mmm-yy"),$D52),'[1]Demanda requerida 2027'!$CI$70:$DS$70,0),FALSE) -> 13287 | L52: =VLOOKUP(L$1,'[1]Demanda requerida 2027'!$CI$74:$DS$97,MATCH(_xlfn.CONCAT(TEXT(DATE($A52,$B52,1),"mmm-yy"),$D52),'[1]Demanda requerida 2027'!$CI$70:$DS$70,0),FALSE) -> 16018 | ... AB52: =VLOOKUP(AB$1,'[1]Demanda requerida 2027'!$CI$74:$DS$97,MATCH(_xlfn.CONCAT(TEXT(DATE($A52,$B52,1),"mmm-yy"),$D52),'[1]Demanda requerida 2027'!$CI$70:$DS$70,0),FALSE) -> 18478 | AC52: =SUM(E52:AB52) -> 500526
A53: 2027 | B53: 6 | C53: 5 | D53: Festivo | E53: =VLOOKUP(E$1,'[1]Demanda requerida 2027'!$CI$74:$DS$97,MATCH(_xlfn.CONCAT(TEXT(DATE($A53,$B53,1),"mmm-yy"),$D53),'[1]Demanda requerida 2027'!$CI$70:$DS$70,0),FALSE) -> 200 | F53: =VLOOKUP(F$1,'[1]Demanda requerida 2027'!$CI$74:$DS$97,MATCH(_xlfn.CONCAT(TEXT(DATE($A53,$B53,1),"mmm-yy"),$D53),'[1]Demanda requerida 2027'!$CI$70:$DS$70,0),FALSE) -> 200 | G53: =VLOOKUP(G$1,'[1]Demanda requerida 2027'!$CI$74:$DS$97,MATCH(_xlfn.CONCAT(TEXT(DATE($A53,$B53,1),"mmm-yy"),$D53),'[1]Demanda requerida 2027'!$CI$70:$DS$70,0),FALSE) -> 200 | H53: =VLOOKUP(H$1,'[1]Demanda requerida 2027'!$CI$74:$DS$97,MATCH(_xlfn.CONCAT(TEXT(DATE($A53,$B53,1),"mmm-yy"),$D53),'[1]Demanda requerida 2027'!$CI$70:$DS$70,0),FALSE) -> 200 | I53: =VLOOKUP(I$1,'[1]Demanda requerida 2027'!$CI$74:$DS$97,MATCH(_xlfn.CONCAT(TEXT(DATE($A53,$B53,1),"mmm-yy"),$D53),'[1]Demanda requerida 2027'!$CI$70:$DS$70,0),FALSE) -> 200 | J53: =VLOOKUP(J$1,'[1]Demanda requerida 2027'!$CI$74:$DS$97,MATCH(_xlfn.CONCAT(TEXT(DATE($A53,$B53,1),"mmm-yy"),$D53),'[1]Demanda requerida 2027'!$CI$70:$DS$70,0),FALSE) -> 200 | K53: =VLOOKUP(K$1,'[1]Demanda requerida 2027'!$CI$74:$DS$97,MATCH(_xlfn.CONCAT(TEXT(DATE($A53,$B53,1),"mmm-yy"),$D53),'[1]Demanda requerida 2027'!$CI$70:$DS$70,0),FALSE) -> 200 | L53: =VLOOKUP(L$1,'[1]Demanda requerida 2027'!$CI$74:$DS$97,MATCH(_xlfn.CONCAT(TEXT(DATE($A53,$B53,1),"mmm-yy"),$D53),'[1]Demanda requerida 2027'!$CI$70:$DS$70,0),FALSE) -> 200 | ... AB53: =VLOOKUP(AB$1,'[1]Demanda requerida 2027'!$CI$74:$DS$97,MATCH(_xlfn.CONCAT(TEXT(DATE($A53,$B53,1),"mmm-yy"),$D53),'[1]Demanda requerida 2027'!$CI$70:$DS$70,0),FALSE) -> 200 | AC53: =SUM(E53:AB53) -> 17990 | AD53: =+SUMPRODUCT(AC53:AC55,C53:C55) -> 4633932
A54: 2027 | B54: 6 | C54: 21 | D54: Ordinario | E54: =VLOOKUP(E$1,'[1]Demanda requerida 2027'!$CI$74:$DS$97,MATCH(_xlfn.CONCAT(TEXT(DATE($A54,$B54,1),"mmm-yy"),$D54),'[1]Demanda requerida 2027'!$CI$70:$DS$70,0),FALSE) -> 1626 | F54: =VLOOKUP(F$1,'[1]Demanda requerida 2027'!$CI$74:$DS$97,MATCH(_xlfn.CONCAT(TEXT(DATE($A54,$B54,1),"mmm-yy"),$D54),'[1]Demanda requerida 2027'!$CI$70:$DS$70,0),FALSE) -> 299 | G54: =VLOOKUP(G$1,'[1]Demanda requerida 2027'!$CI$74:$DS$97,MATCH(_xlfn.CONCAT(TEXT(DATE($A54,$B54,1),"mmm-yy"),$D54),'[1]Demanda requerida 2027'!$CI$70:$DS$70,0),FALSE) -> 200 | H54: =VLOOKUP(H$1,'[1]Demanda requerida 2027'!$CI$74:$DS$97,MATCH(_xlfn.CONCAT(TEXT(DATE($A54,$B54,1),"mmm-yy"),$D54),'[1]Demanda requerida 2027'!$CI$70:$DS$70,0),FALSE) -> 200 | I54: =VLOOKUP(I$1,'[1]Demanda requerida 2027'!$CI$74:$DS$97,MATCH(_xlfn.CONCAT(TEXT(DATE($A54,$B54,1),"mmm-yy"),$D54),'[1]Demanda requerida 2027'!$CI$70:$DS$70,0),FALSE) -> 200 | J54: =VLOOKUP(J$1,'[1]Demanda requerida 2027'!$CI$74:$DS$97,MATCH(_xlfn.CONCAT(TEXT(DATE($A54,$B54,1),"mmm-yy"),$D54),'[1]Demanda requerida 2027'!$CI$70:$DS$70,0),FALSE) -> 213 | K54: =VLOOKUP(K$1,'[1]Demanda requerida 2027'!$CI$74:$DS$97,MATCH(_xlfn.CONCAT(TEXT(DATE($A54,$B54,1),"mmm-yy"),$D54),'[1]Demanda requerida 2027'!$CI$70:$DS$70,0),FALSE) -> 1795 | L54: =VLOOKUP(L$1,'[1]Demanda requerida 2027'!$CI$74:$DS$97,MATCH(_xlfn.CONCAT(TEXT(DATE($A54,$B54,1),"mmm-yy"),$D54),'[1]Demanda requerida 2027'!$CI$70:$DS$70,0),FALSE) -> 4043 | ... AB54: =VLOOKUP(AB$1,'[1]Demanda requerida 2027'!$CI$74:$DS$97,MATCH(_xlfn.CONCAT(TEXT(DATE($A54,$B54,1),"mmm-yy"),$D54),'[1]Demanda requerida 2027'!$CI$70:$DS$70,0),FALSE) -> 5873 | AC54: =SUM(E54:AB54) -> 187382
A55: 2027 | B55: 6 | C55: 4 | D55: Sábado | E55: =VLOOKUP(E$1,'[1]Demanda requerida 2027'!$CI$74:$DS$97,MATCH(_xlfn.CONCAT(TEXT(DATE($A55,$B55,1),"mmm-yy"),$D55),'[1]Demanda requerida 2027'!$CI$70:$DS$70,0),FALSE) -> 200 | F55: =VLOOKUP(F$1,'[1]Demanda requerida 2027'!$CI$74:$DS$97,MATCH(_xlfn.CONCAT(TEXT(DATE($A55,$B55,1),"mmm-yy"),$D55),'[1]Demanda requerida 2027'!$CI$70:$DS$70,0),FALSE) -> 200 | G55: =VLOOKUP(G$1,'[1]Demanda requerida 2027'!$CI$74:$DS$97,MATCH(_xlfn.CONCAT(TEXT(DATE($A55,$B55,1),"mmm-yy"),$D55),'[1]Demanda requerida 2027'!$CI$70:$DS$70,0),FALSE) -> 200 | H55: =VLOOKUP(H$1,'[1]Demanda requerida 2027'!$CI$74:$DS$97,MATCH(_xlfn.CONCAT(TEXT(DATE($A55,$B55,1),"mmm-yy"),$D55),'[1]Demanda requerida 2027'!$CI$70:$DS$70,0),FALSE) -> 200 | I55: =VLOOKUP(I$1,'[1]Demanda requerida 2027'!$CI$74:$DS$97,MATCH(_xlfn.CONCAT(TEXT(DATE($A55,$B55,1),"mmm-yy"),$D55),'[1]Demanda requerida 2027'!$CI$70:$DS$70,0),FALSE) -> 200 | J55: =VLOOKUP(J$1,'[1]Demanda requerida 2027'!$CI$74:$DS$97,MATCH(_xlfn.CONCAT(TEXT(DATE($A55,$B55,1),"mmm-yy"),$D55),'[1]Demanda requerida 2027'!$CI$70:$DS$70,0),FALSE) -> 200 | K55: =VLOOKUP(K$1,'[1]Demanda requerida 2027'!$CI$74:$DS$97,MATCH(_xlfn.CONCAT(TEXT(DATE($A55,$B55,1),"mmm-yy"),$D55),'[1]Demanda requerida 2027'!$CI$70:$DS$70,0),FALSE) -> 200 | L55: =VLOOKUP(L$1,'[1]Demanda requerida 2027'!$CI$74:$DS$97,MATCH(_xlfn.CONCAT(TEXT(DATE($A55,$B55,1),"mmm-yy"),$D55),'[1]Demanda requerida 2027'!$CI$70:$DS$70,0),FALSE) -> 1443 | ... AB55: =VLOOKUP(AB$1,'[1]Demanda requerida 2027'!$CI$74:$DS$97,MATCH(_xlfn.CONCAT(TEXT(DATE($A55,$B55,1),"mmm-yy"),$D55),'[1]Demanda requerida 2027'!$CI$70:$DS$70,0),FALSE) -> 6325 | AC55: =SUM(E55:AB55) -> 152240
A56: 2027 | B56: 7 | C56: 6 | D56: Festivo | E56: =VLOOKUP(E$1,'[1]Demanda requerida 2027'!$CI$74:$DS$97,MATCH(_xlfn.CONCAT(TEXT(DATE($A56,$B56,1),"mmm-yy"),$D56),'[1]Demanda requerida 2027'!$CI$70:$DS$70,0),FALSE) -> 200 | F56: =VLOOKUP(F$1,'[1]Demanda requerida 2027'!$CI$74:$DS$97,MATCH(_xlfn.CONCAT(TEXT(DATE($A56,$B56,1),"mmm-yy"),$D56),'[1]Demanda requerida 2027'!$CI$70:$DS$70,0),FALSE) -> 200 | G56: =VLOOKUP(G$1,'[1]Demanda requerida 2027'!$CI$74:$DS$97,MATCH(_xlfn.CONCAT(TEXT(DATE($A56,$B56,1),"mmm-yy"),$D56),'[1]Demanda requerida 2027'!$CI$70:$DS$70,0),FALSE) -> 200 | H56: =VLOOKUP(H$1,'[1]Demanda requerida 2027'!$CI$74:$DS$97,MATCH(_xlfn.CONCAT(TEXT(DATE($A56,$B56,1),"mmm-yy"),$D56),'[1]Demanda requerida 2027'!$CI$70:$DS$70,0),FALSE) -> 200 | I56: =VLOOKUP(I$1,'[1]Demanda requerida 2027'!$CI$74:$DS$97,MATCH(_xlfn.CONCAT(TEXT(DATE($A56,$B56,1),"mmm-yy"),$D56),'[1]Demanda requerida 2027'!$CI$70:$DS$70,0),FALSE) -> 200 | J56: =VLOOKUP(J$1,'[1]Demanda requerida 2027'!$CI$74:$DS$97,MATCH(_xlfn.CONCAT(TEXT(DATE($A56,$B56,1),"mmm-yy"),$D56),'[1]Demanda requerida 2027'!$CI$70:$DS$70,0),FALSE) -> 200 | K56: =VLOOKUP(K$1,'[1]Demanda requerida 2027'!$CI$74:$DS$97,MATCH(_xlfn.CONCAT(TEXT(DATE($A56,$B56,1),"mmm-yy"),$D56),'[1]Demanda requerida 2027'!$CI$70:$DS$70,0),FALSE) -> 200 | L56: =VLOOKUP(L$1,'[1]Demanda requerida 2027'!$CI$74:$DS$97,MATCH(_xlfn.CONCAT(TEXT(DATE($A56,$B56,1),"mmm-yy"),$D56),'[1]Demanda requerida 2027'!$CI$70:$DS$70,0),FALSE) -> 200 | ... AB56: =VLOOKUP(AB$1,'[1]Demanda requerida 2027'!$CI$74:$DS$97,MATCH(_xlfn.CONCAT(TEXT(DATE($A56,$B56,1),"mmm-yy"),$D56),'[1]Demanda requerida 2027'!$CI$70:$DS$70,0),FALSE) -> 200 | AC56: =SUM(E56:AB56) -> 16004 | AD56: =+SUMPRODUCT(AC56:AC58,C56:C58) -> 7973639
A57: 2027 | B57: 7 | C57: 20 | D57: Ordinario | E57: =VLOOKUP(E$1,'[1]Demanda requerida 2027'!$CI$74:$DS$97,MATCH(_xlfn.CONCAT(TEXT(DATE($A57,$B57,1),"mmm-yy"),$D57),'[1]Demanda requerida 2027'!$CI$70:$DS$70,0),FALSE) -> 8349 | F57: =VLOOKUP(F$1,'[1]Demanda requerida 2027'!$CI$74:$DS$97,MATCH(_xlfn.CONCAT(TEXT(DATE($A57,$B57,1),"mmm-yy"),$D57),'[1]Demanda requerida 2027'!$CI$70:$DS$70,0),FALSE) -> 7053 | G57: =VLOOKUP(G$1,'[1]Demanda requerida 2027'!$CI$74:$DS$97,MATCH(_xlfn.CONCAT(TEXT(DATE($A57,$B57,1),"mmm-yy"),$D57),'[1]Demanda requerida 2027'!$CI$70:$DS$70,0),FALSE) -> 6148 | H57: =VLOOKUP(H$1,'[1]Demanda requerida 2027'!$CI$74:$DS$97,MATCH(_xlfn.CONCAT(TEXT(DATE($A57,$B57,1),"mmm-yy"),$D57),'[1]Demanda requerida 2027'!$CI$70:$DS$70,0),FALSE) -> 5674 | I57: =VLOOKUP(I$1,'[1]Demanda requerida 2027'!$CI$74:$DS$97,MATCH(_xlfn.CONCAT(TEXT(DATE($A57,$B57,1),"mmm-yy"),$D57),'[1]Demanda requerida 2027'!$CI$70:$DS$70,0),FALSE) -> 5660 | J57: =VLOOKUP(J$1,'[1]Demanda requerida 2027'!$CI$74:$DS$97,MATCH(_xlfn.CONCAT(TEXT(DATE($A57,$B57,1),"mmm-yy"),$D57),'[1]Demanda requerida 2027'!$CI$70:$DS$70,0),FALSE) -> 6947 | K57: =VLOOKUP(K$1,'[1]Demanda requerida 2027'!$CI$74:$DS$97,MATCH(_xlfn.CONCAT(TEXT(DATE($A57,$B57,1),"mmm-yy"),$D57),'[1]Demanda requerida 2027'!$CI$70:$DS$70,0),FALSE) -> 8570 | L57: =VLOOKUP(L$1,'[1]Demanda requerida 2027'!$CI$74:$DS$97,MATCH(_xlfn.CONCAT(TEXT(DATE($A57,$B57,1),"mmm-yy"),$D57),'[1]Demanda requerida 2027'!$CI$70:$DS$70,0),FALSE) -> 10352 | ... AB57: =VLOOKUP(AB$1,'[1]Demanda requerida 2027'!$CI$74:$DS$97,MATCH(_xlfn.CONCAT(TEXT(DATE($A57,$B57,1),"mmm-yy"),$D57),'[1]Demanda requerida 2027'!$CI$70:$DS$70,0),FALSE) -> 11588 | AC57: =SUM(E57:AB57) -> 336754
A58: 2027 | B58: 7 | C58: 5 | D58: Sábado | E58: =VLOOKUP(E$1,'[1]Demanda requerida 2027'!$CI$74:$DS$97,MATCH(_xlfn.CONCAT(TEXT(DATE($A58,$B58,1),"mmm-yy"),$D58),'[1]Demanda requerida 2027'!$CI$70:$DS$70,0),FALSE) -> 4581 | F58: =VLOOKUP(F$1,'[1]Demanda requerida 2027'!$CI$74:$DS$97,MATCH(_xlfn.CONCAT(TEXT(DATE($A58,$B58,1),"mmm-yy"),$D58),'[1]Demanda requerida 2027'!$CI$70:$DS$70,0),FALSE) -> 3500 | G58: =VLOOKUP(G$1,'[1]Demanda requerida 2027'!$CI$74:$DS$97,MATCH(_xlfn.CONCAT(TEXT(DATE($A58,$B58,1),"mmm-yy"),$D58),'[1]Demanda requerida 2027'!$CI$70:$DS$70,0),FALSE) -> 2855 | H58: =VLOOKUP(H$1,'[1]Demanda requerida 2027'!$CI$74:$DS$97,MATCH(_xlfn.CONCAT(TEXT(DATE($A58,$B58,1),"mmm-yy"),$D58),'[1]Demanda requerida 2027'!$CI$70:$DS$70,0),FALSE) -> 2238 | I58: =VLOOKUP(I$1,'[1]Demanda requerida 2027'!$CI$74:$DS$97,MATCH(_xlfn.CONCAT(TEXT(DATE($A58,$B58,1),"mmm-yy"),$D58),'[1]Demanda requerida 2027'!$CI$70:$DS$70,0),FALSE) -> 2069 | J58: =VLOOKUP(J$1,'[1]Demanda requerida 2027'!$CI$74:$DS$97,MATCH(_xlfn.CONCAT(TEXT(DATE($A58,$B58,1),"mmm-yy"),$D58),'[1]Demanda requerida 2027'!$CI$70:$DS$70,0),FALSE) -> 2372 | K58: =VLOOKUP(K$1,'[1]Demanda requerida 2027'!$CI$74:$DS$97,MATCH(_xlfn.CONCAT(TEXT(DATE($A58,$B58,1),"mmm-yy"),$D58),'[1]Demanda requerida 2027'!$CI$70:$DS$70,0),FALSE) -> 3025 | L58: =VLOOKUP(L$1,'[1]Demanda requerida 2027'!$CI$74:$DS$97,MATCH(_xlfn.CONCAT(TEXT(DATE($A58,$B58,1),"mmm-yy"),$D58),'[1]Demanda requerida 2027'!$CI$70:$DS$70,0),FALSE) -> 5355 | ... AB58: =VLOOKUP(AB$1,'[1]Demanda requerida 2027'!$CI$74:$DS$97,MATCH(_xlfn.CONCAT(TEXT(DATE($A58,$B58,1),"mmm-yy"),$D58),'[1]Demanda requerida 2027'!$CI$70:$DS$70,0),FALSE) -> 8890 | AC58: =SUM(E58:AB58) -> 228507
A59: 2027 | B59: 8 | C59: 7 | D59: Festivo | E59: =VLOOKUP(E$1,'[1]Demanda requerida 2027'!$CI$74:$DS$97,MATCH(_xlfn.CONCAT(TEXT(DATE($A59,$B59,1),"mmm-yy"),$D59),'[1]Demanda requerida 2027'!$CI$70:$DS$70,0),FALSE) -> 200 | F59: =VLOOKUP(F$1,'[1]Demanda requerida 2027'!$CI$74:$DS$97,MATCH(_xlfn.CONCAT(TEXT(DATE($A59,$B59,1),"mmm-yy"),$D59),'[1]Demanda requerida 2027'!$CI$70:$DS$70,0),FALSE) -> 200 | G59: =VLOOKUP(G$1,'[1]Demanda requerida 2027'!$CI$74:$DS$97,MATCH(_xlfn.CONCAT(TEXT(DATE($A59,$B59,1),"mmm-yy"),$D59),'[1]Demanda requerida 2027'!$CI$70:$DS$70,0),FALSE) -> 200 | H59: =VLOOKUP(H$1,'[1]Demanda requerida 2027'!$CI$74:$DS$97,MATCH(_xlfn.CONCAT(TEXT(DATE($A59,$B59,1),"mmm-yy"),$D59),'[1]Demanda requerida 2027'!$CI$70:$DS$70,0),FALSE) -> 200 | I59: =VLOOKUP(I$1,'[1]Demanda requerida 2027'!$CI$74:$DS$97,MATCH(_xlfn.CONCAT(TEXT(DATE($A59,$B59,1),"mmm-yy"),$D59),'[1]Demanda requerida 2027'!$CI$70:$DS$70,0),FALSE) -> 200 | J59: =VLOOKUP(J$1,'[1]Demanda requerida 2027'!$CI$74:$DS$97,MATCH(_xlfn.CONCAT(TEXT(DATE($A59,$B59,1),"mmm-yy"),$D59),'[1]Demanda requerida 2027'!$CI$70:$DS$70,0),FALSE) -> 200 | K59: =VLOOKUP(K$1,'[1]Demanda requerida 2027'!$CI$74:$DS$97,MATCH(_xlfn.CONCAT(TEXT(DATE($A59,$B59,1),"mmm-yy"),$D59),'[1]Demanda requerida 2027'!$CI$70:$DS$70,0),FALSE) -> 200 | L59: =VLOOKUP(L$1,'[1]Demanda requerida 2027'!$CI$74:$DS$97,MATCH(_xlfn.CONCAT(TEXT(DATE($A59,$B59,1),"mmm-yy"),$D59),'[1]Demanda requerida 2027'!$CI$70:$DS$70,0),FALSE) -> 200 | ... AB59: =VLOOKUP(AB$1,'[1]Demanda requerida 2027'!$CI$74:$DS$97,MATCH(_xlfn.CONCAT(TEXT(DATE($A59,$B59,1),"mmm-yy"),$D59),'[1]Demanda requerida 2027'!$CI$70:$DS$70,0),FALSE) -> 200 | AC59: =SUM(E59:AB59) -> 22830 | AD59: =+SUMPRODUCT(AC59:AC61,C59:C61) -> 6832722
A60: 2027 | B60: 8 | C60: 21 | D60: Ordinario | E60: =VLOOKUP(E$1,'[1]Demanda requerida 2027'!$CI$74:$DS$97,MATCH(_xlfn.CONCAT(TEXT(DATE($A60,$B60,1),"mmm-yy"),$D60),'[1]Demanda requerida 2027'!$CI$70:$DS$70,0),FALSE) -> 4419 | F60: =VLOOKUP(F$1,'[1]Demanda requerida 2027'!$CI$74:$DS$97,MATCH(_xlfn.CONCAT(TEXT(DATE($A60,$B60,1),"mmm-yy"),$D60),'[1]Demanda requerida 2027'!$CI$70:$DS$70,0),FALSE) -> 3493 | G60: =VLOOKUP(G$1,'[1]Demanda requerida 2027'!$CI$74:$DS$97,MATCH(_xlfn.CONCAT(TEXT(DATE($A60,$B60,1),"mmm-yy"),$D60),'[1]Demanda requerida 2027'!$CI$70:$DS$70,0),FALSE) -> 2791 | H60: =VLOOKUP(H$1,'[1]Demanda requerida 2027'!$CI$74:$DS$97,MATCH(_xlfn.CONCAT(TEXT(DATE($A60,$B60,1),"mmm-yy"),$D60),'[1]Demanda requerida 2027'!$CI$70:$DS$70,0),FALSE) -> 2283 | I60: =VLOOKUP(I$1,'[1]Demanda requerida 2027'!$CI$74:$DS$97,MATCH(_xlfn.CONCAT(TEXT(DATE($A60,$B60,1),"mmm-yy"),$D60),'[1]Demanda requerida 2027'!$CI$70:$DS$70,0),FALSE) -> 2282 | J60: =VLOOKUP(J$1,'[1]Demanda requerida 2027'!$CI$74:$DS$97,MATCH(_xlfn.CONCAT(TEXT(DATE($A60,$B60,1),"mmm-yy"),$D60),'[1]Demanda requerida 2027'!$CI$70:$DS$70,0),FALSE) -> 3662 | K60: =VLOOKUP(K$1,'[1]Demanda requerida 2027'!$CI$74:$DS$97,MATCH(_xlfn.CONCAT(TEXT(DATE($A60,$B60,1),"mmm-yy"),$D60),'[1]Demanda requerida 2027'!$CI$70:$DS$70,0),FALSE) -> 5273 | L60: =VLOOKUP(L$1,'[1]Demanda requerida 2027'!$CI$74:$DS$97,MATCH(_xlfn.CONCAT(TEXT(DATE($A60,$B60,1),"mmm-yy"),$D60),'[1]Demanda requerida 2027'!$CI$70:$DS$70,0),FALSE) -> 6780 | ... AB60: =VLOOKUP(AB$1,'[1]Demanda requerida 2027'!$CI$74:$DS$97,MATCH(_xlfn.CONCAT(TEXT(DATE($A60,$B60,1),"mmm-yy"),$D60),'[1]Demanda requerida 2027'!$CI$70:$DS$70,0),FALSE) -> 7353 | AC60: =SUM(E60:AB60) -> 253170
A61: 2027 | B61: 8 | C61: 3 | D61: Sábado | E61: =VLOOKUP(E$1,'[1]Demanda requerida 2027'!$CI$74:$DS$97,MATCH(_xlfn.CONCAT(TEXT(DATE($A61,$B61,1),"mmm-yy"),$D61),'[1]Demanda requerida 2027'!$CI$70:$DS$70,0),FALSE) -> 10879 | F61: =VLOOKUP(F$1,'[1]Demanda requerida 2027'!$CI$74:$DS$97,MATCH(_xlfn.CONCAT(TEXT(DATE($A61,$B61,1),"mmm-yy"),$D61),'[1]Demanda requerida 2027'!$CI$70:$DS$70,0),FALSE) -> 10528 | G61: =VLOOKUP(G$1,'[1]Demanda requerida 2027'!$CI$74:$DS$97,MATCH(_xlfn.CONCAT(TEXT(DATE($A61,$B61,1),"mmm-yy"),$D61),'[1]Demanda requerida 2027'!$CI$70:$DS$70,0),FALSE) -> 9725 | H61: =VLOOKUP(H$1,'[1]Demanda requerida 2027'!$CI$74:$DS$97,MATCH(_xlfn.CONCAT(TEXT(DATE($A61,$B61,1),"mmm-yy"),$D61),'[1]Demanda requerida 2027'!$CI$70:$DS$70,0),FALSE) -> 8910 | I61: =VLOOKUP(I$1,'[1]Demanda requerida 2027'!$CI$74:$DS$97,MATCH(_xlfn.CONCAT(TEXT(DATE($A61,$B61,1),"mmm-yy"),$D61),'[1]Demanda requerida 2027'!$CI$70:$DS$70,0),FALSE) -> 8745 | J61: =VLOOKUP(J$1,'[1]Demanda requerida 2027'!$CI$74:$DS$97,MATCH(_xlfn.CONCAT(TEXT(DATE($A61,$B61,1),"mmm-yy"),$D61),'[1]Demanda requerida 2027'!$CI$70:$DS$70,0),FALSE) -> 9145 | K61: =VLOOKUP(K$1,'[1]Demanda requerida 2027'!$CI$74:$DS$97,MATCH(_xlfn.CONCAT(TEXT(DATE($A61,$B61,1),"mmm-yy"),$D61),'[1]Demanda requerida 2027'!$CI$70:$DS$70,0),FALSE) -> 10350 | L61: =VLOOKUP(L$1,'[1]Demanda requerida 2027'!$CI$74:$DS$97,MATCH(_xlfn.CONCAT(TEXT(DATE($A61,$B61,1),"mmm-yy"),$D61),'[1]Demanda requerida 2027'!$CI$70:$DS$70,0),FALSE) -> 13545 | ... AB61: =VLOOKUP(AB$1,'[1]Demanda requerida 2027'!$CI$74:$DS$97,MATCH(_xlfn.CONCAT(TEXT(DATE($A61,$B61,1),"mmm-yy"),$D61),'[1]Demanda requerida 2027'!$CI$70:$DS$70,0),FALSE) -> 16385 | AC61: =SUM(E61:AB61) -> 452114
A62: 2027 | B62: 9 | C62: 4 | D62: Festivo | E62: =VLOOKUP(E$1,'[1]Demanda requerida 2027'!$CI$74:$DS$97,MATCH(_xlfn.CONCAT(TEXT(DATE($A62,$B62,1),"mmm-yy"),$D62),'[1]Demanda requerida 2027'!$CI$70:$DS$70,0),FALSE) -> 200 | F62: =VLOOKUP(F$1,'[1]Demanda requerida 2027'!$CI$74:$DS$97,MATCH(_xlfn.CONCAT(TEXT(DATE($A62,$B62,1),"mmm-yy"),$D62),'[1]Demanda requerida 2027'!$CI$70:$DS$70,0),FALSE) -> 200 | G62: =VLOOKUP(G$1,'[1]Demanda requerida 2027'!$CI$74:$DS$97,MATCH(_xlfn.CONCAT(TEXT(DATE($A62,$B62,1),"mmm-yy"),$D62),'[1]Demanda requerida 2027'!$CI$70:$DS$70,0),FALSE) -> 200 | H62: =VLOOKUP(H$1,'[1]Demanda requerida 2027'!$CI$74:$DS$97,MATCH(_xlfn.CONCAT(TEXT(DATE($A62,$B62,1),"mmm-yy"),$D62),'[1]Demanda requerida 2027'!$CI$70:$DS$70,0),FALSE) -> 200 | I62: =VLOOKUP(I$1,'[1]Demanda requerida 2027'!$CI$74:$DS$97,MATCH(_xlfn.CONCAT(TEXT(DATE($A62,$B62,1),"mmm-yy"),$D62),'[1]Demanda requerida 2027'!$CI$70:$DS$70,0),FALSE) -> 200 | J62: =VLOOKUP(J$1,'[1]Demanda requerida 2027'!$CI$74:$DS$97,MATCH(_xlfn.CONCAT(TEXT(DATE($A62,$B62,1),"mmm-yy"),$D62),'[1]Demanda requerida 2027'!$CI$70:$DS$70,0),FALSE) -> 200 | K62: =VLOOKUP(K$1,'[1]Demanda requerida 2027'!$CI$74:$DS$97,MATCH(_xlfn.CONCAT(TEXT(DATE($A62,$B62,1),"mmm-yy"),$D62),'[1]Demanda requerida 2027'!$CI$70:$DS$70,0),FALSE) -> 200 | L62: =VLOOKUP(L$1,'[1]Demanda requerida 2027'!$CI$74:$DS$97,MATCH(_xlfn.CONCAT(TEXT(DATE($A62,$B62,1),"mmm-yy"),$D62),'[1]Demanda requerida 2027'!$CI$70:$DS$70,0),FALSE) -> 200 | ... AB62: =VLOOKUP(AB$1,'[1]Demanda requerida 2027'!$CI$74:$DS$97,MATCH(_xlfn.CONCAT(TEXT(DATE($A62,$B62,1),"mmm-yy"),$D62),'[1]Demanda requerida 2027'!$CI$70:$DS$70,0),FALSE) -> 200 | AC62: =SUM(E62:AB62) -> 37938 | AD62: =+SUMPRODUCT(AC62:AC64,C62:C64) -> 2528108
A63: 2027 | B63: 9 | C63: 22 | D63: Ordinario | E63: =VLOOKUP(E$1,'[1]Demanda requerida 2027'!$CI$74:$DS$97,MATCH(_xlfn.CONCAT(TEXT(DATE($A63,$B63,1),"mmm-yy"),$D63),'[1]Demanda requerida 2027'!$CI$70:$DS$70,0),FALSE) -> 200 | F63: =VLOOKUP(F$1,'[1]Demanda requerida 2027'!$CI$74:$DS$97,MATCH(_xlfn.CONCAT(TEXT(DATE($A63,$B63,1),"mmm-yy"),$D63),'[1]Demanda requerida 2027'!$CI$70:$DS$70,0),FALSE) -> 200 | G63: =VLOOKUP(G$1,'[1]Demanda requerida 2027'!$CI$74:$DS$97,MATCH(_xlfn.CONCAT(TEXT(DATE($A63,$B63,1),"mmm-yy"),$D63),'[1]Demanda requerida 2027'!$CI$70:$DS$70,0),FALSE) -> 200 | H63: =VLOOKUP(H$1,'[1]Demanda requerida 2027'!$CI$74:$DS$97,MATCH(_xlfn.CONCAT(TEXT(DATE($A63,$B63,1),"mmm-yy"),$D63),'[1]Demanda requerida 2027'!$CI$70:$DS$70,0),FALSE) -> 200 | I63: =VLOOKUP(I$1,'[1]Demanda requerida 2027'!$CI$74:$DS$97,MATCH(_xlfn.CONCAT(TEXT(DATE($A63,$B63,1),"mmm-yy"),$D63),'[1]Demanda requerida 2027'!$CI$70:$DS$70,0),FALSE) -> 200 | J63: =VLOOKUP(J$1,'[1]Demanda requerida 2027'!$CI$74:$DS$97,MATCH(_xlfn.CONCAT(TEXT(DATE($A63,$B63,1),"mmm-yy"),$D63),'[1]Demanda requerida 2027'!$CI$70:$DS$70,0),FALSE) -> 200 | K63: =VLOOKUP(K$1,'[1]Demanda requerida 2027'!$CI$74:$DS$97,MATCH(_xlfn.CONCAT(TEXT(DATE($A63,$B63,1),"mmm-yy"),$D63),'[1]Demanda requerida 2027'!$CI$70:$DS$70,0),FALSE) -> 200 | L63: =VLOOKUP(L$1,'[1]Demanda requerida 2027'!$CI$74:$DS$97,MATCH(_xlfn.CONCAT(TEXT(DATE($A63,$B63,1),"mmm-yy"),$D63),'[1]Demanda requerida 2027'!$CI$70:$DS$70,0),FALSE) -> 200 | ... AB63: =VLOOKUP(AB$1,'[1]Demanda requerida 2027'!$CI$74:$DS$97,MATCH(_xlfn.CONCAT(TEXT(DATE($A63,$B63,1),"mmm-yy"),$D63),'[1]Demanda requerida 2027'!$CI$70:$DS$70,0),FALSE) -> 151 | AC63: =SUM(E63:AB63) -> 96136
A64: 2027 | B64: 9 | C64: 4 | D64: Sábado | E64: =VLOOKUP(E$1,'[1]Demanda requerida 2027'!$CI$74:$DS$97,MATCH(_xlfn.CONCAT(TEXT(DATE($A64,$B64,1),"mmm-yy"),$D64),'[1]Demanda requerida 2027'!$CI$70:$DS$70,0),FALSE) -> 200 | F64: =VLOOKUP(F$1,'[1]Demanda requerida 2027'!$CI$74:$DS$97,MATCH(_xlfn.CONCAT(TEXT(DATE($A64,$B64,1),"mmm-yy"),$D64),'[1]Demanda requerida 2027'!$CI$70:$DS$70,0),FALSE) -> 200 | G64: =VLOOKUP(G$1,'[1]Demanda requerida 2027'!$CI$74:$DS$97,MATCH(_xlfn.CONCAT(TEXT(DATE($A64,$B64,1),"mmm-yy"),$D64),'[1]Demanda requerida 2027'!$CI$70:$DS$70,0),FALSE) -> 200 | H64: =VLOOKUP(H$1,'[1]Demanda requerida 2027'!$CI$74:$DS$97,MATCH(_xlfn.CONCAT(TEXT(DATE($A64,$B64,1),"mmm-yy"),$D64),'[1]Demanda requerida 2027'!$CI$70:$DS$70,0),FALSE) -> 200 | I64: =VLOOKUP(I$1,'[1]Demanda requerida 2027'!$CI$74:$DS$97,MATCH(_xlfn.CONCAT(TEXT(DATE($A64,$B64,1),"mmm-yy"),$D64),'[1]Demanda requerida 2027'!$CI$70:$DS$70,0),FALSE) -> 200 | J64: =VLOOKUP(J$1,'[1]Demanda requerida 2027'!$CI$74:$DS$97,MATCH(_xlfn.CONCAT(TEXT(DATE($A64,$B64,1),"mmm-yy"),$D64),'[1]Demanda requerida 2027'!$CI$70:$DS$70,0),FALSE) -> 200 | K64: =VLOOKUP(K$1,'[1]Demanda requerida 2027'!$CI$74:$DS$97,MATCH(_xlfn.CONCAT(TEXT(DATE($A64,$B64,1),"mmm-yy"),$D64),'[1]Demanda requerida 2027'!$CI$70:$DS$70,0),FALSE) -> 200 | L64: =VLOOKUP(L$1,'[1]Demanda requerida 2027'!$CI$74:$DS$97,MATCH(_xlfn.CONCAT(TEXT(DATE($A64,$B64,1),"mmm-yy"),$D64),'[1]Demanda requerida 2027'!$CI$70:$DS$70,0),FALSE) -> 200 | ... AB64: =VLOOKUP(AB$1,'[1]Demanda requerida 2027'!$CI$74:$DS$97,MATCH(_xlfn.CONCAT(TEXT(DATE($A64,$B64,1),"mmm-yy"),$D64),'[1]Demanda requerida 2027'!$CI$70:$DS$70,0),FALSE) -> 200 | AC64: =SUM(E64:AB64) -> 65341
A65: 2027 | B65: 10 | C65: 6 | D65: Festivo | E65: =VLOOKUP(E$1,'[1]Demanda requerida 2027'!$CI$74:$DS$97,MATCH(_xlfn.CONCAT(TEXT(DATE($A65,$B65,1),"mmm-yy"),$D65),'[1]Demanda requerida 2027'!$CI$70:$DS$70,0),FALSE) -> 200 | F65: =VLOOKUP(F$1,'[1]Demanda requerida 2027'!$CI$74:$DS$97,MATCH(_xlfn.CONCAT(TEXT(DATE($A65,$B65,1),"mmm-yy"),$D65),'[1]Demanda requerida 2027'!$CI$70:$DS$70,0),FALSE) -> 200 | G65: =VLOOKUP(G$1,'[1]Demanda requerida 2027'!$CI$74:$DS$97,MATCH(_xlfn.CONCAT(TEXT(DATE($A65,$B65,1),"mmm-yy"),$D65),'[1]Demanda requerida 2027'!$CI$70:$DS$70,0),FALSE) -> 200 | H65: =VLOOKUP(H$1,'[1]Demanda requerida 2027'!$CI$74:$DS$97,MATCH(_xlfn.CONCAT(TEXT(DATE($A65,$B65,1),"mmm-yy"),$D65),'[1]Demanda requerida 2027'!$CI$70:$DS$70,0),FALSE) -> 200 | I65: =VLOOKUP(I$1,'[1]Demanda requerida 2027'!$CI$74:$DS$97,MATCH(_xlfn.CONCAT(TEXT(DATE($A65,$B65,1),"mmm-yy"),$D65),'[1]Demanda requerida 2027'!$CI$70:$DS$70,0),FALSE) -> 200 | J65: =VLOOKUP(J$1,'[1]Demanda requerida 2027'!$CI$74:$DS$97,MATCH(_xlfn.CONCAT(TEXT(DATE($A65,$B65,1),"mmm-yy"),$D65),'[1]Demanda requerida 2027'!$CI$70:$DS$70,0),FALSE) -> 200 | K65: =VLOOKUP(K$1,'[1]Demanda requerida 2027'!$CI$74:$DS$97,MATCH(_xlfn.CONCAT(TEXT(DATE($A65,$B65,1),"mmm-yy"),$D65),'[1]Demanda requerida 2027'!$CI$70:$DS$70,0),FALSE) -> 200 | L65: =VLOOKUP(L$1,'[1]Demanda requerida 2027'!$CI$74:$DS$97,MATCH(_xlfn.CONCAT(TEXT(DATE($A65,$B65,1),"mmm-yy"),$D65),'[1]Demanda requerida 2027'!$CI$70:$DS$70,0),FALSE) -> 200 | ... AB65: =VLOOKUP(AB$1,'[1]Demanda requerida 2027'!$CI$74:$DS$97,MATCH(_xlfn.CONCAT(TEXT(DATE($A65,$B65,1),"mmm-yy"),$D65),'[1]Demanda requerida 2027'!$CI$70:$DS$70,0),FALSE) -> 200 | AC65: =SUM(E65:AB65) -> 4800 | AD65: =+SUMPRODUCT(AC65:AC67,C65:C67) -> 2320125
A66: 2027 | B66: 10 | C66: 20 | D66: Ordinario | E66: =VLOOKUP(E$1,'[1]Demanda requerida 2027'!$CI$74:$DS$97,MATCH(_xlfn.CONCAT(TEXT(DATE($A66,$B66,1),"mmm-yy"),$D66),'[1]Demanda requerida 2027'!$CI$70:$DS$70,0),FALSE) -> 200 | F66: =VLOOKUP(F$1,'[1]Demanda requerida 2027'!$CI$74:$DS$97,MATCH(_xlfn.CONCAT(TEXT(DATE($A66,$B66,1),"mmm-yy"),$D66),'[1]Demanda requerida 2027'!$CI$70:$DS$70,0),FALSE) -> 200 | G66: =VLOOKUP(G$1,'[1]Demanda requerida 2027'!$CI$74:$DS$97,MATCH(_xlfn.CONCAT(TEXT(DATE($A66,$B66,1),"mmm-yy"),$D66),'[1]Demanda requerida 2027'!$CI$70:$DS$70,0),FALSE) -> 200 | H66: =VLOOKUP(H$1,'[1]Demanda requerida 2027'!$CI$74:$DS$97,MATCH(_xlfn.CONCAT(TEXT(DATE($A66,$B66,1),"mmm-yy"),$D66),'[1]Demanda requerida 2027'!$CI$70:$DS$70,0),FALSE) -> 200 | I66: =VLOOKUP(I$1,'[1]Demanda requerida 2027'!$CI$74:$DS$97,MATCH(_xlfn.CONCAT(TEXT(DATE($A66,$B66,1),"mmm-yy"),$D66),'[1]Demanda requerida 2027'!$CI$70:$DS$70,0),FALSE) -> 200 | J66: =VLOOKUP(J$1,'[1]Demanda requerida 2027'!$CI$74:$DS$97,MATCH(_xlfn.CONCAT(TEXT(DATE($A66,$B66,1),"mmm-yy"),$D66),'[1]Demanda requerida 2027'!$CI$70:$DS$70,0),FALSE) -> 200 | K66: =VLOOKUP(K$1,'[1]Demanda requerida 2027'!$CI$74:$DS$97,MATCH(_xlfn.CONCAT(TEXT(DATE($A66,$B66,1),"mmm-yy"),$D66),'[1]Demanda requerida 2027'!$CI$70:$DS$70,0),FALSE) -> 200 | L66: =VLOOKUP(L$1,'[1]Demanda requerida 2027'!$CI$74:$DS$97,MATCH(_xlfn.CONCAT(TEXT(DATE($A66,$B66,1),"mmm-yy"),$D66),'[1]Demanda requerida 2027'!$CI$70:$DS$70,0),FALSE) -> 200 | ... AB66: =VLOOKUP(AB$1,'[1]Demanda requerida 2027'!$CI$74:$DS$97,MATCH(_xlfn.CONCAT(TEXT(DATE($A66,$B66,1),"mmm-yy"),$D66),'[1]Demanda requerida 2027'!$CI$70:$DS$70,0),FALSE) -> 565 | AC66: =SUM(E66:AB66) -> 96670
A67: 2027 | B67: 10 | C67: 5 | D67: Sábado | E67: =VLOOKUP(E$1,'[1]Demanda requerida 2027'!$CI$74:$DS$97,MATCH(_xlfn.CONCAT(TEXT(DATE($A67,$B67,1),"mmm-yy"),$D67),'[1]Demanda requerida 2027'!$CI$70:$DS$70,0),FALSE) -> 200 | F67: =VLOOKUP(F$1,'[1]Demanda requerida 2027'!$CI$74:$DS$97,MATCH(_xlfn.CONCAT(TEXT(DATE($A67,$B67,1),"mmm-yy"),$D67),'[1]Demanda requerida 2027'!$CI$70:$DS$70,0),FALSE) -> 200 | G67: =VLOOKUP(G$1,'[1]Demanda requerida 2027'!$CI$74:$DS$97,MATCH(_xlfn.CONCAT(TEXT(DATE($A67,$B67,1),"mmm-yy"),$D67),'[1]Demanda requerida 2027'!$CI$70:$DS$70,0),FALSE) -> 200 | H67: =VLOOKUP(H$1,'[1]Demanda requerida 2027'!$CI$74:$DS$97,MATCH(_xlfn.CONCAT(TEXT(DATE($A67,$B67,1),"mmm-yy"),$D67),'[1]Demanda requerida 2027'!$CI$70:$DS$70,0),FALSE) -> 200 | I67: =VLOOKUP(I$1,'[1]Demanda requerida 2027'!$CI$74:$DS$97,MATCH(_xlfn.CONCAT(TEXT(DATE($A67,$B67,1),"mmm-yy"),$D67),'[1]Demanda requerida 2027'!$CI$70:$DS$70,0),FALSE) -> 200 | J67: =VLOOKUP(J$1,'[1]Demanda requerida 2027'!$CI$74:$DS$97,MATCH(_xlfn.CONCAT(TEXT(DATE($A67,$B67,1),"mmm-yy"),$D67),'[1]Demanda requerida 2027'!$CI$70:$DS$70,0),FALSE) -> 200 | K67: =VLOOKUP(K$1,'[1]Demanda requerida 2027'!$CI$74:$DS$97,MATCH(_xlfn.CONCAT(TEXT(DATE($A67,$B67,1),"mmm-yy"),$D67),'[1]Demanda requerida 2027'!$CI$70:$DS$70,0),FALSE) -> 200 | L67: =VLOOKUP(L$1,'[1]Demanda requerida 2027'!$CI$74:$DS$97,MATCH(_xlfn.CONCAT(TEXT(DATE($A67,$B67,1),"mmm-yy"),$D67),'[1]Demanda requerida 2027'!$CI$70:$DS$70,0),FALSE) -> 200 | ... AB67: =VLOOKUP(AB$1,'[1]Demanda requerida 2027'!$CI$74:$DS$97,MATCH(_xlfn.CONCAT(TEXT(DATE($A67,$B67,1),"mmm-yy"),$D67),'[1]Demanda requerida 2027'!$CI$70:$DS$70,0),FALSE) -> 200 | AC67: =SUM(E67:AB67) -> 71585
A68: 2027 | B68: 11 | C68: 6 | D68: Festivo | E68: =VLOOKUP(E$1,'[1]Demanda requerida 2027'!$CI$74:$DS$97,MATCH(_xlfn.CONCAT(TEXT(DATE($A68,$B68,1),"mmm-yy"),$D68),'[1]Demanda requerida 2027'!$CI$70:$DS$70,0),FALSE) -> 200 | F68: =VLOOKUP(F$1,'[1]Demanda requerida 2027'!$CI$74:$DS$97,MATCH(_xlfn.CONCAT(TEXT(DATE($A68,$B68,1),"mmm-yy"),$D68),'[1]Demanda requerida 2027'!$CI$70:$DS$70,0),FALSE) -> 200 | G68: =VLOOKUP(G$1,'[1]Demanda requerida 2027'!$CI$74:$DS$97,MATCH(_xlfn.CONCAT(TEXT(DATE($A68,$B68,1),"mmm-yy"),$D68),'[1]Demanda requerida 2027'!$CI$70:$DS$70,0),FALSE) -> 200 | H68: =VLOOKUP(H$1,'[1]Demanda requerida 2027'!$CI$74:$DS$97,MATCH(_xlfn.CONCAT(TEXT(DATE($A68,$B68,1),"mmm-yy"),$D68),'[1]Demanda requerida 2027'!$CI$70:$DS$70,0),FALSE) -> 200 | I68: =VLOOKUP(I$1,'[1]Demanda requerida 2027'!$CI$74:$DS$97,MATCH(_xlfn.CONCAT(TEXT(DATE($A68,$B68,1),"mmm-yy"),$D68),'[1]Demanda requerida 2027'!$CI$70:$DS$70,0),FALSE) -> 200 | J68: =VLOOKUP(J$1,'[1]Demanda requerida 2027'!$CI$74:$DS$97,MATCH(_xlfn.CONCAT(TEXT(DATE($A68,$B68,1),"mmm-yy"),$D68),'[1]Demanda requerida 2027'!$CI$70:$DS$70,0),FALSE) -> 200 | K68: =VLOOKUP(K$1,'[1]Demanda requerida 2027'!$CI$74:$DS$97,MATCH(_xlfn.CONCAT(TEXT(DATE($A68,$B68,1),"mmm-yy"),$D68),'[1]Demanda requerida 2027'!$CI$70:$DS$70,0),FALSE) -> 200 | L68: =VLOOKUP(L$1,'[1]Demanda requerida 2027'!$CI$74:$DS$97,MATCH(_xlfn.CONCAT(TEXT(DATE($A68,$B68,1),"mmm-yy"),$D68),'[1]Demanda requerida 2027'!$CI$70:$DS$70,0),FALSE) -> 200 | ... AB68: =VLOOKUP(AB$1,'[1]Demanda requerida 2027'!$CI$74:$DS$97,MATCH(_xlfn.CONCAT(TEXT(DATE($A68,$B68,1),"mmm-yy"),$D68),'[1]Demanda requerida 2027'!$CI$70:$DS$70,0),FALSE) -> 200 | AC68: =SUM(E68:AB68) -> 4800 | AD68: =+SUMPRODUCT(AC68:AC70,C68:C70) -> 2665816
A69: 2027 | B69: 11 | C69: 20 | D69: Ordinario | E69: =VLOOKUP(E$1,'[1]Demanda requerida 2027'!$CI$74:$DS$97,MATCH(_xlfn.CONCAT(TEXT(DATE($A69,$B69,1),"mmm-yy"),$D69),'[1]Demanda requerida 2027'!$CI$70:$DS$70,0),FALSE) -> 200 | F69: =VLOOKUP(F$1,'[1]Demanda requerida 2027'!$CI$74:$DS$97,MATCH(_xlfn.CONCAT(TEXT(DATE($A69,$B69,1),"mmm-yy"),$D69),'[1]Demanda requerida 2027'!$CI$70:$DS$70,0),FALSE) -> 200 | G69: =VLOOKUP(G$1,'[1]Demanda requerida 2027'!$CI$74:$DS$97,MATCH(_xlfn.CONCAT(TEXT(DATE($A69,$B69,1),"mmm-yy"),$D69),'[1]Demanda requerida 2027'!$CI$70:$DS$70,0),FALSE) -> 200 | H69: =VLOOKUP(H$1,'[1]Demanda requerida 2027'!$CI$74:$DS$97,MATCH(_xlfn.CONCAT(TEXT(DATE($A69,$B69,1),"mmm-yy"),$D69),'[1]Demanda requerida 2027'!$CI$70:$DS$70,0),FALSE) -> 200 | I69: =VLOOKUP(I$1,'[1]Demanda requerida 2027'!$CI$74:$DS$97,MATCH(_xlfn.CONCAT(TEXT(DATE($A69,$B69,1),"mmm-yy"),$D69),'[1]Demanda requerida 2027'!$CI$70:$DS$70,0),FALSE) -> 200 | J69: =VLOOKUP(J$1,'[1]Demanda requerida 2027'!$CI$74:$DS$97,MATCH(_xlfn.CONCAT(TEXT(DATE($A69,$B69,1),"mmm-yy"),$D69),'[1]Demanda requerida 2027'!$CI$70:$DS$70,0),FALSE) -> 200 | K69: =VLOOKUP(K$1,'[1]Demanda requerida 2027'!$CI$74:$DS$97,MATCH(_xlfn.CONCAT(TEXT(DATE($A69,$B69,1),"mmm-yy"),$D69),'[1]Demanda requerida 2027'!$CI$70:$DS$70,0),FALSE) -> 200 | L69: =VLOOKUP(L$1,'[1]Demanda requerida 2027'!$CI$74:$DS$97,MATCH(_xlfn.CONCAT(TEXT(DATE($A69,$B69,1),"mmm-yy"),$D69),'[1]Demanda requerida 2027'!$CI$70:$DS$70,0),FALSE) -> 470 | ... AB69: =VLOOKUP(AB$1,'[1]Demanda requerida 2027'!$CI$74:$DS$97,MATCH(_xlfn.CONCAT(TEXT(DATE($A69,$B69,1),"mmm-yy"),$D69),'[1]Demanda requerida 2027'!$CI$70:$DS$70,0),FALSE) -> 1418 | AC69: =SUM(E69:AB69) -> 120118
A70: 2027 | B70: 11 | C70: 4 | D70: Sábado | E70: =VLOOKUP(E$1,'[1]Demanda requerida 2027'!$CI$74:$DS$97,MATCH(_xlfn.CONCAT(TEXT(DATE($A70,$B70,1),"mmm-yy"),$D70),'[1]Demanda requerida 2027'!$CI$70:$DS$70,0),FALSE) -> 200 | F70: =VLOOKUP(F$1,'[1]Demanda requerida 2027'!$CI$74:$DS$97,MATCH(_xlfn.CONCAT(TEXT(DATE($A70,$B70,1),"mmm-yy"),$D70),'[1]Demanda requerida 2027'!$CI$70:$DS$70,0),FALSE) -> 200 | G70: =VLOOKUP(G$1,'[1]Demanda requerida 2027'!$CI$74:$DS$97,MATCH(_xlfn.CONCAT(TEXT(DATE($A70,$B70,1),"mmm-yy"),$D70),'[1]Demanda requerida 2027'!$CI$70:$DS$70,0),FALSE) -> 200 | H70: =VLOOKUP(H$1,'[1]Demanda requerida 2027'!$CI$74:$DS$97,MATCH(_xlfn.CONCAT(TEXT(DATE($A70,$B70,1),"mmm-yy"),$D70),'[1]Demanda requerida 2027'!$CI$70:$DS$70,0),FALSE) -> 200 | I70: =VLOOKUP(I$1,'[1]Demanda requerida 2027'!$CI$74:$DS$97,MATCH(_xlfn.CONCAT(TEXT(DATE($A70,$B70,1),"mmm-yy"),$D70),'[1]Demanda requerida 2027'!$CI$70:$DS$70,0),FALSE) -> 200 | J70: =VLOOKUP(J$1,'[1]Demanda requerida 2027'!$CI$74:$DS$97,MATCH(_xlfn.CONCAT(TEXT(DATE($A70,$B70,1),"mmm-yy"),$D70),'[1]Demanda requerida 2027'!$CI$70:$DS$70,0),FALSE) -> 200 | K70: =VLOOKUP(K$1,'[1]Demanda requerida 2027'!$CI$74:$DS$97,MATCH(_xlfn.CONCAT(TEXT(DATE($A70,$B70,1),"mmm-yy"),$D70),'[1]Demanda requerida 2027'!$CI$70:$DS$70,0),FALSE) -> 200 | L70: =VLOOKUP(L$1,'[1]Demanda requerida 2027'!$CI$74:$DS$97,MATCH(_xlfn.CONCAT(TEXT(DATE($A70,$B70,1),"mmm-yy"),$D70),'[1]Demanda requerida 2027'!$CI$70:$DS$70,0),FALSE) -> 200 | ... AB70: =VLOOKUP(AB$1,'[1]Demanda requerida 2027'!$CI$74:$DS$97,MATCH(_xlfn.CONCAT(TEXT(DATE($A70,$B70,1),"mmm-yy"),$D70),'[1]Demanda requerida 2027'!$CI$70:$DS$70,0),FALSE) -> 200 | AC70: =SUM(E70:AB70) -> 58664
A71: 2027 | B71: 12 | C71: 6 | D71: Festivo | E71: =VLOOKUP(E$1,'[1]Demanda requerida 2027'!$CI$74:$DS$97,MATCH(_xlfn.CONCAT(TEXT(DATE($A71,$B71,1),"mmm-yy"),$D71),'[1]Demanda requerida 2027'!$CI$70:$DS$70,0),FALSE) -> 200 | F71: =VLOOKUP(F$1,'[1]Demanda requerida 2027'!$CI$74:$DS$97,MATCH(_xlfn.CONCAT(TEXT(DATE($A71,$B71,1),"mmm-yy"),$D71),'[1]Demanda requerida 2027'!$CI$70:$DS$70,0),FALSE) -> 200 | G71: =VLOOKUP(G$1,'[1]Demanda requerida 2027'!$CI$74:$DS$97,MATCH(_xlfn.CONCAT(TEXT(DATE($A71,$B71,1),"mmm-yy"),$D71),'[1]Demanda requerida 2027'!$CI$70:$DS$70,0),FALSE) -> 200 | H71: =VLOOKUP(H$1,'[1]Demanda requerida 2027'!$CI$74:$DS$97,MATCH(_xlfn.CONCAT(TEXT(DATE($A71,$B71,1),"mmm-yy"),$D71),'[1]Demanda requerida 2027'!$CI$70:$DS$70,0),FALSE) -> 200 | I71: =VLOOKUP(I$1,'[1]Demanda requerida 2027'!$CI$74:$DS$97,MATCH(_xlfn.CONCAT(TEXT(DATE($A71,$B71,1),"mmm-yy"),$D71),'[1]Demanda requerida 2027'!$CI$70:$DS$70,0),FALSE) -> 200 | J71: =VLOOKUP(J$1,'[1]Demanda requerida 2027'!$CI$74:$DS$97,MATCH(_xlfn.CONCAT(TEXT(DATE($A71,$B71,1),"mmm-yy"),$D71),'[1]Demanda requerida 2027'!$CI$70:$DS$70,0),FALSE) -> 200 | K71: =VLOOKUP(K$1,'[1]Demanda requerida 2027'!$CI$74:$DS$97,MATCH(_xlfn.CONCAT(TEXT(DATE($A71,$B71,1),"mmm-yy"),$D71),'[1]Demanda requerida 2027'!$CI$70:$DS$70,0),FALSE) -> 200 | L71: =VLOOKUP(L$1,'[1]Demanda requerida 2027'!$CI$74:$DS$97,MATCH(_xlfn.CONCAT(TEXT(DATE($A71,$B71,1),"mmm-yy"),$D71),'[1]Demanda requerida 2027'!$CI$70:$DS$70,0),FALSE) -> 200 | ... AB71: =VLOOKUP(AB$1,'[1]Demanda requerida 2027'!$CI$74:$DS$97,MATCH(_xlfn.CONCAT(TEXT(DATE($A71,$B71,1),"mmm-yy"),$D71),'[1]Demanda requerida 2027'!$CI$70:$DS$70,0),FALSE) -> 200 | AC71: =SUM(E71:AB71) -> 9952 | AD71: =+SUMPRODUCT(AC71:AC73,C71:C73) -> 10003291
A72: 2027 | B72: 12 | C72: 22 | D72: Ordinario | E72: =VLOOKUP(E$1,'[1]Demanda requerida 2027'!$CI$74:$DS$97,MATCH(_xlfn.CONCAT(TEXT(DATE($A72,$B72,1),"mmm-yy"),$D72),'[1]Demanda requerida 2027'!$CI$70:$DS$70,0),FALSE) -> 11031 | F72: =VLOOKUP(F$1,'[1]Demanda requerida 2027'!$CI$74:$DS$97,MATCH(_xlfn.CONCAT(TEXT(DATE($A72,$B72,1),"mmm-yy"),$D72),'[1]Demanda requerida 2027'!$CI$70:$DS$70,0),FALSE) -> 9816 | G72: =VLOOKUP(G$1,'[1]Demanda requerida 2027'!$CI$74:$DS$97,MATCH(_xlfn.CONCAT(TEXT(DATE($A72,$B72,1),"mmm-yy"),$D72),'[1]Demanda requerida 2027'!$CI$70:$DS$70,0),FALSE) -> 8886 | H72: =VLOOKUP(H$1,'[1]Demanda requerida 2027'!$CI$74:$DS$97,MATCH(_xlfn.CONCAT(TEXT(DATE($A72,$B72,1),"mmm-yy"),$D72),'[1]Demanda requerida 2027'!$CI$70:$DS$70,0),FALSE) -> 8262 | I72: =VLOOKUP(I$1,'[1]Demanda requerida 2027'!$CI$74:$DS$97,MATCH(_xlfn.CONCAT(TEXT(DATE($A72,$B72,1),"mmm-yy"),$D72),'[1]Demanda requerida 2027'!$CI$70:$DS$70,0),FALSE) -> 8116 | J72: =VLOOKUP(J$1,'[1]Demanda requerida 2027'!$CI$74:$DS$97,MATCH(_xlfn.CONCAT(TEXT(DATE($A72,$B72,1),"mmm-yy"),$D72),'[1]Demanda requerida 2027'!$CI$70:$DS$70,0),FALSE) -> 8771 | K72: =VLOOKUP(K$1,'[1]Demanda requerida 2027'!$CI$74:$DS$97,MATCH(_xlfn.CONCAT(TEXT(DATE($A72,$B72,1),"mmm-yy"),$D72),'[1]Demanda requerida 2027'!$CI$70:$DS$70,0),FALSE) -> 9965 | L72: =VLOOKUP(L$1,'[1]Demanda requerida 2027'!$CI$74:$DS$97,MATCH(_xlfn.CONCAT(TEXT(DATE($A72,$B72,1),"mmm-yy"),$D72),'[1]Demanda requerida 2027'!$CI$70:$DS$70,0),FALSE) -> 12295 | ... AB72: =VLOOKUP(AB$1,'[1]Demanda requerida 2027'!$CI$74:$DS$97,MATCH(_xlfn.CONCAT(TEXT(DATE($A72,$B72,1),"mmm-yy"),$D72),'[1]Demanda requerida 2027'!$CI$70:$DS$70,0),FALSE) -> 14275 | AC72: =SUM(E72:AB72) -> 378178
A73: 2027 | B73: 12 | C73: 3 | D73: Sábado | E73: =VLOOKUP(E$1,'[1]Demanda requerida 2027'!$CI$74:$DS$97,MATCH(_xlfn.CONCAT(TEXT(DATE($A73,$B73,1),"mmm-yy"),$D73),'[1]Demanda requerida 2027'!$CI$70:$DS$70,0),FALSE) -> 17262 | F73: =VLOOKUP(F$1,'[1]Demanda requerida 2027'!$CI$74:$DS$97,MATCH(_xlfn.CONCAT(TEXT(DATE($A73,$B73,1),"mmm-yy"),$D73),'[1]Demanda requerida 2027'!$CI$70:$DS$70,0),FALSE) -> 15508 | G73: =VLOOKUP(G$1,'[1]Demanda requerida 2027'!$CI$74:$DS$97,MATCH(_xlfn.CONCAT(TEXT(DATE($A73,$B73,1),"mmm-yy"),$D73),'[1]Demanda requerida 2027'!$CI$70:$DS$70,0),FALSE) -> 14478 | H73: =VLOOKUP(H$1,'[1]Demanda requerida 2027'!$CI$74:$DS$97,MATCH(_xlfn.CONCAT(TEXT(DATE($A73,$B73,1),"mmm-yy"),$D73),'[1]Demanda requerida 2027'!$CI$70:$DS$70,0),FALSE) -> 13563 | I73: =VLOOKUP(I$1,'[1]Demanda requerida 2027'!$CI$74:$DS$97,MATCH(_xlfn.CONCAT(TEXT(DATE($A73,$B73,1),"mmm-yy"),$D73),'[1]Demanda requerida 2027'!$CI$70:$DS$70,0),FALSE) -> 13180 | J73: =VLOOKUP(J$1,'[1]Demanda requerida 2027'!$CI$74:$DS$97,MATCH(_xlfn.CONCAT(TEXT(DATE($A73,$B73,1),"mmm-yy"),$D73),'[1]Demanda requerida 2027'!$CI$70:$DS$70,0),FALSE) -> 13461 | K73: =VLOOKUP(K$1,'[1]Demanda requerida 2027'!$CI$74:$DS$97,MATCH(_xlfn.CONCAT(TEXT(DATE($A73,$B73,1),"mmm-yy"),$D73),'[1]Demanda requerida 2027'!$CI$70:$DS$70,0),FALSE) -> 14710 | L73: =VLOOKUP(L$1,'[1]Demanda requerida 2027'!$CI$74:$DS$97,MATCH(_xlfn.CONCAT(TEXT(DATE($A73,$B73,1),"mmm-yy"),$D73),'[1]Demanda requerida 2027'!$CI$70:$DS$70,0),FALSE) -> 17132 | ... AB73: =VLOOKUP(AB$1,'[1]Demanda requerida 2027'!$CI$74:$DS$97,MATCH(_xlfn.CONCAT(TEXT(DATE($A73,$B73,1),"mmm-yy"),$D73),'[1]Demanda requerida 2027'!$CI$70:$DS$70,0),FALSE) -> 21911 | AC73: =SUM(E73:AB73) -> 541221
A74: 2028 | B74: 1 | C74: 7 | D74: Festivo | E74: =VLOOKUP(E$1,'[1]Demanda requerida 2028'!$CB$75:$DL$98,MATCH(_xlfn.CONCAT(TEXT(DATE($A74,$B74,1),"mmm-yy"),$D74),'[1]Demanda requerida 2028'!$CB$71:$DL$71,0),FALSE) -> 304 | F74: =VLOOKUP(F$1,'[1]Demanda requerida 2028'!$CB$75:$DL$98,MATCH(_xlfn.CONCAT(TEXT(DATE($A74,$B74,1),"mmm-yy"),$D74),'[1]Demanda requerida 2028'!$CB$71:$DL$71,0),FALSE) -> 200 | G74: =VLOOKUP(G$1,'[1]Demanda requerida 2028'!$CB$75:$DL$98,MATCH(_xlfn.CONCAT(TEXT(DATE($A74,$B74,1),"mmm-yy"),$D74),'[1]Demanda requerida 2028'!$CB$71:$DL$71,0),FALSE) -> 200 | H74: =VLOOKUP(H$1,'[1]Demanda requerida 2028'!$CB$75:$DL$98,MATCH(_xlfn.CONCAT(TEXT(DATE($A74,$B74,1),"mmm-yy"),$D74),'[1]Demanda requerida 2028'!$CB$71:$DL$71,0),FALSE) -> 200 | I74: =VLOOKUP(I$1,'[1]Demanda requerida 2028'!$CB$75:$DL$98,MATCH(_xlfn.CONCAT(TEXT(DATE($A74,$B74,1),"mmm-yy"),$D74),'[1]Demanda requerida 2028'!$CB$71:$DL$71,0),FALSE) -> 200 | J74: =VLOOKUP(J$1,'[1]Demanda requerida 2028'!$CB$75:$DL$98,MATCH(_xlfn.CONCAT(TEXT(DATE($A74,$B74,1),"mmm-yy"),$D74),'[1]Demanda requerida 2028'!$CB$71:$DL$71,0),FALSE) -> 200 | K74: =VLOOKUP(K$1,'[1]Demanda requerida 2028'!$CB$75:$DL$98,MATCH(_xlfn.CONCAT(TEXT(DATE($A74,$B74,1),"mmm-yy"),$D74),'[1]Demanda requerida 2028'!$CB$71:$DL$71,0),FALSE) -> 200 | L74: =VLOOKUP(L$1,'[1]Demanda requerida 2028'!$CB$75:$DL$98,MATCH(_xlfn.CONCAT(TEXT(DATE($A74,$B74,1),"mmm-yy"),$D74),'[1]Demanda requerida 2028'!$CB$71:$DL$71,0),FALSE) -> 200 | ... AB74: =VLOOKUP(AB$1,'[1]Demanda requerida 2028'!$CB$75:$DL$98,MATCH(_xlfn.CONCAT(TEXT(DATE($A74,$B74,1),"mmm-yy"),$D74),'[1]Demanda requerida 2028'!$CB$71:$DL$71,0),FALSE) -> 2038 | AC74: =SUM(E74:AB74) -> 76791 | AD74: =+SUMPRODUCT(AC74:AC76,C74:C76) -> 3774561 | AE74: =+SUM(AD74:AD109) -> 63351821
A75: 2028 | B75: 1 | C75: 20 | D75: Ordinario | E75: =VLOOKUP(E$1,'[1]Demanda requerida 2028'!$CB$75:$DL$98,MATCH(_xlfn.CONCAT(TEXT(DATE($A75,$B75,1),"mmm-yy"),$D75),'[1]Demanda requerida 2028'!$CB$71:$DL$71,0),FALSE) -> 419 | F75: =VLOOKUP(F$1,'[1]Demanda requerida 2028'!$CB$75:$DL$98,MATCH(_xlfn.CONCAT(TEXT(DATE($A75,$B75,1),"mmm-yy"),$D75),'[1]Demanda requerida 2028'!$CB$71:$DL$71,0),FALSE) -> 200 | G75: =VLOOKUP(G$1,'[1]Demanda requerida 2028'!$CB$75:$DL$98,MATCH(_xlfn.CONCAT(TEXT(DATE($A75,$B75,1),"mmm-yy"),$D75),'[1]Demanda requerida 2028'!$CB$71:$DL$71,0),FALSE) -> 200 | H75: =VLOOKUP(H$1,'[1]Demanda requerida 2028'!$CB$75:$DL$98,MATCH(_xlfn.CONCAT(TEXT(DATE($A75,$B75,1),"mmm-yy"),$D75),'[1]Demanda requerida 2028'!$CB$71:$DL$71,0),FALSE) -> 200 | I75: =VLOOKUP(I$1,'[1]Demanda requerida 2028'!$CB$75:$DL$98,MATCH(_xlfn.CONCAT(TEXT(DATE($A75,$B75,1),"mmm-yy"),$D75),'[1]Demanda requerida 2028'!$CB$71:$DL$71,0),FALSE) -> 200 | J75: =VLOOKUP(J$1,'[1]Demanda requerida 2028'!$CB$75:$DL$98,MATCH(_xlfn.CONCAT(TEXT(DATE($A75,$B75,1),"mmm-yy"),$D75),'[1]Demanda requerida 2028'!$CB$71:$DL$71,0),FALSE) -> 200 | K75: =VLOOKUP(K$1,'[1]Demanda requerida 2028'!$CB$75:$DL$98,MATCH(_xlfn.CONCAT(TEXT(DATE($A75,$B75,1),"mmm-yy"),$D75),'[1]Demanda requerida 2028'!$CB$71:$DL$71,0),FALSE) -> 200 | L75: =VLOOKUP(L$1,'[1]Demanda requerida 2028'!$CB$75:$DL$98,MATCH(_xlfn.CONCAT(TEXT(DATE($A75,$B75,1),"mmm-yy"),$D75),'[1]Demanda requerida 2028'!$CB$71:$DL$71,0),FALSE) -> 1250 | ... AB75: =VLOOKUP(AB$1,'[1]Demanda requerida 2028'!$CB$75:$DL$98,MATCH(_xlfn.CONCAT(TEXT(DATE($A75,$B75,1),"mmm-yy"),$D75),'[1]Demanda requerida 2028'!$CB$71:$DL$71,0),FALSE) -> 3752 | AC75: =SUM(E75:AB75) -> 137414
A76: 2028 | B76: 1 | C76: 4 | D76: Sábado | E76: =VLOOKUP(E$1,'[1]Demanda requerida 2028'!$CB$75:$DL$98,MATCH(_xlfn.CONCAT(TEXT(DATE($A76,$B76,1),"mmm-yy"),$D76),'[1]Demanda requerida 2028'!$CB$71:$DL$71,0),FALSE) -> 200 | F76: =VLOOKUP(F$1,'[1]Demanda requerida 2028'!$CB$75:$DL$98,MATCH(_xlfn.CONCAT(TEXT(DATE($A76,$B76,1),"mmm-yy"),$D76),'[1]Demanda requerida 2028'!$CB$71:$DL$71,0),FALSE) -> 200 | G76: =VLOOKUP(G$1,'[1]Demanda requerida 2028'!$CB$75:$DL$98,MATCH(_xlfn.CONCAT(TEXT(DATE($A76,$B76,1),"mmm-yy"),$D76),'[1]Demanda requerida 2028'!$CB$71:$DL$71,0),FALSE) -> 200 | H76: =VLOOKUP(H$1,'[1]Demanda requerida 2028'!$CB$75:$DL$98,MATCH(_xlfn.CONCAT(TEXT(DATE($A76,$B76,1),"mmm-yy"),$D76),'[1]Demanda requerida 2028'!$CB$71:$DL$71,0),FALSE) -> 200 | I76: =VLOOKUP(I$1,'[1]Demanda requerida 2028'!$CB$75:$DL$98,MATCH(_xlfn.CONCAT(TEXT(DATE($A76,$B76,1),"mmm-yy"),$D76),'[1]Demanda requerida 2028'!$CB$71:$DL$71,0),FALSE) -> 200 | J76: =VLOOKUP(J$1,'[1]Demanda requerida 2028'!$CB$75:$DL$98,MATCH(_xlfn.CONCAT(TEXT(DATE($A76,$B76,1),"mmm-yy"),$D76),'[1]Demanda requerida 2028'!$CB$71:$DL$71,0),FALSE) -> 200 | K76: =VLOOKUP(K$1,'[1]Demanda requerida 2028'!$CB$75:$DL$98,MATCH(_xlfn.CONCAT(TEXT(DATE($A76,$B76,1),"mmm-yy"),$D76),'[1]Demanda requerida 2028'!$CB$71:$DL$71,0),FALSE) -> 200 | L76: =VLOOKUP(L$1,'[1]Demanda requerida 2028'!$CB$75:$DL$98,MATCH(_xlfn.CONCAT(TEXT(DATE($A76,$B76,1),"mmm-yy"),$D76),'[1]Demanda requerida 2028'!$CB$71:$DL$71,0),FALSE) -> 200 | ... AB76: =VLOOKUP(AB$1,'[1]Demanda requerida 2028'!$CB$75:$DL$98,MATCH(_xlfn.CONCAT(TEXT(DATE($A76,$B76,1),"mmm-yy"),$D76),'[1]Demanda requerida 2028'!$CB$71:$DL$71,0),FALSE) -> 3809 | AC76: =SUM(E76:AB76) -> 122186
A77: 2028 | B77: 2 | C77: 4 | D77: Festivo | E77: =VLOOKUP(E$1,'[1]Demanda requerida 2028'!$CB$75:$DL$98,MATCH(_xlfn.CONCAT(TEXT(DATE($A77,$B77,1),"mmm-yy"),$D77),'[1]Demanda requerida 2028'!$CB$71:$DL$71,0),FALSE) -> 2095 | F77: =VLOOKUP(F$1,'[1]Demanda requerida 2028'!$CB$75:$DL$98,MATCH(_xlfn.CONCAT(TEXT(DATE($A77,$B77,1),"mmm-yy"),$D77),'[1]Demanda requerida 2028'!$CB$71:$DL$71,0),FALSE) -> 832 | G77: =VLOOKUP(G$1,'[1]Demanda requerida 2028'!$CB$75:$DL$98,MATCH(_xlfn.CONCAT(TEXT(DATE($A77,$B77,1),"mmm-yy"),$D77),'[1]Demanda requerida 2028'!$CB$71:$DL$71,0),FALSE) -> 200 | H77: =VLOOKUP(H$1,'[1]Demanda requerida 2028'!$CB$75:$DL$98,MATCH(_xlfn.CONCAT(TEXT(DATE($A77,$B77,1),"mmm-yy"),$D77),'[1]Demanda requerida 2028'!$CB$71:$DL$71,0),FALSE) -> 200 | I77: =VLOOKUP(I$1,'[1]Demanda requerida 2028'!$CB$75:$DL$98,MATCH(_xlfn.CONCAT(TEXT(DATE($A77,$B77,1),"mmm-yy"),$D77),'[1]Demanda requerida 2028'!$CB$71:$DL$71,0),FALSE) -> 200 | J77: =VLOOKUP(J$1,'[1]Demanda requerida 2028'!$CB$75:$DL$98,MATCH(_xlfn.CONCAT(TEXT(DATE($A77,$B77,1),"mmm-yy"),$D77),'[1]Demanda requerida 2028'!$CB$71:$DL$71,0),FALSE) -> 200 | K77: =VLOOKUP(K$1,'[1]Demanda requerida 2028'!$CB$75:$DL$98,MATCH(_xlfn.CONCAT(TEXT(DATE($A77,$B77,1),"mmm-yy"),$D77),'[1]Demanda requerida 2028'!$CB$71:$DL$71,0),FALSE) -> 200 | L77: =VLOOKUP(L$1,'[1]Demanda requerida 2028'!$CB$75:$DL$98,MATCH(_xlfn.CONCAT(TEXT(DATE($A77,$B77,1),"mmm-yy"),$D77),'[1]Demanda requerida 2028'!$CB$71:$DL$71,0),FALSE) -> 23 | ... AB77: =VLOOKUP(AB$1,'[1]Demanda requerida 2028'!$CB$75:$DL$98,MATCH(_xlfn.CONCAT(TEXT(DATE($A77,$B77,1),"mmm-yy"),$D77),'[1]Demanda requerida 2028'!$CB$71:$DL$71,0),FALSE) -> 3767 | AC77: =SUM(E77:AB77) -> 109839 | AD77: =+SUMPRODUCT(AC77:AC79,C77:C79) -> 3526018
A78: 2028 | B78: 2 | C78: 21 | D78: Ordinario | E78: =VLOOKUP(E$1,'[1]Demanda requerida 2028'!$CB$75:$DL$98,MATCH(_xlfn.CONCAT(TEXT(DATE($A78,$B78,1),"mmm-yy"),$D78),'[1]Demanda requerida 2028'!$CB$71:$DL$71,0),FALSE) -> 200 | F78: =VLOOKUP(F$1,'[1]Demanda requerida 2028'!$CB$75:$DL$98,MATCH(_xlfn.CONCAT(TEXT(DATE($A78,$B78,1),"mmm-yy"),$D78),'[1]Demanda requerida 2028'!$CB$71:$DL$71,0),FALSE) -> 200 | G78: =VLOOKUP(G$1,'[1]Demanda requerida 2028'!$CB$75:$DL$98,MATCH(_xlfn.CONCAT(TEXT(DATE($A78,$B78,1),"mmm-yy"),$D78),'[1]Demanda requerida 2028'!$CB$71:$DL$71,0),FALSE) -> 200 | H78: =VLOOKUP(H$1,'[1]Demanda requerida 2028'!$CB$75:$DL$98,MATCH(_xlfn.CONCAT(TEXT(DATE($A78,$B78,1),"mmm-yy"),$D78),'[1]Demanda requerida 2028'!$CB$71:$DL$71,0),FALSE) -> 200 | I78: =VLOOKUP(I$1,'[1]Demanda requerida 2028'!$CB$75:$DL$98,MATCH(_xlfn.CONCAT(TEXT(DATE($A78,$B78,1),"mmm-yy"),$D78),'[1]Demanda requerida 2028'!$CB$71:$DL$71,0),FALSE) -> 200 | J78: =VLOOKUP(J$1,'[1]Demanda requerida 2028'!$CB$75:$DL$98,MATCH(_xlfn.CONCAT(TEXT(DATE($A78,$B78,1),"mmm-yy"),$D78),'[1]Demanda requerida 2028'!$CB$71:$DL$71,0),FALSE) -> 200 | K78: =VLOOKUP(K$1,'[1]Demanda requerida 2028'!$CB$75:$DL$98,MATCH(_xlfn.CONCAT(TEXT(DATE($A78,$B78,1),"mmm-yy"),$D78),'[1]Demanda requerida 2028'!$CB$71:$DL$71,0),FALSE) -> 200 | L78: =VLOOKUP(L$1,'[1]Demanda requerida 2028'!$CB$75:$DL$98,MATCH(_xlfn.CONCAT(TEXT(DATE($A78,$B78,1),"mmm-yy"),$D78),'[1]Demanda requerida 2028'!$CB$71:$DL$71,0),FALSE) -> 645 | ... AB78: =VLOOKUP(AB$1,'[1]Demanda requerida 2028'!$CB$75:$DL$98,MATCH(_xlfn.CONCAT(TEXT(DATE($A78,$B78,1),"mmm-yy"),$D78),'[1]Demanda requerida 2028'!$CB$71:$DL$71,0),FALSE) -> 2587 | AC78: =SUM(E78:AB78) -> 119906
A79: 2028 | B79: 2 | C79: 4 | D79: Sábado | E79: =VLOOKUP(E$1,'[1]Demanda requerida 2028'!$CB$75:$DL$98,MATCH(_xlfn.CONCAT(TEXT(DATE($A79,$B79,1),"mmm-yy"),$D79),'[1]Demanda requerida 2028'!$CB$71:$DL$71,0),FALSE) -> 1276 | F79: =VLOOKUP(F$1,'[1]Demanda requerida 2028'!$CB$75:$DL$98,MATCH(_xlfn.CONCAT(TEXT(DATE($A79,$B79,1),"mmm-yy"),$D79),'[1]Demanda requerida 2028'!$CB$71:$DL$71,0),FALSE) -> 0 | G79: =VLOOKUP(G$1,'[1]Demanda requerida 2028'!$CB$75:$DL$98,MATCH(_xlfn.CONCAT(TEXT(DATE($A79,$B79,1),"mmm-yy"),$D79),'[1]Demanda requerida 2028'!$CB$71:$DL$71,0),FALSE) -> 200 | H79: =VLOOKUP(H$1,'[1]Demanda requerida 2028'!$CB$75:$DL$98,MATCH(_xlfn.CONCAT(TEXT(DATE($A79,$B79,1),"mmm-yy"),$D79),'[1]Demanda requerida 2028'!$CB$71:$DL$71,0),FALSE) -> 200 | I79: =VLOOKUP(I$1,'[1]Demanda requerida 2028'!$CB$75:$DL$98,MATCH(_xlfn.CONCAT(TEXT(DATE($A79,$B79,1),"mmm-yy"),$D79),'[1]Demanda requerida 2028'!$CB$71:$DL$71,0),FALSE) -> 200 | J79: =VLOOKUP(J$1,'[1]Demanda requerida 2028'!$CB$75:$DL$98,MATCH(_xlfn.CONCAT(TEXT(DATE($A79,$B79,1),"mmm-yy"),$D79),'[1]Demanda requerida 2028'!$CB$71:$DL$71,0),FALSE) -> 200 | K79: =VLOOKUP(K$1,'[1]Demanda requerida 2028'!$CB$75:$DL$98,MATCH(_xlfn.CONCAT(TEXT(DATE($A79,$B79,1),"mmm-yy"),$D79),'[1]Demanda requerida 2028'!$CB$71:$DL$71,0),FALSE) -> 200 | L79: =VLOOKUP(L$1,'[1]Demanda requerida 2028'!$CB$75:$DL$98,MATCH(_xlfn.CONCAT(TEXT(DATE($A79,$B79,1),"mmm-yy"),$D79),'[1]Demanda requerida 2028'!$CB$71:$DL$71,0),FALSE) -> 1522 | ... AB79: =VLOOKUP(AB$1,'[1]Demanda requerida 2028'!$CB$75:$DL$98,MATCH(_xlfn.CONCAT(TEXT(DATE($A79,$B79,1),"mmm-yy"),$D79),'[1]Demanda requerida 2028'!$CB$71:$DL$71,0),FALSE) -> 5533 | AC79: =SUM(E79:AB79) -> 142159
A80: 2028 | B80: 3 | C80: 5 | D80: Festivo | E80: =VLOOKUP(E$1,'[1]Demanda requerida 2028'!$CB$75:$DL$98,MATCH(_xlfn.CONCAT(TEXT(DATE($A80,$B80,1),"mmm-yy"),$D80),'[1]Demanda requerida 2028'!$CB$71:$DL$71,0),FALSE) -> 200 | F80: =VLOOKUP(F$1,'[1]Demanda requerida 2028'!$CB$75:$DL$98,MATCH(_xlfn.CONCAT(TEXT(DATE($A80,$B80,1),"mmm-yy"),$D80),'[1]Demanda requerida 2028'!$CB$71:$DL$71,0),FALSE) -> 200 | G80: =VLOOKUP(G$1,'[1]Demanda requerida 2028'!$CB$75:$DL$98,MATCH(_xlfn.CONCAT(TEXT(DATE($A80,$B80,1),"mmm-yy"),$D80),'[1]Demanda requerida 2028'!$CB$71:$DL$71,0),FALSE) -> 200 | H80: =VLOOKUP(H$1,'[1]Demanda requerida 2028'!$CB$75:$DL$98,MATCH(_xlfn.CONCAT(TEXT(DATE($A80,$B80,1),"mmm-yy"),$D80),'[1]Demanda requerida 2028'!$CB$71:$DL$71,0),FALSE) -> 200 | I80: =VLOOKUP(I$1,'[1]Demanda requerida 2028'!$CB$75:$DL$98,MATCH(_xlfn.CONCAT(TEXT(DATE($A80,$B80,1),"mmm-yy"),$D80),'[1]Demanda requerida 2028'!$CB$71:$DL$71,0),FALSE) -> 200 | J80: =VLOOKUP(J$1,'[1]Demanda requerida 2028'!$CB$75:$DL$98,MATCH(_xlfn.CONCAT(TEXT(DATE($A80,$B80,1),"mmm-yy"),$D80),'[1]Demanda requerida 2028'!$CB$71:$DL$71,0),FALSE) -> 200 | K80: =VLOOKUP(K$1,'[1]Demanda requerida 2028'!$CB$75:$DL$98,MATCH(_xlfn.CONCAT(TEXT(DATE($A80,$B80,1),"mmm-yy"),$D80),'[1]Demanda requerida 2028'!$CB$71:$DL$71,0),FALSE) -> 200 | L80: =VLOOKUP(L$1,'[1]Demanda requerida 2028'!$CB$75:$DL$98,MATCH(_xlfn.CONCAT(TEXT(DATE($A80,$B80,1),"mmm-yy"),$D80),'[1]Demanda requerida 2028'!$CB$71:$DL$71,0),FALSE) -> 200 | ... AB80: =VLOOKUP(AB$1,'[1]Demanda requerida 2028'!$CB$75:$DL$98,MATCH(_xlfn.CONCAT(TEXT(DATE($A80,$B80,1),"mmm-yy"),$D80),'[1]Demanda requerida 2028'!$CB$71:$DL$71,0),FALSE) -> 3456 | AC80: =SUM(E80:AB80) -> 68685 | AD80: =+SUMPRODUCT(AC80:AC82,C80:C82) -> 4012629
A81: 2028 | B81: 3 | C81: 22 | D81: Ordinario | E81: =VLOOKUP(E$1,'[1]Demanda requerida 2028'!$CB$75:$DL$98,MATCH(_xlfn.CONCAT(TEXT(DATE($A81,$B81,1),"mmm-yy"),$D81),'[1]Demanda requerida 2028'!$CB$71:$DL$71,0),FALSE) -> 971 | F81: =VLOOKUP(F$1,'[1]Demanda requerida 2028'!$CB$75:$DL$98,MATCH(_xlfn.CONCAT(TEXT(DATE($A81,$B81,1),"mmm-yy"),$D81),'[1]Demanda requerida 2028'!$CB$71:$DL$71,0),FALSE) -> 200 | G81: =VLOOKUP(G$1,'[1]Demanda requerida 2028'!$CB$75:$DL$98,MATCH(_xlfn.CONCAT(TEXT(DATE($A81,$B81,1),"mmm-yy"),$D81),'[1]Demanda requerida 2028'!$CB$71:$DL$71,0),FALSE) -> 200 | H81: =VLOOKUP(H$1,'[1]Demanda requerida 2028'!$CB$75:$DL$98,MATCH(_xlfn.CONCAT(TEXT(DATE($A81,$B81,1),"mmm-yy"),$D81),'[1]Demanda requerida 2028'!$CB$71:$DL$71,0),FALSE) -> 200 | I81: =VLOOKUP(I$1,'[1]Demanda requerida 2028'!$CB$75:$DL$98,MATCH(_xlfn.CONCAT(TEXT(DATE($A81,$B81,1),"mmm-yy"),$D81),'[1]Demanda requerida 2028'!$CB$71:$DL$71,0),FALSE) -> 200 | J81: =VLOOKUP(J$1,'[1]Demanda requerida 2028'!$CB$75:$DL$98,MATCH(_xlfn.CONCAT(TEXT(DATE($A81,$B81,1),"mmm-yy"),$D81),'[1]Demanda requerida 2028'!$CB$71:$DL$71,0),FALSE) -> 200 | K81: =VLOOKUP(K$1,'[1]Demanda requerida 2028'!$CB$75:$DL$98,MATCH(_xlfn.CONCAT(TEXT(DATE($A81,$B81,1),"mmm-yy"),$D81),'[1]Demanda requerida 2028'!$CB$71:$DL$71,0),FALSE) -> 762 | L81: =VLOOKUP(L$1,'[1]Demanda requerida 2028'!$CB$75:$DL$98,MATCH(_xlfn.CONCAT(TEXT(DATE($A81,$B81,1),"mmm-yy"),$D81),'[1]Demanda requerida 2028'!$CB$71:$DL$71,0),FALSE) -> 1923 | ... AB81: =VLOOKUP(AB$1,'[1]Demanda requerida 2028'!$CB$75:$DL$98,MATCH(_xlfn.CONCAT(TEXT(DATE($A81,$B81,1),"mmm-yy"),$D81),'[1]Demanda requerida 2028'!$CB$71:$DL$71,0),FALSE) -> 4491 | AC81: =SUM(E81:AB81) -> 145622
A82: 2028 | B82: 3 | C82: 4 | D82: Sábado | E82: =VLOOKUP(E$1,'[1]Demanda requerida 2028'!$CB$75:$DL$98,MATCH(_xlfn.CONCAT(TEXT(DATE($A82,$B82,1),"mmm-yy"),$D82),'[1]Demanda requerida 2028'!$CB$71:$DL$71,0),FALSE) -> 715 | F82: =VLOOKUP(F$1,'[1]Demanda requerida 2028'!$CB$75:$DL$98,MATCH(_xlfn.CONCAT(TEXT(DATE($A82,$B82,1),"mmm-yy"),$D82),'[1]Demanda requerida 2028'!$CB$71:$DL$71,0),FALSE) -> 200 | G82: =VLOOKUP(G$1,'[1]Demanda requerida 2028'!$CB$75:$DL$98,MATCH(_xlfn.CONCAT(TEXT(DATE($A82,$B82,1),"mmm-yy"),$D82),'[1]Demanda requerida 2028'!$CB$71:$DL$71,0),FALSE) -> 200 | H82: =VLOOKUP(H$1,'[1]Demanda requerida 2028'!$CB$75:$DL$98,MATCH(_xlfn.CONCAT(TEXT(DATE($A82,$B82,1),"mmm-yy"),$D82),'[1]Demanda requerida 2028'!$CB$71:$DL$71,0),FALSE) -> 200 | I82: =VLOOKUP(I$1,'[1]Demanda requerida 2028'!$CB$75:$DL$98,MATCH(_xlfn.CONCAT(TEXT(DATE($A82,$B82,1),"mmm-yy"),$D82),'[1]Demanda requerida 2028'!$CB$71:$DL$71,0),FALSE) -> 200 | J82: =VLOOKUP(J$1,'[1]Demanda requerida 2028'!$CB$75:$DL$98,MATCH(_xlfn.CONCAT(TEXT(DATE($A82,$B82,1),"mmm-yy"),$D82),'[1]Demanda requerida 2028'!$CB$71:$DL$71,0),FALSE) -> 200 | K82: =VLOOKUP(K$1,'[1]Demanda requerida 2028'!$CB$75:$DL$98,MATCH(_xlfn.CONCAT(TEXT(DATE($A82,$B82,1),"mmm-yy"),$D82),'[1]Demanda requerida 2028'!$CB$71:$DL$71,0),FALSE) -> 200 | L82: =VLOOKUP(L$1,'[1]Demanda requerida 2028'!$CB$75:$DL$98,MATCH(_xlfn.CONCAT(TEXT(DATE($A82,$B82,1),"mmm-yy"),$D82),'[1]Demanda requerida 2028'!$CB$71:$DL$71,0),FALSE) -> 200 | ... AB82: =VLOOKUP(AB$1,'[1]Demanda requerida 2028'!$CB$75:$DL$98,MATCH(_xlfn.CONCAT(TEXT(DATE($A82,$B82,1),"mmm-yy"),$D82),'[1]Demanda requerida 2028'!$CB$71:$DL$71,0),FALSE) -> 2014 | AC82: =SUM(E82:AB82) -> 116380
A83: 2028 | B83: 4 | C83: 7 | D83: Festivo | E83: =VLOOKUP(E$1,'[1]Demanda requerida 2028'!$CB$75:$DL$98,MATCH(_xlfn.CONCAT(TEXT(DATE($A83,$B83,1),"mmm-yy"),$D83),'[1]Demanda requerida 2028'!$CB$71:$DL$71,0),FALSE) -> 200 | F83: =VLOOKUP(F$1,'[1]Demanda requerida 2028'!$CB$75:$DL$98,MATCH(_xlfn.CONCAT(TEXT(DATE($A83,$B83,1),"mmm-yy"),$D83),'[1]Demanda requerida 2028'!$CB$71:$DL$71,0),FALSE) -> 200 | G83: =VLOOKUP(G$1,'[1]Demanda requerida 2028'!$CB$75:$DL$98,MATCH(_xlfn.CONCAT(TEXT(DATE($A83,$B83,1),"mmm-yy"),$D83),'[1]Demanda requerida 2028'!$CB$71:$DL$71,0),FALSE) -> 200 | H83: =VLOOKUP(H$1,'[1]Demanda requerida 2028'!$CB$75:$DL$98,MATCH(_xlfn.CONCAT(TEXT(DATE($A83,$B83,1),"mmm-yy"),$D83),'[1]Demanda requerida 2028'!$CB$71:$DL$71,0),FALSE) -> 200 | I83: =VLOOKUP(I$1,'[1]Demanda requerida 2028'!$CB$75:$DL$98,MATCH(_xlfn.CONCAT(TEXT(DATE($A83,$B83,1),"mmm-yy"),$D83),'[1]Demanda requerida 2028'!$CB$71:$DL$71,0),FALSE) -> 200 | J83: =VLOOKUP(J$1,'[1]Demanda requerida 2028'!$CB$75:$DL$98,MATCH(_xlfn.CONCAT(TEXT(DATE($A83,$B83,1),"mmm-yy"),$D83),'[1]Demanda requerida 2028'!$CB$71:$DL$71,0),FALSE) -> 200 | K83: =VLOOKUP(K$1,'[1]Demanda requerida 2028'!$CB$75:$DL$98,MATCH(_xlfn.CONCAT(TEXT(DATE($A83,$B83,1),"mmm-yy"),$D83),'[1]Demanda requerida 2028'!$CB$71:$DL$71,0),FALSE) -> 200 | L83: =VLOOKUP(L$1,'[1]Demanda requerida 2028'!$CB$75:$DL$98,MATCH(_xlfn.CONCAT(TEXT(DATE($A83,$B83,1),"mmm-yy"),$D83),'[1]Demanda requerida 2028'!$CB$71:$DL$71,0),FALSE) -> 200 | ... AB83: =VLOOKUP(AB$1,'[1]Demanda requerida 2028'!$CB$75:$DL$98,MATCH(_xlfn.CONCAT(TEXT(DATE($A83,$B83,1),"mmm-yy"),$D83),'[1]Demanda requerida 2028'!$CB$71:$DL$71,0),FALSE) -> 200 | AC83: =SUM(E83:AB83) -> 19643 | AD83: =+SUMPRODUCT(AC83:AC85,C83:C85) -> 7226259
A84: 2028 | B84: 4 | C84: 18 | D84: Ordinario | E84: =VLOOKUP(E$1,'[1]Demanda requerida 2028'!$CB$75:$DL$98,MATCH(_xlfn.CONCAT(TEXT(DATE($A84,$B84,1),"mmm-yy"),$D84),'[1]Demanda requerida 2028'!$CB$71:$DL$71,0),FALSE) -> 7468 | F84: =VLOOKUP(F$1,'[1]Demanda requerida 2028'!$CB$75:$DL$98,MATCH(_xlfn.CONCAT(TEXT(DATE($A84,$B84,1),"mmm-yy"),$D84),'[1]Demanda requerida 2028'!$CB$71:$DL$71,0),FALSE) -> 6016 | G84: =VLOOKUP(G$1,'[1]Demanda requerida 2028'!$CB$75:$DL$98,MATCH(_xlfn.CONCAT(TEXT(DATE($A84,$B84,1),"mmm-yy"),$D84),'[1]Demanda requerida 2028'!$CB$71:$DL$71,0),FALSE) -> 5290 | H84: =VLOOKUP(H$1,'[1]Demanda requerida 2028'!$CB$75:$DL$98,MATCH(_xlfn.CONCAT(TEXT(DATE($A84,$B84,1),"mmm-yy"),$D84),'[1]Demanda requerida 2028'!$CB$71:$DL$71,0),FALSE) -> 4673 | I84: =VLOOKUP(I$1,'[1]Demanda requerida 2028'!$CB$75:$DL$98,MATCH(_xlfn.CONCAT(TEXT(DATE($A84,$B84,1),"mmm-yy"),$D84),'[1]Demanda requerida 2028'!$CB$71:$DL$71,0),FALSE) -> 4489 | J84: =VLOOKUP(J$1,'[1]Demanda requerida 2028'!$CB$75:$DL$98,MATCH(_xlfn.CONCAT(TEXT(DATE($A84,$B84,1),"mmm-yy"),$D84),'[1]Demanda requerida 2028'!$CB$71:$DL$71,0),FALSE) -> 5927 | K84: =VLOOKUP(K$1,'[1]Demanda requerida 2028'!$CB$75:$DL$98,MATCH(_xlfn.CONCAT(TEXT(DATE($A84,$B84,1),"mmm-yy"),$D84),'[1]Demanda requerida 2028'!$CB$71:$DL$71,0),FALSE) -> 7435 | L84: =VLOOKUP(L$1,'[1]Demanda requerida 2028'!$CB$75:$DL$98,MATCH(_xlfn.CONCAT(TEXT(DATE($A84,$B84,1),"mmm-yy"),$D84),'[1]Demanda requerida 2028'!$CB$71:$DL$71,0),FALSE) -> 9194 | ... AB84: =VLOOKUP(AB$1,'[1]Demanda requerida 2028'!$CB$75:$DL$98,MATCH(_xlfn.CONCAT(TEXT(DATE($A84,$B84,1),"mmm-yy"),$D84),'[1]Demanda requerida 2028'!$CB$71:$DL$71,0),FALSE) -> 11312 | AC84: =SUM(E84:AB84) -> 328691
A85: 2028 | B85: 4 | C85: 5 | D85: Sábado | E85: =VLOOKUP(E$1,'[1]Demanda requerida 2028'!$CB$75:$DL$98,MATCH(_xlfn.CONCAT(TEXT(DATE($A85,$B85,1),"mmm-yy"),$D85),'[1]Demanda requerida 2028'!$CB$71:$DL$71,0),FALSE) -> 5861 | F85: =VLOOKUP(F$1,'[1]Demanda requerida 2028'!$CB$75:$DL$98,MATCH(_xlfn.CONCAT(TEXT(DATE($A85,$B85,1),"mmm-yy"),$D85),'[1]Demanda requerida 2028'!$CB$71:$DL$71,0),FALSE) -> 4493 | G85: =VLOOKUP(G$1,'[1]Demanda requerida 2028'!$CB$75:$DL$98,MATCH(_xlfn.CONCAT(TEXT(DATE($A85,$B85,1),"mmm-yy"),$D85),'[1]Demanda requerida 2028'!$CB$71:$DL$71,0),FALSE) -> 3655 | H85: =VLOOKUP(H$1,'[1]Demanda requerida 2028'!$CB$75:$DL$98,MATCH(_xlfn.CONCAT(TEXT(DATE($A85,$B85,1),"mmm-yy"),$D85),'[1]Demanda requerida 2028'!$CB$71:$DL$71,0),FALSE) -> 3014 | I85: =VLOOKUP(I$1,'[1]Demanda requerida 2028'!$CB$75:$DL$98,MATCH(_xlfn.CONCAT(TEXT(DATE($A85,$B85,1),"mmm-yy"),$D85),'[1]Demanda requerida 2028'!$CB$71:$DL$71,0),FALSE) -> 1227 | J85: =VLOOKUP(J$1,'[1]Demanda requerida 2028'!$CB$75:$DL$98,MATCH(_xlfn.CONCAT(TEXT(DATE($A85,$B85,1),"mmm-yy"),$D85),'[1]Demanda requerida 2028'!$CB$71:$DL$71,0),FALSE) -> 3146 | K85: =VLOOKUP(K$1,'[1]Demanda requerida 2028'!$CB$75:$DL$98,MATCH(_xlfn.CONCAT(TEXT(DATE($A85,$B85,1),"mmm-yy"),$D85),'[1]Demanda requerida 2028'!$CB$71:$DL$71,0),FALSE) -> 3335 | L85: =VLOOKUP(L$1,'[1]Demanda requerida 2028'!$CB$75:$DL$98,MATCH(_xlfn.CONCAT(TEXT(DATE($A85,$B85,1),"mmm-yy"),$D85),'[1]Demanda requerida 2028'!$CB$71:$DL$71,0),FALSE) -> 5522 | ... AB85: =VLOOKUP(AB$1,'[1]Demanda requerida 2028'!$CB$75:$DL$98,MATCH(_xlfn.CONCAT(TEXT(DATE($A85,$B85,1),"mmm-yy"),$D85),'[1]Demanda requerida 2028'!$CB$71:$DL$71,0),FALSE) -> 8012 | AC85: =SUM(E85:AB85) -> 234464
A86: 2028 | B86: 5 | C86: 6 | D86: Festivo | E86: =VLOOKUP(E$1,'[1]Demanda requerida 2028'!$CB$75:$DL$98,MATCH(_xlfn.CONCAT(TEXT(DATE($A86,$B86,1),"mmm-yy"),$D86),'[1]Demanda requerida 2028'!$CB$71:$DL$71,0),FALSE) -> 200 | F86: =VLOOKUP(F$1,'[1]Demanda requerida 2028'!$CB$75:$DL$98,MATCH(_xlfn.CONCAT(TEXT(DATE($A86,$B86,1),"mmm-yy"),$D86),'[1]Demanda requerida 2028'!$CB$71:$DL$71,0),FALSE) -> 200 | G86: =VLOOKUP(G$1,'[1]Demanda requerida 2028'!$CB$75:$DL$98,MATCH(_xlfn.CONCAT(TEXT(DATE($A86,$B86,1),"mmm-yy"),$D86),'[1]Demanda requerida 2028'!$CB$71:$DL$71,0),FALSE) -> 200 | H86: =VLOOKUP(H$1,'[1]Demanda requerida 2028'!$CB$75:$DL$98,MATCH(_xlfn.CONCAT(TEXT(DATE($A86,$B86,1),"mmm-yy"),$D86),'[1]Demanda requerida 2028'!$CB$71:$DL$71,0),FALSE) -> 200 | I86: =VLOOKUP(I$1,'[1]Demanda requerida 2028'!$CB$75:$DL$98,MATCH(_xlfn.CONCAT(TEXT(DATE($A86,$B86,1),"mmm-yy"),$D86),'[1]Demanda requerida 2028'!$CB$71:$DL$71,0),FALSE) -> 200 | J86: =VLOOKUP(J$1,'[1]Demanda requerida 2028'!$CB$75:$DL$98,MATCH(_xlfn.CONCAT(TEXT(DATE($A86,$B86,1),"mmm-yy"),$D86),'[1]Demanda requerida 2028'!$CB$71:$DL$71,0),FALSE) -> 200 | K86: =VLOOKUP(K$1,'[1]Demanda requerida 2028'!$CB$75:$DL$98,MATCH(_xlfn.CONCAT(TEXT(DATE($A86,$B86,1),"mmm-yy"),$D86),'[1]Demanda requerida 2028'!$CB$71:$DL$71,0),FALSE) -> 200 | L86: =VLOOKUP(L$1,'[1]Demanda requerida 2028'!$CB$75:$DL$98,MATCH(_xlfn.CONCAT(TEXT(DATE($A86,$B86,1),"mmm-yy"),$D86),'[1]Demanda requerida 2028'!$CB$71:$DL$71,0),FALSE) -> 200 | ... AB86: =VLOOKUP(AB$1,'[1]Demanda requerida 2028'!$CB$75:$DL$98,MATCH(_xlfn.CONCAT(TEXT(DATE($A86,$B86,1),"mmm-yy"),$D86),'[1]Demanda requerida 2028'!$CB$71:$DL$71,0),FALSE) -> 200 | AC86: =SUM(E86:AB86) -> 4800 | AD86: =+SUMPRODUCT(AC86:AC88,C86:C88) -> 5462581
A87: 2028 | B87: 5 | C87: 21 | D87: Ordinario | E87: =VLOOKUP(E$1,'[1]Demanda requerida 2028'!$CB$75:$DL$98,MATCH(_xlfn.CONCAT(TEXT(DATE($A87,$B87,1),"mmm-yy"),$D87),'[1]Demanda requerida 2028'!$CB$71:$DL$71,0),FALSE) -> 3786 | F87: =VLOOKUP(F$1,'[1]Demanda requerida 2028'!$CB$75:$DL$98,MATCH(_xlfn.CONCAT(TEXT(DATE($A87,$B87,1),"mmm-yy"),$D87),'[1]Demanda requerida 2028'!$CB$71:$DL$71,0),FALSE) -> 2595 | G87: =VLOOKUP(G$1,'[1]Demanda requerida 2028'!$CB$75:$DL$98,MATCH(_xlfn.CONCAT(TEXT(DATE($A87,$B87,1),"mmm-yy"),$D87),'[1]Demanda requerida 2028'!$CB$71:$DL$71,0),FALSE) -> 1717 | H87: =VLOOKUP(H$1,'[1]Demanda requerida 2028'!$CB$75:$DL$98,MATCH(_xlfn.CONCAT(TEXT(DATE($A87,$B87,1),"mmm-yy"),$D87),'[1]Demanda requerida 2028'!$CB$71:$DL$71,0),FALSE) -> 1335 | I87: =VLOOKUP(I$1,'[1]Demanda requerida 2028'!$CB$75:$DL$98,MATCH(_xlfn.CONCAT(TEXT(DATE($A87,$B87,1),"mmm-yy"),$D87),'[1]Demanda requerida 2028'!$CB$71:$DL$71,0),FALSE) -> 1008 | J87: =VLOOKUP(J$1,'[1]Demanda requerida 2028'!$CB$75:$DL$98,MATCH(_xlfn.CONCAT(TEXT(DATE($A87,$B87,1),"mmm-yy"),$D87),'[1]Demanda requerida 2028'!$CB$71:$DL$71,0),FALSE) -> 2282 | K87: =VLOOKUP(K$1,'[1]Demanda requerida 2028'!$CB$75:$DL$98,MATCH(_xlfn.CONCAT(TEXT(DATE($A87,$B87,1),"mmm-yy"),$D87),'[1]Demanda requerida 2028'!$CB$71:$DL$71,0),FALSE) -> 3654 | L87: =VLOOKUP(L$1,'[1]Demanda requerida 2028'!$CB$75:$DL$98,MATCH(_xlfn.CONCAT(TEXT(DATE($A87,$B87,1),"mmm-yy"),$D87),'[1]Demanda requerida 2028'!$CB$71:$DL$71,0),FALSE) -> 5377 | ... AB87: =VLOOKUP(AB$1,'[1]Demanda requerida 2028'!$CB$75:$DL$98,MATCH(_xlfn.CONCAT(TEXT(DATE($A87,$B87,1),"mmm-yy"),$D87),'[1]Demanda requerida 2028'!$CB$71:$DL$71,0),FALSE) -> 7415 | AC87: =SUM(E87:AB87) -> 230385
