Workbook

Sheet Formato -Producto N° 1  plano 
A5: Formato Oferta Producto No. 1 Carga Plana Convocatoria Pública DISPAC S.A. E.S.P.
A8: PROPONENTE
A10: MES | B10: DEMANDA REQUERIDA DISPAC KWh | C10: DEMANDA PERIODO REQUERIDA DISPAC KWh | D10: PORCENTAJE (%) OFERTADO DE LA DEMANDA REQUERIDA | E10: DEMANDA OFERTADA KWh - MES | F10: DEMANDA PERIODO OFERTADA KWh | G10: PRECIO OFERTADO $ kWh (0.00)
A11: 46235 | B11: 8928000 | C11: 25500000 | D11: 0
A12: 46266 | B12: 2520000 | D12: 0
A13: 46296 | B13: 2604000 | D13: 0
A14: 46327 | B14: 2520000 | D14: 0
A15: 46357 | B15: 8928000 | D15: 0
A16: 46388 | B16: ='Cantidades -Producto 1'!AG22 -> 8928000 | C16: =SUM(B16:B27) -> 86556000 | D16: 0
A17: 46419 | B17: ='Cantidades -Producto 1'!AG23 -> 8064000 | D17: 0
A18: 46447 | B18: ='Cantidades -Producto 1'!AG24 -> 8928000 | D18: 0
A19: 46478 | B19: ='Cantidades -Producto 1'!AG25 -> 8640000 | D19: 0
A20: 46508 | B20: ='Cantidades -Producto 1'!AG26 -> 8928000 | D20: 0
A21: 46539 | B21: ='Cantidades -Producto 1'!AG27 -> 8640000 | D21: 0
A22: 46569 | B22: ='Cantidades -Producto 1'!AG28 -> 8928000 | D22: 0
A23: 46600 | B23: ='Cantidades -Producto 1'!AG29 -> 8928000 | D23: 0
A24: 46631 | B24: ='Cantidades -Producto 1'!AG30 -> 2520000 | D24: 0
A25: 46661 | B25: ='Cantidades -Producto 1'!AG31 -> 2604000 | D25: 0
A26: 46692 | B26: ='Cantidades -Producto 1'!AG32 -> 2520000 | D26: 0
A27: 46722 | B27: ='Cantidades -Producto 1'!AG33 -> 8928000 | D27: 0
A28: 46753 | B28: ='Cantidades -Producto 1'!AG61 -> 8928000 | C28: =SUM(B28:B39) -> 79440000 | D28: 0
A29: 46784 | B29: ='Cantidades -Producto 1'!AG62 -> 8064000 | D29: 0
A30: 46813 | B30: ='Cantidades -Producto 1'!AG63 -> 8928000 | D30: 0
A31: 46844 | B31: ='Cantidades -Producto 1'!AG64 -> 8640000 | D31: 0
A32: 46874 | B32: ='Cantidades -Producto 1'!AG65 -> 5208000 | D32: 0
A33: 46905 | B33: ='Cantidades -Producto 1'!AG66 -> 5040000 | D33: 0
A34: 46935 | B34: ='Cantidades -Producto 1'!AG67 -> 5208000 | D34: 0
A35: 46966 | B35: ='Cantidades -Producto 1'!AG68 -> 5208000 | D35: 0
A36: 46997 | B36: ='Cantidades -Producto 1'!AG69 -> 5040000 | D36: 0
A37: 47027 | B37: ='Cantidades -Producto 1'!AG70 -> 5208000 | D37: 0
A38: 47058 | B38: ='Cantidades -Producto 1'!AG71 -> 5040000 | D38: 0
A39: 47088 | B39: ='Cantidades -Producto 1'!AG72 -> 8928000 | D39: 0
A40: 47119 | B40: ='Cantidades -Producto 1'!AG100 -> 11160000 | C40: =SUM(B40:B51) -> 131400000 | D40: 0
A41: 47150 | B41: ='Cantidades -Producto 1'!AG101 -> 10080000 | D41: 0
A42: 47178 | B42: ='Cantidades -Producto 1'!AG102 -> 11160000 | D42: 0
A43: 47209 | B43: ='Cantidades -Producto 1'!AG103 -> 10800000 | D43: 0
A44: 47239 | B44: ='Cantidades -Producto 1'!AG104 -> 11160000 | D44: 0
A45: 47270 | B45: ='Cantidades -Producto 1'!AG105 -> 10800000 | D45: 0
A46: 47300 | B46: ='Cantidades -Producto 1'!AG106 -> 11160000 | D46: 0
A47: 47331 | B47: ='Cantidades -Producto 1'!AG107 -> 11160000 | D47: 0
A48: 47362 | B48: ='Cantidades -Producto 1'!AG108 -> 10800000 | D48: 0
A49: 47392 | B49: ='Cantidades -Producto 1'!AG109 -> 11160000 | D49: 0
A50: 47423 | B50: ='Cantidades -Producto 1'!AG110 -> 10800000 | D50: 0
A51: 47453 | B51: ='Cantidades -Producto 1'!AG111 -> 11160000 | D51: 0
A52: 47484 | B52: ='Cantidades -Producto 1'!AG139 -> 11160000 | C52: =SUM(B52:B63) -> 131400000 | D52: 0
A53: 47515 | B53: ='Cantidades -Producto 1'!AG140 -> 10080000 | D53: 0
A54: 47543 | B54: ='Cantidades -Producto 1'!AG141 -> 11160000 | D54: 0
A55: 47574 | B55: ='Cantidades -Producto 1'!AG142 -> 10800000 | D55: 0
A56: 47604 | B56: ='Cantidades -Producto 1'!AG143 -> 11160000 | D56: 0
A57: 47635 | B57: ='Cantidades -Producto 1'!AG144 -> 10800000 | D57: 0
A58: 47665 | B58: ='Cantidades -Producto 1'!AG145 -> 11160000 | D58: 0
A59: 47696 | B59: ='Cantidades -Producto 1'!AG146 -> 11160000 | D59: 0
A60: 47727 | B60: ='Cantidades -Producto 1'!AG147 -> 10800000 | D60: 0
A61: 47757 | B61: ='Cantidades -Producto 1'!AG148 -> 11160000 | D61: 0
A62: 47788 | B62: ='Cantidades -Producto 1'!AG149 -> 10800000 | D62: 0
A63: 47818 | B63: ='Cantidades -Producto 1'!AG150 -> 11160000 | D63: 0
A64: 47849 | B64: ='Cantidades -Producto 1'!AG178 -> 11160000 | C64: =SUM(B64:B75) -> 131400000 | D64: 0
A65: 47880 | B65: ='Cantidades -Producto 1'!AG179 -> 10080000 | D65: 0
A66: 47908 | B66: ='Cantidades -Producto 1'!AG180 -> 11160000 | D66: 0
A67: 47939 | B67: ='Cantidades -Producto 1'!AG181 -> 10800000 | D67: 0
A68: 47969 | B68: ='Cantidades -Producto 1'!AG182 -> 11160000 | D68: 0
A69: 48000 | B69: ='Cantidades -Producto 1'!AG183 -> 10800000 | D69: 0
A70: 48030 | B70: ='Cantidades -Producto 1'!AG184 -> 11160000 | D70: 0
A71: 48061 | B71: ='Cantidades -Producto 1'!AG185 -> 11160000 | D71: 0
A72: 48092 | B72: ='Cantidades -Producto 1'!AG186 -> 10800000 | D72: 0
A73: 48122 | B73: ='Cantidades -Producto 1'!AG187 -> 11160000 | D73: 0
A74: 48153 | B74: ='Cantidades -Producto 1'!AG188 -> 10800000 | D74: 0
A75: 48183 | B75: ='Cantidades -Producto 1'!AG189 -> 11160000 | D75: 0
A76: 48214 | B76: ='Cantidades -Producto 1'!AG217 -> 8928000 | C76: =SUM(B76:B87) -> 105120000 | D76: 0
A77: 48245 | B77: ='Cantidades -Producto 1'!AG218 -> 8064000 | D77: 0
A78: 48274 | B78: ='Cantidades -Producto 1'!AG219 -> 8928000 | D78: 0
A79: 48305 | B79: ='Cantidades -Producto 1'!AG220 -> 8640000 | D79: 0
A80: 48335 | B80: ='Cantidades -Producto 1'!AG221 -> 8928000 | D80: 0
A81: 48366 | B81: ='Cantidades -Producto 1'!AG222 -> 8640000 | D81: 0
A82: 48396 | B82: ='Cantidades -Producto 1'!AG223 -> 8928000 | D82: 0
A83: 48427 | B83: ='Cantidades -Producto 1'!AG224 -> 8928000 | D83: 0
A84: 48458 | B84: ='Cantidades -Producto 1'!AG225 -> 8640000 | D84: 0
A85: 48488 | B85: ='Cantidades -Producto 1'!AG226 -> 8928000 | D85: 0
A86: 48519 | B86: ='Cantidades -Producto 1'!AG227 -> 8640000 | D86: 0
A87: 48549 | B87: ='Cantidades -Producto 1'!AG228 -> 8928000 | D87: 0
A88: 48580 | B88: ='Cantidades -Producto 1'!AG256 -> 8928000 | C88: =SUM(B88:B99) -> 129168000 | D88: 0
A89: 48611 | B89: ='Cantidades -Producto 1'!AG257 -> 10080000 | D89: 0
A90: 48639 | B90: ='Cantidades -Producto 1'!AG258 -> 11160000 | D90: 0
A91: 48670 | B91: ='Cantidades -Producto 1'!AG259 -> 10800000 | D91: 0
A92: 48700 | B92: ='Cantidades -Producto 1'!AG260 -> 11160000 | D92: 0
A93: 48731 | B93: ='Cantidades -Producto 1'!AG261 -> 10800000 | D93: 0
A94: 48761 | B94: ='Cantidades -Producto 1'!AG262 -> 11160000 | D94: 0
A95: 48792 | B95: ='Cantidades -Producto 1'!AG263 -> 11160000 | D95: 0
A96: 48823 | B96: ='Cantidades -Producto 1'!AG264 -> 10800000 | D96: 0
A97: 48853 | B97: ='Cantidades -Producto 1'!AG265 -> 11160000 | D97: 0
A98: 48884 | B98: ='Cantidades -Producto 1'!AG266 -> 10800000 | D98: 0
A99: 48914 | B99: ='Cantidades -Producto 1'!AG267 -> 11160000 | D99: 0
A100: 48945 | B100: ='Cantidades -Producto 1'!AG295 -> 12648000 | C100: =SUM(B100:B111) -> 148920000 | D100: 0
A101: 48976 | B101: ='Cantidades -Producto 1'!AG296 -> 11424000 | D101: 0
A102: 49004 | B102: ='Cantidades -Producto 1'!AG297 -> 12648000 | D102: 0
A103: 49035 | B103: ='Cantidades -Producto 1'!AG298 -> 12240000 | D103: 0
A104: 49065 | B104: ='Cantidades -Producto 1'!AG299 -> 12648000 | D104: 0
A105: 49096 | B105: ='Cantidades -Producto 1'!AG300 -> 12240000 | D105: 0
A106: 49126 | B106: ='Cantidades -Producto 1'!AG301 -> 12648000 | D106: 0
A107: 49157 | B107: ='Cantidades -Producto 1'!AG302 -> 12648000 | D107: 0
...

Sheet Cantidades -Producto 1
A2: PRODUCTO 1 | AF2: MES | AG2: DEMANDA REQUERIDA DISPAC KWh
A3: Mes | B3: Tipo de día | C3: No. de Días | D3: HORA 01 | E3: HORA 02 | F3: HORA 03 | G3: HORA 04 | H3: HORA 05 | I3: HORA 06 | J3: HORA 07 | K3: HORA 08 | L3: HORA 09 | M3: HORA 10 | N3: HORA 11 | O3: HORA 12 | P3: HORA 13 | Q3: HORA 14 | R3: HORA 15 | S3: HORA 16 | T3: HORA 17 | U3: HORA 18 | V3: HORA 19 | W3: HORA 20 | X3: HORA 21 | Y3: HORA 22 | Z3: HORA 23 | AA3: HORA 24 | AB3: Total | AF3: 46235 | AG3: =AC4 -> 8928000
A4: 46235 | B4: SÁBADO | C4: 5 | D4: 12000 | E4: 12000 | F4: 12000 | G4: 12000 | H4: 12000 | I4: 12000 | J4: 12000 | K4: 12000 | L4: 12000 | M4: 12000 | N4: 12000 | O4: 12000 | P4: 12000 | Q4: 12000 | R4: 12000 | S4: 12000 | T4: 12000 | U4: 12000 | V4: 12000 | W4: 12000 | X4: 12000 | Y4: 12000 | Z4: 12000 | AA4: 12000 | AB4: =SUM(D4:AA4)*C4 -> 1440000 | AC4: =+AB4+AB5+AB6 -> 8928000 | AF4: 46266 | AG4: =AC7 -> 2520000
B5: FESTIVO | C5: 5 | D5: 12000 | E5: 12000 | F5: 12000 | G5: 12000 | H5: 12000 | I5: 12000 | J5: 12000 | K5: 12000 | L5: 12000 | M5: 12000 | N5: 12000 | O5: 12000 | P5: 12000 | Q5: 12000 | R5: 12000 | S5: 12000 | T5: 12000 | U5: 12000 | V5: 12000 | W5: 12000 | X5: 12000 | Y5: 12000 | Z5: 12000 | AA5: 12000 | AB5: =SUM(D5:AA5)*C5 -> 1440000 | AF5: 46296 | AG5: =AC10 -> 2604000
B6: ORDINARIO | C6: 21 | D6: 12000 | E6: 12000 | F6: 12000 | G6: 12000 | H6: 12000 | I6: 12000 | J6: 12000 | K6: 12000 | L6: 12000 | M6: 12000 | N6: 12000 | O6: 12000 | P6: 12000 | Q6: 12000 | R6: 12000 | S6: 12000 | T6: 12000 | U6: 12000 | V6: 12000 | W6: 12000 | X6: 12000 | Y6: 12000 | Z6: 12000 | AA6: 12000 | AB6: =SUM(D6:AA6)*C6 -> 6048000 | AF6: 46327 | AG6: =AC13 -> 2520000
A7: 46266 | B7: SÁBADO | C7: 4 | D7: 3500 | E7: 3500 | F7: 3500 | G7: 3500 | H7: 3500 | I7: 3500 | J7: 3500 | K7: 3500 | L7: 3500 | M7: 3500 | N7: 3500 | O7: 3500 | P7: 3500 | Q7: 3500 | R7: 3500 | S7: 3500 | T7: 3500 | U7: 3500 | V7: 3500 | W7: 3500 | X7: 3500 | Y7: 3500 | Z7: 3500 | AA7: 3500 | AB7: =SUM(D7:AA7)*C7 -> 336000 | AC7: =+AB7+AB8+AB9 -> 2520000 | AF7: 46357 | AG7: =AC16 -> 8928000
B8: FESTIVO | C8: 4 | D8: 3500 | E8: 3500 | F8: 3500 | G8: 3500 | H8: 3500 | I8: 3500 | J8: 3500 | K8: 3500 | L8: 3500 | M8: 3500 | N8: 3500 | O8: 3500 | P8: 3500 | Q8: 3500 | R8: 3500 | S8: 3500 | T8: 3500 | U8: 3500 | V8: 3500 | W8: 3500 | X8: 3500 | Y8: 3500 | Z8: 3500 | AA8: 3500 | AB8: =SUM(D8:AA8)*C8 -> 336000
B9: ORDINARIO | C9: 22 | D9: 3500 | E9: 3500 | F9: 3500 | G9: 3500 | H9: 3500 | I9: 3500 | J9: 3500 | K9: 3500 | L9: 3500 | M9: 3500 | N9: 3500 | O9: 3500 | P9: 3500 | Q9: 3500 | R9: 3500 | S9: 3500 | T9: 3500 | U9: 3500 | V9: 3500 | W9: 3500 | X9: 3500 | Y9: 3500 | Z9: 3500 | AA9: 3500 | AB9: =SUM(D9:AA9)*C9 -> 1848000
A10: 46296 | B10: SÁBADO | C10: 5 | D10: 3500 | E10: 3500 | F10: 3500 | G10: 3500 | H10: 3500 | I10: 3500 | J10: 3500 | K10: 3500 | L10: 3500 | M10: 3500 | N10: 3500 | O10: 3500 | P10: 3500 | Q10: 3500 | R10: 3500 | S10: 3500 | T10: 3500 | U10: 3500 | V10: 3500 | W10: 3500 | X10: 3500 | Y10: 3500 | Z10: 3500 | AA10: 3500 | AB10: =SUM(D10:AA10)*C10 -> 420000 | AC10: =+AB10+AB11+AB12 -> 2604000
B11: FESTIVO | C11: 4 | D11: 3500 | E11: 3500 | F11: 3500 | G11: 3500 | H11: 3500 | I11: 3500 | J11: 3500 | K11: 3500 | L11: 3500 | M11: 3500 | N11: 3500 | O11: 3500 | P11: 3500 | Q11: 3500 | R11: 3500 | S11: 3500 | T11: 3500 | U11: 3500 | V11: 3500 | W11: 3500 | X11: 3500 | Y11: 3500 | Z11: 3500 | AA11: 3500 | AB11: =SUM(D11:AA11)*C11 -> 336000
B12: ORDINARIO | C12: 22 | D12: 3500 | E12: 3500 | F12: 3500 | G12: 3500 | H12: 3500 | I12: 3500 | J12: 3500 | K12: 3500 | L12: 3500 | M12: 3500 | N12: 3500 | O12: 3500 | P12: 3500 | Q12: 3500 | R12: 3500 | S12: 3500 | T12: 3500 | U12: 3500 | V12: 3500 | W12: 3500 | X12: 3500 | Y12: 3500 | Z12: 3500 | AA12: 3500 | AB12: =SUM(D12:AA12)*C12 -> 1848000
A13: 46327 | B13: SÁBADO | C13: 4 | D13: 3500 | E13: 3500 | F13: 3500 | G13: 3500 | H13: 3500 | I13: 3500 | J13: 3500 | K13: 3500 | L13: 3500 | M13: 3500 | N13: 3500 | O13: 3500 | P13: 3500 | Q13: 3500 | R13: 3500 | S13: 3500 | T13: 3500 | U13: 3500 | V13: 3500 | W13: 3500 | X13: 3500 | Y13: 3500 | Z13: 3500 | AA13: 3500 | AB13: =SUM(D13:AA13)*C13 -> 336000 | AC13: =+AB13+AB14+AB15 -> 2520000
B14: FESTIVO | C14: 5 | D14: 3500 | E14: 3500 | F14: 3500 | G14: 3500 | H14: 3500 | I14: 3500 | J14: 3500 | K14: 3500 | L14: 3500 | M14: 3500 | N14: 3500 | O14: 3500 | P14: 3500 | Q14: 3500 | R14: 3500 | S14: 3500 | T14: 3500 | U14: 3500 | V14: 3500 | W14: 3500 | X14: 3500 | Y14: 3500 | Z14: 3500 | AA14: 3500 | AB14: =SUM(D14:AA14)*C14 -> 420000
B15: ORDINARIO | C15: 21 | D15: 3500 | E15: 3500 | F15: 3500 | G15: 3500 | H15: 3500 | I15: 3500 | J15: 3500 | K15: 3500 | L15: 3500 | M15: 3500 | N15: 3500 | O15: 3500 | P15: 3500 | Q15: 3500 | R15: 3500 | S15: 3500 | T15: 3500 | U15: 3500 | V15: 3500 | W15: 3500 | X15: 3500 | Y15: 3500 | Z15: 3500 | AA15: 3500 | AB15: =SUM(D15:AA15)*C15 -> 1764000
A16: 46357 | B16: SÁBADO | C16: 4 | D16: 12000 | E16: 12000 | F16: 12000 | G16: 12000 | H16: 12000 | I16: 12000 | J16: 12000 | K16: 12000 | L16: 12000 | M16: 12000 | N16: 12000 | O16: 12000 | P16: 12000 | Q16: 12000 | R16: 12000 | S16: 12000 | T16: 12000 | U16: 12000 | V16: 12000 | W16: 12000 | X16: 12000 | Y16: 12000 | Z16: 12000 | AA16: 12000 | AB16: =SUM(D16:AA16)*C16 -> 1152000 | AC16: =+AB16+AB17+AB18 -> 8928000
B17: FESTIVO | C17: 4 | D17: 12000 | E17: 12000 | F17: 12000 | G17: 12000 | H17: 12000 | I17: 12000 | J17: 12000 | K17: 12000 | L17: 12000 | M17: 12000 | N17: 12000 | O17: 12000 | P17: 12000 | Q17: 12000 | R17: 12000 | S17: 12000 | T17: 12000 | U17: 12000 | V17: 12000 | W17: 12000 | X17: 12000 | Y17: 12000 | Z17: 12000 | AA17: 12000 | AB17: =SUM(D17:AA17)*C17 -> 1152000
B18: ORDINARIO | C18: 23 | D18: 12000 | E18: 12000 | F18: 12000 | G18: 12000 | H18: 12000 | I18: 12000 | J18: 12000 | K18: 12000 | L18: 12000 | M18: 12000 | N18: 12000 | O18: 12000 | P18: 12000 | Q18: 12000 | R18: 12000 | S18: 12000 | T18: 12000 | U18: 12000 | V18: 12000 | W18: 12000 | X18: 12000 | Y18: 12000 | Z18: 12000 | AA18: 12000 | AB18: =SUM(D18:AA18)*C18 -> 6624000
A21: Mes | B21: Tipo de día | C21: No. de Días | D21: HORA 01 | E21: HORA 02 | F21: HORA 03 | G21: HORA 04 | H21: HORA 05 | I21: HORA 06 | J21: HORA 07 | K21: HORA 08 | L21: HORA 09 | M21: HORA 10 | N21: HORA 11 | O21: HORA 12 | P21: HORA 13 | Q21: HORA 14 | R21: HORA 15 | S21: HORA 16 | T21: HORA 17 | U21: HORA 18 | V21: HORA 19 | W21: HORA 20 | X21: HORA 21 | Y21: HORA 22 | Z21: HORA 23 | AA21: HORA 24 | AB21: Total
A22: 46388 | B22: SÁBADO | C22: 5 | D22: 12000 | E22: 12000 | F22: 12000 | G22: 12000 | H22: 12000 | I22: 12000 | J22: 12000 | K22: 12000 | L22: 12000 | M22: 12000 | N22: 12000 | O22: 12000 | P22: 12000 | Q22: 12000 | R22: 12000 | S22: 12000 | T22: 12000 | U22: 12000 | V22: 12000 | W22: 12000 | X22: 12000 | Y22: 12000 | Z22: 12000 | AA22: 12000 | AB22: =SUM(D22:AA22)*C22 -> 1440000 | AC22: =+AB22+AB23+AB24 -> 8928000 | AF22: 46388 | AG22: =AC22 -> 8928000
B23: FESTIVO | C23: 7 | D23: 12000 | E23: 12000 | F23: 12000 | G23: 12000 | H23: 12000 | I23: 12000 | J23: 12000 | K23: 12000 | L23: 12000 | M23: 12000 | N23: 12000 | O23: 12000 | P23: 12000 | Q23: 12000 | R23: 12000 | S23: 12000 | T23: 12000 | U23: 12000 | V23: 12000 | W23: 12000 | X23: 12000 | Y23: 12000 | Z23: 12000 | AA23: 12000 | AB23: =SUM(D23:AA23)*C23 -> 2016000 | AF23: 46419 | AG23: =AC25 -> 8064000
B24: ORDINARIO | C24: 19 | D24: 12000 | E24: 12000 | F24: 12000 | G24: 12000 | H24: 12000 | I24: 12000 | J24: 12000 | K24: 12000 | L24: 12000 | M24: 12000 | N24: 12000 | O24: 12000 | P24: 12000 | Q24: 12000 | R24: 12000 | S24: 12000 | T24: 12000 | U24: 12000 | V24: 12000 | W24: 12000 | X24: 12000 | Y24: 12000 | Z24: 12000 | AA24: 12000 | AB24: =SUM(D24:AA24)*C24 -> 5472000 | AF24: 46447 | AG24: =AC28 -> 8928000
A25: 46419 | B25: SÁBADO | C25: 4 | D25: 12000 | E25: 12000 | F25: 12000 | G25: 12000 | H25: 12000 | I25: 12000 | J25: 12000 | K25: 12000 | L25: 12000 | M25: 12000 | N25: 12000 | O25: 12000 | P25: 12000 | Q25: 12000 | R25: 12000 | S25: 12000 | T25: 12000 | U25: 12000 | V25: 12000 | W25: 12000 | X25: 12000 | Y25: 12000 | Z25: 12000 | AA25: 12000 | AB25: =SUM(D25:AA25)*C25 -> 1152000 | AC25: =+AB25+AB26+AB27 -> 8064000 | AF25: 46478 | AG25: =AC31 -> 8640000
B26: FESTIVO | C26: 4 | D26: 12000 | E26: 12000 | F26: 12000 | G26: 12000 | H26: 12000 | I26: 12000 | J26: 12000 | K26: 12000 | L26: 12000 | M26: 12000 | N26: 12000 | O26: 12000 | P26: 12000 | Q26: 12000 | R26: 12000 | S26: 12000 | T26: 12000 | U26: 12000 | V26: 12000 | W26: 12000 | X26: 12000 | Y26: 12000 | Z26: 12000 | AA26: 12000 | AB26: =SUM(D26:AA26)*C26 -> 1152000 | AF26: 46508 | AG26: =AC34 -> 8928000
B27: ORDINARIO | C27: 20 | D27: 12000 | E27: 12000 | F27: 12000 | G27: 12000 | H27: 12000 | I27: 12000 | J27: 12000 | K27: 12000 | L27: 12000 | M27: 12000 | N27: 12000 | O27: 12000 | P27: 12000 | Q27: 12000 | R27: 12000 | S27: 12000 | T27: 12000 | U27: 12000 | V27: 12000 | W27: 12000 | X27: 12000 | Y27: 12000 | Z27: 12000 | AA27: 12000 | AB27: =SUM(D27:AA27)*C27 -> 5760000 | AF27: 46539 | AG27: =AC37 -> 8640000
A28: 46447 | B28: SÁBADO | C28: 4 | D28: 12000 | E28: 12000 | F28: 12000 | G28: 12000 | H28: 12000 | I28: 12000 | J28: 12000 | K28: 12000 | L28: 12000 | M28: 12000 | N28: 12000 | O28: 12000 | P28: 12000 | Q28: 12000 | R28: 12000 | S28: 12000 | T28: 12000 | U28: 12000 | V28: 12000 | W28: 12000 | X28: 12000 | Y28: 12000 | Z28: 12000 | AA28: 12000 | AB28: =SUM(D28:AA28)*C28 -> 1152000 | AC28: =+AB28+AB29+AB30 -> 8928000 | AF28: 46569 | AG28: =AC40 -> 8928000
B29: FESTIVO | C29: 4 | D29: 12000 | E29: 12000 | F29: 12000 | G29: 12000 | H29: 12000 | I29: 12000 | J29: 12000 | K29: 12000 | L29: 12000 | M29: 12000 | N29: 12000 | O29: 12000 | P29: 12000 | Q29: 12000 | R29: 12000 | S29: 12000 | T29: 12000 | U29: 12000 | V29: 12000 | W29: 12000 | X29: 12000 | Y29: 12000 | Z29: 12000 | AA29: 12000 | AB29: =SUM(D29:AA29)*C29 -> 1152000 | AF29: 46600 | AG29: =AC43 -> 8928000
B30: ORDINARIO | C30: 23 | D30: 12000 | E30: 12000 | F30: 12000 | G30: 12000 | H30: 12000 | I30: 12000 | J30: 12000 | K30: 12000 | L30: 12000 | M30: 12000 | N30: 12000 | O30: 12000 | P30: 12000 | Q30: 12000 | R30: 12000 | S30: 12000 | T30: 12000 | U30: 12000 | V30: 12000 | W30: 12000 | X30: 12000 | Y30: 12000 | Z30: 12000 | AA30: 12000 | AB30: =SUM(D30:AA30)*C30 -> 6624000 | AF30: 46631 | AG30: =AC46 -> 2520000
A31: 46478 | B31: SÁBADO | C31: 4 | D31: 12000 | E31: 12000 | F31: 12000 | G31: 12000 | H31: 12000 | I31: 12000 | J31: 12000 | K31: 12000 | L31: 12000 | M31: 12000 | N31: 12000 | O31: 12000 | P31: 12000 | Q31: 12000 | R31: 12000 | S31: 12000 | T31: 12000 | U31: 12000 | V31: 12000 | W31: 12000 | X31: 12000 | Y31: 12000 | Z31: 12000 | AA31: 12000 | AB31: =SUM(D31:AA31)*C31 -> 1152000 | AC31: =+AB31+AB32+AB33 -> 8640000 | AF31: 46661 | AG31: =AC49 -> 2604000
B32: FESTIVO | C32: 4 | D32: 12000 | E32: 12000 | F32: 12000 | G32: 12000 | H32: 12000 | I32: 12000 | J32: 12000 | K32: 12000 | L32: 12000 | M32: 12000 | N32: 12000 | O32: 12000 | P32: 12000 | Q32: 12000 | R32: 12000 | S32: 12000 | T32: 12000 | U32: 12000 | V32: 12000 | W32: 12000 | X32: 12000 | Y32: 12000 | Z32: 12000 | AA32: 12000 | AB32: =SUM(D32:AA32)*C32 -> 1152000 | AF32: 46692 | AG32: =AC52 -> 2520000
B33: ORDINARIO | C33: 22 | D33: 12000 | E33: 12000 | F33: 12000 | G33: 12000 | H33: 12000 | I33: 12000 | J33: 12000 | K33: 12000 | L33: 12000 | M33: 12000 | N33: 12000 | O33: 12000 | P33: 12000 | Q33: 12000 | R33: 12000 | S33: 12000 | T33: 12000 | U33: 12000 | V33: 12000 | W33: 12000 | X33: 12000 | Y33: 12000 | Z33: 12000 | AA33: 12000 | AB33: =SUM(D33:AA33)*C33 -> 6336000 | AF33: 46722 | AG33: =AC55 -> 8928000
A34: 46508 | B34: SÁBADO | C34: 5 | D34: 12000 | E34: 12000 | F34: 12000 | G34: 12000 | H34: 12000 | I34: 12000 | J34: 12000 | K34: 12000 | L34: 12000 | M34: 12000 | N34: 12000 | O34: 12000 | P34: 12000 | Q34: 12000 | R34: 12000 | S34: 12000 | T34: 12000 | U34: 12000 | V34: 12000 | W34: 12000 | X34: 12000 | Y34: 12000 | Z34: 12000 | AA34: 12000 | AB34: =SUM(D34:AA34)*C34 -> 1440000 | AC34: =+AB34+AB35+AB36 -> 8928000
B35: FESTIVO | C35: 5 | D35: 12000 | E35: 12000 | F35: 12000 | G35: 12000 | H35: 12000 | I35: 12000 | J35: 12000 | K35: 12000 | L35: 12000 | M35: 12000 | N35: 12000 | O35: 12000 | P35: 12000 | Q35: 12000 | R35: 12000 | S35: 12000 | T35: 12000 | U35: 12000 | V35: 12000 | W35: 12000 | X35: 12000 | Y35: 12000 | Z35: 12000 | AA35: 12000 | AB35: =SUM(D35:AA35)*C35 -> 1440000
B36: ORDINARIO | C36: 21 | D36: 12000 | E36: 12000 | F36: 12000 | G36: 12000 | H36: 12000 | I36: 12000 | J36: 12000 | K36: 12000 | L36: 12000 | M36: 12000 | N36: 12000 | O36: 12000 | P36: 12000 | Q36: 12000 | R36: 12000 | S36: 12000 | T36: 12000 | U36: 12000 | V36: 12000 | W36: 12000 | X36: 12000 | Y36: 12000 | Z36: 12000 | AA36: 12000 | AB36: =SUM(D36:AA36)*C36 -> 6048000
A37: 46539 | B37: SÁBADO | C37: 4 | D37: 12000 | E37: 12000 | F37: 12000 | G37: 12000 | H37: 12000 | I37: 12000 | J37: 12000 | K37: 12000 | L37: 12000 | M37: 12000 | N37: 12000 | O37: 12000 | P37: 12000 | Q37: 12000 | R37: 12000 | S37: 12000 | T37: 12000 | U37: 12000 | V37: 12000 | W37: 12000 | X37: 12000 | Y37: 12000 | Z37: 12000 | AA37: 12000 | AB37: =SUM(D37:AA37)*C37 -> 1152000 | AC37: =+AB37+AB38+AB39 -> 8640000
B38: FESTIVO | C38: 4 | D38: 12000 | E38: 12000 | F38: 12000 | G38: 12000 | H38: 12000 | I38: 12000 | J38: 12000 | K38: 12000 | L38: 12000 | M38: 12000 | N38: 12000 | O38: 12000 | P38: 12000 | Q38: 12000 | R38: 12000 | S38: 12000 | T38: 12000 | U38: 12000 | V38: 12000 | W38: 12000 | X38: 12000 | Y38: 12000 | Z38: 12000 | AA38: 12000 | AB38: =SUM(D38:AA38)*C38 -> 1152000
B39: ORDINARIO | C39: 22 | D39: 12000 | E39: 12000 | F39: 12000 | G39: 12000 | H39: 12000 | I39: 12000 | J39: 12000 | K39: 12000 | L39: 12000 | M39: 12000 | N39: 12000 | O39: 12000 | P39: 12000 | Q39: 12000 | R39: 12000 | S39: 12000 | T39: 12000 | U39: 12000 | V39: 12000 | W39: 12000 | X39: 12000 | Y39: 12000 | Z39: 12000 | AA39: 12000 | AB39: =SUM(D39:AA39)*C39 -> 6336000
A40: 46569 | B40: SÁBADO | C40: 5 | D40: 12000 | E40: 12000 | F40: 12000 | G40: 12000 | H40: 12000 | I40: 12000 | J40: 12000 | K40: 12000 | L40: 12000 | M40: 12000 | N40: 12000 | O40: 12000 | P40: 12000 | Q40: 12000 | R40: 12000 | S40: 12000 | T40: 12000 | U40: 12000 | V40: 12000 | W40: 12000 | X40: 12000 | Y40: 12000 | Z40: 12000 | AA40: 12000 | AB40: =SUM(D40:AA40)*C40 -> 1440000 | AC40: =+AB40+AB41+AB42 -> 8928000
B41: FESTIVO | C41: 4 | D41: 12000 | E41: 12000 | F41: 12000 | G41: 12000 | H41: 12000 | I41: 12000 | J41: 12000 | K41: 12000 | L41: 12000 | M41: 12000 | N41: 12000 | O41: 12000 | P41: 12000 | Q41: 12000 | R41: 12000 | S41: 12000 | T41: 12000 | U41: 12000 | V41: 12000 | W41: 12000 | X41: 12000 | Y41: 12000 | Z41: 12000 | AA41: 12000 | AB41: =SUM(D41:AA41)*C41 -> 1152000
B42: ORDINARIO | C42: 22 | D42: 12000 | E42: 12000 | F42: 12000 | G42: 12000 | H42: 12000 | I42: 12000 | J42: 12000 | K42: 12000 | L42: 12000 | M42: 12000 | N42: 12000 | O42: 12000 | P42: 12000 | Q42: 12000 | R42: 12000 | S42: 12000 | T42: 12000 | U42: 12000 | V42: 12000 | W42: 12000 | X42: 12000 | Y42: 12000 | Z42: 12000 | AA42: 12000 | AB42: =SUM(D42:AA42)*C42 -> 6336000
A43: 46600 | B43: SÁBADO | C43: 4 | D43: 12000 | E43: 12000 | F43: 12000 | G43: 12000 | H43: 12000 | I43: 12000 | J43: 12000 | K43: 12000 | L43: 12000 | M43: 12000 | N43: 12000 | O43: 12000 | P43: 12000 | Q43: 12000 | R43: 12000 | S43: 12000 | T43: 12000 | U43: 12000 | V43: 12000 | W43: 12000 | X43: 12000 | Y43: 12000 | Z43: 12000 | AA43: 12000 | AB43: =SUM(D43:AA43)*C43 -> 1152000 | AC43: =+AB43+AB44+AB45 -> 8928000
B44: FESTIVO | C44: 5 | D44: 12000 | E44: 12000 | F44: 12000 | G44: 12000 | H44: 12000 | I44: 12000 | J44: 12000 | K44: 12000 | L44: 12000 | M44: 12000 | N44: 12000 | O44: 12000 | P44: 12000 | Q44: 12000 | R44: 12000 | S44: 12000 | T44: 12000 | U44: 12000 | V44: 12000 | W44: 12000 | X44: 12000 | Y44: 12000 | Z44: 12000 | AA44: 12000 | AB44: =SUM(D44:AA44)*C44 -> 1440000
B45: ORDINARIO | C45: 22 | D45: 12000 | E45: 12000 | F45: 12000 | G45: 12000 | H45: 12000 | I45: 12000 | J45: 12000 | K45: 12000 | L45: 12000 | M45: 12000 | N45: 12000 | O45: 12000 | P45: 12000 | Q45: 12000 | R45: 12000 | S45: 12000 | T45: 12000 | U45: 12000 | V45: 12000 | W45: 12000 | X45: 12000 | Y45: 12000 | Z45: 12000 | AA45: 12000 | AB45: =SUM(D45:AA45)*C45 -> 6336000
A46: 46631 | B46: SÁBADO | C46: 4 | D46: 3500 | E46: 3500 | F46: 3500 | G46: 3500 | H46: 3500 | I46: 3500 | J46: 3500 | K46: 3500 | L46: 3500 | M46: 3500 | N46: 3500 | O46: 3500 | P46: 3500 | Q46: 3500 | R46: 3500 | S46: 3500 | T46: 3500 | U46: 3500 | V46: 3500 | W46: 3500 | X46: 3500 | Y46: 3500 | Z46: 3500 | AA46: 3500 | AB46: =SUM(D46:AA46)*C46 -> 336000 | AC46: =+AB46+AB47+AB48 -> 2520000
B47: FESTIVO | C47: 4 | D47: 3500 | E47: 3500 | F47: 3500 | G47: 3500 | H47: 3500 | I47: 3500 | J47: 3500 | K47: 3500 | L47: 3500 | M47: 3500 | N47: 3500 | O47: 3500 | P47: 3500 | Q47: 3500 | R47: 3500 | S47: 3500 | T47: 3500 | U47: 3500 | V47: 3500 | W47: 3500 | X47: 3500 | Y47: 3500 | Z47: 3500 | AA47: 3500 | AB47: =SUM(D47:AA47)*C47 -> 336000
B48: ORDINARIO | C48: 22 | D48: 3500 | E48: 3500 | F48: 3500 | G48: 3500 | H48: 3500 | I48: 3500 | J48: 3500 | K48: 3500 | L48: 3500 | M48: 3500 | N48: 3500 | O48: 3500 | P48: 3500 | Q48: 3500 | R48: 3500 | S48: 3500 | T48: 3500 | U48: 3500 | V48: 3500 | W48: 3500 | X48: 3500 | Y48: 3500 | Z48: 3500 | AA48: 3500 | AB48: =SUM(D48:AA48)*C48 -> 1848000
A49: 46661 | B49: SÁBADO | C49: 5 | D49: 3500 | E49: 3500 | F49: 3500 | G49: 3500 | H49: 3500 | I49: 3500 | J49: 3500 | K49: 3500 | L49: 3500 | M49: 3500 | N49: 3500 | O49: 3500 | P49: 3500 | Q49: 3500 | R49: 3500 | S49: 3500 | T49: 3500 | U49: 3500 | V49: 3500 | W49: 3500 | X49: 3500 | Y49: 3500 | Z49: 3500 | AA49: 3500 | AB49: =SUM(D49:AA49)*C49 -> 420000 | AC49: =+AB49+AB50+AB51 -> 2604000
B50: FESTIVO | C50: 5 | D50: 3500 | E50: 3500 | F50: 3500 | G50: 3500 | H50: 3500 | I50: 3500 | J50: 3500 | K50: 3500 | L50: 3500 | M50: 3500 | N50: 3500 | O50: 3500 | P50: 3500 | Q50: 3500 | R50: 3500 | S50: 3500 | T50: 3500 | U50: 3500 | V50: 3500 | W50: 3500 | X50: 3500 | Y50: 3500 | Z50: 3500 | AA50: 3500 | AB50: =SUM(D50:AA50)*C50 -> 420000
B51: ORDINARIO | C51: 21 | D51: 3500 | E51: 3500 | F51: 3500 | G51: 3500 | H51: 3500 | I51: 3500 | J51: 3500 | K51: 3500 | L51: 3500 | M51: 3500 | N51: 3500 | O51: 3500 | P51: 3500 | Q51: 3500 | R51: 3500 | S51: 3500 | T51: 3500 | U51: 3500 | V51: 3500 | W51: 3500 | X51: 3500 | Y51: 3500 | Z51: 3500 | AA51: 3500 | AB51: =SUM(D51:AA51)*C51 -> 1764000
A52: 46692 | B52: SÁBADO | C52: 4 | D52: 3500 | E52: 3500 | F52: 3500 | G52: 3500 | H52: 3500 | I52: 3500 | J52: 3500 | K52: 3500 | L52: 3500 | M52: 3500 | N52: 3500 | O52: 3500 | P52: 3500 | Q52: 3500 | R52: 3500 | S52: 3500 | T52: 3500 | U52: 3500 | V52: 3500 | W52: 3500 | X52: 3500 | Y52: 3500 | Z52: 3500 | AA52: 3500 | AB52: =SUM(D52:AA52)*C52 -> 336000 | AC52: =+AB52+AB53+AB54 -> 2520000
B53: FESTIVO | C53: 4 | D53: 3500 | E53: 3500 | F53: 3500 | G53: 3500 | H53: 3500 | I53: 3500 | J53: 3500 | K53: 3500 | L53: 3500 | M53: 3500 | N53: 3500 | O53: 3500 | P53: 3500 | Q53: 3500 | R53: 3500 | S53: 3500 | T53: 3500 | U53: 3500 | V53: 3500 | W53: 3500 | X53: 3500 | Y53: 3500 | Z53: 3500 | AA53: 3500 | AB53: =SUM(D53:AA53)*C53 -> 336000
B54: ORDINARIO | C54: 22 | D54: 3500 | E54: 3500 | F54: 3500 | G54: 3500 | H54: 3500 | I54: 3500 | J54: 3500 | K54: 3500 | L54: 3500 | M54: 3500 | N54: 3500 | O54: 3500 | P54: 3500 | Q54: 3500 | R54: 3500 | S54: 3500 | T54: 3500 | U54: 3500 | V54: 3500 | W54: 3500 | X54: 3500 | Y54: 3500 | Z54: 3500 | AA54: 3500 | AB54: =SUM(D54:AA54)*C54 -> 1848000
A55: 46722 | B55: SÁBADO | C55: 4 | D55: 12000 | E55: 12000 | F55: 12000 | G55: 12000 | H55: 12000 | I55: 12000 | J55: 12000 | K55: 12000 | L55: 12000 | M55: 12000 | N55: 12000 | O55: 12000 | P55: 12000 | Q55: 12000 | R55: 12000 | S55: 12000 | T55: 12000 | U55: 12000 | V55: 12000 | W55: 12000 | X55: 12000 | Y55: 12000 | Z55: 12000 | AA55: 12000 | AB55: =SUM(D55:AA55)*C55 -> 1152000 | AC55: =+AB55+AB56+AB57 -> 8928000
B56: FESTIVO | C56: 4 | D56: 12000 | E56: 12000 | F56: 12000 | G56: 12000 | H56: 12000 | I56: 12000 | J56: 12000 | K56: 12000 | L56: 12000 | M56: 12000 | N56: 12000 | O56: 12000 | P56: 12000 | Q56: 12000 | R56: 12000 | S56: 12000 | T56: 12000 | U56: 12000 | V56: 12000 | W56: 12000 | X56: 12000 | Y56: 12000 | Z56: 12000 | AA56: 12000 | AB56: =SUM(D56:AA56)*C56 -> 1152000
B57: ORDINARIO | C57: 23 | D57: 12000 | E57: 12000 | F57: 12000 | G57: 12000 | H57: 12000 | I57: 12000 | J57: 12000 | K57: 12000 | L57: 12000 | M57: 12000 | N57: 12000 | O57: 12000 | P57: 12000 | Q57: 12000 | R57: 12000 | S57: 12000 | T57: 12000 | U57: 12000 | V57: 12000 | W57: 12000 | X57: 12000 | Y57: 12000 | Z57: 12000 | AA57: 12000 | AB57: =SUM(D57:AA57)*C57 -> 6624000
A60: Mes | B60: Tipo de día | C60: No. de Días | D60: HORA 01 | E60: HORA 02 | F60: HORA 03 | G60: HORA 04 | H60: HORA 05 | I60: HORA 06 | J60: HORA 07 | K60: HORA 08 | L60: HORA 09 | M60: HORA 10 | N60: HORA 11 | O60: HORA 12 | P60: HORA 13 | Q60: HORA 14 | R60: HORA 15 | S60: HORA 16 | T60: HORA 17 | U60: HORA 18 | V60: HORA 19 | W60: HORA 20 | X60: HORA 21 | Y60: HORA 22 | Z60: HORA 23 | AA60: HORA 24 | AB60: Total
A61: 46753 | B61: SÁBADO | C61: 4 | D61: 12000 | E61: 12000 | F61: 12000 | G61: 12000 | H61: 12000 | I61: 12000 | J61: 12000 | K61: 12000 | L61: 12000 | M61: 12000 | N61: 12000 | O61: 12000 | P61: 12000 | Q61: 12000 | R61: 12000 | S61: 12000 | T61: 12000 | U61: 12000 | V61: 12000 | W61: 12000 | X61: 12000 | Y61: 12000 | Z61: 12000 | AA61: 12000 | AB61: =SUM(D61:AA61)*C61 -> 1152000 | AC61: =+AB61+AB62+AB63 -> 8928000 | AF61: 46753 | AG61: =AC61 -> 8928000
B62: FESTIVO | C62: 7 | D62: 12000 | E62: 12000 | F62: 12000 | G62: 12000 | H62: 12000 | I62: 12000 | J62: 12000 | K62: 12000 | L62: 12000 | M62: 12000 | N62: 12000 | O62: 12000 | P62: 12000 | Q62: 12000 | R62: 12000 | S62: 12000 | T62: 12000 | U62: 12000 | V62: 12000 | W62: 12000 | X62: 12000 | Y62: 12000 | Z62: 12000 | AA62: 12000 | AB62: =SUM(D62:AA62)*C62 -> 2016000 | AF62: 46784 | AG62: =AC64 -> 8064000
B63: ORDINARIO | C63: 20 | D63: 12000 | E63: 12000 | F63: 12000 | G63: 12000 | H63: 12000 | I63: 12000 | J63: 12000 | K63: 12000 | L63: 12000 | M63: 12000 | N63: 12000 | O63: 12000 | P63: 12000 | Q63: 12000 | R63: 12000 | S63: 12000 | T63: 12000 | U63: 12000 | V63: 12000 | W63: 12000 | X63: 12000 | Y63: 12000 | Z63: 12000 | AA63: 12000 | AB63: =SUM(D63:AA63)*C63 -> 5760000 | AF63: 46813 | AG63: =AC67 -> 8928000
A64: 46784 | B64: SÁBADO | C64: 4 | D64: 12000 | E64: 12000 | F64: 12000 | G64: 12000 | H64: 12000 | I64: 12000 | J64: 12000 | K64: 12000 | L64: 12000 | M64: 12000 | N64: 12000 | O64: 12000 | P64: 12000 | Q64: 12000 | R64: 12000 | S64: 12000 | T64: 12000 | U64: 12000 | V64: 12000 | W64: 12000 | X64: 12000 | Y64: 12000 | Z64: 12000 | AA64: 12000 | AB64: =SUM(D64:AA64)*C64 -> 1152000 | AC64: =+AB64+AB65+AB66 -> 8064000 | AF64: 46844 | AG64: =AC70 -> 8640000
B65: FESTIVO | C65: 4 | D65: 12000 | E65: 12000 | F65: 12000 | G65: 12000 | H65: 12000 | I65: 12000 | J65: 12000 | K65: 12000 | L65: 12000 | M65: 12000 | N65: 12000 | O65: 12000 | P65: 12000 | Q65: 12000 | R65: 12000 | S65: 12000 | T65: 12000 | U65: 12000 | V65: 12000 | W65: 12000 | X65: 12000 | Y65: 12000 | Z65: 12000 | AA65: 12000 | AB65: =SUM(D65:AA65)*C65 -> 1152000 | AF65: 46874 | AG65: =AC73 -> 5208000
B66: ORDINARIO | C66: 20 | D66: 12000 | E66: 12000 | F66: 12000 | G66: 12000 | H66: 12000 | I66: 12000 | J66: 12000 | K66: 12000 | L66: 12000 | M66: 12000 | N66: 12000 | O66: 12000 | P66: 12000 | Q66: 12000 | R66: 12000 | S66: 12000 | T66: 12000 | U66: 12000 | V66: 12000 | W66: 12000 | X66: 12000 | Y66: 12000 | Z66: 12000 | AA66: 12000 | AB66: =SUM(D66:AA66)*C66 -> 5760000 | AF66: 46905 | AG66: =AC76 -> 5040000
A67: 46813 | B67: SÁBADO | C67: 4 | D67: 12000 | E67: 12000 | F67: 12000 | G67: 12000 | H67: 12000 | I67: 12000 | J67: 12000 | K67: 12000 | L67: 12000 | M67: 12000 | N67: 12000 | O67: 12000 | P67: 12000 | Q67: 12000 | R67: 12000 | S67: 12000 | T67: 12000 | U67: 12000 | V67: 12000 | W67: 12000 | X67: 12000 | Y67: 12000 | Z67: 12000 | AA67: 12000 | AB67: =SUM(D67:AA67)*C67 -> 1152000 | AC67: =+AB67+AB68+AB69 -> 8928000 | AF67: 46935 | AG67: =AC79 -> 5208000
B68: FESTIVO | C68: 5 | D68: 12000 | E68: 12000 | F68: 12000 | G68: 12000 | H68: 12000 | I68: 12000 | J68: 12000 | K68: 12000 | L68: 12000 | M68: 12000 | N68: 12000 | O68: 12000 | P68: 12000 | Q68: 12000 | R68: 12000 | S68: 12000 | T68: 12000 | U68: 12000 | V68: 12000 | W68: 12000 | X68: 12000 | Y68: 12000 | Z68: 12000 | AA68: 12000 | AB68: =SUM(D68:AA68)*C68 -> 1440000 | AF68: 46966 | AG68: =AC82 -> 5208000
B69: ORDINARIO | C69: 22 | D69: 12000 | E69: 12000 | F69: 12000 | G69: 12000 | H69: 12000 | I69: 12000 | J69: 12000 | K69: 12000 | L69: 12000 | M69: 12000 | N69: 12000 | O69: 12000 | P69: 12000 | Q69: 12000 | R69: 12000 | S69: 12000 | T69: 12000 | U69: 12000 | V69: 12000 | W69: 12000 | X69: 12000 | Y69: 12000 | Z69: 12000 | AA69: 12000 | AB69: =SUM(D69:AA69)*C69 -> 6336000 | AF69: 46997 | AG69: =AC85 -> 5040000
A70: 46844 | B70: SÁBADO | C70: 5 | D70: 12000 | E70: 12000 | F70: 12000 | G70: 12000 | H70: 12000 | I70: 12000 | J70: 12000 | K70: 12000 | L70: 12000 | M70: 12000 | N70: 12000 | O70: 12000 | P70: 12000 | Q70: 12000 | R70: 12000 | S70: 12000 | T70: 12000 | U70: 12000 | V70: 12000 | W70: 12000 | X70: 12000 | Y70: 12000 | Z70: 12000 | AA70: 12000 | AB70: =SUM(D70:AA70)*C70 -> 1440000 | AC70: =+AB70+AB71+AB72 -> 8640000 | AF70: 47027 | AG70: =AC88 -> 5208000
B71: FESTIVO | C71: 5 | D71: 12000 | E71: 12000 | F71: 12000 | G71: 12000 | H71: 12000 | I71: 12000 | J71: 12000 | K71: 12000 | L71: 12000 | M71: 12000 | N71: 12000 | O71: 12000 | P71: 12000 | Q71: 12000 | R71: 12000 | S71: 12000 | T71: 12000 | U71: 12000 | V71: 12000 | W71: 12000 | X71: 12000 | Y71: 12000 | Z71: 12000 | AA71: 12000 | AB71: =SUM(D71:AA71)*C71 -> 1440000 | AF71: 47058 | AG71: =AC91 -> 5040000
B72: ORDINARIO | C72: 20 | D72: 12000 | E72: 12000 | F72: 12000 | G72: 12000 | H72: 12000 | I72: 12000 | J72: 12000 | K72: 12000 | L72: 12000 | M72: 12000 | N72: 12000 | O72: 12000 | P72: 12000 | Q72: 12000 | R72: 12000 | S72: 12000 | T72: 12000 | U72: 12000 | V72: 12000 | W72: 12000 | X72: 12000 | Y72: 12000 | Z72: 12000 | AA72: 12000 | AB72: =SUM(D72:AA72)*C72 -> 5760000 | AF72: 47088 | AG72: =AC94 -> 8928000
A73: 46874 | B73: SÁBADO | C73: 4 | D73: 7000 | E73: 7000 | F73: 7000 | G73: 7000 | H73: 7000 | I73: 7000 | J73: 7000 | K73: 7000 | L73: 7000 | M73: 7000 | N73: 7000 | O73: 7000 | P73: 7000 | Q73: 7000 | R73: 7000 | S73: 7000 | T73: 7000 | U73: 7000 | V73: 7000 | W73: 7000 | X73: 7000 | Y73: 7000 | Z73: 7000 | AA73: 7000 | AB73: =SUM(D73:AA73)*C73 -> 672000 | AC73: =+AB73+AB74+AB75 -> 5208000
B74: FESTIVO | C74: 4 | D74: 7000 | E74: 7000 | F74: 7000 | G74: 7000 | H74: 7000 | I74: 7000 | J74: 7000 | K74: 7000 | L74: 7000 | M74: 7000 | N74: 7000 | O74: 7000 | P74: 7000 | Q74: 7000 | R74: 7000 | S74: 7000 | T74: 7000 | U74: 7000 | V74: 7000 | W74: 7000 | X74: 7000 | Y74: 7000 | Z74: 7000 | AA74: 7000 | AB74: =SUM(D74:AA74)*C74 -> 672000
B75: ORDINARIO | C75: 23 | D75: 7000 | E75: 7000 | F75: 7000 | G75: 7000 | H75: 7000 | I75: 7000 | J75: 7000 | K75: 7000 | L75: 7000 | M75: 7000 | N75: 7000 | O75: 7000 | P75: 7000 | Q75: 7000 | R75: 7000 | S75: 7000 | T75: 7000 | U75: 7000 | V75: 7000 | W75: 7000 | X75: 7000 | Y75: 7000 | Z75: 7000 | AA75: 7000 | AB75: =SUM(D75:AA75)*C75 -> 3864000
A76: 46905 | B76: SÁBADO | C76: 4 | D76: 7000 | E76: 7000 | F76: 7000 | G76: 7000 | H76: 7000 | I76: 7000 | J76: 7000 | K76: 7000 | L76: 7000 | M76: 7000 | N76: 7000 | O76: 7000 | P76: 7000 | Q76: 7000 | R76: 7000 | S76: 7000 | T76: 7000 | U76: 7000 | V76: 7000 | W76: 7000 | X76: 7000 | Y76: 7000 | Z76: 7000 | AA76: 7000 | AB76: =SUM(D76:AA76)*C76 -> 672000 | AC76: =+AB76+AB77+AB78 -> 5040000
B77: FESTIVO | C77: 4 | D77: 7000 | E77: 7000 | F77: 7000 | G77: 7000 | H77: 7000 | I77: 7000 | J77: 7000 | K77: 7000 | L77: 7000 | M77: 7000 | N77: 7000 | O77: 7000 | P77: 7000 | Q77: 7000 | R77: 7000 | S77: 7000 | T77: 7000 | U77: 7000 | V77: 7000 | W77: 7000 | X77: 7000 | Y77: 7000 | Z77: 7000 | AA77: 7000 | AB77: =SUM(D77:AA77)*C77 -> 672000
B78: ORDINARIO | C78: 22 | D78: 7000 | E78: 7000 | F78: 7000 | G78: 7000 | H78: 7000 | I78: 7000 | J78: 7000 | K78: 7000 | L78: 7000 | M78: 7000 | N78: 7000 | O78: 7000 | P78: 7000 | Q78: 7000 | R78: 7000 | S78: 7000 | T78: 7000 | U78: 7000 | V78: 7000 | W78: 7000 | X78: 7000 | Y78: 7000 | Z78: 7000 | AA78: 7000 | AB78: =SUM(D78:AA78)*C78 -> 3696000
A79: 46935 | B79: SÁBADO | C79: 5 | D79: 7000 | E79: 7000 | F79: 7000 | G79: 7000 | H79: 7000 | I79: 7000 | J79: 7000 | K79: 7000 | L79: 7000 | M79: 7000 | N79: 7000 | O79: 7000 | P79: 7000 | Q79: 7000 | R79: 7000 | S79: 7000 | T79: 7000 | U79: 7000 | V79: 7000 | W79: 7000 | X79: 7000 | Y79: 7000 | Z79: 7000 | AA79: 7000 | AB79: =SUM(D79:AA79)*C79 -> 840000 | AC79: =+AB79+AB80+AB81 -> 5208000
B80: FESTIVO | C80: 5 | D80: 7000 | E80: 7000 | F80: 7000 | G80: 7000 | H80: 7000 | I80: 7000 | J80: 7000 | K80: 7000 | L80: 7000 | M80: 7000 | N80: 7000 | O80: 7000 | P80: 7000 | Q80: 7000 | R80: 7000 | S80: 7000 | T80: 7000 | U80: 7000 | V80: 7000 | W80: 7000 | X80: 7000 | Y80: 7000 | Z80: 7000 | AA80: 7000 | AB80: =SUM(D80:AA80)*C80 -> 840000
B81: ORDINARIO | C81: 21 | D81: 7000 | E81: 7000 | F81: 7000 | G81: 7000 | H81: 7000 | I81: 7000 | J81: 7000 | K81: 7000 | L81: 7000 | M81: 7000 | N81: 7000 | O81: 7000 | P81: 7000 | Q81: 7000 | R81: 7000 | S81: 7000 | T81: 7000 | U81: 7000 | V81: 7000 | W81: 7000 | X81: 7000 | Y81: 7000 | Z81: 7000 | AA81: 7000 | AB81: =SUM(D81:AA81)*C81 -> 3528000
A82: 46966 | B82: SÁBADO | C82: 4 | D82: 7000 | E82: 7000 | F82: 7000 | G82: 7000 | H82: 7000 | I82: 7000 | J82: 7000 | K82: 7000 | L82: 7000 | M82: 7000 | N82: 7000 | O82: 7000 | P82: 7000 | Q82: 7000 | R82: 7000 | S82: 7000 | T82: 7000 | U82: 7000 | V82: 7000 | W82: 7000 | X82: 7000 | Y82: 7000 | Z82: 7000 | AA82: 7000 | AB82: =SUM(D82:AA82)*C82 -> 672000 | AC82: =+AB82+AB83+AB84 -> 5208000
B83: FESTIVO | C83: 4 | D83: 7000 | E83: 7000 | F83: 7000 | G83: 7000 | H83: 7000 | I83: 7000 | J83: 7000 | K83: 7000 | L83: 7000 | M83: 7000 | N83: 7000 | O83: 7000 | P83: 7000 | Q83: 7000 | R83: 7000 | S83: 7000 | T83: 7000 | U83: 7000 | V83: 7000 | W83: 7000 | X83: 7000 | Y83: 7000 | Z83: 7000 | AA83: 7000 | AB83: =SUM(D83:AA83)*C83 -> 672000
B84: ORDINARIO | C84: 23 | D84: 7000 | E84: 7000 | F84: 7000 | G84: 7000 | H84: 7000 | I84: 7000 | J84: 7000 | K84: 7000 | L84: 7000 | M84: 7000 | N84: 7000 | O84: 7000 | P84: 7000 | Q84: 7000 | R84: 7000 | S84: 7000 | T84: 7000 | U84: 7000 | V84: 7000 | W84: 7000 | X84: 7000 | Y84: 7000 | Z84: 7000 | AA84: 7000 | AB84: =SUM(D84:AA84)*C84 -> 3864000
A85: 46997 | B85: SÁBADO | C85: 5 | D85: 7000 | E85: 7000 | F85: 7000 | G85: 7000 | H85: 7000 | I85: 7000 | J85: 7000 | K85: 7000 | L85: 7000 | M85: 7000 | N85: 7000 | O85: 7000 | P85: 7000 | Q85: 7000 | R85: 7000 | S85: 7000 | T85: 7000 | U85: 7000 | V85: 7000 | W85: 7000 | X85: 7000 | Y85: 7000 | Z85: 7000 | AA85: 7000 | AB85: =SUM(D85:AA85)*C85 -> 840000 | AC85: =+AB85+AB86+AB87 -> 5040000
B86: FESTIVO | C86: 4 | D86: 7000 | E86: 7000 | F86: 7000 | G86: 7000 | H86: 7000 | I86: 7000 | J86: 7000 | K86: 7000 | L86: 7000 | M86: 7000 | N86: 7000 | O86: 7000 | P86: 7000 | Q86: 7000 | R86: 7000 | S86: 7000 | T86: 7000 | U86: 7000 | V86: 7000 | W86: 7000 | X86: 7000 | Y86: 7000 | Z86: 7000 | AA86: 7000 | AB86: =SUM(D86:AA86)*C86 -> 672000
B87: ORDINARIO | C87: 21 | D87: 7000 | E87: 7000 | F87: 7000 | G87: 7000 | H87: 7000 | I87: 7000 | J87: 7000 | K87: 7000 | L87: 7000 | M87: 7000 | N87: 7000 | O87: 7000 | P87: 7000 | Q87: 7000 | R87: 7000 | S87: 7000 | T87: 7000 | U87: 7000 | V87: 7000 | W87: 7000 | X87: 7000 | Y87: 7000 | Z87: 7000 | AA87: 7000 | AB87: =SUM(D87:AA87)*C87 -> 3528000
A88: 47027 | B88: SÁBADO | C88: 4 | D88: 7000 | E88: 7000 | F88: 7000 | G88: 7000 | H88: 7000 | I88: 7000 | J88: 7000 | K88: 7000 | L88: 7000 | M88: 7000 | N88: 7000 | O88: 7000 | P88: 7000 | Q88: 7000 | R88: 7000 | S88: 7000 | T88: 7000 | U88: 7000 | V88: 7000 | W88: 7000 | X88: 7000 | Y88: 7000 | Z88: 7000 | AA88: 7000 | AB88: =SUM(D88:AA88)*C88 -> 672000 | AC88: =+AB88+AB89+AB90 -> 5208000
B89: FESTIVO | C89: 5 | D89: 7000 | E89: 7000 | F89: 7000 | G89: 7000 | H89: 7000 | I89: 7000 | J89: 7000 | K89: 7000 | L89: 7000 | M89: 7000 | N89: 7000 | O89: 7000 | P89: 7000 | Q89: 7000 | R89: 7000 | S89: 7000 | T89: 7000 | U89: 7000 | V89: 7000 | W89: 7000 | X89: 7000 | Y89: 7000 | Z89: 7000 | AA89: 7000 | AB89: =SUM(D89:AA89)*C89 -> 840000
B90: ORDINARIO | C90: 22 | D90: 7000 | E90: 7000 | F90: 7000 | G90: 7000 | H90: 7000 | I90: 7000 | J90: 7000 | K90: 7000 | L90: 7000 | M90: 7000 | N90: 7000 | O90: 7000 | P90: 7000 | Q90: 7000 | R90: 7000 | S90: 7000 | T90: 7000 | U90: 7000 | V90: 7000 | W90: 7000 | X90: 7000 | Y90: 7000 | Z90: 7000 | AA90: 7000 | AB90: =SUM(D90:AA90)*C90 -> 3696000
A91: 47058 | B91: SÁBADO | C91: 4 | D91: 7000 | E91: 7000 | F91: 7000 | G91: 7000 | H91: 7000 | I91: 7000 | J91: 7000 | K91: 7000 | L91: 7000 | M91: 7000 | N91: 7000 | O91: 7000 | P91: 7000 | Q91: 7000 | R91: 7000 | S91: 7000 | T91: 7000 | U91: 7000 | V91: 7000 | W91: 7000 | X91: 7000 | Y91: 7000 | Z91: 7000 | AA91: 7000 | AB91: =SUM(D91:AA91)*C91 -> 672000 | AC91: =+AB91+AB92+AB93 -> 5040000
B92: FESTIVO | C92: 4 | D92: 7000 | E92: 7000 | F92: 7000 | G92: 7000 | H92: 7000 | I92: 7000 | J92: 7000 | K92: 7000 | L92: 7000 | M92: 7000 | N92: 7000 | O92: 7000 | P92: 7000 | Q92: 7000 | R92: 7000 | S92: 7000 | T92: 7000 | U92: 7000 | V92: 7000 | W92: 7000 | X92: 7000 | Y92: 7000 | Z92: 7000 | AA92: 7000 | AB92: =SUM(D92:AA92)*C92 -> 672000
B93: ORDINARIO | C93: 22 | D93: 7000 | E93: 7000 | F93: 7000 | G93: 7000 | H93: 7000 | I93: 7000 | J93: 7000 | K93: 7000 | L93: 7000 | M93: 7000 | N93: 7000 | O93: 7000 | P93: 7000 | Q93: 7000 | R93: 7000 | S93: 7000 | T93: 7000 | U93: 7000 | V93: 7000 | W93: 7000 | X93: 7000 | Y93: 7000 | Z93: 7000 | AA93: 7000 | AB93: =SUM(D93:AA93)*C93 -> 3696000
A94: 47088 | B94: SÁBADO | C94: 5 | D94: 12000 | E94: 12000 | F94: 12000 | G94: 12000 | H94: 12000 | I94: 12000 | J94: 12000 | K94: 12000 | L94: 12000 | M94: 12000 | N94: 12000 | O94: 12000 | P94: 12000 | Q94: 12000 | R94: 12000 | S94: 12000 | T94: 12000 | U94: 12000 | V94: 12000 | W94: 12000 | X94: 12000 | Y94: 12000 | Z94: 12000 | AA94: 12000 | AB94: =SUM(D94:AA94)*C94 -> 1440000 | AC94: =+AB94+AB95+AB96 -> 8928000
B95: FESTIVO | C95: 5 | D95: 12000 | E95: 12000 | F95: 12000 | G95: 12000 | H95: 12000 | I95: 12000 | J95: 12000 | K95: 12000 | L95: 12000 | M95: 12000 | N95: 12000 | O95: 12000 | P95: 12000 | Q95: 12000 | R95: 12000 | S95: 12000 | T95: 12000 | U95: 12000 | V95: 12000 | W95: 12000 | X95: 12000 | Y95: 12000 | Z95: 12000 | AA95: 12000 | AB95: =SUM(D95:AA95)*C95 -> 1440000
B96: ORDINARIO | C96: 21 | D96: 12000 | E96: 12000 | F96: 12000 | G96: 12000 | H96: 12000 | I96: 12000 | J96: 12000 | K96: 12000 | L96: 12000 | M96: 12000 | N96: 12000 | O96: 12000 | P96: 12000 | Q96: 12000 | R96: 12000 | S96: 12000 | T96: 12000 | U96: 12000 | V96: 12000 | W96: 12000 | X96: 12000 | Y96: 12000 | Z96: 12000 | AA96: 12000 | AB96: =SUM(D96:AA96)*C96 -> 6048000
A99: Mes | B99: Tipo de día | C99: No. de Días | D99: HORA 01 | E99: HORA 02 | F99: HORA 03 | G99: HORA 04 | H99: HORA 05 | I99: HORA 06 | J99: HORA 07 | K99: HORA 08 | L99: HORA 09 | M99: HORA 10 | N99: HORA 11 | O99: HORA 12 | P99: HORA 13 | Q99: HORA 14 | R99: HORA 15 | S99: HORA 16 | T99: HORA 17 | U99: HORA 18 | V99: HORA 19 | W99: HORA 20 | X99: HORA 21 | Y99: HORA 22 | Z99: HORA 23 | AA99: HORA 24 | AB99: Total
A100: 47119 | B100: SÁBADO | C100: 4 | D100: 15000 | E100: 15000 | F100: 15000 | G100: 15000 | H100: 15000 | I100: 15000 | J100: 15000 | K100: 15000 | L100: 15000 | M100: 15000 | N100: 15000 | O100: 15000 | P100: 15000 | Q100: 15000 | R100: 15000 | S100: 15000 | T100: 15000 | U100: 15000 | V100: 15000 | W100: 15000 | X100: 15000 | Y100: 15000 | Z100: 15000 | AA100: 15000 | AB100: =SUM(D100:AA100)*C100 -> 1440000 | AC100: =+AB100+AB101+AB102 -> 11160000 | AF100: 47119 | AG100: =AC100 -> 11160000
B101: FESTIVO | C101: 6 | D101: 15000 | E101: 15000 | F101: 15000 | G101: 15000 | H101: 15000 | I101: 15000 | J101: 15000 | K101: 15000 | L101: 15000 | M101: 15000 | N101: 15000 | O101: 15000 | P101: 15000 | Q101: 15000 | R101: 15000 | S101: 15000 | T101: 15000 | U101: 15000 | V101: 15000 | W101: 15000 | X101: 15000 | Y101: 15000 | Z101: 15000 | AA101: 15000 | AB101: =SUM(D101:AA101)*C101 -> 2160000 | AF101: 47150 | AG101: =AC103 -> 10080000
B102: ORDINARIO | C102: 21 | D102: 15000 | E102: 15000 | F102: 15000 | G102: 15000 | H102: 15000 | I102: 15000 | J102: 15000 | K102: 15000 | L102: 15000 | M102: 15000 | N102: 15000 | O102: 15000 | P102: 15000 | Q102: 15000 | R102: 15000 | S102: 15000 | T102: 15000 | U102: 15000 | V102: 15000 | W102: 15000 | X102: 15000 | Y102: 15000 | Z102: 15000 | AA102: 15000 | AB102: =SUM(D102:AA102)*C102 -> 7560000 | AF102: 47178 | AG102: =AC106 -> 11160000
A103: 47150 | B103: SÁBADO | C103: 4 | D103: 15000 | E103: 15000 | F103: 15000 | G103: 15000 | H103: 15000 | I103: 15000 | J103: 15000 | K103: 15000 | L103: 15000 | M103: 15000 | N103: 15000 | O103: 15000 | P103: 15000 | Q103: 15000 | R103: 15000 | S103: 15000 | T103: 15000 | U103: 15000 | V103: 15000 | W103: 15000 | X103: 15000 | Y103: 15000 | Z103: 15000 | AA103: 15000 | AB103: =SUM(D103:AA103)*C103 -> 1440000 | AC103: =+AB103+AB104+AB105 -> 10080000 | AF103: 47209 | AG103: =AC109 -> 10800000
B104: FESTIVO | C104: 4 | D104: 15000 | E104: 15000 | F104: 15000 | G104: 15000 | H104: 15000 | I104: 15000 | J104: 15000 | K104: 15000 | L104: 15000 | M104: 15000 | N104: 15000 | O104: 15000 | P104: 15000 | Q104: 15000 | R104: 15000 | S104: 15000 | T104: 15000 | U104: 15000 | V104: 15000 | W104: 15000 | X104: 15000 | Y104: 15000 | Z104: 15000 | AA104: 15000 | AB104: =SUM(D104:AA104)*C104 -> 1440000 | AF104: 47239 | AG104: =AC112 -> 11160000
B105: ORDINARIO | C105: 20 | D105: 15000 | E105: 15000 | F105: 15000 | G105: 15000 | H105: 15000 | I105: 15000 | J105: 15000 | K105: 15000 | L105: 15000 | M105: 15000 | N105: 15000 | O105: 15000 | P105: 15000 | Q105: 15000 | R105: 15000 | S105: 15000 | T105: 15000 | U105: 15000 | V105: 15000 | W105: 15000 | X105: 15000 | Y105: 15000 | Z105: 15000 | AA105: 15000 | AB105: =SUM(D105:AA105)*C105 -> 7200000 | AF105: 47270 | AG105: =AC115 -> 10800000
A106: 47178 | B106: SÁBADO | C106: 5 | D106: 15000 | E106: 15000 | F106: 15000 | G106: 15000 | H106: 15000 | I106: 15000 | J106: 15000 | K106: 15000 | L106: 15000 | M106: 15000 | N106: 15000 | O106: 15000 | P106: 15000 | Q106: 15000 | R106: 15000 | S106: 15000 | T106: 15000 | U106: 15000 | V106: 15000 | W106: 15000 | X106: 15000 | Y106: 15000 | Z106: 15000 | AA106: 15000 | AB106: =SUM(D106:AA106)*C106 -> 1800000 | AC106: =+AB106+AB107+AB108 -> 11160000 | AF106: 47300 | AG106: =AC118 -> 11160000
B107: FESTIVO | C107: 7 | D107: 15000 | E107: 15000 | F107: 15000 | G107: 15000 | H107: 15000 | I107: 15000 | J107: 15000 | K107: 15000 | L107: 15000 | M107: 15000 | N107: 15000 | O107: 15000 | P107: 15000 | Q107: 15000 | R107: 15000 | S107: 15000 | T107: 15000 | U107: 15000 | V107: 15000 | W107: 15000 | X107: 15000 | Y107: 15000 | Z107: 15000 | AA107: 15000 | AB107: =SUM(D107:AA107)*C107 -> 2520000 | AF107: 47331 | AG107: =AC121 -> 11160000
...

Sheet Formato -Producto N° 2  Curva
A5: Formato No. 1. Oferta Producto No. 2 Curva Convocatoria Pública DISPAC S.A. E.S.P.
A8: PROPONENTE
A10: MES | B10: DEMANDA REQUERIDA DISPAC KWh | C10: DEMANDA PERIODO REQUERIDA DISPAC KWh | D10: PORCENTAJE (%) OFERTADO DE LA DEMANDA REQUERIDA | E10: DEMANDA OFERTADA KWh - MES | F10: DEMANDA PERIODO OFERTADA KWh | G10: PRECIO OFERTADO $ kWh (0.00)
A11: 46235 | B11: 7024968.8 | C11: =SUM(B11:B15) -> 22523730 | D11: 0
A12: 46266 | B12: 2275335.9 | D12: 0
A13: 46296 | B13: 2149277.1 | D13: 0
A14: 46327 | B14: 2095521.4 | D14: 0
A15: 46357 | B15: 8978626.9 | D15: 0
A16: 46388 | B16: ='Cantidades -Producto 2'!AG22 -> 7839429.9 | C16: =SUM(B16:B27) -> 75224915 | D16: 0
A17: 46419 | B17: ='Cantidades -Producto 2'!AG23 -> 6751684.7 | D17: 0
A18: 46447 | B18: ='Cantidades -Producto 2'!AG24 -> 8300034.2 | D18: 0
A19: 46478 | B19: ='Cantidades -Producto 2'!AG25 -> 7930619.7 | D19: 0
A20: 46508 | B20: ='Cantidades -Producto 2'!AG26 -> 7510979.5 | D20: 0
A21: 46539 | B21: ='Cantidades -Producto 2'!AG27 -> 7268434 | D21: 0
A22: 46569 | B22: ='Cantidades -Producto 2'!AG28 -> 7399601.8 | D22: 0
A23: 46600 | B23: ='Cantidades -Producto 2'!AG29 -> 7183515.3 | D23: 0
A24: 46631 | B24: ='Cantidades -Producto 2'!AG30 -> 2065944.3 | D24: 0
A25: 46661 | B25: ='Cantidades -Producto 2'!AG31 -> 1878101 | D25: 0
A26: 46692 | B26: ='Cantidades -Producto 2'!AG32 -> 1922771.6 | D26: 0
A27: 46722 | B27: ='Cantidades -Producto 2'!AG33 -> 9173799.3 | D27: 0
A28: 46753 | B28: ='Cantidades -Producto 2'!AG61 -> 6921496.2 | C28: =SUM(B28:B39) -> 76156871 | D28: 0
A29: 46784 | B29: ='Cantidades -Producto 2'!AG62 -> 5803036.3 | D29: 0
A30: 46813 | B30: ='Cantidades -Producto 2'!AG63 -> 7335720.2 | D30: 0
A31: 46844 | B31: ='Cantidades -Producto 2'!AG64 -> 6914373.1 | D31: 0
A32: 46874 | B32: ='Cantidades -Producto 2'!AG65 -> 4526703.4 | D32: 0
A33: 46905 | B33: ='Cantidades -Producto 2'!AG66 -> 4322879.6 | D33: 0
A34: 46935 | B34: ='Cantidades -Producto 2'!AG67 -> 4291029.3 | D34: 0
A35: 46966 | B35: ='Cantidades -Producto 2'!AG68 -> 6546836.8 | D35: 0
A36: 46997 | B36: ='Cantidades -Producto 2'!AG69 -> 6870287.5 | D36: 0
A37: 47027 | B37: ='Cantidades -Producto 2'!AG70 -> 7266240.7 | D37: 0
A38: 47058 | B38: ='Cantidades -Producto 2'!AG71 -> 7127709.9 | D38: 0
A39: 47088 | B39: ='Cantidades -Producto 2'!AG72 -> 8230558 | D39: 0
A40: 47119 | B40: ='Cantidades -Producto 2'!AG100 -> 6809640.7 | C40: =SUM(B40:B51) -> 86260492 | D40: 0
A41: 47150 | B41: ='Cantidades -Producto 2'!AG101 -> 5723692.4 | D41: 0
A42: 47178 | B42: ='Cantidades -Producto 2'!AG102 -> 7092058.5 | D42: 0
A43: 47209 | B43: ='Cantidades -Producto 2'!AG103 -> 6778314 | D43: 0
A44: 47239 | B44: ='Cantidades -Producto 2'!AG104 -> 7580413.9 | D44: 0
A45: 47270 | B45: ='Cantidades -Producto 2'!AG105 -> 7278300.6 | D45: 0
A46: 47300 | B46: ='Cantidades -Producto 2'!AG106 -> 7391065.4 | D46: 0
A47: 47331 | B47: ='Cantidades -Producto 2'!AG107 -> 7218033.1 | D47: 0
A48: 47362 | B48: ='Cantidades -Producto 2'!AG108 -> 7435131.7 | D48: 0
A49: 47392 | B49: ='Cantidades -Producto 2'!AG109 -> 7534835.6 | D49: 0
A50: 47423 | B50: ='Cantidades -Producto 2'!AG110 -> 7339145.1 | D50: 0
A51: 47453 | B51: ='Cantidades -Producto 2'!AG111 -> 8079860.8 | D51: 0
A52: 47484 | B52: ='Cantidades -Producto 2'!AG139 -> 7387035.9 | C52: =SUM(B52:B63) -> 93113391 | D52: 0
A53: 47515 | B53: ='Cantidades -Producto 2'!AG140 -> 6235177.3 | D53: 0
A54: 47543 | B54: ='Cantidades -Producto 2'!AG141 -> 7714097.2 | D54: 0
A55: 47574 | B55: ='Cantidades -Producto 2'!AG142 -> 7255521.6 | D55: 0
A56: 47604 | B56: ='Cantidades -Producto 2'!AG143 -> 8123518.5 | D56: 0
A57: 47635 | B57: ='Cantidades -Producto 2'!AG144 -> 7823756 | D57: 0
A58: 47665 | B58: ='Cantidades -Producto 2'!AG145 -> 8030676.3 | D58: 0
A59: 47696 | B59: ='Cantidades -Producto 2'!AG146 -> 7788436.7 | D59: 0
A60: 47727 | B60: ='Cantidades -Producto 2'!AG147 -> 8020389.7 | D60: 0
A61: 47757 | B61: ='Cantidades -Producto 2'!AG148 -> 8129272.9 | D61: 0
A62: 47788 | B62: ='Cantidades -Producto 2'!AG149 -> 7906906.1 | D62: 0
A63: 47818 | B63: ='Cantidades -Producto 2'!AG150 -> 8698603.3 | D63: 0
A64: 47849 | B64: ='Cantidades -Producto 2'!AG178 -> 7977999.8 | C64: =SUM(B64:B75) -> 1.00156e+08 | D64: 0
A65: 47880 | B65: ='Cantidades -Producto 2'!AG179 -> 6758682.1 | D65: 0
A66: 47908 | B66: ='Cantidades -Producto 2'!AG180 -> 8312747.1 | D66: 0
A67: 47939 | B67: ='Cantidades -Producto 2'!AG181 -> 7829931.5 | D67: 0
A68: 47969 | B68: ='Cantidades -Producto 2'!AG182 -> 8673993.6 | D68: 0
A69: 48000 | B69: ='Cantidades -Producto 2'!AG183 -> 8415628.9 | D69: 0
A70: 48030 | B70: ='Cantidades -Producto 2'!AG184 -> 8636765.9 | D70: 0
A71: 48061 | B71: ='Cantidades -Producto 2'!AG185 -> 8351302.3 | D71: 0
A72: 48092 | B72: ='Cantidades -Producto 2'!AG186 -> 8662552.9 | D72: 0
A73: 48122 | B73: ='Cantidades -Producto 2'!AG187 -> 8737679.5 | D73: 0
A74: 48153 | B74: ='Cantidades -Producto 2'!AG188 -> 8451777 | D74: 0
A75: 48183 | B75: ='Cantidades -Producto 2'!AG189 -> 9346943.5 | D75: 0
A76: 48214 | B76: ='Cantidades -Producto 2'!AG217 -> 5598870.6 | C76: =SUM(B76:B87) -> 72190554 | D76: 0
A77: 48245 | B77: ='Cantidades -Producto 2'!AG218 -> 4239587.1 | D77: 0
A78: 48274 | B78: ='Cantidades -Producto 2'!AG219 -> 5922130.1 | D78: 0
A79: 48305 | B79: ='Cantidades -Producto 2'!AG220 -> 5732490 | D79: 0
A80: 48335 | B80: ='Cantidades -Producto 2'!AG221 -> 6228647.8 | D80: 0
A81: 48366 | B81: ='Cantidades -Producto 2'!AG222 -> 6182689.7 | D81: 0
A82: 48396 | B82: ='Cantidades -Producto 2'!AG223 -> 6263982 | D82: 0
A83: 48427 | B83: ='Cantidades -Producto 2'!AG224 -> 6021283.5 | D83: 0
A84: 48458 | B84: ='Cantidades -Producto 2'!AG225 -> 6404524.2 | D84: 0
A85: 48488 | B85: ='Cantidades -Producto 2'!AG226 -> 6329685.5 | D85: 0
A86: 48519 | B86: ='Cantidades -Producto 2'!AG227 -> 6243719.2 | D86: 0
A87: 48549 | B87: ='Cantidades -Producto 2'!AG228 -> 7022944.7 | D87: 0
A88: 48580 | B88: ='Cantidades -Producto 2'!AG256 -> 11358036 | C88: =SUM(B88:B99) -> 1.2370656e+08 | D88: 0
A89: 48611 | B89: ='Cantidades -Producto 2'!AG257 -> 8396889 | D89: 0
A90: 48639 | B90: ='Cantidades -Producto 2'!AG258 -> 10204131 | D90: 0
A91: 48670 | B91: ='Cantidades -Producto 2'!AG259 -> 9705330.7 | D91: 0
A92: 48700 | B92: ='Cantidades -Producto 2'!AG260 -> 10548724 | D92: 0
A93: 48731 | B93: ='Cantidades -Producto 2'!AG261 -> 10226686 | D93: 0
A94: 48761 | B94: ='Cantidades -Producto 2'!AG262 -> 10420461 | D94: 0
A95: 48792 | B95: ='Cantidades -Producto 2'!AG263 -> 10263431 | D95: 0
A96: 48823 | B96: ='Cantidades -Producto 2'!AG264 -> 10485351 | D96: 0
A97: 48853 | B97: ='Cantidades -Producto 2'!AG265 -> 10539765 | D97: 0
A98: 48884 | B98: ='Cantidades -Producto 2'!AG266 -> 10320767 | D98: 0
A99: 48914 | B99: ='Cantidades -Producto 2'!AG267 -> 11236989 | D99: 0
A100: 48945 | B100: ='Cantidades -Producto 2'!AG295 -> 14643909 | C100: =SUM(B100:B111) -> 1.7855005e+08 | D100: 0
A101: 48976 | B101: ='Cantidades -Producto 2'!AG296 -> 12752508 | D101: 0
A102: 49004 | B102: ='Cantidades -Producto 2'!AG297 -> 15037519 | D102: 0
A103: 49035 | B103: ='Cantidades -Producto 2'!AG298 -> 14249122 | D103: 0
A104: 49065 | B104: ='Cantidades -Producto 2'!AG299 -> 15386325 | D104: 0
A105: 49096 | B105: ='Cantidades -Producto 2'!AG300 -> 14908458 | D105: 0
A106: 49126 | B106: ='Cantidades -Producto 2'!AG301 -> 15151108 | D106: 0
A107: 49157 | B107: ='Cantidades -Producto 2'!AG302 -> 15017951 | D107: 0
...

Sheet Cantidades -Producto 2
A2: PRODUCTO 2
A3: Mes | B3: Tipo de día | C3: No. de Días | D3: HORA 01 | E3: HORA 02 | F3: HORA 03 | G3: HORA 04 | H3: HORA 05 | I3: HORA 06 | J3: HORA 07 | K3: HORA 08 | L3: HORA 09 | M3: HORA 10 | N3: HORA 11 | O3: HORA 12 | P3: HORA 13 | Q3: HORA 14 | R3: HORA 15 | S3: HORA 16 | T3: HORA 17 | U3: HORA 18 | V3: HORA 19 | W3: HORA 20 | X3: HORA 21 | Y3: HORA 22 | Z3: HORA 23 | AA3: HORA 24 | AB3: Total
A4: 46235 | B4: SÁBADO | C4: 5 | D4: 6655.8915 | E4: 5098.4853 | F4: 4540.3207 | G4: 4119.1307 | H4: 4032.7905 | I4: 4176.3429 | J4: 4834.8828 | K4: 6323.5222 | L4: 8568.8617 | M4: 9560.2106 | N4: 11205.755 | O4: 12404.361 | P4: 12792.348 | Q4: 12646.441 | R4: 12212.81 | S4: 12047.187 | T4: 11734.815 | U4: 11247.929 | V4: 12789.276 | W4: 13483.546 | X4: 12833.886 | Y4: 11280.739 | Z4: 9254.1347 | AA4: 7766.5713 | AB4: =SUM(D4:AA4)*C4 -> 1108051.2 | AC4: =+AB4+AB5+AB6 -> 7024968.8
B5: FESTIVO | C5: 5 | D5: 6571.5688 | E5: 5859.9659 | F5: 5166.8701 | G5: 4610.2769 | H5: 4246.3436 | I5: 4327.8315 | J5: 4731.191 | K5: 6251.709 | L5: 8128.0515 | M5: 9363.0921 | N5: 10087.772 | O5: 11154.556 | P5: 11804.192 | Q5: 11731.971 | R5: 11079.07 | S5: 10660.833 | T5: 10373.152 | U5: 10122.717 | V5: 11069.617 | W5: 12617.149 | X5: 12122.304 | Y5: 10700.708 | Z5: 8925.8007 | AA5: 7346.7666 | AB5: =SUM(D5:AA5)*C5 -> 1045267.5 | AF5: MES | AG5: DEMANDA REQUERIDA DISPAC KWh
B6: ORDINARIO | C6: 21 | D6: 6612.0713 | E6: 5856.6634 | F6: 5341.0986 | G6: 4990.0866 | H6: 4882.5114 | I6: 5649.3782 | J6: 6703.4592 | K6: 7987.4049 | L6: 9724.1351 | M6: 10969.14 | N6: 11638.729 | O6: 11758.439 | P6: 11102.089 | Q6: 11480.265 | R6: 11823.165 | S6: 11881.225 | T6: 12967.356 | U6: 12457.592 | V6: 12671.562 | W6: 13306.391 | X6: 12831.818 | Y6: 11633.734 | Z6: 9771.6858 | AA6: 7943.3366 | AB6: =SUM(D6:AA6)*C6 -> 4871650.1 | AF6: 46235 | AG6: =AC4 -> 7024968.8
A7: 46266 | B7: SÁBADO | C7: 4 | D7: 1995.8493 | E7: 1903.5485 | F7: 1741.9735 | G7: 1651.3014 | H7: 1639.5365 | I7: 1680.9493 | J7: 1869.2305 | K7: 2458.9738 | L7: 3114.5501 | M7: 3530.0926 | N7: 3839.9754 | O7: 4169.7478 | P7: 4287.6735 | Q7: 4248.0771 | R7: 4118.1641 | S7: 3936.186 | T7: 3782.265 | U7: 3720.8176 | V7: 4157.759 | W7: 4324.155 | X7: 4114.7351 | Y7: 3711.1627 | Z7: 3243.3569 | AA7: 2745.1674 | AB7: =SUM(D7:AA7)*C7 -> 303940.99 | AC7: =+AB7+AB8+AB9 -> 2275335.9 | AF7: 46266 | AG7: =AC7 -> 2275335.9
B8: FESTIVO | C8: 4 | D8: 2371.2536 | E8: 2108.3313 | F8: 1915.1711 | G8: 1799.8288 | H8: 1714.7492 | I8: 1704.7121 | J8: 1752.7084 | K8: 2145.1167 | L8: 2656.5851 | M8: 2936.8946 | N8: 3181.0164 | O8: 3537.0109 | P8: 3705.3896 | Q8: 3585.5179 | R8: 3315.3409 | S8: 3191.7289 | T8: 3079.619 | U8: 3124.2599 | V8: 3699.626 | W8: 3916.7319 | X8: 3778.0726 | Y8: 3449.1398 | Z8: 2907.9168 | AA8: 2432.5337 | AB8: =SUM(D8:AA8)*C8 -> 272037.02 | AF8: 46296 | AG8: =AC10 -> 2149277.1
B9: ORDINARIO | C9: 22 | D9: 2083.7031 | E9: 1890.607 | F9: 1745.6189 | G9: 1610.5085 | H9: 1638.7102 | I9: 1903.1409 | J9: 2252.1277 | K9: 2638.8079 | L9: 3201.8121 | M9: 3498.1403 | N9: 3738.7915 | O9: 4059.1052 | P9: 4114.131 | Q9: 4162.0085 | R9: 4267.7888 | S9: 4226.7811 | T9: 4155.8542 | U9: 4015.1461 | V9: 4333.8665 | W9: 4429.813 | X9: 4179.6027 | Y9: 3670.2184 | Z9: 2987.3946 | AA9: 2439.8599 | AB9: =SUM(D9:AA9)*C9 -> 1699357.8 | AF9: 46327 | AG9: =AC13 -> 2095521.4
A10: 46296 | B10: SÁBADO | C10: 5 | D10: 1876.9936 | E10: 1670.3156 | F10: 1537.4479 | G10: 1416.6354 | H10: 1358.9881 | I10: 1395.9471 | J10: 1504.3773 | K10: 2042.5884 | L10: 2702.1127 | M10: 3193.6563 | N10: 3542.9084 | O10: 3914.4735 | P10: 4007.5011 | Q10: 3902.312 | R10: 3786.6444 | S10: 3629.2463 | T10: 3495.9897 | U10: 3490.5993 | V10: 3821.006 | W10: 3859.779 | X10: 3720.1107 | Y10: 3384.8929 | Z10: 2917.6038 | AA10: 2453.0632 | AB10: =SUM(D10:AA10)*C10 -> 343125.96 | AC10: =+AB10+AB11+AB12 -> 2149277.1 | AF10: 46357 | AG10: =AC16 -> 8978626.9
B11: FESTIVO | C11: 4 | D11: 2009.6729 | E11: 1769.9382 | F11: 1592.5844 | G11: 1492.7507 | H11: 1445.435 | I11: 1460.3636 | J11: 1498.2843 | K11: 1894.599 | L11: 2347.6272 | M11: 2686.1667 | N11: 2867.6029 | O11: 3284.9312 | P11: 3507.1369 | Q11: 3443.2045 | R11: 3158.1157 | S11: 2817.24 | T11: 2869.3859 | U11: 3004.9894 | V11: 3538.8105 | W11: 3647.6333 | X11: 3377.8069 | Y11: 2956.0978 | Z11: 2439.9414 | AA11: 2014.7688 | AB11: =SUM(D11:AA11)*C11 -> 244500.35
B12: ORDINARIO | C12: 22 | D12: 1904.8269 | E12: 1700.0784 | F12: 1550.5538 | G12: 1396.7978 | H12: 1446.975 | I12: 1651.3989 | J12: 1935.9218 | K12: 2388.1025 | L12: 2886.7683 | M12: 3192.8532 | N12: 3388.8737 | O12: 3622.2765 | P12: 3812.8134 | Q12: 3816.2657 | R12: 3931.6314 | S12: 3976.8457 | T12: 3938.3377 | U12: 3755.3932 | V12: 4153.282 | W12: 4130.716 | X12: 3909.2975 | Y12: 3400.3405 | Z12: 2800.3742 | AA12: 2293.4023 | AB12: =SUM(D12:AA12)*C12 -> 1561650.8
A13: 46327 | B13: SÁBADO | C13: 4 | D13: 1815.6678 | E13: 1745.0633 | F13: 1568.1195 | G13: 1425.3553 | H13: 1423.366 | I13: 1481.9407 | J13: 1631.6561 | K13: 2164.0416 | L13: 2864.4358 | M13: 3290.4323 | N13: 3562.5532 | O13: 3841.3237 | P13: 3968.9502 | Q13: 3889.6187 | R13: 3769.4954 | S13: 3615.7998 | T13: 3477.7518 | U13: 3554.3074 | V13: 4002.8463 | W13: 4015.8501 | X13: 3827.4511 | Y13: 3432.2921 | Z13: 2961.9795 | AA13: 2490.4443 | AB13: =SUM(D13:AA13)*C13 -> 279282.97 | AC13: =+AB13+AB14+AB15 -> 2095521.4
B14: FESTIVO | C14: 5 | D14: 2066.5216 | E14: 1834.7903 | F14: 1697.1509 | G14: 1583.0877 | H14: 1539.2364 | I14: 1556.1221 | J14: 1646.6465 | K14: 2040.3889 | L14: 2559.6896 | M14: 2882.2177 | N14: 3064.7564 | O14: 3303.0161 | P14: 3432.4984 | Q14: 3332.8545 | R14: 3127.0937 | S14: 2973.6002 | T14: 2915.3065 | U14: 2969.188 | V14: 3577.523 | W14: 3725.6314 | X14: 3501.0205 | Y14: 3111.5363 | Z14: 2655.458 | AA14: 2241.5885 | AB14: =SUM(D14:AA14)*C14 -> 316684.62
B15: ORDINARIO | C15: 21 | D15: 1904.2589 | E15: 1696.9282 | F15: 1563.7304 | G15: 1476.0198 | H15: 1470.1933 | I15: 1667.2948 | J15: 1989.7803 | K15: 2464.6609 | L15: 2975.2143 | M15: 3250.569 | N15: 3521.9378 | O15: 3807.5629 | P15: 3898.7359 | Q15: 3865.5107 | R15: 3955.3398 | S15: 3856.137 | T15: 3720.9613 | U15: 3663.6588 | V15: 4094.7803 | W15: 4036.5066 | X15: 3884.0726 | Y15: 3462.9055 | Z15: 2853.7346 | AA15: 2326.8294 | AB15: =SUM(D15:AA15)*C15 -> 1499553.8
A16: 46357 | B16: SÁBADO | C16: 4 | D16: 8696.0576 | E16: 7748.4034 | F16: 7253.1108 | G16: 6926.1405 | H16: 6835.462 | I16: 7188.8053 | J16: 7646.0629 | K16: 9390.2012 | L16: 11738.856 | M16: 13040.321 | N16: 13919.369 | O16: 14798.957 | P16: 15094.698 | Q16: 15035.84 | R16: 14548.416 | S16: 14146.644 | T16: 13803.863 | U16: 13746.476 | V16: 15557.057 | W16: 15812.561 | X16: 15124.312 | Y16: 13953.932 | Z16: 12304.827 | AA16: 10815.897 | AB16: =SUM(D16:AA16)*C16 -> 1140505.1 | AC16: =+AB16+AB17+AB18 -> 8978626.9
B17: FESTIVO | C17: 4 | D17: 9628.4129 | E17: 8775.5904 | F17: 8180.0392 | G17: 7707.9188 | H17: 7499.8902 | I17: 7607.6222 | J17: 7635.3178 | K17: 8947.9855 | L17: 10602.419 | M17: 11991.614 | N17: 12683.249 | O17: 13703.438 | P17: 14212.662 | Q17: 14227.638 | R17: 13638.363 | S17: 13024.943 | T17: 12738.92 | U17: 12630.797 | V17: 14664.533 | W17: 15300.135 | X17: 14320.735 | Y17: 13014.263 | Z17: 12029.801 | AA17: 10591.872 | AB17: =SUM(D17:AA17)*C17 -> 1101432.6
B18: ORDINARIO | C18: 23 | D18: 9028.7515 | E18: 8140.113 | F18: 7576.1334 | G18: 7174.1144 | H18: 7077.4298 | I18: 7470.7272 | J18: 8256.9084 | K18: 10145.498 | L18: 12394.149 | M18: 13195.971 | N18: 13684.349 | O18: 14626.491 | P18: 14708.813 | Q18: 14806.114 | R18: 14816.162 | S18: 14849.092 | T18: 14562.906 | U18: 14380.941 | V18: 16349.38 | W18: 16540.68 | X18: 15773.257 | Y18: 14259.476 | Z18: 12420.26 | AA18: 10661.812 | AB18: =SUM(D18:AA18)*C18 -> 6736689.2
A21: Mes | B21: Tipo de día | C21: No. de Días | D21: HORA 01 | E21: HORA 02 | F21: HORA 03 | G21: HORA 04 | H21: HORA 05 | I21: HORA 06 | J21: HORA 07 | K21: HORA 08 | L21: HORA 09 | M21: HORA 10 | N21: HORA 11 | O21: HORA 12 | P21: HORA 13 | Q21: HORA 14 | R21: HORA 15 | S21: HORA 16 | T21: HORA 17 | U21: HORA 18 | V21: HORA 19 | W21: HORA 20 | X21: HORA 21 | Y21: HORA 22 | Z21: HORA 23 | AA21: HORA 24 | AB21: Total
A22: 46388 | B22: SÁBADO | C22: 5 | D22: 7310.7867 | E22: 6523.7313 | F22: 6036.1581 | G22: 5583.7552 | H22: 5525.8676 | I22: 5691.2791 | J22: 6023.8439 | K22: 7601.418 | L22: 9976.1894 | M22: 11424.443 | N22: 12274.86 | O22: 13501.914 | P22: 13867.56 | Q22: 13484.78 | R22: 12975.861 | S22: 13083.556 | T22: 12706.656 | U22: 12437.639 | V22: 13721.342 | W22: 14622.668 | X22: 14056.222 | Y22: 12747.661 | Z22: 10938.14 | AA22: 9231.6895 | AB22: =SUM(D22:AA22)*C22 -> 1256740.1 | AC22: =+AB22+AB23+AB24 -> 7839429.9 | AF22: 46388 | AG22: =AC22 -> 7839429.9
B23: FESTIVO | C23: 7 | D23: 7633.0562 | E23: 6872.0968 | F23: 6176.1075 | G23: 5802.8932 | H23: 5468.3145 | I23: 5435.2751 | J23: 5502.8447 | K23: 6508.1104 | L23: 8212.4685 | M23: 9371.6878 | N23: 9960.7627 | O23: 10933.605 | P23: 11546.043 | Q23: 11494.96 | R23: 10688.351 | S23: 10334.838 | T23: 10068.339 | U23: 9928.7518 | V23: 11903.505 | W23: 13193.259 | X23: 12642.69 | Y23: 11150.5 | Z23: 9528.643 | AA23: 7982.2172 | AB23: =SUM(D23:AA23)*C23 -> 1528375.2 | AF23: 46419 | AG23: =AC25 -> 6751684.7
B24: ORDINARIO | C24: 19 | D24: 7714.2867 | E24: 6819.783 | F24: 6303.2985 | G24: 5996.7637 | H24: 5953.0172 | I24: 6460.1664 | J24: 7189.1724 | K24: 8675.0232 | L24: 10932.986 | M24: 11848.403 | N24: 12673.088 | O24: 13927.139 | P24: 14327.474 | Q24: 14281.857 | R24: 14298.399 | S24: 14202.947 | T24: 13836.841 | U24: 13400.791 | V24: 14218.831 | W24: 15087.572 | X24: 14460.177 | Y24: 13111.769 | Z24: 11105.216 | AA24: 9191.5568 | AB24: =SUM(D24:AA24)*C24 -> 5054314.6 | AF24: 46447 | AG24: =AC28 -> 8300034.2
A25: 46419 | B25: SÁBADO | C25: 4 | D25: 6751.5849 | E25: 5861.7392 | F25: 5437.2705 | G25: 4975.9365 | H25: 4875.1653 | I25: 5036.2755 | J25: 5618.0038 | K25: 7300.7972 | L25: 9699.1755 | M25: 10718.368 | N25: 11453.692 | O25: 12436.464 | P25: 12684.705 | Q25: 12894.647 | R25: 12608.101 | S25: 11374.428 | T25: 11636.539 | U25: 11557.072 | V25: 12781.76 | W25: 13606.421 | X25: 13194.288 | Y25: 11784.286 | Z25: 9886.4337 | AA25: 8301.2649 | AB25: =SUM(D25:AA25)*C25 -> 929897.67 | AC25: =+AB25+AB26+AB27 -> 6751684.7 | AF25: 46478 | AG25: =AC31 -> 7930619.7
B26: FESTIVO | C26: 4 | D26: 7118.6521 | E26: 6422.8471 | F26: 5746.3833 | G26: 5382.4665 | H26: 5206.6016 | I26: 5336.3499 | J26: 5568.0926 | K26: 6839.9936 | L26: 8654.1562 | M26: 9729.7942 | N26: 10398.786 | O26: 11395.639 | P26: 12292.747 | Q26: 12185.014 | R26: 11328.489 | S26: 10844.029 | T26: 10257.002 | U26: 10368.565 | V26: 12055.071 | W26: 12274.676 | X26: 12275.617 | Y26: 11097.475 | Z26: 9467.3956 | AA26: 7650.0657 | AB26: =SUM(D26:AA26)*C26 -> 879583.63 | AF26: 46508 | AG26: =AC34 -> 7510979.5
B27: ORDINARIO | C27: 20 | D27: 6599.4807 | E27: 5901.3231 | F27: 5446.8501 | G27: 5018.2222 | H27: 5075.0299 | I27: 6180.9773 | J27: 7386.0734 | K27: 8473.9573 | L27: 10132.192 | M27: 10841.266 | N27: 11955.434 | O27: 13056.356 | P27: 13316.841 | Q27: 13159.038 | R27: 13432.276 | S27: 13453.579 | T27: 13266.991 | U27: 12679.073 | V27: 13595.614 | W27: 14434.665 | X27: 13813.205 | Y27: 12167.847 | Z27: 9961.5929 | AA27: 7762.2858 | AB27: =SUM(D27:AA27)*C27 -> 4942203.4 | AF27: 46539 | AG27: =AC37 -> 7268434
A28: 46447 | B28: SÁBADO | C28: 4 | D28: 7808.2171 | E28: 6897.4848 | F28: 6343.7033 | G28: 5918.8423 | H28: 5859.8527 | I28: 6125.4038 | J28: 6732.1826 | K28: 8418.448 | L28: 10862.328 | M28: 12170.097 | N28: 13180.068 | O28: 14519.704 | P28: 14952.86 | Q28: 14921.5 | R28: 14836.221 | S28: 14564.061 | T28: 13769.722 | U28: 13393.137 | V28: 14562.672 | W28: 15595.672 | X28: 14987.653 | Y28: 13785.93 | Z28: 11955.584 | AA28: 10290.704 | AB28: =SUM(D28:AA28)*C28 -> 1089808.2 | AC28: =+AB28+AB29+AB30 -> 8300034.2 | AF28: 46569 | AG28: =AC40 -> 7399601.8
B29: FESTIVO | C29: 4 | D29: 8888.1474 | E29: 7953.2608 | F29: 7246.4114 | G29: 6656.8556 | H29: 6278.797 | I29: 6423.9699 | J29: 6449.4673 | K29: 7806.5453 | L29: 9236.018 | M29: 10307.034 | N29: 11297.332 | O29: 12315.979 | P29: 13178.494 | Q29: 13015.581 | R29: 12130.866 | S29: 11596.422 | T29: 11193.9 | U29: 11039.506 | V29: 12629.487 | W29: 14217.674 | X29: 13824.319 | Y29: 12463.214 | Z29: 10417.062 | AA29: 8646.6742 | AB29: =SUM(D29:AA29)*C29 -> 980852.07 | AF29: 46600 | AG29: =AC43 -> 7183515.3
B30: ORDINARIO | C30: 23 | D30: 7437.5016 | E30: 6687.9562 | F30: 6185.4122 | G30: 5863.3984 | H30: 5852.4792 | I30: 6848.8959 | J30: 7933.7612 | K30: 9258.2838 | L30: 11007.219 | M30: 11971.653 | N30: 12946.381 | O30: 13996.082 | P30: 14097.443 | Q30: 14116.441 | R30: 14764.598 | S30: 14786.131 | T30: 14631.967 | U30: 14026.52 | V30: 14851.64 | W30: 15693.492 | X30: 14812.127 | Y30: 13171.292 | Z30: 10973.029 | AA30: 8928.6393 | AB30: =SUM(D30:AA30)*C30 -> 6229373.9 | AF30: 46631 | AG30: =AC46 -> 2065944.3
A31: 46478 | B31: SÁBADO | C31: 4 | D31: 7711.8254 | E31: 6913.0307 | F31: 6295.371 | G31: 5942.8263 | H31: 5776.2613 | I31: 5896.1598 | J31: 4899.3483 | K31: 8221.1511 | L31: 10502.264 | M31: 11890.599 | N31: 12536.461 | O31: 13565.874 | P31: 13890.112 | Q31: 14447.174 | R31: 14223.448 | S31: 13608.953 | T31: 12552.867 | U31: 12060.175 | V31: 12300.851 | W31: 12761.059 | X31: 12646.855 | Y31: 12522.91 | Z31: 10940.943 | AA31: 9383.2913 | AB31: =SUM(D31:AA31)*C31 -> 1005959.2 | AC31: =+AB31+AB32+AB33 -> 7930619.7 | AF31: 46661 | AG31: =AC49 -> 1878101
B32: FESTIVO | C32: 4 | D32: 7183.2241 | E32: 6312.8224 | F32: 5833.4439 | G32: 5343.7005 | H32: 5175.4633 | I32: 4268.9805 | J32: 5494.2954 | K32: 6828.4824 | L32: 8296.3502 | M32: 9234.2527 | N32: 9960.804 | O32: 10650.261 | P32: 11254.143 | Q32: 11174.19 | R32: 10984.859 | S32: 10791.435 | T32: 10505.821 | U32: 10281.862 | V32: 10746.151 | W32: 12609.958 | X32: 12635.535 | Y32: 11964.395 | Z32: 10793.058 | AA32: 9028.6932 | AB32: =SUM(D32:AA32)*C32 -> 869408.72 | AF32: 46692 | AG32: =AC52 -> 1922771.6
B33: ORDINARIO | C33: 22 | D33: 7968.6713 | E33: 7187.1973 | F33: 6631.9586 | G33: 6274.7926 | H33: 6174.8355 | I33: 7021.3435 | J33: 7968.4932 | K33: 9514.2069 | L33: 11424.811 | M33: 12564.915 | N33: 13523.701 | O33: 14653.821 | P33: 14862.991 | Q33: 15056.282 | R33: 15400.244 | S33: 15106.117 | T33: 14346.439 | U33: 13961.614 | V33: 13763.476 | W33: 14689.779 | X33: 14315.813 | Y33: 12832.934 | Z33: 10957.616 | AA33: 9036.6627 | AB33: =SUM(D33:AA33)*C33 -> 6055251.7 | AF33: 46722 | AG33: =AC55 -> 9173799.3
A34: 46508 | B34: SÁBADO | C34: 5 | D34: 7427.8298 | E34: 6597.0007 | F34: 6074.0933 | G34: 5706.092 | H34: 5602.6943 | I34: 5763.9757 | J34: 6223.9797 | K34: 7982.6191 | L34: 10225.541 | M34: 11412.171 | N34: 12251.597 | O34: 13126.965 | P34: 13687.009 | Q34: 13517.787 | R34: 13266.513 | S34: 12854.58 | T34: 12057.799 | U34: 12060.155 | V34: 12986.491 | W34: 13645.069 | X34: 13002.008 | Y34: 11753.482 | Z34: 9912.5336 | AA34: 8354.7183 | AB34: =SUM(D34:AA34)*C34 -> 1227463.5 | AC34: =+AB34+AB35+AB36 -> 7510979.5
B35: FESTIVO | C35: 5 | D35: 7087.2072 | E35: 5923.9358 | F35: 5321.8088 | G35: 5011.1076 | H35: 4813.4426 | I35: 4863.233 | J35: 5075.2594 | K35: 6723.8889 | L35: 8538.0933 | M35: 9660.6178 | N35: 10692.522 | O35: 11329.824 | P35: 12091.582 | Q35: 11745.416 | R35: 11003.256 | S35: 10439.814 | T35: 10171.318 | U35: 10036.963 | V35: 11389.859 | W35: 12610.539 | X35: 12147.717 | Y35: 11044.906 | Z35: 9324.0518 | AA35: 7741.5689 | AB35: =SUM(D35:AA35)*C35 -> 1073939.7
B36: ORDINARIO | C36: 21 | D36: 6675.9841 | E36: 5796.3851 | F36: 5304.3216 | G36: 5040.8385 | H36: 5052.7501 | I36: 5796.84 | J36: 6733.1222 | K36: 8200.1916 | L36: 10229.284 | M36: 11321.56 | N36: 12286.845 | O36: 13372.463 | P36: 13457.672 | Q36: 13420.663 | R36: 13649.473 | S36: 13588.288 | T36: 13270.888 | U36: 12962.59 | V36: 13697.422 | W36: 14373.849 | X36: 13547.364 | Y36: 12020.576 | Z36: 10102.2 | AA36: 8173.4922 | AB36: =SUM(D36:AA36)*C36 -> 5209576.3
A37: 46539 | B37: SÁBADO | C37: 4 | D37: 6168.2099 | E37: 5684.8976 | F37: 5419.7179 | G37: 4985.0098 | H37: 4824.7844 | I37: 5247.4142 | J37: 5625.0855 | K37: 7519.476 | L37: 10003.854 | M37: 11286.513 | N37: 11872.087 | O37: 13018.137 | P37: 13205.585 | Q37: 12630.151 | R37: 12986.78 | S37: 12581.963 | T37: 11604.943 | U37: 11699.712 | V37: 13602.301 | W37: 15035.173 | X37: 14009.373 | Y37: 12773.723 | Z37: 11166.006 | AA37: 9617.4256 | AB37: =SUM(D37:AA37)*C37 -> 970273.3 | AC37: =+AB37+AB38+AB39 -> 7268434
B38: FESTIVO | C38: 4 | D38: 8129.4246 | E38: 7062.7202 | F38: 6270.5718 | G38: 5831.2771 | H38: 5653.7297 | I38: 5816.0535 | J38: 5873.6825 | K38: 7638.7435 | L38: 9446.9964 | M38: 10330.297 | N38: 10940.92 | O38: 11935.901 | P38: 12398.165 | Q38: 11904.801 | R38: 11237.659 | S38: 10647.38 | T38: 10149.586 | U38: 10052.228 | V38: 11934.226 | W38: 13278.332 | X38: 12293.184 | Y38: 10794.153 | Z38: 9223.662 | AA38: 7543.103 | AB38: =SUM(D38:AA38)*C38 -> 905547.18
B39: ORDINARIO | C39: 22 | D39: 6409.0264 | E39: 5555.0665 | F39: 4998.3998 | G39: 4692.1839 | H39: 4812.5552 | I39: 5499.4167 | J39: 6517.7355 | K39: 8304.9292 | L39: 10314.453 | M39: 11406.532 | N39: 12363.642 | O39: 13338.807 | P39: 13540.52 | Q39: 13692.306 | R39: 13754.559 | S39: 13567.154 | T39: 13190.419 | U39: 12896.269 | V39: 13460.905 | W39: 13953.567 | X39: 13226.097 | Y39: 11595.454 | Z39: 9684.9175 | AA39: 8343.8832 | AB39: =SUM(D39:AA39)*C39 -> 5392613.6
A40: 46569 | B40: SÁBADO | C40: 5 | D40: 6204.7271 | E40: 5477.2942 | F40: 5043.9031 | G40: 4628.9337 | H40: 4515.2299 | I40: 4719.1311 | J40: 5158.1177 | K40: 7081.7249 | L40: 9283.6216 | M40: 10119.715 | N40: 10620.042 | O40: 12022.22 | P40: 12463.474 | Q40: 12350.546 | R40: 12211.065 | S40: 12116 | T40: 11823.869 | U40: 11650.003 | V40: 12625.046 | W40: 13474.815 | X40: 12886.3 | Y40: 11604.89 | Z40: 10030.124 | AA40: 8269.2925 | AB40: =SUM(D40:AA40)*C40 -> 1131900.4 | AC40: =+AB40+AB41+AB42 -> 7399601.8
B41: FESTIVO | C41: 4 | D41: 7044.981 | E41: 6144.6993 | F41: 5515.1237 | G41: 4976.9611 | H41: 4790.9459 | I41: 4888.7445 | J41: 5212.5412 | K41: 6522.5101 | L41: 8157.2883 | M41: 8558.2105 | N41: 9615.6138 | O41: 11038.247 | P41: 11839.647 | Q41: 11773.109 | R41: 11210.543 | S41: 11088.241 | T41: 10750.634 | U41: 10418.588 | V41: 11090.898 | W41: 13197.566 | X41: 12689.303 | Y41: 11324.458 | Z41: 9399.5785 | AA41: 7777.7708 | AB41: =SUM(D41:AA41)*C41 -> 860104.81
B42: ORDINARIO | C42: 22 | D42: 6852.9741 | E42: 6060.6626 | F42: 5507.4972 | G42: 5217.6854 | H42: 5209.3173 | I42: 5995.8586 | J42: 6988.3793 | K42: 8402.2224 | L42: 10125.349 | M42: 10788.236 | N42: 11617.071 | O42: 12756.837 | P42: 12642.912 | Q42: 13049.184 | R42: 13735.117 | S42: 13778.742 | T42: 13175.088 | U42: 12703.053 | V42: 13336.201 | W42: 14302.254 | X42: 13709.154 | Y42: 11947.06 | Z42: 9822.7773 | AA42: 8076.2138 | AB42: =SUM(D42:AA42)*C42 -> 5407596.6
A43: 46600 | B43: SÁBADO | C43: 4 | D43: 6829.0574 | E43: 5257.1953 | F43: 4693.8497 | G43: 4268.7501 | H43: 4181.6085 | I43: 4326.4934 | J43: 4991.146 | K43: 6493.603 | L43: 8759.784 | M43: 9760.3347 | N43: 11421.153 | O43: 12630.884 | P43: 13022.473 | Q43: 12875.212 | R43: 12437.556 | S43: 12270.395 | T43: 11955.124 | U43: 11463.719 | V43: 13019.373 | W43: 13720.087 | X43: 13064.397 | Y43: 11496.833 | Z43: 9451.4178 | AA43: 7950.0466 | AB43: =SUM(D43:AA43)*C43 -> 905361.97 | AC43: =+AB43+AB44+AB45 -> 7183515.3
B44: FESTIVO | C44: 5 | D44: 6743.952 | E44: 6025.7439 | F44: 5326.2147 | G44: 4764.4552 | H44: 4397.1438 | I44: 4479.3882 | J44: 4886.4916 | K44: 6421.1232 | L44: 8314.8821 | M44: 9561.3866 | N44: 10292.793 | O44: 11369.479 | P44: 12025.145 | Q44: 11952.254 | R44: 11293.293 | S44: 10871.173 | T44: 10580.822 | U44: 10328.062 | V44: 11283.752 | W44: 12845.648 | X44: 12346.21 | Y44: 10911.419 | Z44: 9120.0361 | AA44: 7526.3452 | AB44: =SUM(D44:AA44)*C44 -> 1068336.1
B45: ORDINARIO | C45: 22 | D45: 6784.8305 | E45: 6022.4108 | F45: 5502.0605 | G45: 5147.7903 | H45: 5039.2166 | I45: 5813.2016 | J45: 6877.0667 | K45: 8172.93 | L45: 9925.7808 | M45: 11182.342 | N45: 11858.146 | O45: 11978.967 | P45: 11316.525 | Q45: 11698.211 | R45: 12044.294 | S45: 12102.893 | T45: 13199.106 | U45: 12684.61 | V45: 12900.566 | W45: 13541.288 | X45: 13062.309 | Y45: 11853.104 | Z45: 9973.7728 | AA45: 8128.4528 | AB45: =SUM(D45:AA45)*C45 -> 5209817.2
A46: 46631 | B46: SÁBADO | C46: 4 | D46: 1755.8694 | E46: 1667.599 | F46: 1513.0793 | G46: 1426.3664 | H46: 1415.1153 | I46: 1454.7198 | J46: 1634.7795 | K46: 2198.7713 | L46: 2825.7214 | M46: 3223.1189 | N46: 3519.4705 | O46: 3834.8432 | P46: 3947.6196 | Q46: 3909.7521 | R46: 3785.5119 | S46: 3611.48 | T46: 3464.2801 | U46: 3405.5158 | V46: 3823.3778 | W46: 3982.5081 | X46: 3782.2326 | Y46: 3396.2826 | Z46: 2948.9037 | AA46: 2472.468 | AB46: =SUM(D46:AA46)*C46 -> 275997.55 | AC46: =+AB46+AB47+AB48 -> 2065944.3
B47: FESTIVO | C47: 4 | D47: 2114.8815 | E47: 1863.4398 | F47: 1678.7141 | G47: 1568.4083 | H47: 1487.0437 | I47: 1477.4449 | J47: 1523.3454 | K47: 1898.6189 | L47: 2387.7538 | M47: 2655.8233 | N47: 2889.2854 | O47: 3229.7352 | P47: 3390.7615 | Q47: 3276.1241 | R47: 3017.7446 | S47: 2899.5302 | T47: 2792.3156 | U47: 2835.0072 | V47: 3385.2496 | W47: 3592.8754 | X47: 3460.2707 | Y47: 3145.701 | Z47: 2628.1109 | AA47: 2173.4857 | AB47: =SUM(D47:AA47)*C47 -> 245486.68
B48: ORDINARIO | C48: 22 | D48: 1839.887 | E48: 1655.2225 | F48: 1516.5655 | G48: 1387.3548 | H48: 1414.325 | I48: 1667.2092 | J48: 2000.9572 | K48: 2370.7528 | L48: 2909.173 | M48: 3192.5619 | N48: 3422.7049 | O48: 3729.0319 | P48: 3781.655 | Q48: 3827.4418 | R48: 3928.6032 | S48: 3889.3861 | T48: 3821.5563 | U48: 3686.9923 | V48: 3991.7955 | W48: 4083.5524 | X48: 3844.2678 | Y48: 3357.126 | Z48: 2704.1182 | AA48: 2180.492 | AB48: =SUM(D48:AA48)*C48 -> 1544460.1
A49: 46661 | B49: SÁBADO | C49: 5 | D49: 1580.7725 | E49: 1385.4805 | F49: 1259.9326 | G49: 1145.7757 | H49: 1091.3042 | I49: 1126.2271 | J49: 1228.6839 | K49: 1737.2446 | L49: 2360.4355 | M49: 2824.8997 | N49: 3154.9113 | O49: 3506.0067 | P49: 3593.9094 | Q49: 3494.5152 | R49: 3385.2198 | S49: 3236.4929 | T49: 3110.5774 | U49: 3105.484 | V49: 3417.6884 | W49: 3454.3254 | X49: 3322.3515 | Y49: 3005.601 | Z49: 2564.055 | AA49: 2125.1062 | AB49: =SUM(D49:AA49)*C49 -> 301085 | AC49: =+AB49+AB50+AB51 -> 1878101
B50: FESTIVO | C50: 5 | D50: 1706.1425 | E50: 1479.6149 | F50: 1312.0316 | G50: 1217.6977 | H50: 1172.9887 | I50: 1187.0949 | J50: 1222.9265 | K50: 1597.408 | L50: 2025.4788 | M50: 2345.3679 | N50: 2516.8087 | O50: 2911.1462 | P50: 3121.1105 | Q50: 3060.7002 | R50: 2791.317 | S50: 2469.2203 | T50: 2518.4934 | U50: 2646.6265 | V50: 3151.0392 | W50: 3253.8668 | X50: 2998.9053 | Y50: 2600.4284 | Z50: 2112.7073 | AA50: 1710.9577 | AB50: =SUM(D50:AA50)*C50 -> 265650.39
B51: ORDINARIO | C51: 21 | D51: 1607.0725 | E51: 1413.6037 | F51: 1272.3164 | G51: 1127.0309 | H51: 1174.4439 | I51: 1367.606 | J51: 1636.4543 | K51: 2063.7242 | L51: 2534.9183 | M51: 2824.1409 | N51: 3009.3625 | O51: 3229.907 | P51: 3409.9471 | Q51: 3413.2092 | R51: 3522.2194 | S51: 3564.9428 | T51: 3528.5563 | U51: 3355.6902 | V51: 3731.6592 | W51: 3710.3364 | X51: 3501.1159 | Y51: 3020.1975 | Z51: 2453.2836 | AA51: 1974.2411 | AB51: =SUM(D51:AA51)*C51 -> 1311365.6
A52: 46692 | B52: SÁBADO | C52: 4 | D52: 1607.7819 | E52: 1539.9386 | F52: 1369.9147 | G52: 1232.7337 | H52: 1230.8223 | I52: 1287.1062 | J52: 1430.9665 | K52: 1942.5314 | L52: 2615.5345 | M52: 3024.871 | N52: 3286.3498 | O52: 3554.2181 | P52: 3676.8533 | Q52: 3600.6244 | R52: 3485.1988 | S52: 3337.514 | T52: 3204.8648 | U52: 3278.4265 | V52: 3709.4239 | W52: 3721.919 | X52: 3540.888 | Y52: 3161.1829 | Z52: 2709.2634 | AA52: 2256.1691 | AB52: =SUM(D52:AA52)*C52 -> 255220.39 | AC52: =+AB52+AB53+AB54 -> 1922771.6
B53: FESTIVO | C53: 4 | D53: 1848.8253 | E53: 1626.1565 | F53: 1493.9 | G53: 1384.2975 | H53: 1342.1612 | I53: 1358.3865 | J53: 1445.3706 | K53: 1823.7145 | L53: 2322.7063 | M53: 2632.6209 | N53: 2808.0208 | O53: 3036.9627 | P53: 3161.3812 | Q53: 3065.6341 | R53: 2867.9203 | S53: 2720.4297 | T53: 2664.4158 | U53: 2716.19 | V53: 3300.7341 | W53: 3443.0503 | X53: 3227.2235 | Y53: 2852.9713 | Z53: 2414.7294 | AA53: 2017.0456 | AB53: =SUM(D53:AA53)*C53 -> 230299.39
B54: ORDINARIO | C54: 22 | D54: 1692.9083 | E54: 1493.6859 | F54: 1365.6972 | G54: 1281.4169 | H54: 1275.8182 | I54: 1465.2114 | J54: 1775.0852 | K54: 2231.394 | L54: 2721.9806 | M54: 2986.5667 | N54: 3247.3228 | O54: 3521.7776 | P54: 3609.385 | Q54: 3577.4591 | R54: 3663.7752 | S54: 3568.4521 | T54: 3438.5629 | U54: 3383.5013 | V54: 3797.7625 | W54: 3741.7677 | X54: 3595.2951 | Y54: 3190.5992 | Z54: 2605.2517 | AA54: 2098.9529 | AB54: =SUM(D54:AA54)*C54 -> 1437251.8
A55: 46722 | B55: SÁBADO | C55: 4 | D55: 8921.6332 | E55: 7963.6501 | F55: 7462.9591 | G55: 7132.425 | H55: 7040.7582 | I55: 7397.9527 | J55: 7860.1942 | K55: 9623.3426 | L55: 11997.597 | M55: 13313.246 | N55: 14201.876 | O55: 15091.051 | P55: 15390.016 | Q55: 15330.515 | R55: 14837.779 | S55: 14431.628 | T55: 14085.111 | U55: 14027.098 | V55: 15857.414 | W55: 16115.703 | X55: 15419.952 | Y55: 14236.816 | Z55: 12569.737 | AA55: 11064.578 | AB55: =SUM(D55:AA55)*C55 -> 1165492.1 | AC55: =+AB55+AB56+AB57 -> 9173799.3
B56: FESTIVO | C56: 4 | D56: 9864.1507 | E56: 9002.0329 | F56: 8399.9905 | G56: 7922.7242 | H56: 7712.4282 | I56: 7821.3345 | J56: 7849.3319 | K56: 9176.307 | L56: 10848.772 | M56: 12253.11 | N56: 12952.283 | O56: 13983.592 | P56: 14498.365 | Q56: 14513.504 | R56: 13917.807 | S56: 13297.702 | T56: 13008.56 | U56: 12899.259 | V56: 14955.162 | W56: 15597.691 | X56: 14607.617 | Y56: 13286.905 | Z56: 12291.712 | AA56: 10838.111 | AB56: =SUM(D56:AA56)*C56 -> 1125993.8
B57: ORDINARIO | C57: 23 | D57: 9257.9533 | E57: 8359.6292 | F57: 7789.5025 | G57: 7383.1017 | H57: 7285.3633 | I57: 7682.9474 | J57: 8477.6975 | K57: 10386.872 | L57: 12660.031 | M57: 13470.593 | N57: 13964.294 | O57: 14916.705 | P57: 14999.925 | Q57: 15098.286 | R57: 15108.444 | S57: 15141.733 | T57: 14852.427 | U57: 14668.479 | V57: 16658.373 | W57: 16851.758 | X57: 16075.97 | Y57: 14545.69 | Z57: 12686.428 | AA57: 10908.813 | AB57: =SUM(D57:AA57)*C57 -> 6882313.3
A60: Mes | B60: Tipo de día | C60: No. de Días | D60: HORA 01 | E60: HORA 02 | F60: HORA 03 | G60: HORA 04 | H60: HORA 05 | I60: HORA 06 | J60: HORA 07 | K60: HORA 08 | L60: HORA 09 | M60: HORA 10 | N60: HORA 11 | O60: HORA 12 | P60: HORA 13 | Q60: HORA 14 | R60: HORA 15 | S60: HORA 16 | T60: HORA 17 | U60: HORA 18 | V60: HORA 19 | W60: HORA 20 | X60: HORA 21 | Y60: HORA 22 | Z60: HORA 23 | AA60: HORA 24 | AB60: Total
A61: 46753 | B61: SÁBADO | C61: 4 | D61: 6237.6621 | E61: 5494.3444 | F61: 5033.8662 | G61: 4606.604 | H61: 4551.9332 | I61: 4708.1526 | J61: 5022.2364 | K61: 6512.1427 | L61: 8754.9451 | M61: 10122.718 | N61: 10925.876 | O61: 12084.741 | P61: 12430.067 | Q61: 12068.559 | R61: 11587.922 | S61: 11689.632 | T61: 11333.676 | U61: 11079.609 | V61: 12291.975 | W61: 13143.213 | X61: 12608.245 | Y61: 11372.403 | Z61: 9663.4392 | AA61: 8051.818 | AB61: =SUM(D61:AA61)*C61 -> 885503.12 | AC61: =+AB61+AB62+AB63 -> 6921496.2 | AF61: 46753 | AG61: =AC61 -> 6921496.2
B62: FESTIVO | C62: 7 | D62: 6542.0227 | E62: 5823.3507 | F62: 5166.0384 | G62: 4813.5641 | H62: 4497.5784 | I62: 4466.375 | J62: 4530.1898 | K62: 5479.5916 | L62: 7089.2364 | M62: 8184.0364 | N62: 8740.3757 | O62: 9659.1562 | P62: 10237.56 | Q62: 10189.316 | R62: 9427.5308 | S62: 9093.6628 | T62: 8841.9734 | U62: 8710.1437 | V62: 10575.157 | W62: 11793.238 | X62: 11273.265 | Y62: 9863.9974 | Z62: 8332.2694 | AA62: 6871.7804 | AB62: =SUM(D62:AA62)*C62 -> 1331409.9 | AF62: 46784 | AG62: =AC64 -> 5803036.3
B63: ORDINARIO | C63: 20 | D63: 6618.7392 | E63: 5773.9441 | F63: 5286.1613 | G63: 4996.6611 | H63: 4955.3456 | I63: 5434.3118 | J63: 6122.8061 | K63: 7526.0863 | L63: 9658.5716 | M63: 10523.117 | N63: 11301.974 | O63: 12486.336 | P63: 12864.424 | Q63: 12821.341 | R63: 12836.964 | S63: 12746.816 | T63: 12401.055 | U63: 11989.237 | V63: 12761.817 | W63: 13582.282 | X63: 12989.752 | Y63: 11716.276 | Z63: 9821.2303 | AA63: 8013.9155 | AB63: =SUM(D63:AA63)*C63 -> 4704583.3 | AF63: 46813 | AG63: =AC67 -> 7335720.2
A64: 46784 | B64: SÁBADO | C64: 4 | D64: 5550.9208 | E64: 4718.0519 | F64: 4320.7619 | G64: 3888.9672 | H64: 3794.6484 | I64: 3945.4427 | J64: 4489.9229 | K64: 6064.967 | L64: 8309.7772 | M64: 9263.7109 | N64: 9951.9519 | O64: 10871.797 | P64: 11104.143 | Q64: 11300.643 | R64: 11032.444 | S64: 9877.7634 | T64: 10123.092 | U64: 10048.712 | V64: 11194.984 | W64: 11966.842 | X64: 11581.098 | Y64: 10261.378 | Z64: 8485.0453 | AA64: 7001.3748 | AB64: =SUM(D64:AA64)*C64 -> 796593.76 | AC64: =+AB64+AB65+AB66 -> 5803036.3 | AF64: 46844 | AG64: =AC70 -> 6914373.1
B65: FESTIVO | C65: 4 | D65: 5894.4847 | E65: 5243.2321 | F65: 4610.0823 | G65: 4269.4671 | H65: 4104.8628 | I65: 4226.3033 | J65: 4443.2075 | K65: 5633.6687 | L65: 7331.6705 | M65: 8338.4354 | N65: 8964.5919 | O65: 9897.6158 | P65: 10737.282 | Q65: 10636.447 | R65: 9834.7657 | S65: 9381.3253 | T65: 8831.8864 | U65: 8936.3061 | V65: 10514.825 | W65: 10720.368 | X65: 10721.249 | Y65: 9618.5432 | Z65: 8092.8381 | AA65: 6391.8719 | AB65: =SUM(D65:AA65)*C65 -> 749501.32 | AF65: 46874 | AG65: =AC73 -> 4526703.4
B66: ORDINARIO | C66: 20 | D66: 5408.5558 | E66: 4755.1013 | F66: 4329.7282 | G66: 3928.5453 | H66: 3981.7157 | I66: 5016.8492 | J66: 6144.783 | K66: 7163.0097 | L66: 8715.0679 | M66: 9378.7395 | N66: 10421.568 | O66: 11451.998 | P66: 11695.803 | Q66: 11548.104 | R66: 11803.847 | S66: 11823.786 | T66: 11649.146 | U66: 11098.871 | V66: 11956.727 | W66: 12742.053 | X66: 12160.385 | Y66: 10620.379 | Z66: 8555.3919 | AA66: 6496.9065 | AB66: =SUM(D66:AA66)*C66 -> 4256941.2 | AF66: 46905 | AG66: =AC76 -> 4322879.6
A67: 46813 | B67: SÁBADO | C67: 4 | D67: 6727.341 | E67: 5866.3046 | F67: 5342.7414 | G67: 4941.0638 | H67: 4885.293 | I67: 5136.3539 | J67: 5710.0224 | K67: 7304.2733 | L67: 9614.7983 | M67: 10851.206 | N67: 11806.065 | O67: 13072.602 | P67: 13482.122 | Q67: 13452.472 | R67: 13371.847 | S67: 13114.538 | T67: 12363.544 | U67: 12007.508 | V67: 13113.225 | W67: 14089.857 | X67: 13515.016 | Y67: 12378.868 | Z67: 10648.398 | AA67: 9074.3662 | AB67: =SUM(D67:AA67)*C67 -> 967479.31 | AC67: =+AB67+AB68+AB69 -> 7335720.2 | AF67: 46935 | AG67: =AC79 -> 4291029.3
B68: FESTIVO | C68: 5 | D68: 7748.3426 | E68: 6864.4701 | F68: 6196.1913 | G68: 5638.8059 | H68: 5281.3768 | I68: 5418.6281 | J68: 5442.7341 | K68: 6725.7604 | L68: 8077.2309 | M68: 9089.8051 | N68: 10026.066 | O68: 10989.128 | P68: 11804.578 | Q68: 11650.554 | R68: 10814.115 | S68: 10308.835 | T68: 9928.2773 | U68: 9782.308 | V68: 11285.529 | W68: 12787.053 | X68: 12415.161 | Y68: 11128.328 | Z68: 9193.829 | AA68: 7520.0459 | AB68: =SUM(D68:AA68)*C68 -> 1080585.8 | AF68: 46966 | AG68: =AC82 -> 6546836.8
B69: ORDINARIO | C69: 22 | D69: 6376.8543 | E69: 5668.2094 | F69: 5193.0877 | G69: 4888.6452 | H69: 4878.3219 | I69: 5820.3671 | J69: 6846.0345 | K69: 8098.2818 | L69: 9751.7831 | M69: 10663.59 | N69: 11585.13 | O69: 12577.553 | P69: 12673.383 | Q69: 12691.344 | R69: 13304.133 | S69: 13324.491 | T69: 13178.739 | U69: 12606.329 | V69: 13386.425 | W69: 14182.339 | X69: 13349.068 | Y69: 11797.769 | Z69: 9719.4585 | AA69: 7786.625 | AB69: =SUM(D69:AA69)*C69 -> 5287655.1 | AF69: 46997 | AG69: =AC85 -> 6870287.5
A70: 46844 | B70: SÁBADO | C70: 5 | D70: 6594.5406 | E70: 5841.0223 | F70: 5258.3722 | G70: 4925.8101 | H70: 4768.6861 | I70: 4881.7887 | J70: 3941.4774 | K70: 7074.9972 | L70: 9226.8145 | M70: 10536.457 | N70: 11145.711 | O70: 12116.776 | P70: 12422.636 | Q70: 12948.123 | R70: 12737.078 | S70: 12157.413 | T70: 11161.187 | U70: 10696.422 | V70: 10923.456 | W70: 11357.579 | X70: 11249.849 | Y70: 11132.928 | Z70: 9640.6293 | AA70: 8171.2663 | AB70: =SUM(D70:AA70)*C70 -> 1104555.1 | AC70: =+AB70+AB71+AB72 -> 6914373.1 | AF70: 47027 | AG70: =AC88 -> 7266240.7
B71: FESTIVO | C71: 5 | D71: 6095.901 | E71: 5274.8344 | F71: 4822.6275 | G71: 4360.6433 | H71: 4201.9419 | I71: 3346.8394 | J71: 4502.7023 | K71: 5761.2663 | L71: 7145.934 | M71: 8030.6753 | N71: 8716.045 | O71: 9366.4229 | P71: 9936.076 | Q71: 9860.6553 | R71: 9682.0556 | S71: 9499.5949 | T71: 9230.1697 | U71: 9018.9047 | V71: 9456.8776 | W71: 11215.042 | X71: 11239.17 | Y71: 10606.07 | Z71: 9501.126 | AA71: 7836.7671 | AB71: =SUM(D71:AA71)*C71 -> 943541.72 | AF71: 47058 | AG71: =AC91 -> 7127709.9
B72: ORDINARIO | C72: 20 | D72: 6836.8282 | E72: 6099.6489 | F72: 5575.8817 | G72: 5238.9602 | H72: 5144.6687 | I72: 5943.1958 | J72: 6836.6602 | K72: 8294.7615 | L72: 10097.071 | M72: 11172.553 | N72: 12076.993 | O72: 13143.057 | P72: 13340.372 | Q72: 13522.707 | R72: 13847.172 | S72: 13569.717 | T72: 12853.098 | U72: 12490.085 | V72: 12303.178 | W72: 13176.977 | X72: 12824.208 | Y72: 11425.38 | Z72: 9656.357 | AA72: 7844.2849 | AB72: =SUM(D72:AA72)*C72 -> 4866276.3 | AF72: 47088 | AG72: =AC94 -> 8230558
A73: 46874 | B73: SÁBADO | C73: 4 | D73: 4479.5687 | E73: 3988.6461 | F73: 3679.6692 | G73: 3462.2236 | H73: 3401.1276 | I73: 3496.426 | J73: 3768.2345 | K73: 4807.3841 | L73: 6132.6876 | M73: 6833.8472 | N73: 7329.8495 | O73: 7847.0889 | P73: 8178.0094 | Q73: 8078.0191 | R73: 7929.5458 | S73: 7686.1417 | T73: 7215.3375 | U73: 7216.7294 | V73: 7764.0855 | W73: 8153.2279 | X73: 7773.2544 | Y73: 7035.5216 | Z73: 5947.7372 | AA73: 5027.2511 | AB73: =SUM(D73:AA73)*C73 -> 588926.45 | AC73: =+AB73+AB74+AB75 -> 4526703.4
B74: FESTIVO | C74: 4 | D74: 4278.3007 | E74: 3590.9437 | F74: 3235.1573 | G74: 3051.5693 | H74: 2934.7724 | I74: 2964.1928 | J74: 3089.4755 | K74: 4063.6222 | L74: 5135.6041 | M74: 5798.8845 | N74: 6408.6189 | O74: 6785.1896 | P74: 7235.2989 | Q74: 7030.7555 | R74: 6592.2263 | S74: 6259.2983 | T74: 6100.6486 | U74: 6021.2606 | V74: 6820.6635 | W74: 7541.9422 | X74: 7268.4686 | Y74: 6616.8366 | Z74: 5600.0134 | AA74: 4664.9516 | AB74: =SUM(D74:AA74)*C74 -> 516354.78
B75: ORDINARIO | C75: 23 | D75: 4035.316 | E75: 3515.5762 | F75: 3224.8244 | G75: 3069.1368 | H75: 3076.1751 | I75: 3515.845 | J75: 4069.0779 | K75: 4935.9439 | L75: 6134.8995 | M75: 6780.3064 | N75: 7350.6768 | O75: 7992.1494 | P75: 8042.4981 | Q75: 8020.6302 | R75: 8155.8303 | S75: 8119.6769 | T75: 7932.1308 | U75: 7749.9629 | V75: 8184.162 | W75: 8583.8512 | X75: 8095.4956 | Y75: 7193.3431 | Z75: 6059.8075 | AA75: 4920.1677 | AB75: =SUM(D75:AA75)*C75 -> 3421422.1
A76: 46905 | B76: SÁBADO | C76: 4 | D76: 3692.8665 | E76: 3408.4139 | F76: 3252.3429 | G76: 2996.4962 | H76: 2902.1959 | I76: 3150.9339 | J76: 3373.2117 | K76: 4488.1517 | L76: 5950.3279 | M76: 6705.2347 | N76: 7049.8728 | O76: 7724.3785 | P76: 7834.7007 | Q76: 7496.0302 | R76: 7705.9234 | S76: 7467.6689 | T76: 6892.646 | U76: 6948.4218 | V76: 8068.1873 | W76: 8911.5013 | X76: 8307.7687 | Y76: 7580.5293 | Z76: 6634.3105 | AA76: 5722.896 | AB76: =SUM(D76:AA76)*C76 -> 577060.04 | AC76: =+AB76+AB77+AB78 -> 4322879.6
B77: FESTIVO | C77: 4 | D77: 4847.1358 | E77: 4219.3289 | F77: 3753.1114 | G77: 3494.5653 | H77: 3390.0701 | I77: 3485.6055 | J77: 3519.5229 | K77: 4558.3463 | L77: 5622.5902 | M77: 6142.4552 | N77: 6501.8361 | O77: 7087.4307 | P77: 7359.495 | Q77: 7069.1267 | R77: 6676.4813 | S77: 6329.074 | T77: 6036.0983 | U77: 5978.7984 | V77: 7086.4444 | W77: 7877.5155 | X77: 7297.7086 | Y77: 6415.4569 | Z77: 5491.1472 | AA77: 4502.0573 | AB77: =SUM(D77:AA77)*C77 -> 538965.61
B78: ORDINARIO | C78: 22 | D78: 3834.5986 | E78: 3332.0021 | F78: 3004.3769 | G78: 2824.1541 | H78: 2894.9984 | I78: 3299.2495 | J78: 3898.5791 | K78: 4950.4287 | L78: 6133.1302 | M78: 6775.8716 | N78: 7339.1768 | O78: 7913.1082 | P78: 8031.8259 | Q78: 8121.1595 | R78: 8157.7982 | S78: 8047.5015 | T78: 7825.7745 | U78: 7652.6531 | V78: 7984.9689 | W78: 8274.9243 | X78: 7846.7728 | Y78: 6887.0612 | Z78: 5762.6183 | AA78: 4973.355 | AB78: =SUM(D78:AA78)*C78 -> 3206853.9
A79: 46935 | B79: SÁBADO | C79: 5 | D79: 3611.0977 | E79: 3187.0945 | F79: 2934.4813 | G79: 2692.6056 | H79: 2626.3304 | I79: 2745.1795 | J79: 3001.0542 | K79: 4122.2786 | L79: 5405.7112 | M79: 5893.0497 | N79: 6184.6787 | O79: 7001.9742 | P79: 7259.1705 | Q79: 7193.3476 | R79: 7112.0474 | S79: 7056.6363 | T79: 6886.3606 | U79: 6785.0178 | V79: 7353.3473 | W79: 7848.6568 | X79: 7505.6261 | Y79: 6758.723 | Z79: 5840.8295 | AA79: 4814.4832 | AB79: =SUM(D79:AA79)*C79 -> 659098.91 | AC79: =+AB79+AB80+AB81 -> 4291029.3
B80: FESTIVO | C80: 5 | D80: 4100.8615 | E80: 3576.1089 | F80: 3209.1444 | G80: 2895.4624 | H80: 2787.0386 | I80: 2844.0431 | J80: 3032.7764 | K80: 3796.3257 | L80: 4749.1987 | M80: 4982.8865 | N80: 5599.2215 | O80: 6428.4403 | P80: 6895.5567 | Q80: 6856.7733 | R80: 6528.8671 | S80: 6457.5805 | T80: 6260.7974 | U80: 6067.256 | V80: 6459.1292 | W80: 7687.0554 | X80: 7390.8008 | Y80: 6595.2658 | Z80: 5473.2997 | AA80: 4527.987 | AB80: =SUM(D80:AA80)*C80 -> 626009.38
B81: ORDINARIO | C81: 21 | D81: 3988.9453 | E81: 3527.1259 | F81: 3204.6991 | G81: 3035.7748 | H81: 3030.8973 | I81: 3489.3532 | J81: 4067.8697 | K81: 4891.9648 | L81: 5896.3336 | M81: 6282.7149 | N81: 6765.8228 | O81: 7430.1653 | P81: 7363.7608 | Q81: 7600.567 | R81: 8000.3809 | S81: 8025.8088 | T81: 7673.9534 | U81: 7398.8153 | V81: 7767.8626 | W81: 8330.9514 | X81: 7985.2477 | Y81: 6958.1653 | Z81: 5719.9721 | AA81: 4701.9423 | AB81: =SUM(D81:AA81)*C81 -> 3005921
A82: 46966 | B82: SÁBADO | C82: 4 | D82: 6717.8302 | E82: 5572.6567 | F82: 5162.2336 | G82: 4852.5291 | H82: 4789.0425 | I82: 4894.5978 | J82: 5378.8276 | K82: 6473.4363 | L82: 8124.4529 | M82: 8853.3999 | N82: 10063.382 | O82: 10944.727 | P82: 11230.017 | Q82: 11122.731 | R82: 10803.878 | S82: 10682.094 | T82: 10452.405 | U82: 10094.393 | V82: 11227.758 | W82: 11738.26 | X82: 11260.56 | Y82: 10118.518 | Z82: 8628.3397 | AA82: 7534.5221 | AB82: =SUM(D82:AA82)*C82 -> 826882.37 | AC82: =+AB82+AB83+AB84 -> 6546836.8
B83: FESTIVO | C83: 4 | D83: 6655.827 | E83: 6132.5795 | F83: 5622.9405 | G83: 5213.6729 | H83: 4946.0698 | I83: 5005.9886 | J83: 5302.5821 | K83: 6420.6314 | L83: 7800.3215 | M83: 8708.457 | N83: 9241.3202 | O83: 10025.735 | P83: 10503.418 | Q83: 10450.313 | R83: 9970.2299 | S83: 9662.6964 | T83: 9451.1625 | U83: 9267.0151 | V83: 9963.2789 | W83: 11101.192 | X83: 10737.328 | Y83: 9692.0173 | Z83: 8386.9131 | AA83: 7225.8363 | AB83: =SUM(D83:AA83)*C83 -> 789950.11
B84: ORDINARIO | C84: 23 | D84: 6685.6089 | E84: 6130.1512 | F84: 5751.0522 | G84: 5492.9502 | H84: 5413.8492 | I84: 5977.7327 | J84: 6752.8071 | K84: 7696.9029 | L84: 8973.9349 | M84: 9889.3974 | N84: 10381.751 | O84: 10469.775 | P84: 9987.156 | Q84: 10265.231 | R84: 10517.369 | S84: 10560.061 | T84: 11358.702 | U84: 10983.869 | V84: 11141.202 | W84: 11607.997 | X84: 11259.04 | Y84: 10378.078 | Z84: 9008.8993 | AA84: 7664.4992 | AB84: =SUM(D84:AA84)*C84 -> 4930004.4
A85: 46997 | B85: SÁBADO | C85: 5 | D85: 6653.7518 | E85: 6424.442 | F85: 6023.0291 | G85: 5797.7656 | H85: 5768.5372 | I85: 5871.4221 | J85: 6339.1831 | K85: 7804.3269 | L85: 9433.0244 | M85: 10465.388 | N85: 11235.253 | O85: 12054.531 | P85: 12347.503 | Q85: 12249.131 | R85: 11926.378 | S85: 11474.276 | T85: 11091.879 | U85: 10939.22 | V85: 12024.747 | W85: 12438.137 | X85: 11917.859 | Y85: 10915.234 | Z85: 9753.0287 | AA85: 8515.3391 | AB85: =SUM(D85:AA85)*C85 -> 1147316.9 | AC85: =+AB85+AB86+AB87 -> 6870287.5
B86: FESTIVO | C86: 4 | D86: 7586.397 | E86: 6933.1994 | F86: 6453.3168 | G86: 6166.7634 | H86: 5955.3936 | I86: 5930.4578 | J86: 6049.6987 | K86: 7024.5879 | L86: 8295.2675 | M86: 8991.6614 | N86: 9598.1516 | O86: 10482.575 | P86: 10900.891 | Q86: 10603.085 | R86: 9931.8641 | S86: 9624.7655 | T86: 9346.2424 | U86: 9457.147 | V86: 10886.572 | W86: 11425.945 | X86: 11081.463 | Y86: 10264.271 | Z86: 8919.6698 | AA86: 7738.6397 | AB86: =SUM(D86:AA86)*C86 -> 838592.11
B87: ORDINARIO | C87: 21 | D87: 6872.0135 | E87: 6392.2903 | F87: 6032.0856 | G87: 5696.4206 | H87: 5766.4842 | I87: 6423.4294 | J87: 7290.4435 | K87: 8251.1023 | L87: 9649.8158 | M87: 10386.006 | N87: 10983.874 | O87: 11779.654 | P87: 11916.358 | Q87: 12035.304 | R87: 12298.102 | S87: 12196.223 | T87: 12020.014 | U87: 11670.443 | V87: 12462.264 | W87: 12700.631 | X87: 12079.015 | Y87: 10813.513 | Z87: 9117.1223 | AA87: 7756.8407 | AB87: =SUM(D87:AA87)*C87 -> 4884378.4
A88: 47027 | B88: SÁBADO | C88: 4 | D88: 7133.389 | E88: 6590.1375 | F88: 6240.8956 | G88: 5923.3409 | H88: 5771.8153 | I88: 5868.9618 | J88: 6153.9698 | K88: 7568.6537 | L88: 9302.2087 | M88: 10594.227 | N88: 11512.234 | O88: 12488.89 | P88: 12733.413 | Q88: 12456.924 | R88: 12152.892 | S88: 11739.173 | T88: 11388.909 | U88: 11374.74 | V88: 12243.212 | W88: 12345.126 | X88: 11978.009 | Y88: 11096.892 | Z88: 9868.6254 | AA88: 8647.5838 | AB88: =SUM(D88:AA88)*C88 -> 932696.89 | AC88: =+AB88+AB89+AB90 -> 7266240.7
B89: FESTIVO | C89: 5 | D89: 7482.1358 | E89: 6851.9948 | F89: 6385.8216 | G89: 6123.4093 | H89: 5999.0403 | I89: 6038.2801 | J89: 6137.9545 | K89: 7179.6647 | L89: 8370.4462 | M89: 9260.2946 | N89: 9737.1985 | O89: 10834.143 | P89: 11418.209 | Q89: 11250.163 | R89: 10500.809 | S89: 9604.8199 | T89: 9741.885 | U89: 10098.318 | V89: 11501.463 | W89: 11787.503 | X89: 11078.266 | Y89: 9969.8068 | Z89: 8613.0933 | AA89: 7495.5302 | AB89: =SUM(D89:AA89)*C89 -> 1067301.2
B90: ORDINARIO | C90: 22 | D90: 7206.5487 | E90: 6668.3688 | F90: 6275.3443 | G90: 5871.1979 | H90: 6003.0883 | I90: 6540.4151 | J90: 7288.2814 | K90: 8476.8351 | L90: 9787.5746 | M90: 10592.117 | N90: 11107.355 | O90: 11720.853 | P90: 12221.678 | Q90: 12230.752 | R90: 12533.99 | S90: 12652.835 | T90: 12551.617 | U90: 12070.749 | V90: 13116.597 | W90: 13057.282 | X90: 12475.285 | Y90: 11137.495 | Z90: 9560.4882 | AA90: 8227.9163 | AB90: =SUM(D90:AA90)*C90 -> 5266242.6
A91: 47058 | B91: SÁBADO | C91: 4 | D91: 6989.017 | E91: 6803.2101 | F91: 6337.5546 | G91: 5961.848 | H91: 5956.613 | I91: 6110.7616 | J91: 6504.7613 | K91: 7905.8174 | L91: 9749.0151 | M91: 10870.092 | N91: 11586.221 | O91: 12319.85 | P91: 12655.719 | Q91: 12446.945 | R91: 12130.822 | S91: 11726.348 | T91: 11363.053 | U91: 11564.521 | V91: 12744.922 | W91: 12779.143 | X91: 12283.342 | Y91: 11243.418 | Z91: 10005.717 | AA91: 8764.7976 | AB91: =SUM(D91:AA91)*C91 -> 947214.03 | AC91: =+AB91+AB92+AB93 -> 7127709.9
B92: FESTIVO | C92: 4 | D92: 7649.1784 | E92: 7039.341 | F92: 6677.1212 | G92: 6376.9458 | H92: 6261.5442 | I92: 6305.9817 | J92: 6544.2107 | K92: 7580.4059 | L92: 8947.0276 | M92: 9795.811 | N92: 10276.19 | O92: 10903.208 | P92: 11243.961 | Q92: 10981.733 | R92: 10440.241 | S92: 10036.298 | T92: 9882.8895 | U92: 10024.687 | V92: 11625.616 | W92: 12015.387 | X92: 11424.288 | Y92: 10399.299 | Z92: 9199.0572 | AA92: 8109.8944 | AB92: =SUM(D92:AA92)*C92 -> 878961.27
B93: ORDINARIO | C93: 22 | D93: 7222.1583 | E93: 6676.5349 | F93: 6326.004 | G93: 6095.1798 | H93: 6079.8463 | I93: 6598.55 | J93: 7447.2215 | K93: 8696.9446 | L93: 10040.546 | M93: 10765.185 | N93: 11479.335 | O93: 12231.003 | P93: 12470.939 | Q93: 12383.501 | R93: 12619.901 | S93: 12358.833 | T93: 12003.097 | U93: 11852.296 | V93: 12986.86 | W93: 12833.504 | X93: 12432.35 | Y93: 11323.983 | Z93: 9720.8532 | AA93: 8334.2192 | AB93: =SUM(D93:AA93)*C93 -> 5301534.6
A94: 47088 | B94: SÁBADO | C94: 5 | D94: 7859.5327 | E94: 6950.1822 | F94: 6474.9091 | G94: 6161.1548 | H94: 6074.1415 | I94: 6413.2028 | J94: 6851.9783 | K94: 8525.6193 | L94: 10779.343 | M94: 12028.203 | N94: 12871.721 | O94: 13715.756 | P94: 13999.543 | Q94: 13943.064 | R94: 13475.341 | S94: 13089.809 | T94: 12760.883 | U94: 12705.815 | V94: 14443.214 | W94: 14688.39 | X94: 14027.96 | Y94: 12904.887 | Z94: 11322.438 | AA94: 9893.6891 | AB94: =SUM(D94:AA94)*C94 -> 1309803.9 | AC94: =+AB94+AB95+AB96 -> 8230558
B95: FESTIVO | C95: 5 | D95: 8754.2026 | E95: 7935.8508 | F95: 7364.3715 | G95: 6911.334 | H95: 6711.7138 | I95: 6815.0914 | J95: 6841.6675 | K95: 8101.2778 | L95: 9688.8394 | M95: 11021.885 | N95: 11685.564 | O95: 12664.517 | P95: 13153.158 | Q95: 13167.529 | R95: 12602.072 | S95: 12013.447 | T95: 11738.984 | U95: 11635.231 | V95: 13586.765 | W95: 14196.676 | X95: 13256.864 | Y95: 12003.198 | Z95: 11058.527 | AA95: 9678.7193 | AB95: =SUM(D95:AA95)*C95 -> 1262937.4
B96: ORDINARIO | C96: 21 | D96: 8178.7793 | E96: 7326.0591 | F96: 6784.8753 | G96: 6399.1058 | H96: 6306.3291 | I96: 6683.7296 | J96: 7438.1337 | K96: 9250.3878 | L96: 11408.149 | M96: 12177.562 | N96: 12646.2 | O96: 13550.261 | P96: 13629.256 | Q96: 13722.623 | R96: 13732.265 | S96: 13763.865 | T96: 13489.245 | U96: 13314.636 | V96: 15203.512 | W96: 15387.08 | X96: 14650.675 | Y96: 13198.08 | Z96: 11433.205 | AA96: 9745.8318 | AB96: =SUM(D96:AA96)*C96 -> 5657816.7
A99: Mes | B99: Tipo de día | C99: No. de Días | D99: HORA 01 | E99: HORA 02 | F99: HORA 03 | G99: HORA 04 | H99: HORA 05 | I99: HORA 06 | J99: HORA 07 | K99: HORA 08 | L99: HORA 09 | M99: HORA 10 | N99: HORA 11 | O99: HORA 12 | P99: HORA 13 | Q99: HORA 14 | R99: HORA 15 | S99: HORA 16 | T99: HORA 17 | U99: HORA 18 | V99: HORA 19 | W99: HORA 20 | X99: HORA 21 | Y99: HORA 22 | Z99: HORA 23 | AA99: HORA 24 | AB99: Total
A100: 47119 | B100: SÁBADO | C100: 4 | D100: 5618.6882 | E100: 4778.3263 | F100: 4257.7302 | G100: 3774.6866 | H100: 3712.8783 | I100: 3889.4929 | J100: 4244.582 | K100: 5929.0038 | L100: 8464.6162 | M100: 10010.959 | N100: 10918.974 | O100: 12229.135 | P100: 12619.546 | Q100: 12210.84 | R100: 11667.453 | S100: 11782.442 | T100: 11380.015 | U100: 11092.778 | V100: 12463.425 | W100: 13425.796 | X100: 12820.986 | Y100: 11423.797 | Z100: 9491.7192 | AA100: 7669.692 | AB100: =SUM(D100:AA100)*C100 -> 863510.24 | AC100: =+AB100+AB101+AB102 -> 6809640.7 | AF100: 47119 | AG100: =AC100 -> 6809640.7
B101: FESTIVO | C101: 6 | D101: 5962.7848 | E101: 5150.2862 | F101: 4407.1582 | G101: 4008.6665 | H101: 3651.4271 | I101: 3616.15 | J101: 3688.2961 | K101: 4761.6475 | L101: 6581.4402 | M101: 7819.1722 | N101: 8448.1447 | O101: 9486.877 | P101: 10140.795 | Q101: 10086.252 | R101: 9225.0116 | S101: 8847.5554 | T101: 8563.0065 | U101: 8413.9657 | V101: 10522.467 | W101: 11899.574 | X101: 11311.717 | Y101: 9718.4613 | Z101: 7986.7578 | AA101: 6335.5941 | AB101: =SUM(D101:AA101)*C101 -> 1083799.2 | AF101: 47150 | AG101: =AC103 -> 5723692.4
B102: ORDINARIO | C102: 21 | D102: 6049.5169 | E102: 5094.4293 | F102: 4542.9638 | G102: 4215.6677 | H102: 4168.9583 | I102: 4710.4562 | J102: 5488.8371 | K102: 7075.3232 | L102: 9486.216 | M102: 10463.633 | N102: 11344.173 | O102: 12683.16 | P102: 13110.609 | Q102: 13061.902 | R102: 13079.565 | S102: 12977.648 | T102: 12586.746 | U102: 12121.162 | V102: 12994.608 | W102: 13922.188 | X102: 13252.3 | Y102: 11812.565 | Z102: 9670.1107 | AA102: 7626.8411 | AB102: =SUM(D102:AA102)*C102 -> 4862331.2 | AF102: 47178 | AG102: =AC106 -> 7092058.5
A103: 47150 | B103: SÁBADO | C103: 4 | D103: 5002.0644 | E103: 4052.8779 | F103: 3600.1028 | G103: 3108.004 | H103: 3000.5128 | I103: 3172.3669 | J103: 3792.8887 | K103: 5587.9018 | L103: 8146.2199 | M103: 9233.3789 | N103: 10017.739 | O103: 11066.048 | P103: 11330.844 | Q103: 11554.787 | R103: 11249.131 | S103: 9933.1894 | T103: 10212.78 | U103: 10128.013 | V103: 11434.372 | W103: 12314.026 | X103: 11874.41 | Y103: 10370.379 | Z103: 8345.9657 | AA103: 6655.0873 | AB103: =SUM(D103:AA103)*C103 -> 780732.36 | AC103: =+AB103+AB104+AB105 -> 5723692.4 | AF103: 47209 | AG103: =AC109 -> 6778314
B104: FESTIVO | C104: 4 | D104: 5393.6101 | E104: 4651.4042 | F104: 3929.8293 | G104: 3541.6442 | H104: 3354.0514 | I104: 3492.4522 | J104: 3739.649 | K104: 5096.3688 | L104: 7031.5118 | M104: 8178.8804 | N104: 8892.4854 | O104: 9955.8143 | P104: 10912.748 | Q104: 10797.83 | R104: 9884.1867 | S104: 9367.4193 | T104: 8741.2463 | U104: 8860.2492 | V104: 10659.222 | W104: 10893.471 | X104: 10894.475 | Y104: 9637.7668 | Z104: 7898.9833 | AA104: 5960.4619 | AB104: =SUM(D104:AA104)*C104 -> 727063.05 | AF104: 47239 | AG104: =AC112 -> 7580413.9
B105: ORDINARIO | C105: 20 | D105: 4839.8169 | E105: 4095.1015 | F105: 3610.3213 | G105: 3153.1097 | H105: 3213.7057 | I105: 4393.4049 | J105: 5678.8648 | K105: 6839.296 | L105: 8608.1131 | M105: 9364.4723 | N105: 10552.941 | O105: 11727.28 | P105: 12005.135 | Q105: 11836.809 | R105: 12128.268 | S105: 12150.992 | T105: 11951.961 | U105: 11324.836 | V105: 12302.498 | W105: 13197.503 | X105: 12534.6 | Y105: 10779.518 | Z105: 8426.1369 | AA105: 6080.1655 | AB105: =SUM(D105:AA105)*C105 -> 4215897 | AF105: 47270 | AG105: =AC115 -> 7278300.6
A106: 47178 | B106: SÁBADO | C106: 5 | D106: 6077.7055 | E106: 5108.6053 | F106: 4519.3325 | G106: 4067.2426 | H106: 4004.4724 | I106: 4287.0425 | J106: 4932.709 | K106: 6727.0455 | L106: 9327.5516 | M106: 10719.134 | N106: 11793.833 | O106: 13219.325 | P106: 13680.241 | Q106: 13646.871 | R106: 13556.127 | S106: 13266.524 | T106: 12421.277 | U106: 12020.557 | V106: 13265.046 | W106: 14364.25 | X106: 13717.264 | Y106: 12438.524 | Z106: 10490.873 | AA106: 8719.2928 | AB106: =SUM(D106:AA106)*C106 -> 1181854.2 | AC106: =+AB106+AB107+AB108 -> 7092058.5 | AF106: 47300 | AG106: =AC118 -> 7391065.4
B107: FESTIVO | C107: 7 | D107: 7226.8474 | E107: 6232.0449 | F107: 5479.8942 | G107: 4852.5544 | H107: 4450.2664 | I107: 4604.7433 | J107: 4631.8748 | K107: 6075.9266 | L107: 7597.0127 | M107: 8736.6694 | N107: 9790.4347 | O107: 10874.366 | P107: 11792.158 | Q107: 11618.804 | R107: 10677.388 | S107: 10108.693 | T107: 9680.3736 | U107: 9516.0845 | V107: 11207.966 | W107: 12897.938 | X107: 12479.373 | Y107: 11031.036 | Z107: 8853.7487 | AA107: 6969.8985 | AB107: =SUM(D107:AA107)*C107 -> 1451702.7 | AF107: 47331 | AG107: =AC121 -> 7218033.1
...
