Workbook

Sheet Producto No. 1 Plana 2025-2033
A5: ANEXO No. 1. Oferta Producto No. 1 Curva Plana (agosto de 2025 a diciembre año 2033) Convocatoria Pública DISPAC S.A. E.S.P.
A8: PROPONENTE
A10: MES | B10: DEMANDA REQUERIDA DISPAC KWh | C10: DEMANDA PERIODO REQUERIDA DISPAC KWh | D10: PORCENTAJE (%) OFERTADO DE LA DEMANDA REQUERIDA | E10: DEMANDA OFERTADA KWh - MES | F10: DEMANDA PERIODO OFERTADA KWh | G10: PRECIO OFERTADO $ kWh (0.00)
A11: AGOSTO DE 2025 | B11: =+'Despacho Horario Producto No. 1'!AD2 -> 550800 | C11: =+SUM(B11:B15) -> 10213200 | E11: =+$D$11*B11 -> 0 | F11: =+SUM(E11:E15) -> 0
A12: SEPTIEMBRE DE 2025 | B12: =+'Despacho Horario Producto No. 1'!AD5 -> 2376000 | E12: =+$D$11*B12 -> 0
A13: OCTUBRE DE 2025 | B13: =+'Despacho Horario Producto No. 1'!AD8 -> 2455200 | E13: =+$D$11*B13 -> 0
A14: NOVIEMBRE DE 2025 | B14: =+'Despacho Horario Producto No. 1'!AD11 -> 2376000 | E14: =+$D$11*B14 -> 0
A15: DICIEMBRE DE 2025 | B15: =+'Despacho Horario Producto No. 1'!AD14 -> 2455200 | E15: =+$D$11*B15 -> 0
A16: ENERO DE 2026 | B16: ='Despacho Horario Producto No. 1'!AD17 -> 9672000 | C16: =SUM(B16:B27) -> 113880000 | E16: =+$D$11*B16 -> 0 | F16: =SUM(E16:E27) -> 0
A17: FEBRERO DE 2026 | B17: ='Despacho Horario Producto No. 1'!AD20 -> 8736000 | E17: =+$D$11*B17 -> 0
A18: MARZO DE 2026 | B18: ='Despacho Horario Producto No. 1'!AD23 -> 9672000 | E18: =+$D$11*B18 -> 0
A19: ABRIL DE 2026 | B19: ='Despacho Horario Producto No. 1'!AD26 -> 9360000 | E19: =+$D$11*B19 -> 0
A20: MAYO DE 2026 | B20: ='Despacho Horario Producto No. 1'!AD29 -> 9672000 | E20: =+$D$11*B20 -> 0
A21: JUNIO DE 2026 | B21: ='Despacho Horario Producto No. 1'!AD32 -> 9360000 | E21: =+$D$11*B21 -> 0
A22: JULIO DE 2026 | B22: ='Despacho Horario Producto No. 1'!AD35 -> 9672000 | E22: =+$D$11*B22 -> 0
A23: AGOSTO DE 2026 | B23: ='Despacho Horario Producto No. 1'!AD38 -> 9672000 | E23: =+$D$11*B23 -> 0
A24: SEPTIEMBRE DE 2026 | B24: ='Despacho Horario Producto No. 1'!AD41 -> 9360000 | E24: =+$D$11*B24 -> 0
A25: OCTUBRE DE 2026 | B25: ='Despacho Horario Producto No. 1'!AD44 -> 9672000 | E25: =+$D$11*B25 -> 0
A26: NOVIEMBRE DE 2026 | B26: ='Despacho Horario Producto No. 1'!AD47 -> 9360000 | E26: =+$D$11*B26 -> 0
A27: DICIEMBRE DE 2026 | B27: ='Despacho Horario Producto No. 1'!AD50 -> 9672000 | E27: =+$D$11*B27 -> 0
A28: ENERO DE 2027 | B28: ='Despacho Horario Producto No. 1'!AD53 -> 9672000 | C28: =SUM(B28:B39) -> 113880000 | E28: =+$D$11*B28 -> 0 | F28: =SUM(E28:E39) -> 0
A29: FEBRERO DE 2027 | B29: ='Despacho Horario Producto No. 1'!AD56 -> 8736000 | E29: =+$D$11*B29 -> 0
A30: MARZO DE 2027 | B30: ='Despacho Horario Producto No. 1'!AD59 -> 9672000 | E30: =+$D$11*B30 -> 0
A31: ABRIL DE 2027 | B31: ='Despacho Horario Producto No. 1'!AD62 -> 9360000 | E31: =+$D$11*B31 -> 0
A32: MAYO DE 2027 | B32: ='Despacho Horario Producto No. 1'!AD65 -> 9672000 | E32: =+$D$11*B32 -> 0
A33: JUNIO DE 2027 | B33: ='Despacho Horario Producto No. 1'!AD68 -> 9360000 | E33: =+$D$11*B33 -> 0
A34: JULIO DE 2027 | B34: ='Despacho Horario Producto No. 1'!AD71 -> 9672000 | E34: =+$D$11*B34 -> 0
A35: AGOSTO DE 2027 | B35: ='Despacho Horario Producto No. 1'!AD74 -> 9672000 | E35: =+$D$11*B35 -> 0
A36: SEPTIEMBRE DE 2027 | B36: ='Despacho Horario Producto No. 1'!AD77 -> 9360000 | E36: =+$D$11*B36 -> 0
A37: OCTUBRE DE 2027 | B37: ='Despacho Horario Producto No. 1'!AD80 -> 9672000 | E37: =+$D$11*B37 -> 0
A38: NOVIEMBRE DE 2027 | B38: ='Despacho Horario Producto No. 1'!AD83 -> 9360000 | E38: =+$D$11*B38 -> 0
A39: DICIEMBRE DE 2027 | B39: ='Despacho Horario Producto No. 1'!AD86 -> 9672000 | E39: =+$D$11*B39 -> 0
A40: ENERO DE 2028 | B40: ='Despacho Horario Producto No. 1'!AD89 -> 9672000 | C40: =SUM(B40:B51) -> 114192000 | E40: =+$D$11*B40 -> 0 | F40: =SUM(E40:E51) -> 0
A41: FEBRERO DE 2028 | B41: ='Despacho Horario Producto No. 1'!AD92 -> 9048000 | E41: =+$D$11*B41 -> 0
A42: MARZO DE 2028 | B42: ='Despacho Horario Producto No. 1'!AD95 -> 9672000 | E42: =+$D$11*B42 -> 0
A43: ABRIL DE 2028 | B43: ='Despacho Horario Producto No. 1'!AD98 -> 9360000 | E43: =+$D$11*B43 -> 0
A44: MAYO DE 2028 | B44: ='Despacho Horario Producto No. 1'!AD101 -> 9672000 | E44: =+$D$11*B44 -> 0
A45: JUNIO DE 2028 | B45: ='Despacho Horario Producto No. 1'!AD104 -> 9360000 | E45: =+$D$11*B45 -> 0
A46: JULIO DE 2028 | B46: ='Despacho Horario Producto No. 1'!AD107 -> 9672000 | E46: =+$D$11*B46 -> 0
A47: AGOSTO DE 2028 | B47: ='Despacho Horario Producto No. 1'!AD110 -> 9672000 | E47: =+$D$11*B47 -> 0
A48: SEPTIEMBRE DE 2028 | B48: ='Despacho Horario Producto No. 1'!AD113 -> 9360000 | E48: =+$D$11*B48 -> 0
A49: OCTUBRE DE 2028 | B49: ='Despacho Horario Producto No. 1'!AD116 -> 9672000 | E49: =+$D$11*B49 -> 0
A50: NOVIEMBRE DE 2028 | B50: ='Despacho Horario Producto No. 1'!AD119 -> 9360000 | E50: =+$D$11*B50 -> 0
A51: DICIEMBRE DE 2028 | B51: ='Despacho Horario Producto No. 1'!AD122 -> 9672000 | E51: =+$D$11*B51 -> 0
A52: ENERO DE 2029 | B52: ='Despacho Horario Producto No. 1'!AD125 -> 9672000 | C52: =SUM(B52:B63) -> 113880000 | E52: =+$D$11*B52 -> 0 | F52: =SUM(E52:E63) -> 0
A53: FEBRERO DE 2029 | B53: ='Despacho Horario Producto No. 1'!AD128 -> 8736000 | E53: =+$D$11*B53 -> 0
A54: MARZO DE 2029 | B54: ='Despacho Horario Producto No. 1'!AD131 -> 9672000 | E54: =+$D$11*B54 -> 0
A55: ABRIL DE 2029 | B55: ='Despacho Horario Producto No. 1'!AD134 -> 9360000 | E55: =+$D$11*B55 -> 0
A56: MAYO DE 2029 | B56: ='Despacho Horario Producto No. 1'!AD137 -> 9672000 | E56: =+$D$11*B56 -> 0
A57: JUNIO DE 2029 | B57: ='Despacho Horario Producto No. 1'!AD140 -> 9360000 | E57: =+$D$11*B57 -> 0
A58: JULIO DE 2029 | B58: ='Despacho Horario Producto No. 1'!AD143 -> 9672000 | E58: =+$D$11*B58 -> 0
A59: AGOSTO DE 2029 | B59: ='Despacho Horario Producto No. 1'!AD146 -> 9672000 | E59: =+$D$11*B59 -> 0
A60: SEPTIEMBRE DE 2029 | B60: ='Despacho Horario Producto No. 1'!AD149 -> 9360000 | E60: =+$D$11*B60 -> 0
A61: OCTUBRE DE 2029 | B61: ='Despacho Horario Producto No. 1'!AD152 -> 9672000 | E61: =+$D$11*B61 -> 0
A62: NOVIEMBRE DE 2029 | B62: ='Despacho Horario Producto No. 1'!AD155 -> 9360000 | E62: =+$D$11*B62 -> 0
A63: DICIEMBRE DE 2029 | B63: ='Despacho Horario Producto No. 1'!AD158 -> 9672000 | E63: =+$D$11*B63 -> 0
A64: ENERO DE 2030 | B64: ='Despacho Horario Producto No. 1'!AD161 -> 9672000 | C64: =SUM(B64:B75) -> 113880000 | E64: =+$D$11*B64 -> 0 | F64: =SUM(E64:E75) -> 0
A65: FEBRERO DE 2030 | B65: ='Despacho Horario Producto No. 1'!AD164 -> 8736000 | E65: =+$D$11*B65 -> 0
A66: MARZO DE 2030 | B66: ='Despacho Horario Producto No. 1'!AD167 -> 9672000 | E66: =+$D$11*B66 -> 0
A67: ABRIL DE 2030 | B67: ='Despacho Horario Producto No. 1'!AD170 -> 9360000 | E67: =+$D$11*B67 -> 0
A68: MAYO DE 2030 | B68: ='Despacho Horario Producto No. 1'!AD173 -> 9672000 | E68: =+$D$11*B68 -> 0
A69: JUNIO DE 2030 | B69: ='Despacho Horario Producto No. 1'!AD176 -> 9360000 | E69: =+$D$11*B69 -> 0
A70: JULIO DE 2030 | B70: ='Despacho Horario Producto No. 1'!AD179 -> 9672000 | E70: =+$D$11*B70 -> 0
A71: AGOSTO DE 2030 | B71: ='Despacho Horario Producto No. 1'!AD182 -> 9672000 | E71: =+$D$11*B71 -> 0
A72: SEPTIEMBRE DE 2030 | B72: ='Despacho Horario Producto No. 1'!AD185 -> 9360000 | E72: =+$D$11*B72 -> 0
A73: OCTUBRE DE 2030 | B73: ='Despacho Horario Producto No. 1'!AD188 -> 9672000 | E73: =+$D$11*B73 -> 0
A74: NOVIEMBRE DE 2030 | B74: ='Despacho Horario Producto No. 1'!AD191 -> 9360000 | E74: =+$D$11*B74 -> 0
A75: DICIEMBRE DE 2030 | B75: ='Despacho Horario Producto No. 1'!AD194 -> 9672000 | E75: =+$D$11*B75 -> 0
A76: ENERO DE 2031 | B76: ='Despacho Horario Producto No. 1'!AD197 -> 9672000 | C76: =SUM(B76:B87) -> 113880000 | E76: =+$D$11*B76 -> 0 | F76: =SUM(E76:E87) -> 0
A77: FEBRERO DE 2031 | B77: ='Despacho Horario Producto No. 1'!AD200 -> 8736000 | E77: =+$D$11*B77 -> 0
A78: MARZO DE 2031 | B78: ='Despacho Horario Producto No. 1'!AD203 -> 9672000 | E78: =+$D$11*B78 -> 0
A79: ABRIL DE 2031 | B79: ='Despacho Horario Producto No. 1'!AD206 -> 9360000 | E79: =+$D$11*B79 -> 0
A80: MAYO DE 2031 | B80: ='Despacho Horario Producto No. 1'!AD209 -> 9672000 | E80: =+$D$11*B80 -> 0
A81: JUNIO DE 2031 | B81: ='Despacho Horario Producto No. 1'!AD212 -> 9360000 | E81: =+$D$11*B81 -> 0
A82: JULIO DE 2031 | B82: ='Despacho Horario Producto No. 1'!AD215 -> 9672000 | E82: =+$D$11*B82 -> 0
A83: AGOSTO DE 2031 | B83: ='Despacho Horario Producto No. 1'!AD218 -> 9672000 | E83: =+$D$11*B83 -> 0
A84: SEPTIEMBRE DE 2031 | B84: ='Despacho Horario Producto No. 1'!AD221 -> 9360000 | E84: =+$D$11*B84 -> 0
A85: OCTUBRE DE 2031 | B85: ='Despacho Horario Producto No. 1'!AD224 -> 9672000 | E85: =+$D$11*B85 -> 0
A86: NOVIEMBRE DE 2031 | B86: ='Despacho Horario Producto No. 1'!AD227 -> 9360000 | E86: =+$D$11*B86 -> 0
A87: DICIEMBRE DE 2031 | B87: ='Despacho Horario Producto No. 1'!AD230 -> 9672000 | E87: =+$D$11*B87 -> 0
A88: ENERO DE 2032 | B88: ='Despacho Horario Producto No. 1'!AD233 -> 9672000 | C88: =SUM(B88:B99) -> 114192000 | E88: =+$D$11*B88 -> 0 | F88: =SUM(E88:E99) -> 0
A89: FEBRERO DE 2032 | B89: ='Despacho Horario Producto No. 1'!AD236 -> 9048000 | E89: =+$D$11*B89 -> 0
A90: MARZO DE 2032 | B90: ='Despacho Horario Producto No. 1'!AD239 -> 9672000 | E90: =+$D$11*B90 -> 0
A91: ABRIL DE 2032 | B91: ='Despacho Horario Producto No. 1'!AD242 -> 9360000 | E91: =+$D$11*B91 -> 0
A92: MAYO DE 2032 | B92: ='Despacho Horario Producto No. 1'!AD245 -> 9672000 | E92: =+$D$11*B92 -> 0
A93: JUNIO DE 2032 | B93: ='Despacho Horario Producto No. 1'!AD248 -> 9360000 | E93: =+$D$11*B93 -> 0
A94: JULIO DE 2032 | B94: ='Despacho Horario Producto No. 1'!AD251 -> 9672000 | E94: =+$D$11*B94 -> 0
A95: AGOSTO DE 2032 | B95: ='Despacho Horario Producto No. 1'!AD254 -> 9672000 | E95: =+$D$11*B95 -> 0
A96: SEPTIEMBRE DE 2032 | B96: ='Despacho Horario Producto No. 1'!AD257 -> 9360000 | E96: =+$D$11*B96 -> 0
A97: OCTUBRE DE 2032 | B97: ='Despacho Horario Producto No. 1'!AD260 -> 9672000 | E97: =+$D$11*B97 -> 0
A98: NOVIEMBRE DE 2032 | B98: ='Despacho Horario Producto No. 1'!AD263 -> 9360000 | E98: =+$D$11*B98 -> 0
A99: DICIEMBRE DE 2032 | B99: ='Despacho Horario Producto No. 1'!AD266 -> 9672000 | E99: =+$D$11*B99 -> 0
A100: ENERO DE 2033 | B100: ='Despacho Horario Producto No. 1'!AD269 -> 9672000 | C100: =SUM(B100:B111) -> 113880000 | E100: =+$D$11*B100 -> 0 | F100: =SUM(E100:E111) -> 0
A101: FEBRERO DE 2033 | B101: ='Despacho Horario Producto No. 1'!AD272 -> 8736000 | E101: =+$D$11*B101 -> 0
A102: MARZO DE 2033 | B102: ='Despacho Horario Producto No. 1'!AD275 -> 9672000 | E102: =+$D$11*B102 -> 0
A103: ABRIL DE 2033 | B103: ='Despacho Horario Producto No. 1'!AD278 -> 9360000 | E103: =+$D$11*B103 -> 0
A104: MAYO DE 2033 | B104: ='Despacho Horario Producto No. 1'!AD281 -> 9672000 | E104: =+$D$11*B104 -> 0
A105: JUNIO DE 2033 | B105: ='Despacho Horario Producto No. 1'!AD284 -> 9360000 | E105: =+$D$11*B105 -> 0
A106: JULIO DE 2033 | B106: ='Despacho Horario Producto No. 1'!AD287 -> 9672000 | E106: =+$D$11*B106 -> 0
A107: AGOSTO DE 2033 | B107: ='Despacho Horario Producto No. 1'!AD290 -> 9672000 | E107: =+$D$11*B107 -> 0
...

Sheet Despacho Horario Producto No. 1
A1: Año | B1: Mes | C1: # días | D1: TPD | E1: H1 | F1: H2 | G1: H3 | H1: H4 | I1: H5 | J1: H6 | K1: H7 | L1: H8 | M1: H9 | N1: H10 | O1: H11 | P1: H12 | Q1: H13 | R1: H14 | S1: H15 | T1: H16 | U1: H17 | V1: H18 | W1: H19 | X1: H20 | Y1: H21 | Z1: H22 | AA1: H23 | AB1: H24 | AC1: kWh/d | AD1: kWh/mes
A2: 2025 | B2: 8 | C2: 4 | D2: Festivo | E2: 1350 | F2: 1350 | G2: 1350 | H2: 1350 | I2: 1350 | J2: 1350 | K2: 1350 | L2: 1350 | M2: 1350 | N2: 1350 | O2: 1350 | P2: 1350 | Q2: 1350 | R2: 1350 | S2: 1350 | T2: 1350 | U2: 1350 | V2: 1350 | W2: 1350 | X2: 1350 | Y2: 1350 | Z2: 1350 | AA2: 1350 | AB2: 1350 | AC2: =+SUM(E2:AB2) -> 32400 | AD2: =+SUMPRODUCT(AC2:AC4,C2:C4) -> 550800
A3: 2025 | B3: 8 | C3: 10 | D3: Hábil | E3: 1350 | F3: 1350 | G3: 1350 | H3: 1350 | I3: 1350 | J3: 1350 | K3: 1350 | L3: 1350 | M3: 1350 | N3: 1350 | O3: 1350 | P3: 1350 | Q3: 1350 | R3: 1350 | S3: 1350 | T3: 1350 | U3: 1350 | V3: 1350 | W3: 1350 | X3: 1350 | Y3: 1350 | Z3: 1350 | AA3: 1350 | AB3: 1350 | AC3: =+SUM(E3:AB3) -> 32400
A4: 2025 | B4: 8 | C4: 3 | D4: Sábado | E4: 1350 | F4: 1350 | G4: 1350 | H4: 1350 | I4: 1350 | J4: 1350 | K4: 1350 | L4: 1350 | M4: 1350 | N4: 1350 | O4: 1350 | P4: 1350 | Q4: 1350 | R4: 1350 | S4: 1350 | T4: 1350 | U4: 1350 | V4: 1350 | W4: 1350 | X4: 1350 | Y4: 1350 | Z4: 1350 | AA4: 1350 | AB4: 1350 | AC4: =+SUM(E4:AB4) -> 32400
A5: 2025 | B5: 9 | C5: 4 | D5: Festivo | E5: 3300 | F5: 3300 | G5: 3300 | H5: 3300 | I5: 3300 | J5: 3300 | K5: 3300 | L5: 3300 | M5: 3300 | N5: 3300 | O5: 3300 | P5: 3300 | Q5: 3300 | R5: 3300 | S5: 3300 | T5: 3300 | U5: 3300 | V5: 3300 | W5: 3300 | X5: 3300 | Y5: 3300 | Z5: 3300 | AA5: 3300 | AB5: 3300 | AC5: =+SUM(E5:AB5) -> 79200 | AD5: =+SUMPRODUCT(AC5:AC7,C5:C7) -> 2376000
A6: 2025 | B6: 9 | C6: 22 | D6: Hábil | E6: 3300 | F6: 3300 | G6: 3300 | H6: 3300 | I6: 3300 | J6: 3300 | K6: 3300 | L6: 3300 | M6: 3300 | N6: 3300 | O6: 3300 | P6: 3300 | Q6: 3300 | R6: 3300 | S6: 3300 | T6: 3300 | U6: 3300 | V6: 3300 | W6: 3300 | X6: 3300 | Y6: 3300 | Z6: 3300 | AA6: 3300 | AB6: 3300 | AC6: =+SUM(E6:AB6) -> 79200
A7: 2025 | B7: 9 | C7: 4 | D7: Sábado | E7: 3300 | F7: 3300 | G7: 3300 | H7: 3300 | I7: 3300 | J7: 3300 | K7: 3300 | L7: 3300 | M7: 3300 | N7: 3300 | O7: 3300 | P7: 3300 | Q7: 3300 | R7: 3300 | S7: 3300 | T7: 3300 | U7: 3300 | V7: 3300 | W7: 3300 | X7: 3300 | Y7: 3300 | Z7: 3300 | AA7: 3300 | AB7: 3300 | AC7: =+SUM(E7:AB7) -> 79200
A8: 2025 | B8: 10 | C8: 5 | D8: Festivo | E8: 3300 | F8: 3300 | G8: 3300 | H8: 3300 | I8: 3300 | J8: 3300 | K8: 3300 | L8: 3300 | M8: 3300 | N8: 3300 | O8: 3300 | P8: 3300 | Q8: 3300 | R8: 3300 | S8: 3300 | T8: 3300 | U8: 3300 | V8: 3300 | W8: 3300 | X8: 3300 | Y8: 3300 | Z8: 3300 | AA8: 3300 | AB8: 3300 | AC8: =+SUM(E8:AB8) -> 79200 | AD8: =+SUMPRODUCT(AC8:AC10,C8:C10) -> 2455200
A9: 2025 | B9: 10 | C9: 22 | D9: Hábil | E9: 3300 | F9: 3300 | G9: 3300 | H9: 3300 | I9: 3300 | J9: 3300 | K9: 3300 | L9: 3300 | M9: 3300 | N9: 3300 | O9: 3300 | P9: 3300 | Q9: 3300 | R9: 3300 | S9: 3300 | T9: 3300 | U9: 3300 | V9: 3300 | W9: 3300 | X9: 3300 | Y9: 3300 | Z9: 3300 | AA9: 3300 | AB9: 3300 | AC9: =+SUM(E9:AB9) -> 79200
A10: 2025 | B10: 10 | C10: 4 | D10: Sábado | E10: 3300 | F10: 3300 | G10: 3300 | H10: 3300 | I10: 3300 | J10: 3300 | K10: 3300 | L10: 3300 | M10: 3300 | N10: 3300 | O10: 3300 | P10: 3300 | Q10: 3300 | R10: 3300 | S10: 3300 | T10: 3300 | U10: 3300 | V10: 3300 | W10: 3300 | X10: 3300 | Y10: 3300 | Z10: 3300 | AA10: 3300 | AB10: 3300 | AC10: =+SUM(E10:AB10) -> 79200
A11: 2025 | B11: 11 | C11: 7 | D11: Festivo | E11: 3300 | F11: 3300 | G11: 3300 | H11: 3300 | I11: 3300 | J11: 3300 | K11: 3300 | L11: 3300 | M11: 3300 | N11: 3300 | O11: 3300 | P11: 3300 | Q11: 3300 | R11: 3300 | S11: 3300 | T11: 3300 | U11: 3300 | V11: 3300 | W11: 3300 | X11: 3300 | Y11: 3300 | Z11: 3300 | AA11: 3300 | AB11: 3300 | AC11: =+SUM(E11:AB11) -> 79200 | AD11: =+SUMPRODUCT(AC11:AC13,C11:C13) -> 2376000
A12: 2025 | B12: 11 | C12: 18 | D12: Hábil | E12: 3300 | F12: 3300 | G12: 3300 | H12: 3300 | I12: 3300 | J12: 3300 | K12: 3300 | L12: 3300 | M12: 3300 | N12: 3300 | O12: 3300 | P12: 3300 | Q12: 3300 | R12: 3300 | S12: 3300 | T12: 3300 | U12: 3300 | V12: 3300 | W12: 3300 | X12: 3300 | Y12: 3300 | Z12: 3300 | AA12: 3300 | AB12: 3300 | AC12: =+SUM(E12:AB12) -> 79200
A13: 2025 | B13: 11 | C13: 5 | D13: Sábado | E13: 3300 | F13: 3300 | G13: 3300 | H13: 3300 | I13: 3300 | J13: 3300 | K13: 3300 | L13: 3300 | M13: 3300 | N13: 3300 | O13: 3300 | P13: 3300 | Q13: 3300 | R13: 3300 | S13: 3300 | T13: 3300 | U13: 3300 | V13: 3300 | W13: 3300 | X13: 3300 | Y13: 3300 | Z13: 3300 | AA13: 3300 | AB13: 3300 | AC13: =+SUM(E13:AB13) -> 79200
A14: 2025 | B14: 12 | C14: 6 | D14: Festivo | E14: 3300 | F14: 3300 | G14: 3300 | H14: 3300 | I14: 3300 | J14: 3300 | K14: 3300 | L14: 3300 | M14: 3300 | N14: 3300 | O14: 3300 | P14: 3300 | Q14: 3300 | R14: 3300 | S14: 3300 | T14: 3300 | U14: 3300 | V14: 3300 | W14: 3300 | X14: 3300 | Y14: 3300 | Z14: 3300 | AA14: 3300 | AB14: 3300 | AC14: =+SUM(E14:AB14) -> 79200 | AD14: =+SUMPRODUCT(AC14:AC16,C14:C16) -> 2455200
A15: 2025 | B15: 12 | C15: 21 | D15: Hábil | E15: 3300 | F15: 3300 | G15: 3300 | H15: 3300 | I15: 3300 | J15: 3300 | K15: 3300 | L15: 3300 | M15: 3300 | N15: 3300 | O15: 3300 | P15: 3300 | Q15: 3300 | R15: 3300 | S15: 3300 | T15: 3300 | U15: 3300 | V15: 3300 | W15: 3300 | X15: 3300 | Y15: 3300 | Z15: 3300 | AA15: 3300 | AB15: 3300 | AC15: =+SUM(E15:AB15) -> 79200
A16: 2025 | B16: 12 | C16: 4 | D16: Sábado | E16: 3300 | F16: 3300 | G16: 3300 | H16: 3300 | I16: 3300 | J16: 3300 | K16: 3300 | L16: 3300 | M16: 3300 | N16: 3300 | O16: 3300 | P16: 3300 | Q16: 3300 | R16: 3300 | S16: 3300 | T16: 3300 | U16: 3300 | V16: 3300 | W16: 3300 | X16: 3300 | Y16: 3300 | Z16: 3300 | AA16: 3300 | AB16: 3300 | AC16: =+SUM(E16:AB16) -> 79200
A17: 2026 | B17: 1 | C17: 6 | D17: Festivo | E17: 13000 | F17: 13000 | G17: 13000 | H17: 13000 | I17: 13000 | J17: 13000 | K17: 13000 | L17: 13000 | M17: 13000 | N17: 13000 | O17: 13000 | P17: 13000 | Q17: 13000 | R17: 13000 | S17: 13000 | T17: 13000 | U17: 13000 | V17: 13000 | W17: 13000 | X17: 13000 | Y17: 13000 | Z17: 13000 | AA17: 13000 | AB17: 13000 | AC17: =+SUM(E17:AB17) -> 312000 | AD17: =+SUMPRODUCT(AC17:AC19,C17:C19) -> 9672000
A18: 2026 | B18: 1 | C18: 20 | D18: Hábil | E18: 13000 | F18: 13000 | G18: 13000 | H18: 13000 | I18: 13000 | J18: 13000 | K18: 13000 | L18: 13000 | M18: 13000 | N18: 13000 | O18: 13000 | P18: 13000 | Q18: 13000 | R18: 13000 | S18: 13000 | T18: 13000 | U18: 13000 | V18: 13000 | W18: 13000 | X18: 13000 | Y18: 13000 | Z18: 13000 | AA18: 13000 | AB18: 13000 | AC18: =+SUM(E18:AB18) -> 312000
A19: 2026 | B19: 1 | C19: 5 | D19: Sábado | E19: 13000 | F19: 13000 | G19: 13000 | H19: 13000 | I19: 13000 | J19: 13000 | K19: 13000 | L19: 13000 | M19: 13000 | N19: 13000 | O19: 13000 | P19: 13000 | Q19: 13000 | R19: 13000 | S19: 13000 | T19: 13000 | U19: 13000 | V19: 13000 | W19: 13000 | X19: 13000 | Y19: 13000 | Z19: 13000 | AA19: 13000 | AB19: 13000 | AC19: =+SUM(E19:AB19) -> 312000
A20: 2026 | B20: 2 | C20: 4 | D20: Festivo | E20: 13000 | F20: 13000 | G20: 13000 | H20: 13000 | I20: 13000 | J20: 13000 | K20: 13000 | L20: 13000 | M20: 13000 | N20: 13000 | O20: 13000 | P20: 13000 | Q20: 13000 | R20: 13000 | S20: 13000 | T20: 13000 | U20: 13000 | V20: 13000 | W20: 13000 | X20: 13000 | Y20: 13000 | Z20: 13000 | AA20: 13000 | AB20: 13000 | AC20: =+SUM(E20:AB20) -> 312000 | AD20: =+SUMPRODUCT(AC20:AC22,C20:C22) -> 8736000
A21: 2026 | B21: 2 | C21: 20 | D21: Hábil | E21: 13000 | F21: 13000 | G21: 13000 | H21: 13000 | I21: 13000 | J21: 13000 | K21: 13000 | L21: 13000 | M21: 13000 | N21: 13000 | O21: 13000 | P21: 13000 | Q21: 13000 | R21: 13000 | S21: 13000 | T21: 13000 | U21: 13000 | V21: 13000 | W21: 13000 | X21: 13000 | Y21: 13000 | Z21: 13000 | AA21: 13000 | AB21: 13000 | AC21: =+SUM(E21:AB21) -> 312000
A22: 2026 | B22: 2 | C22: 4 | D22: Sábado | E22: 13000 | F22: 13000 | G22: 13000 | H22: 13000 | I22: 13000 | J22: 13000 | K22: 13000 | L22: 13000 | M22: 13000 | N22: 13000 | O22: 13000 | P22: 13000 | Q22: 13000 | R22: 13000 | S22: 13000 | T22: 13000 | U22: 13000 | V22: 13000 | W22: 13000 | X22: 13000 | Y22: 13000 | Z22: 13000 | AA22: 13000 | AB22: 13000 | AC22: =+SUM(E22:AB22) -> 312000
A23: 2026 | B23: 3 | C23: 6 | D23: Festivo | E23: 13000 | F23: 13000 | G23: 13000 | H23: 13000 | I23: 13000 | J23: 13000 | K23: 13000 | L23: 13000 | M23: 13000 | N23: 13000 | O23: 13000 | P23: 13000 | Q23: 13000 | R23: 13000 | S23: 13000 | T23: 13000 | U23: 13000 | V23: 13000 | W23: 13000 | X23: 13000 | Y23: 13000 | Z23: 13000 | AA23: 13000 | AB23: 13000 | AC23: =+SUM(E23:AB23) -> 312000 | AD23: =+SUMPRODUCT(AC23:AC25,C23:C25) -> 9672000
A24: 2026 | B24: 3 | C24: 21 | D24: Hábil | E24: 13000 | F24: 13000 | G24: 13000 | H24: 13000 | I24: 13000 | J24: 13000 | K24: 13000 | L24: 13000 | M24: 13000 | N24: 13000 | O24: 13000 | P24: 13000 | Q24: 13000 | R24: 13000 | S24: 13000 | T24: 13000 | U24: 13000 | V24: 13000 | W24: 13000 | X24: 13000 | Y24: 13000 | Z24: 13000 | AA24: 13000 | AB24: 13000 | AC24: =+SUM(E24:AB24) -> 312000
A25: 2026 | B25: 3 | C25: 4 | D25: Sábado | E25: 13000 | F25: 13000 | G25: 13000 | H25: 13000 | I25: 13000 | J25: 13000 | K25: 13000 | L25: 13000 | M25: 13000 | N25: 13000 | O25: 13000 | P25: 13000 | Q25: 13000 | R25: 13000 | S25: 13000 | T25: 13000 | U25: 13000 | V25: 13000 | W25: 13000 | X25: 13000 | Y25: 13000 | Z25: 13000 | AA25: 13000 | AB25: 13000 | AC25: =+SUM(E25:AB25) -> 312000
A26: 2026 | B26: 4 | C26: 6 | D26: Festivo | E26: 13000 | F26: 13000 | G26: 13000 | H26: 13000 | I26: 13000 | J26: 13000 | K26: 13000 | L26: 13000 | M26: 13000 | N26: 13000 | O26: 13000 | P26: 13000 | Q26: 13000 | R26: 13000 | S26: 13000 | T26: 13000 | U26: 13000 | V26: 13000 | W26: 13000 | X26: 13000 | Y26: 13000 | Z26: 13000 | AA26: 13000 | AB26: 13000 | AC26: =+SUM(E26:AB26) -> 312000 | AD26: =+SUMPRODUCT(AC26:AC28,C26:C28) -> 9360000
A27: 2026 | B27: 4 | C27: 20 | D27: Hábil | E27: 13000 | F27: 13000 | G27: 13000 | H27: 13000 | I27: 13000 | J27: 13000 | K27: 13000 | L27: 13000 | M27: 13000 | N27: 13000 | O27: 13000 | P27: 13000 | Q27: 13000 | R27: 13000 | S27: 13000 | T27: 13000 | U27: 13000 | V27: 13000 | W27: 13000 | X27: 13000 | Y27: 13000 | Z27: 13000 | AA27: 13000 | AB27: 13000 | AC27: =+SUM(E27:AB27) -> 312000
A28: 2026 | B28: 4 | C28: 4 | D28: Sábado | E28: 13000 | F28: 13000 | G28: 13000 | H28: 13000 | I28: 13000 | J28: 13000 | K28: 13000 | L28: 13000 | M28: 13000 | N28: 13000 | O28: 13000 | P28: 13000 | Q28: 13000 | R28: 13000 | S28: 13000 | T28: 13000 | U28: 13000 | V28: 13000 | W28: 13000 | X28: 13000 | Y28: 13000 | Z28: 13000 | AA28: 13000 | AB28: 13000 | AC28: =+SUM(E28:AB28) -> 312000
A29: 2026 | B29: 5 | C29: 7 | D29: Festivo | E29: 13000 | F29: 13000 | G29: 13000 | H29: 13000 | I29: 13000 | J29: 13000 | K29: 13000 | L29: 13000 | M29: 13000 | N29: 13000 | O29: 13000 | P29: 13000 | Q29: 13000 | R29: 13000 | S29: 13000 | T29: 13000 | U29: 13000 | V29: 13000 | W29: 13000 | X29: 13000 | Y29: 13000 | Z29: 13000 | AA29: 13000 | AB29: 13000 | AC29: =+SUM(E29:AB29) -> 312000 | AD29: =+SUMPRODUCT(AC29:AC31,C29:C31) -> 9672000
A30: 2026 | B30: 5 | C30: 19 | D30: Hábil | E30: 13000 | F30: 13000 | G30: 13000 | H30: 13000 | I30: 13000 | J30: 13000 | K30: 13000 | L30: 13000 | M30: 13000 | N30: 13000 | O30: 13000 | P30: 13000 | Q30: 13000 | R30: 13000 | S30: 13000 | T30: 13000 | U30: 13000 | V30: 13000 | W30: 13000 | X30: 13000 | Y30: 13000 | Z30: 13000 | AA30: 13000 | AB30: 13000 | AC30: =+SUM(E30:AB30) -> 312000
A31: 2026 | B31: 5 | C31: 5 | D31: Sábado | E31: 13000 | F31: 13000 | G31: 13000 | H31: 13000 | I31: 13000 | J31: 13000 | K31: 13000 | L31: 13000 | M31: 13000 | N31: 13000 | O31: 13000 | P31: 13000 | Q31: 13000 | R31: 13000 | S31: 13000 | T31: 13000 | U31: 13000 | V31: 13000 | W31: 13000 | X31: 13000 | Y31: 13000 | Z31: 13000 | AA31: 13000 | AB31: 13000 | AC31: =+SUM(E31:AB31) -> 312000
A32: 2026 | B32: 6 | C32: 6 | D32: Festivo | E32: 13000 | F32: 13000 | G32: 13000 | H32: 13000 | I32: 13000 | J32: 13000 | K32: 13000 | L32: 13000 | M32: 13000 | N32: 13000 | O32: 13000 | P32: 13000 | Q32: 13000 | R32: 13000 | S32: 13000 | T32: 13000 | U32: 13000 | V32: 13000 | W32: 13000 | X32: 13000 | Y32: 13000 | Z32: 13000 | AA32: 13000 | AB32: 13000 | AC32: =+SUM(E32:AB32) -> 312000 | AD32: =+SUMPRODUCT(AC32:AC34,C32:C34) -> 9360000
A33: 2026 | B33: 6 | C33: 20 | D33: Hábil | E33: 13000 | F33: 13000 | G33: 13000 | H33: 13000 | I33: 13000 | J33: 13000 | K33: 13000 | L33: 13000 | M33: 13000 | N33: 13000 | O33: 13000 | P33: 13000 | Q33: 13000 | R33: 13000 | S33: 13000 | T33: 13000 | U33: 13000 | V33: 13000 | W33: 13000 | X33: 13000 | Y33: 13000 | Z33: 13000 | AA33: 13000 | AB33: 13000 | AC33: =+SUM(E33:AB33) -> 312000
A34: 2026 | B34: 6 | C34: 4 | D34: Sábado | E34: 13000 | F34: 13000 | G34: 13000 | H34: 13000 | I34: 13000 | J34: 13000 | K34: 13000 | L34: 13000 | M34: 13000 | N34: 13000 | O34: 13000 | P34: 13000 | Q34: 13000 | R34: 13000 | S34: 13000 | T34: 13000 | U34: 13000 | V34: 13000 | W34: 13000 | X34: 13000 | Y34: 13000 | Z34: 13000 | AA34: 13000 | AB34: 13000 | AC34: =+SUM(E34:AB34) -> 312000
A35: 2026 | B35: 7 | C35: 6 | D35: Festivo | E35: 13000 | F35: 13000 | G35: 13000 | H35: 13000 | I35: 13000 | J35: 13000 | K35: 13000 | L35: 13000 | M35: 13000 | N35: 13000 | O35: 13000 | P35: 13000 | Q35: 13000 | R35: 13000 | S35: 13000 | T35: 13000 | U35: 13000 | V35: 13000 | W35: 13000 | X35: 13000 | Y35: 13000 | Z35: 13000 | AA35: 13000 | AB35: 13000 | AC35: =+SUM(E35:AB35) -> 312000 | AD35: =+SUMPRODUCT(AC35:AC37,C35:C37) -> 9672000
A36: 2026 | B36: 7 | C36: 21 | D36: Hábil | E36: 13000 | F36: 13000 | G36: 13000 | H36: 13000 | I36: 13000 | J36: 13000 | K36: 13000 | L36: 13000 | M36: 13000 | N36: 13000 | O36: 13000 | P36: 13000 | Q36: 13000 | R36: 13000 | S36: 13000 | T36: 13000 | U36: 13000 | V36: 13000 | W36: 13000 | X36: 13000 | Y36: 13000 | Z36: 13000 | AA36: 13000 | AB36: 13000 | AC36: =+SUM(E36:AB36) -> 312000
A37: 2026 | B37: 7 | C37: 4 | D37: Sábado | E37: 13000 | F37: 13000 | G37: 13000 | H37: 13000 | I37: 13000 | J37: 13000 | K37: 13000 | L37: 13000 | M37: 13000 | N37: 13000 | O37: 13000 | P37: 13000 | Q37: 13000 | R37: 13000 | S37: 13000 | T37: 13000 | U37: 13000 | V37: 13000 | W37: 13000 | X37: 13000 | Y37: 13000 | Z37: 13000 | AA37: 13000 | AB37: 13000 | AC37: =+SUM(E37:AB37) -> 312000
A38: 2026 | B38: 8 | C38: 7 | D38: Festivo | E38: 13000 | F38: 13000 | G38: 13000 | H38: 13000 | I38: 13000 | J38: 13000 | K38: 13000 | L38: 13000 | M38: 13000 | N38: 13000 | O38: 13000 | P38: 13000 | Q38: 13000 | R38: 13000 | S38: 13000 | T38: 13000 | U38: 13000 | V38: 13000 | W38: 13000 | X38: 13000 | Y38: 13000 | Z38: 13000 | AA38: 13000 | AB38: 13000 | AC38: =+SUM(E38:AB38) -> 312000 | AD38: =+SUMPRODUCT(AC38:AC40,C38:C40) -> 9672000
A39: 2026 | B39: 8 | C39: 19 | D39: Hábil | E39: 13000 | F39: 13000 | G39: 13000 | H39: 13000 | I39: 13000 | J39: 13000 | K39: 13000 | L39: 13000 | M39: 13000 | N39: 13000 | O39: 13000 | P39: 13000 | Q39: 13000 | R39: 13000 | S39: 13000 | T39: 13000 | U39: 13000 | V39: 13000 | W39: 13000 | X39: 13000 | Y39: 13000 | Z39: 13000 | AA39: 13000 | AB39: 13000 | AC39: =+SUM(E39:AB39) -> 312000
A40: 2026 | B40: 8 | C40: 5 | D40: Sábado | E40: 13000 | F40: 13000 | G40: 13000 | H40: 13000 | I40: 13000 | J40: 13000 | K40: 13000 | L40: 13000 | M40: 13000 | N40: 13000 | O40: 13000 | P40: 13000 | Q40: 13000 | R40: 13000 | S40: 13000 | T40: 13000 | U40: 13000 | V40: 13000 | W40: 13000 | X40: 13000 | Y40: 13000 | Z40: 13000 | AA40: 13000 | AB40: 13000 | AC40: =+SUM(E40:AB40) -> 312000
A41: 2026 | B41: 9 | C41: 4 | D41: Festivo | E41: 13000 | F41: 13000 | G41: 13000 | H41: 13000 | I41: 13000 | J41: 13000 | K41: 13000 | L41: 13000 | M41: 13000 | N41: 13000 | O41: 13000 | P41: 13000 | Q41: 13000 | R41: 13000 | S41: 13000 | T41: 13000 | U41: 13000 | V41: 13000 | W41: 13000 | X41: 13000 | Y41: 13000 | Z41: 13000 | AA41: 13000 | AB41: 13000 | AC41: =+SUM(E41:AB41) -> 312000 | AD41: =+SUMPRODUCT(AC41:AC43,C41:C43) -> 9360000
A42: 2026 | B42: 9 | C42: 22 | D42: Hábil | E42: 13000 | F42: 13000 | G42: 13000 | H42: 13000 | I42: 13000 | J42: 13000 | K42: 13000 | L42: 13000 | M42: 13000 | N42: 13000 | O42: 13000 | P42: 13000 | Q42: 13000 | R42: 13000 | S42: 13000 | T42: 13000 | U42: 13000 | V42: 13000 | W42: 13000 | X42: 13000 | Y42: 13000 | Z42: 13000 | AA42: 13000 | AB42: 13000 | AC42: =+SUM(E42:AB42) -> 312000
A43: 2026 | B43: 9 | C43: 4 | D43: Sábado | E43: 13000 | F43: 13000 | G43: 13000 | H43: 13000 | I43: 13000 | J43: 13000 | K43: 13000 | L43: 13000 | M43: 13000 | N43: 13000 | O43: 13000 | P43: 13000 | Q43: 13000 | R43: 13000 | S43: 13000 | T43: 13000 | U43: 13000 | V43: 13000 | W43: 13000 | X43: 13000 | Y43: 13000 | Z43: 13000 | AA43: 13000 | AB43: 13000 | AC43: =+SUM(E43:AB43) -> 312000
A44: 2026 | B44: 10 | C44: 5 | D44: Festivo | E44: 13000 | F44: 13000 | G44: 13000 | H44: 13000 | I44: 13000 | J44: 13000 | K44: 13000 | L44: 13000 | M44: 13000 | N44: 13000 | O44: 13000 | P44: 13000 | Q44: 13000 | R44: 13000 | S44: 13000 | T44: 13000 | U44: 13000 | V44: 13000 | W44: 13000 | X44: 13000 | Y44: 13000 | Z44: 13000 | AA44: 13000 | AB44: 13000 | AC44: =+SUM(E44:AB44) -> 312000 | AD44: =+SUMPRODUCT(AC44:AC46,C44:C46) -> 9672000
A45: 2026 | B45: 10 | C45: 21 | D45: Hábil | E45: 13000 | F45: 13000 | G45: 13000 | H45: 13000 | I45: 13000 | J45: 13000 | K45: 13000 | L45: 13000 | M45: 13000 | N45: 13000 | O45: 13000 | P45: 13000 | Q45: 13000 | R45: 13000 | S45: 13000 | T45: 13000 | U45: 13000 | V45: 13000 | W45: 13000 | X45: 13000 | Y45: 13000 | Z45: 13000 | AA45: 13000 | AB45: 13000 | AC45: =+SUM(E45:AB45) -> 312000
A46: 2026 | B46: 10 | C46: 5 | D46: Sábado | E46: 13000 | F46: 13000 | G46: 13000 | H46: 13000 | I46: 13000 | J46: 13000 | K46: 13000 | L46: 13000 | M46: 13000 | N46: 13000 | O46: 13000 | P46: 13000 | Q46: 13000 | R46: 13000 | S46: 13000 | T46: 13000 | U46: 13000 | V46: 13000 | W46: 13000 | X46: 13000 | Y46: 13000 | Z46: 13000 | AA46: 13000 | AB46: 13000 | AC46: =+SUM(E46:AB46) -> 312000
A47: 2026 | B47: 11 | C47: 7 | D47: Festivo | E47: 13000 | F47: 13000 | G47: 13000 | H47: 13000 | I47: 13000 | J47: 13000 | K47: 13000 | L47: 13000 | M47: 13000 | N47: 13000 | O47: 13000 | P47: 13000 | Q47: 13000 | R47: 13000 | S47: 13000 | T47: 13000 | U47: 13000 | V47: 13000 | W47: 13000 | X47: 13000 | Y47: 13000 | Z47: 13000 | AA47: 13000 | AB47: 13000 | AC47: =+SUM(E47:AB47) -> 312000 | AD47: =+SUMPRODUCT(AC47:AC49,C47:C49) -> 9360000
A48: 2026 | B48: 11 | C48: 19 | D48: Hábil | E48: 13000 | F48: 13000 | G48: 13000 | H48: 13000 | I48: 13000 | J48: 13000 | K48: 13000 | L48: 13000 | M48: 13000 | N48: 13000 | O48: 13000 | P48: 13000 | Q48: 13000 | R48: 13000 | S48: 13000 | T48: 13000 | U48: 13000 | V48: 13000 | W48: 13000 | X48: 13000 | Y48: 13000 | Z48: 13000 | AA48: 13000 | AB48: 13000 | AC48: =+SUM(E48:AB48) -> 312000
A49: 2026 | B49: 11 | C49: 4 | D49: Sábado | E49: 13000 | F49: 13000 | G49: 13000 | H49: 13000 | I49: 13000 | J49: 13000 | K49: 13000 | L49: 13000 | M49: 13000 | N49: 13000 | O49: 13000 | P49: 13000 | Q49: 13000 | R49: 13000 | S49: 13000 | T49: 13000 | U49: 13000 | V49: 13000 | W49: 13000 | X49: 13000 | Y49: 13000 | Z49: 13000 | AA49: 13000 | AB49: 13000 | AC49: =+SUM(E49:AB49) -> 312000
A50: 2026 | B50: 12 | C50: 6 | D50: Festivo | E50: 13000 | F50: 13000 | G50: 13000 | H50: 13000 | I50: 13000 | J50: 13000 | K50: 13000 | L50: 13000 | M50: 13000 | N50: 13000 | O50: 13000 | P50: 13000 | Q50: 13000 | R50: 13000 | S50: 13000 | T50: 13000 | U50: 13000 | V50: 13000 | W50: 13000 | X50: 13000 | Y50: 13000 | Z50: 13000 | AA50: 13000 | AB50: 13000 | AC50: =+SUM(E50:AB50) -> 312000 | AD50: =+SUMPRODUCT(AC50:AC52,C50:C52) -> 9672000
A51: 2026 | B51: 12 | C51: 21 | D51: Hábil | E51: 13000 | F51: 13000 | G51: 13000 | H51: 13000 | I51: 13000 | J51: 13000 | K51: 13000 | L51: 13000 | M51: 13000 | N51: 13000 | O51: 13000 | P51: 13000 | Q51: 13000 | R51: 13000 | S51: 13000 | T51: 13000 | U51: 13000 | V51: 13000 | W51: 13000 | X51: 13000 | Y51: 13000 | Z51: 13000 | AA51: 13000 | AB51: 13000 | AC51: =+SUM(E51:AB51) -> 312000
A52: 2026 | B52: 12 | C52: 4 | D52: Sábado | E52: 13000 | F52: 13000 | G52: 13000 | H52: 13000 | I52: 13000 | J52: 13000 | K52: 13000 | L52: 13000 | M52: 13000 | N52: 13000 | O52: 13000 | P52: 13000 | Q52: 13000 | R52: 13000 | S52: 13000 | T52: 13000 | U52: 13000 | V52: 13000 | W52: 13000 | X52: 13000 | Y52: 13000 | Z52: 13000 | AA52: 13000 | AB52: 13000 | AC52: =+SUM(E52:AB52) -> 312000
A53: 2027 | B53: 1 | C53: 7 | D53: Festivo | E53: 13000 | F53: 13000 | G53: 13000 | H53: 13000 | I53: 13000 | J53: 13000 | K53: 13000 | L53: 13000 | M53: 13000 | N53: 13000 | O53: 13000 | P53: 13000 | Q53: 13000 | R53: 13000 | S53: 13000 | T53: 13000 | U53: 13000 | V53: 13000 | W53: 13000 | X53: 13000 | Y53: 13000 | Z53: 13000 | AA53: 13000 | AB53: 13000 | AC53: =+SUM(E53:AB53) -> 312000 | AD53: =+SUMPRODUCT(AC53:AC55,C53:C55) -> 9672000
A54: 2027 | B54: 1 | C54: 19 | D54: Hábil | E54: 13000 | F54: 13000 | G54: 13000 | H54: 13000 | I54: 13000 | J54: 13000 | K54: 13000 | L54: 13000 | M54: 13000 | N54: 13000 | O54: 13000 | P54: 13000 | Q54: 13000 | R54: 13000 | S54: 13000 | T54: 13000 | U54: 13000 | V54: 13000 | W54: 13000 | X54: 13000 | Y54: 13000 | Z54: 13000 | AA54: 13000 | AB54: 13000 | AC54: =+SUM(E54:AB54) -> 312000
A55: 2027 | B55: 1 | C55: 5 | D55: Sábado | E55: 13000 | F55: 13000 | G55: 13000 | H55: 13000 | I55: 13000 | J55: 13000 | K55: 13000 | L55: 13000 | M55: 13000 | N55: 13000 | O55: 13000 | P55: 13000 | Q55: 13000 | R55: 13000 | S55: 13000 | T55: 13000 | U55: 13000 | V55: 13000 | W55: 13000 | X55: 13000 | Y55: 13000 | Z55: 13000 | AA55: 13000 | AB55: 13000 | AC55: =+SUM(E55:AB55) -> 312000
A56: 2027 | B56: 2 | C56: 4 | D56: Festivo | E56: 13000 | F56: 13000 | G56: 13000 | H56: 13000 | I56: 13000 | J56: 13000 | K56: 13000 | L56: 13000 | M56: 13000 | N56: 13000 | O56: 13000 | P56: 13000 | Q56: 13000 | R56: 13000 | S56: 13000 | T56: 13000 | U56: 13000 | V56: 13000 | W56: 13000 | X56: 13000 | Y56: 13000 | Z56: 13000 | AA56: 13000 | AB56: 13000 | AC56: =+SUM(E56:AB56) -> 312000 | AD56: =+SUMPRODUCT(AC56:AC58,C56:C58) -> 8736000
A57: 2027 | B57: 2 | C57: 20 | D57: Hábil | E57: 13000 | F57: 13000 | G57: 13000 | H57: 13000 | I57: 13000 | J57: 13000 | K57: 13000 | L57: 13000 | M57: 13000 | N57: 13000 | O57: 13000 | P57: 13000 | Q57: 13000 | R57: 13000 | S57: 13000 | T57: 13000 | U57: 13000 | V57: 13000 | W57: 13000 | X57: 13000 | Y57: 13000 | Z57: 13000 | AA57: 13000 | AB57: 13000 | AC57: =+SUM(E57:AB57) -> 312000
A58: 2027 | B58: 2 | C58: 4 | D58: Sábado | E58: 13000 | F58: 13000 | G58: 13000 | H58: 13000 | I58: 13000 | J58: 13000 | K58: 13000 | L58: 13000 | M58: 13000 | N58: 13000 | O58: 13000 | P58: 13000 | Q58: 13000 | R58: 13000 | S58: 13000 | T58: 13000 | U58: 13000 | V58: 13000 | W58: 13000 | X58: 13000 | Y58: 13000 | Z58: 13000 | AA58: 13000 | AB58: 13000 | AC58: =+SUM(E58:AB58) -> 312000
A59: 2027 | B59: 3 | C59: 7 | D59: Festivo | E59: 13000 | F59: 13000 | G59: 13000 | H59: 13000 | I59: 13000 | J59: 13000 | K59: 13000 | L59: 13000 | M59: 13000 | N59: 13000 | O59: 13000 | P59: 13000 | Q59: 13000 | R59: 13000 | S59: 13000 | T59: 13000 | U59: 13000 | V59: 13000 | W59: 13000 | X59: 13000 | Y59: 13000 | Z59: 13000 | AA59: 13000 | AB59: 13000 | AC59: =+SUM(E59:AB59) -> 312000 | AD59: =+SUMPRODUCT(AC59:AC61,C59:C61) -> 9672000
A60: 2027 | B60: 3 | C60: 20 | D60: Hábil | E60: 13000 | F60: 13000 | G60: 13000 | H60: 13000 | I60: 13000 | J60: 13000 | K60: 13000 | L60: 13000 | M60: 13000 | N60: 13000 | O60: 13000 | P60: 13000 | Q60: 13000 | R60: 13000 | S60: 13000 | T60: 13000 | U60: 13000 | V60: 13000 | W60: 13000 | X60: 13000 | Y60: 13000 | Z60: 13000 | AA60: 13000 | AB60: 13000 | AC60: =+SUM(E60:AB60) -> 312000
A61: 2027 | B61: 3 | C61: 4 | D61: Sábado | E61: 13000 | F61: 13000 | G61: 13000 | H61: 13000 | I61: 13000 | J61: 13000 | K61: 13000 | L61: 13000 | M61: 13000 | N61: 13000 | O61: 13000 | P61: 13000 | Q61: 13000 | R61: 13000 | S61: 13000 | T61: 13000 | U61: 13000 | V61: 13000 | W61: 13000 | X61: 13000 | Y61: 13000 | Z61: 13000 | AA61: 13000 | AB61: 13000 | AC61: =+SUM(E61:AB61) -> 312000
A62: 2027 | B62: 4 | C62: 4 | D62: Festivo | E62: 13000 | F62: 13000 | G62: 13000 | H62: 13000 | I62: 13000 | J62: 13000 | K62: 13000 | L62: 13000 | M62: 13000 | N62: 13000 | O62: 13000 | P62: 13000 | Q62: 13000 | R62: 13000 | S62: 13000 | T62: 13000 | U62: 13000 | V62: 13000 | W62: 13000 | X62: 13000 | Y62: 13000 | Z62: 13000 | AA62: 13000 | AB62: 13000 | AC62: =+SUM(E62:AB62) -> 312000 | AD62: =+SUMPRODUCT(AC62:AC64,C62:C64) -> 9360000
A63: 2027 | B63: 4 | C63: 22 | D63: Hábil | E63: 13000 | F63: 13000 | G63: 13000 | H63: 13000 | I63: 13000 | J63: 13000 | K63: 13000 | L63: 13000 | M63: 13000 | N63: 13000 | O63: 13000 | P63: 13000 | Q63: 13000 | R63: 13000 | S63: 13000 | T63: 13000 | U63: 13000 | V63: 13000 | W63: 13000 | X63: 13000 | Y63: 13000 | Z63: 13000 | AA63: 13000 | AB63: 13000 | AC63: =+SUM(E63:AB63) -> 312000
A64: 2027 | B64: 4 | C64: 4 | D64: Sábado | E64: 13000 | F64: 13000 | G64: 13000 | H64: 13000 | I64: 13000 | J64: 13000 | K64: 13000 | L64: 13000 | M64: 13000 | N64: 13000 | O64: 13000 | P64: 13000 | Q64: 13000 | R64: 13000 | S64: 13000 | T64: 13000 | U64: 13000 | V64: 13000 | W64: 13000 | X64: 13000 | Y64: 13000 | Z64: 13000 | AA64: 13000 | AB64: 13000 | AC64: =+SUM(E64:AB64) -> 312000
A65: 2027 | B65: 5 | C65: 7 | D65: Festivo | E65: 13000 | F65: 13000 | G65: 13000 | H65: 13000 | I65: 13000 | J65: 13000 | K65: 13000 | L65: 13000 | M65: 13000 | N65: 13000 | O65: 13000 | P65: 13000 | Q65: 13000 | R65: 13000 | S65: 13000 | T65: 13000 | U65: 13000 | V65: 13000 | W65: 13000 | X65: 13000 | Y65: 13000 | Z65: 13000 | AA65: 13000 | AB65: 13000 | AC65: =+SUM(E65:AB65) -> 312000 | AD65: =+SUMPRODUCT(AC65:AC67,C65:C67) -> 9672000
A66: 2027 | B66: 5 | C66: 20 | D66: Hábil | E66: 13000 | F66: 13000 | G66: 13000 | H66: 13000 | I66: 13000 | J66: 13000 | K66: 13000 | L66: 13000 | M66: 13000 | N66: 13000 | O66: 13000 | P66: 13000 | Q66: 13000 | R66: 13000 | S66: 13000 | T66: 13000 | U66: 13000 | V66: 13000 | W66: 13000 | X66: 13000 | Y66: 13000 | Z66: 13000 | AA66: 13000 | AB66: 13000 | AC66: =+SUM(E66:AB66) -> 312000
A67: 2027 | B67: 5 | C67: 4 | D67: Sábado | E67: 13000 | F67: 13000 | G67: 13000 | H67: 13000 | I67: 13000 | J67: 13000 | K67: 13000 | L67: 13000 | M67: 13000 | N67: 13000 | O67: 13000 | P67: 13000 | Q67: 13000 | R67: 13000 | S67: 13000 | T67: 13000 | U67: 13000 | V67: 13000 | W67: 13000 | X67: 13000 | Y67: 13000 | Z67: 13000 | AA67: 13000 | AB67: 13000 | AC67: =+SUM(E67:AB67) -> 312000
A68: 2027 | B68: 6 | C68: 6 | D68: Festivo | E68: 13000 | F68: 13000 | G68: 13000 | H68: 13000 | I68: 13000 | J68: 13000 | K68: 13000 | L68: 13000 | M68: 13000 | N68: 13000 | O68: 13000 | P68: 13000 | Q68: 13000 | R68: 13000 | S68: 13000 | T68: 13000 | U68: 13000 | V68: 13000 | W68: 13000 | X68: 13000 | Y68: 13000 | Z68: 13000 | AA68: 13000 | AB68: 13000 | AC68: =+SUM(E68:AB68) -> 312000 | AD68: =+SUMPRODUCT(AC68:AC70,C68:C70) -> 9360000
A69: 2027 | B69: 6 | C69: 20 | D69: Hábil | E69: 13000 | F69: 13000 | G69: 13000 | H69: 13000 | I69: 13000 | J69: 13000 | K69: 13000 | L69: 13000 | M69: 13000 | N69: 13000 | O69: 13000 | P69: 13000 | Q69: 13000 | R69: 13000 | S69: 13000 | T69: 13000 | U69: 13000 | V69: 13000 | W69: 13000 | X69: 13000 | Y69: 13000 | Z69: 13000 | AA69: 13000 | AB69: 13000 | AC69: =+SUM(E69:AB69) -> 312000
A70: 2027 | B70: 6 | C70: 4 | D70: Sábado | E70: 13000 | F70: 13000 | G70: 13000 | H70: 13000 | I70: 13000 | J70: 13000 | K70: 13000 | L70: 13000 | M70: 13000 | N70: 13000 | O70: 13000 | P70: 13000 | Q70: 13000 | R70: 13000 | S70: 13000 | T70: 13000 | U70: 13000 | V70: 13000 | W70: 13000 | X70: 13000 | Y70: 13000 | Z70: 13000 | AA70: 13000 | AB70: 13000 | AC70: =+SUM(E70:AB70) -> 312000
A71: 2027 | B71: 7 | C71: 6 | D71: Festivo | E71: 13000 | F71: 13000 | G71: 13000 | H71: 13000 | I71: 13000 | J71: 13000 | K71: 13000 | L71: 13000 | M71: 13000 | N71: 13000 | O71: 13000 | P71: 13000 | Q71: 13000 | R71: 13000 | S71: 13000 | T71: 13000 | U71: 13000 | V71: 13000 | W71: 13000 | X71: 13000 | Y71: 13000 | Z71: 13000 | AA71: 13000 | AB71: 13000 | AC71: =+SUM(E71:AB71) -> 312000 | AD71: =+SUMPRODUCT(AC71:AC73,C71:C73) -> 9672000
A72: 2027 | B72: 7 | C72: 20 | D72: Hábil | E72: 13000 | F72: 13000 | G72: 13000 | H72: 13000 | I72: 13000 | J72: 13000 | K72: 13000 | L72: 13000 | M72: 13000 | N72: 13000 | O72: 13000 | P72: 13000 | Q72: 13000 | R72: 13000 | S72: 13000 | T72: 13000 | U72: 13000 | V72: 13000 | W72: 13000 | X72: 13000 | Y72: 13000 | Z72: 13000 | AA72: 13000 | AB72: 13000 | AC72: =+SUM(E72:AB72) -> 312000
A73: 2027 | B73: 7 | C73: 5 | D73: Sábado | E73: 13000 | F73: 13000 | G73: 13000 | H73: 13000 | I73: 13000 | J73: 13000 | K73: 13000 | L73: 13000 | M73: 13000 | N73: 13000 | O73: 13000 | P73: 13000 | Q73: 13000 | R73: 13000 | S73: 13000 | T73: 13000 | U73: 13000 | V73: 13000 | W73: 13000 | X73: 13000 | Y73: 13000 | Z73: 13000 | AA73: 13000 | AB73: 13000 | AC73: =+SUM(E73:AB73) -> 312000
A74: 2027 | B74: 8 | C74: 7 | D74: Festivo | E74: 13000 | F74: 13000 | G74: 13000 | H74: 13000 | I74: 13000 | J74: 13000 | K74: 13000 | L74: 13000 | M74: 13000 | N74: 13000 | O74: 13000 | P74: 13000 | Q74: 13000 | R74: 13000 | S74: 13000 | T74: 13000 | U74: 13000 | V74: 13000 | W74: 13000 | X74: 13000 | Y74: 13000 | Z74: 13000 | AA74: 13000 | AB74: 13000 | AC74: =+SUM(E74:AB74) -> 312000 | AD74: =+SUMPRODUCT(AC74:AC76,C74:C76) -> 9672000
A75: 2027 | B75: 8 | C75: 21 | D75: Hábil | E75: 13000 | F75: 13000 | G75: 13000 | H75: 13000 | I75: 13000 | J75: 13000 | K75: 13000 | L75: 13000 | M75: 13000 | N75: 13000 | O75: 13000 | P75: 13000 | Q75: 13000 | R75: 13000 | S75: 13000 | T75: 13000 | U75: 13000 | V75: 13000 | W75: 13000 | X75: 13000 | Y75: 13000 | Z75: 13000 | AA75: 13000 | AB75: 13000 | AC75: =+SUM(E75:AB75) -> 312000
A76: 2027 | B76: 8 | C76: 3 | D76: Sábado | E76: 13000 | F76: 13000 | G76: 13000 | H76: 13000 | I76: 13000 | J76: 13000 | K76: 13000 | L76: 13000 | M76: 13000 | N76: 13000 | O76: 13000 | P76: 13000 | Q76: 13000 | R76: 13000 | S76: 13000 | T76: 13000 | U76: 13000 | V76: 13000 | W76: 13000 | X76: 13000 | Y76: 13000 | Z76: 13000 | AA76: 13000 | AB76: 13000 | AC76: =+SUM(E76:AB76) -> 312000
A77: 2027 | B77: 9 | C77: 4 | D77: Festivo | E77: 13000 | F77: 13000 | G77: 13000 | H77: 13000 | I77: 13000 | J77: 13000 | K77: 13000 | L77: 13000 | M77: 13000 | N77: 13000 | O77: 13000 | P77: 13000 | Q77: 13000 | R77: 13000 | S77: 13000 | T77: 13000 | U77: 13000 | V77: 13000 | W77: 13000 | X77: 13000 | Y77: 13000 | Z77: 13000 | AA77: 13000 | AB77: 13000 | AC77: =+SUM(E77:AB77) -> 312000 | AD77: =+SUMPRODUCT(AC77:AC79,C77:C79) -> 9360000
A78: 2027 | B78: 9 | C78: 22 | D78: Hábil | E78: 13000 | F78: 13000 | G78: 13000 | H78: 13000 | I78: 13000 | J78: 13000 | K78: 13000 | L78: 13000 | M78: 13000 | N78: 13000 | O78: 13000 | P78: 13000 | Q78: 13000 | R78: 13000 | S78: 13000 | T78: 13000 | U78: 13000 | V78: 13000 | W78: 13000 | X78: 13000 | Y78: 13000 | Z78: 13000 | AA78: 13000 | AB78: 13000 | AC78: =+SUM(E78:AB78) -> 312000
A79: 2027 | B79: 9 | C79: 4 | D79: Sábado | E79: 13000 | F79: 13000 | G79: 13000 | H79: 13000 | I79: 13000 | J79: 13000 | K79: 13000 | L79: 13000 | M79: 13000 | N79: 13000 | O79: 13000 | P79: 13000 | Q79: 13000 | R79: 13000 | S79: 13000 | T79: 13000 | U79: 13000 | V79: 13000 | W79: 13000 | X79: 13000 | Y79: 13000 | Z79: 13000 | AA79: 13000 | AB79: 13000 | AC79: =+SUM(E79:AB79) -> 312000
A80: 2027 | B80: 10 | C80: 6 | D80: Festivo | E80: 13000 | F80: 13000 | G80: 13000 | H80: 13000 | I80: 13000 | J80: 13000 | K80: 13000 | L80: 13000 | M80: 13000 | N80: 13000 | O80: 13000 | P80: 13000 | Q80: 13000 | R80: 13000 | S80: 13000 | T80: 13000 | U80: 13000 | V80: 13000 | W80: 13000 | X80: 13000 | Y80: 13000 | Z80: 13000 | AA80: 13000 | AB80: 13000 | AC80: =+SUM(E80:AB80) -> 312000 | AD80: =+SUMPRODUCT(AC80:AC82,C80:C82) -> 9672000
A81: 2027 | B81: 10 | C81: 20 | D81: Hábil | E81: 13000 | F81: 13000 | G81: 13000 | H81: 13000 | I81: 13000 | J81: 13000 | K81: 13000 | L81: 13000 | M81: 13000 | N81: 13000 | O81: 13000 | P81: 13000 | Q81: 13000 | R81: 13000 | S81: 13000 | T81: 13000 | U81: 13000 | V81: 13000 | W81: 13000 | X81: 13000 | Y81: 13000 | Z81: 13000 | AA81: 13000 | AB81: 13000 | AC81: =+SUM(E81:AB81) -> 312000
A82: 2027 | B82: 10 | C82: 5 | D82: Sábado | E82: 13000 | F82: 13000 | G82: 13000 | H82: 13000 | I82: 13000 | J82: 13000 | K82: 13000 | L82: 13000 | M82: 13000 | N82: 13000 | O82: 13000 | P82: 13000 | Q82: 13000 | R82: 13000 | S82: 13000 | T82: 13000 | U82: 13000 | V82: 13000 | W82: 13000 | X82: 13000 | Y82: 13000 | Z82: 13000 | AA82: 13000 | AB82: 13000 | AC82: =+SUM(E82:AB82) -> 312000
A83: 2027 | B83: 11 | C83: 6 | D83: Festivo | E83: 13000 | F83: 13000 | G83: 13000 | H83: 13000 | I83: 13000 | J83: 13000 | K83: 13000 | L83: 13000 | M83: 13000 | N83: 13000 | O83: 13000 | P83: 13000 | Q83: 13000 | R83: 13000 | S83: 13000 | T83: 13000 | U83: 13000 | V83: 13000 | W83: 13000 | X83: 13000 | Y83: 13000 | Z83: 13000 | AA83: 13000 | AB83: 13000 | AC83: =+SUM(E83:AB83) -> 312000 | AD83: =+SUMPRODUCT(AC83:AC85,C83:C85) -> 9360000
A84: 2027 | B84: 11 | C84: 20 | D84: Hábil | E84: 13000 | F84: 13000 | G84: 13000 | H84: 13000 | I84: 13000 | J84: 13000 | K84: 13000 | L84: 13000 | M84: 13000 | N84: 13000 | O84: 13000 | P84: 13000 | Q84: 13000 | R84: 13000 | S84: 13000 | T84: 13000 | U84: 13000 | V84: 13000 | W84: 13000 | X84: 13000 | Y84: 13000 | Z84: 13000 | AA84: 13000 | AB84: 13000 | AC84: =+SUM(E84:AB84) -> 312000
A85: 2027 | B85: 11 | C85: 4 | D85: Sábado | E85: 13000 | F85: 13000 | G85: 13000 | H85: 13000 | I85: 13000 | J85: 13000 | K85: 13000 | L85: 13000 | M85: 13000 | N85: 13000 | O85: 13000 | P85: 13000 | Q85: 13000 | R85: 13000 | S85: 13000 | T85: 13000 | U85: 13000 | V85: 13000 | W85: 13000 | X85: 13000 | Y85: 13000 | Z85: 13000 | AA85: 13000 | AB85: 13000 | AC85: =+SUM(E85:AB85) -> 312000
A86: 2027 | B86: 12 | C86: 6 | D86: Festivo | E86: 13000 | F86: 13000 | G86: 13000 | H86: 13000 | I86: 13000 | J86: 13000 | K86: 13000 | L86: 13000 | M86: 13000 | N86: 13000 | O86: 13000 | P86: 13000 | Q86: 13000 | R86: 13000 | S86: 13000 | T86: 13000 | U86: 13000 | V86: 13000 | W86: 13000 | X86: 13000 | Y86: 13000 | Z86: 13000 | AA86: 13000 | AB86: 13000 | AC86: =+SUM(E86:AB86) -> 312000 | AD86: =+SUMPRODUCT(AC86:AC88,C86:C88) -> 9672000
A87: 2027 | B87: 12 | C87: 22 | D87: Hábil | E87: 13000 | F87: 13000 | G87: 13000 | H87: 13000 | I87: 13000 | J87: 13000 | K87: 13000 | L87: 13000 | M87: 13000 | N87: 13000 | O87: 13000 | P87: 13000 | Q87: 13000 | R87: 13000 | S87: 13000 | T87: 13000 | U87: 13000 | V87: 13000 | W87: 13000 | X87: 13000 | Y87: 13000 | Z87: 13000 | AA87: 13000 | AB87: 13000 | AC87: =+SUM(E87:AB87) -> 312000
A88: 2027 | B88: 12 | C88: 3 | D88: Sábado | E88: 13000 | F88: 13000 | G88: 13000 | H88: 13000 | I88: 13000 | J88: 13000 | K88: 13000 | L88: 13000 | M88: 13000 | N88: 13000 | O88: 13000 | P88: 13000 | Q88: 13000 | R88: 13000 | S88: 13000 | T88: 13000 | U88: 13000 | V88: 13000 | W88: 13000 | X88: 13000 | Y88: 13000 | Z88: 13000 | AA88: 13000 | AB88: 13000 | AC88: =+SUM(E88:AB88) -> 312000
A89: 2028 | B89: 1 | C89: 7 | D89: Festivo | E89: 13000 | F89: 13000 | G89: 13000 | H89: 13000 | I89: 13000 | J89: 13000 | K89: 13000 | L89: 13000 | M89: 13000 | N89: 13000 | O89: 13000 | P89: 13000 | Q89: 13000 | R89: 13000 | S89: 13000 | T89: 13000 | U89: 13000 | V89: 13000 | W89: 13000 | X89: 13000 | Y89: 13000 | Z89: 13000 | AA89: 13000 | AB89: 13000 | AC89: =+SUM(E89:AB89) -> 312000 | AD89: =+SUMPRODUCT(AC89:AC91,C89:C91) -> 9672000
A90: 2028 | B90: 1 | C90: 20 | D90: Hábil | E90: 13000 | F90: 13000 | G90: 13000 | H90: 13000 | I90: 13000 | J90: 13000 | K90: 13000 | L90: 13000 | M90: 13000 | N90: 13000 | O90: 13000 | P90: 13000 | Q90: 13000 | R90: 13000 | S90: 13000 | T90: 13000 | U90: 13000 | V90: 13000 | W90: 13000 | X90: 13000 | Y90: 13000 | Z90: 13000 | AA90: 13000 | AB90: 13000 | AC90: =+SUM(E90:AB90) -> 312000
A91: 2028 | B91: 1 | C91: 4 | D91: Sábado | E91: 13000 | F91: 13000 | G91: 13000 | H91: 13000 | I91: 13000 | J91: 13000 | K91: 13000 | L91: 13000 | M91: 13000 | N91: 13000 | O91: 13000 | P91: 13000 | Q91: 13000 | R91: 13000 | S91: 13000 | T91: 13000 | U91: 13000 | V91: 13000 | W91: 13000 | X91: 13000 | Y91: 13000 | Z91: 13000 | AA91: 13000 | AB91: 13000 | AC91: =+SUM(E91:AB91) -> 312000
A92: 2028 | B92: 2 | C92: 4 | D92: Festivo | E92: 13000 | F92: 13000 | G92: 13000 | H92: 13000 | I92: 13000 | J92: 13000 | K92: 13000 | L92: 13000 | M92: 13000 | N92: 13000 | O92: 13000 | P92: 13000 | Q92: 13000 | R92: 13000 | S92: 13000 | T92: 13000 | U92: 13000 | V92: 13000 | W92: 13000 | X92: 13000 | Y92: 13000 | Z92: 13000 | AA92: 13000 | AB92: 13000 | AC92: =+SUM(E92:AB92) -> 312000 | AD92: =+SUMPRODUCT(AC92:AC94,C92:C94) -> 9048000
A93: 2028 | B93: 2 | C93: 21 | D93: Hábil | E93: 13000 | F93: 13000 | G93: 13000 | H93: 13000 | I93: 13000 | J93: 13000 | K93: 13000 | L93: 13000 | M93: 13000 | N93: 13000 | O93: 13000 | P93: 13000 | Q93: 13000 | R93: 13000 | S93: 13000 | T93: 13000 | U93: 13000 | V93: 13000 | W93: 13000 | X93: 13000 | Y93: 13000 | Z93: 13000 | AA93: 13000 | AB93: 13000 | AC93: =+SUM(E93:AB93) -> 312000
A94: 2028 | B94: 2 | C94: 4 | D94: Sábado | E94: 13000 | F94: 13000 | G94: 13000 | H94: 13000 | I94: 13000 | J94: 13000 | K94: 13000 | L94: 13000 | M94: 13000 | N94: 13000 | O94: 13000 | P94: 13000 | Q94: 13000 | R94: 13000 | S94: 13000 | T94: 13000 | U94: 13000 | V94: 13000 | W94: 13000 | X94: 13000 | Y94: 13000 | Z94: 13000 | AA94: 13000 | AB94: 13000 | AC94: =+SUM(E94:AB94) -> 312000
A95: 2028 | B95: 3 | C95: 5 | D95: Festivo | E95: 13000 | F95: 13000 | G95: 13000 | H95: 13000 | I95: 13000 | J95: 13000 | K95: 13000 | L95: 13000 | M95: 13000 | N95: 13000 | O95: 13000 | P95: 13000 | Q95: 13000 | R95: 13000 | S95: 13000 | T95: 13000 | U95: 13000 | V95: 13000 | W95: 13000 | X95: 13000 | Y95: 13000 | Z95: 13000 | AA95: 13000 | AB95: 13000 | AC95: =+SUM(E95:AB95) -> 312000 | AD95: =+SUMPRODUCT(AC95:AC97,C95:C97) -> 9672000
A96: 2028 | B96: 3 | C96: 22 | D96: Hábil | E96: 13000 | F96: 13000 | G96: 13000 | H96: 13000 | I96: 13000 | J96: 13000 | K96: 13000 | L96: 13000 | M96: 13000 | N96: 13000 | O96: 13000 | P96: 13000 | Q96: 13000 | R96: 13000 | S96: 13000 | T96: 13000 | U96: 13000 | V96: 13000 | W96: 13000 | X96: 13000 | Y96: 13000 | Z96: 13000 | AA96: 13000 | AB96: 13000 | AC96: =+SUM(E96:AB96) -> 312000
A97: 2028 | B97: 3 | C97: 4 | D97: Sábado | E97: 13000 | F97: 13000 | G97: 13000 | H97: 13000 | I97: 13000 | J97: 13000 | K97: 13000 | L97: 13000 | M97: 13000 | N97: 13000 | O97: 13000 | P97: 13000 | Q97: 13000 | R97: 13000 | S97: 13000 | T97: 13000 | U97: 13000 | V97: 13000 | W97: 13000 | X97: 13000 | Y97: 13000 | Z97: 13000 | AA97: 13000 | AB97: 13000 | AC97: =+SUM(E97:AB97) -> 312000
A98: 2028 | B98: 4 | C98: 7 | D98: Festivo | E98: 13000 | F98: 13000 | G98: 13000 | H98: 13000 | I98: 13000 | J98: 13000 | K98: 13000 | L98: 13000 | M98: 13000 | N98: 13000 | O98: 13000 | P98: 13000 | Q98: 13000 | R98: 13000 | S98: 13000 | T98: 13000 | U98: 13000 | V98: 13000 | W98: 13000 | X98: 13000 | Y98: 13000 | Z98: 13000 | AA98: 13000 | AB98: 13000 | AC98: =+SUM(E98:AB98) -> 312000 | AD98: =+SUMPRODUCT(AC98:AC100,C98:C100) -> 9360000
A99: 2028 | B99: 4 | C99: 18 | D99: Hábil | E99: 13000 | F99: 13000 | G99: 13000 | H99: 13000 | I99: 13000 | J99: 13000 | K99: 13000 | L99: 13000 | M99: 13000 | N99: 13000 | O99: 13000 | P99: 13000 | Q99: 13000 | R99: 13000 | S99: 13000 | T99: 13000 | U99: 13000 | V99: 13000 | W99: 13000 | X99: 13000 | Y99: 13000 | Z99: 13000 | AA99: 13000 | AB99: 13000 | AC99: =+SUM(E99:AB99) -> 312000
A100: 2028 | B100: 4 | C100: 5 | D100: Sábado | E100: 13000 | F100: 13000 | G100: 13000 | H100: 13000 | I100: 13000 | J100: 13000 | K100: 13000 | L100: 13000 | M100: 13000 | N100: 13000 | O100: 13000 | P100: 13000 | Q100: 13000 | R100: 13000 | S100: 13000 | T100: 13000 | U100: 13000 | V100: 13000 | W100: 13000 | X100: 13000 | Y100: 13000 | Z100: 13000 | AA100: 13000 | AB100: 13000 | AC100: =+SUM(E100:AB100) -> 312000
...

Sheet Producto No. 2 Curva 2026-2033
A5: ANEXO No. 1. Oferta Producto No. 2 Curva (Enero de 2026 a diciembre año 2033) Convocatoria Pública DISPAC S.A. E.S.P.
A8: PROPONENTE
A10: MES | B10: DEMANDA REQUERIDA DISPAC KWh | C10: DEMANDA PERIODO REQUERIDA DISPAC KWh | D10: PORCENTAJE (%) OFERTADO DE LA DEMANDA REQUERIDA | E10: DEMANDA OFERTADA KWh - MES | F10: DEMANDA PERIODO OFERTADA KWh | G10: PRECIO OFERTADO $ kWh (0.00)
A11: ENERO DE 2026 | B11: ='Despacho Horario Producto No, 2'!AD2 -> 4166702 | C11: =SUM(B11:B22) -> 38713630 | E11: =+$D$11*B11 -> 0 | F11: =SUM(E11:E22) -> 0
A12: FEBRERO DE 2026 | B12: ='Despacho Horario Producto No, 2'!AD5 -> 4120884.4 | E12: =+$D$11*B12 -> 0
A13: MARZO DE 2026 | B13: ='Despacho Horario Producto No, 2'!AD8 -> 4663890.8 | E13: =+$D$11*B13 -> 0
A14: ABRIL DE 2026 | B14: ='Despacho Horario Producto No, 2'!AD11 -> 4125328.2 | E14: =+$D$11*B14 -> 0
A15: MAYO DE 2026 | B15: ='Despacho Horario Producto No, 2'!AD14 -> 4694989 | E15: =+$D$11*B15 -> 0
A16: JUNIO DE 2026 | B16: ='Despacho Horario Producto No, 2'!AD17 -> 4033377.8 | E16: =+$D$11*B16 -> 0
A17: JULIO DE 2026 | B17: ='Despacho Horario Producto No, 2'!AD20 -> 4425238.2 | E17: =+$D$11*B17 -> 0
A18: AGOSTO DE 2026 | B18: ='Despacho Horario Producto No, 2'!AD23 -> 0 | E18: =+$D$11*B18 -> 0
A19: SEPTIEMBRE DE 2026 | B19: ='Despacho Horario Producto No, 2'!AD26 -> 0 | E19: =+$D$11*B19 -> 0
A20: OCTUBRE DE 2026 | B20: ='Despacho Horario Producto No, 2'!AD29 -> 0 | E20: =+$D$11*B20 -> 0
A21: NOVIEMBRE DE 2026 | B21: ='Despacho Horario Producto No, 2'!AD32 -> 4072572.2 | E21: =+$D$11*B21 -> 0
A22: DICIEMBRE DE 2026 | B22: ='Despacho Horario Producto No, 2'!AD35 -> 4410647.3 | E22: =+$D$11*B22 -> 0
A23: ENERO DE 2027 | B23: ='Despacho Horario Producto No, 2'!AD38 -> 4309001.1 | C23: =SUM(B23:B34) -> 33291869 | E23: =+$D$23*B23 -> 0 | F23: =SUM(E23:E34) -> 0
A24: FEBRERO DE 2027 | B24: ='Despacho Horario Producto No, 2'!AD41 -> 3102795.8 | E24: =+$D$23*B24 -> 0
A25: MARZO DE 2027 | B25: ='Despacho Horario Producto No, 2'!AD44 -> 3909486.4 | E25: =+$D$23*B25 -> 0
A26: ABRIL DE 2027 | B26: ='Despacho Horario Producto No, 2'!AD47 -> 3499668.7 | E26: =+$D$23*B26 -> 0
A27: MAYO DE 2027 | B27: ='Despacho Horario Producto No, 2'!AD50 -> 3990561.1 | E27: =+$D$23*B27 -> 0
A28: JUNIO DE 2027 | B28: ='Despacho Horario Producto No, 2'!AD53 -> 3355721.8 | E28: =+$D$23*B28 -> 0
A29: JULIO DE 2027 | B29: ='Despacho Horario Producto No, 2'!AD56 -> 3719326.8 | E29: =+$D$23*B29 -> 0
A30: AGOSTO DE 2027 | B30: ='Despacho Horario Producto No, 2'!AD59 -> 0 | E30: =+$D$23*B30 -> 0
A31: SEPTIEMBRE DE 2027 | B31: ='Despacho Horario Producto No, 2'!AD62 -> 0 | E31: =+$D$23*B31 -> 0
A32: OCTUBRE DE 2027 | B32: ='Despacho Horario Producto No, 2'!AD65 -> 0 | E32: =+$D$23*B32 -> 0
A33: NOVIEMBRE DE 2027 | B33: ='Despacho Horario Producto No, 2'!AD68 -> 3389657.3 | E33: =+$D$23*B33 -> 0
A34: DICIEMBRE DE 2027 | B34: ='Despacho Horario Producto No, 2'!AD71 -> 4015650.2 | E34: =+$D$23*B34 -> 0
A35: ENERO DE 2028 | B35: ='Despacho Horario Producto No, 2'!AD74 -> 4664066 | C35: =SUM(B35:B46) -> 49336295 | E35: =+$D$35*B35 -> 0 | F35: =SUM(E35:E46) -> 0
A36: FEBRERO DE 2028 | B36: ='Despacho Horario Producto No, 2'!AD77 -> 3763314.2 | E36: =+$D$35*B36 -> 0
A37: MARZO DE 2028 | B37: ='Despacho Horario Producto No, 2'!AD80 -> 4349346.7 | E37: =+$D$35*B37 -> 0
A38: ABRIL DE 2028 | B38: ='Despacho Horario Producto No, 2'!AD83 -> 3815278.6 | E38: =+$D$35*B38 -> 0
A39: MAYO DE 2028 | B39: ='Despacho Horario Producto No, 2'!AD86 -> 4368914.2 | E39: =+$D$35*B39 -> 0
A40: JUNIO DE 2028 | B40: ='Despacho Horario Producto No, 2'!AD89 -> 3724343.2 | E40: =+$D$35*B40 -> 0
A41: JULIO DE 2028 | B41: ='Despacho Horario Producto No, 2'!AD92 -> 4100617.1 | E41: =+$D$35*B41 -> 0
A42: AGOSTO DE 2028 | B42: ='Despacho Horario Producto No, 2'!AD95 -> 4242356.2 | E42: =+$D$35*B42 -> 0
A43: SEPTIEMBRE DE 2028 | B43: ='Despacho Horario Producto No, 2'!AD98 -> 3958090.5 | E43: =+$D$35*B43 -> 0
A44: OCTUBRE DE 2028 | B44: ='Despacho Horario Producto No, 2'!AD101 -> 4205647.1 | E44: =+$D$35*B44 -> 0
A45: NOVIEMBRE DE 2028 | B45: ='Despacho Horario Producto No, 2'!AD104 -> 3758465 | E45: =+$D$35*B45 -> 0
A46: DICIEMBRE DE 2028 | B46: ='Despacho Horario Producto No, 2'!AD107 -> 4385856.1 | E46: =+$D$35*B46 -> 0
A47: ENERO DE 2029 | B47: ='Despacho Horario Producto No, 2'!AD110 -> 5070005.8 | C47: =SUM(B47:B58) -> 53544167 | E47: =+$D$47*B47 -> 0 | F47: =SUM(E47:E58) -> 0
A48: FEBRERO DE 2029 | B48: ='Despacho Horario Producto No, 2'!AD113 -> 3794561.7 | E48: =+$D$47*B48 -> 0
A49: MARZO DE 2029 | B49: ='Despacho Horario Producto No, 2'!AD116 -> 4669978.7 | E49: =+$D$47*B49 -> 0
A50: ABRIL DE 2029 | B50: ='Despacho Horario Producto No, 2'!AD119 -> 4240026.5 | E50: =+$D$47*B50 -> 0
A51: MAYO DE 2029 | B51: ='Despacho Horario Producto No, 2'!AD122 -> 4750862.5 | E51: =+$D$47*B51 -> 0
A52: JUNIO DE 2029 | B52: ='Despacho Horario Producto No, 2'!AD125 -> 4092787.6 | E52: =+$D$47*B52 -> 0
A53: JULIO DE 2029 | B53: ='Despacho Horario Producto No, 2'!AD128 -> 4481873.1 | E53: =+$D$47*B53 -> 0
A54: AGOSTO DE 2029 | B54: ='Despacho Horario Producto No, 2'!AD131 -> 4623381.3 | E54: =+$D$47*B54 -> 0
A55: SEPTIEMBRE DE 2029 | B55: ='Despacho Horario Producto No, 2'!AD134 -> 4328073.6 | E55: =+$D$47*B55 -> 0
A56: OCTUBRE DE 2029 | B56: ='Despacho Horario Producto No, 2'!AD137 -> 4587286.6 | E56: =+$D$47*B56 -> 0
A57: NOVIEMBRE DE 2029 | B57: ='Despacho Horario Producto No, 2'!AD140 -> 4127263.8 | E57: =+$D$47*B57 -> 0
A58: DICIEMBRE DE 2029 | B58: ='Despacho Horario Producto No, 2'!AD143 -> 4778065.8 | E58: =+$D$47*B58 -> 0
A59: ENERO DE 2030 | B59: ='Despacho Horario Producto No, 2'!AD146 -> 5450346.8 | C59: =SUM(B59:B70) -> 58066283 | E59: =+$D$59*B59 -> 0 | F59: =SUM(E59:E70) -> 0
A60: FEBRERO DE 2030 | B60: ='Despacho Horario Producto No, 2'!AD149 -> 4139884 | E60: =+$D$59*B60 -> 0
A61: MARZO DE 2030 | B61: ='Despacho Horario Producto No, 2'!AD152 -> 5112318.4 | E61: =+$D$59*B61 -> 0
A62: ABRIL DE 2030 | B62: ='Despacho Horario Producto No, 2'!AD155 -> 4552379.8 | E62: =+$D$59*B62 -> 0
A63: MAYO DE 2030 | B63: ='Despacho Horario Producto No, 2'!AD158 -> 5140192.4 | E63: =+$D$59*B63 -> 0
A64: JUNIO DE 2030 | B64: ='Despacho Horario Producto No, 2'!AD161 -> 4461123.3 | E64: =+$D$59*B64 -> 0
A65: JULIO DE 2030 | B65: ='Despacho Horario Producto No, 2'!AD164 -> 4867904.8 | E65: =+$D$59*B65 -> 0
A66: AGOSTO DE 2030 | B66: ='Despacho Horario Producto No, 2'!AD167 -> 5004348.3 | E66: =+$D$59*B66 -> 0
A67: SEPTIEMBRE DE 2030 | B67: ='Despacho Horario Producto No, 2'!AD170 -> 4698058.8 | E67: =+$D$59*B67 -> 0
A68: OCTUBRE DE 2030 | B68: ='Despacho Horario Producto No, 2'!AD173 -> 4968875.5 | E68: =+$D$59*B68 -> 0
A69: NOVIEMBRE DE 2030 | B69: ='Despacho Horario Producto No, 2'!AD176 -> 4496026.7 | E69: =+$D$59*B69 -> 0
A70: DICIEMBRE DE 2030 | B70: ='Despacho Horario Producto No, 2'!AD179 -> 5174823.8 | E70: =+$D$59*B70 -> 0
A71: ENERO DE 2031 | B71: ='Despacho Horario Producto No, 2'!AD182 -> 5540324 | C71: =SUM(B71:B82) -> 55362536 | E71: =+$D$71*B71 -> 0 | F71: =SUM(E71:E82) -> 0
A72: FEBRERO DE 2031 | B72: ='Despacho Horario Producto No, 2'!AD185 -> 4239314.7 | E72: =+$D$71*B72 -> 0
A73: MARZO DE 2031 | B73: ='Despacho Horario Producto No, 2'!AD188 -> 5209210.6 | E73: =+$D$71*B73 -> 0
A74: ABRIL DE 2031 | B74: ='Despacho Horario Producto No, 2'!AD191 -> 4652443.8 | E74: =+$D$71*B74 -> 0
A75: MAYO DE 2031 | B75: ='Despacho Horario Producto No, 2'!AD194 -> 5233036 | E75: =+$D$71*B75 -> 0
A76: JUNIO DE 2031 | B76: ='Despacho Horario Producto No, 2'!AD197 -> 4537391.5 | E76: =+$D$71*B76 -> 0
A77: JULIO DE 2031 | B77: ='Despacho Horario Producto No, 2'!AD200 -> 5004921.9 | E77: =+$D$71*B77 -> 0
A78: AGOSTO DE 2031 | B78: ='Despacho Horario Producto No, 2'!AD203 -> 5076410.1 | E78: =+$D$71*B78 -> 0
A79: SEPTIEMBRE DE 2031 | B79: ='Despacho Horario Producto No, 2'!AD206 -> 4846841 | E79: =+$D$71*B79 -> 0
A80: OCTUBRE DE 2031 | B80: ='Despacho Horario Producto No, 2'!AD209 -> 5066491.3 | E80: =+$D$71*B80 -> 0
A81: NOVIEMBRE DE 2031 | B81: ='Despacho Horario Producto No, 2'!AD212 -> 4574068 | E81: =+$D$71*B81 -> 0
A82: DICIEMBRE DE 2031 | B82: ='Despacho Horario Producto No, 2'!AD215 -> 1382083.6 | E82: =+$D$71*B82 -> 0
A83: ENERO DE 2032 | B83: ='Despacho Horario Producto No, 2'!AD218 -> 617983.15 | C83: =SUM(B83:B94) -> 7685730.4 | E83: =+$D$83*B83 -> 0 | F83: =SUM(E83:E94) -> 0
A84: FEBRERO DE 2032 | B84: ='Despacho Horario Producto No, 2'!AD221 -> 152010.71 | E84: =+$D$83*B84 -> 0
A85: MARZO DE 2032 | B85: ='Despacho Horario Producto No, 2'!AD224 -> 471428.71 | E85: =+$D$83*B85 -> 0
A86: ABRIL DE 2032 | B86: ='Despacho Horario Producto No, 2'!AD227 -> 244712.63 | E86: =+$D$83*B86 -> 0
A87: MAYO DE 2032 | B87: ='Despacho Horario Producto No, 2'!AD230 -> 513472.02 | E87: =+$D$83*B87 -> 0
A88: JUNIO DE 2032 | B88: ='Despacho Horario Producto No, 2'!AD233 -> 189172.89 | E88: =+$D$83*B88 -> 0
A89: JULIO DE 2032 | B89: ='Despacho Horario Producto No, 2'!AD236 -> 353421.41 | E89: =+$D$83*B89 -> 0
A90: AGOSTO DE 2032 | B90: ='Despacho Horario Producto No, 2'!AD239 -> 505462.9 | E90: =+$D$83*B90 -> 0
A91: SEPTIEMBRE DE 2032 | B91: ='Despacho Horario Producto No, 2'!AD242 -> 326558.56 | E91: =+$D$83*B91 -> 0
A92: OCTUBRE DE 2032 | B92: ='Despacho Horario Producto No, 2'!AD245 -> 448762.56 | E92: =+$D$83*B92 -> 0
A93: NOVIEMBRE DE 2032 | B93: ='Despacho Horario Producto No, 2'!AD248 -> 194499.33 | E93: =+$D$83*B93 -> 0
A94: DICIEMBRE DE 2032 | B94: ='Despacho Horario Producto No, 2'!AD251 -> 3668245.5 | E94: =+$D$83*B94 -> 0
A95: ENERO DE 2033 | B95: ='Despacho Horario Producto No, 2'!AD254 -> 3868612.5 | C95: =SUM(B95:B106) -> 45282704 | E95: =+$D$95*B95 -> 0 | F95: =SUM(E95:E106) -> 0
A96: FEBRERO DE 2033 | B96: ='Despacho Horario Producto No, 2'!AD257 -> 2973766.2 | E96: =+$D$95*B96 -> 0
A97: MARZO DE 2033 | B97: ='Despacho Horario Producto No, 2'!AD260 -> 3695701.4 | E97: =+$D$95*B97 -> 0
A98: ABRIL DE 2033 | B98: ='Despacho Horario Producto No, 2'!AD263 -> 3228119.8 | E98: =+$D$95*B98 -> 0
A99: MAYO DE 2033 | B99: ='Despacho Horario Producto No, 2'!AD266 -> 3675599.9 | E99: =+$D$95*B99 -> 0
A100: JUNIO DE 2033 | B100: ='Despacho Horario Producto No, 2'!AD269 -> 3192888.3 | E100: =+$D$95*B100 -> 0
A101: JULIO DE 2033 | B101: ='Despacho Horario Producto No, 2'!AD272 -> 3441533.6 | E101: =+$D$95*B101 -> 0
A102: AGOSTO DE 2033 | B102: ='Despacho Horario Producto No, 2'!AD275 -> 3602040.8 | E102: =+$D$95*B102 -> 0
A103: SEPTIEMBRE DE 2033 | B103: ='Despacho Horario Producto No, 2'!AD278 -> 3410759.6 | E103: =+$D$95*B103 -> 0
A104: OCTUBRE DE 2033 | B104: ='Despacho Horario Producto No, 2'!AD281 -> 3501018.2 | E104: =+$D$95*B104 -> 0
A105: NOVIEMBRE DE 2033 | B105: ='Despacho Horario Producto No, 2'!AD284 -> 3204107.2 | E105: =+$D$95*B105 -> 0
A106: DICIEMBRE DE 2033 | B106: ='Despacho Horario Producto No, 2'!AD287 -> 7488556.2 | E106: =+$D$95*B106 -> 0
A107: TOTALES | B107: =SUM(B11:B106) -> 3.4128321e+08 | C107: =SUM(C11:C106) -> 3.4128321e+08 | E107: =SUM(E11:E106) -> 0 | F107: =SUM(F11:F106) -> 0 | G107: =IFERROR(SUMPRODUCT(F11:F106,G11:G106)/SUM(F11:F106),"")
...

Sheet Despacho Horario Producto No, 2
A1: Año | B1: Mes | C1: # días | D1: TPD | E1: H1 | F1: H2 | G1: H3 | H1: H4 | I1: H5 | J1: H6 | K1: H7 | L1: H8 | M1: H9 | N1: H10 | O1: H11 | P1: H12 | Q1: H13 | R1: H14 | S1: H15 | T1: H16 | U1: H17 | V1: H18 | W1: H19 | X1: H20 | Y1: H21 | Z1: H22 | AA1: H23 | AB1: H24 | AC1: kWh/d | AD1: kWh/mes
A2: 2026 | B2: 1 | C2: 6 | D2: Festivo | E2: 3492.3228 | F2: 2788.9359 | G2: 2232.8087 | H2: 1904.4924 | I2: 1744.5994 | J2: 1748.2336 | K2: 1614.8319 | L2: 2366.3359 | M2: 3490.5116 | N2: 4492.667 | O2: 4982.3334 | P2: 5650.0256 | Q2: 6149.8096 | R2: 6108.4311 | S2: 5447.5972 | T2: 5160.4368 | U2: 4926.5063 | V2: 4811.8723 | W2: 6413.3869 | X2: 7702.4791 | Y2: 7586.1546 | Z2: 6653.7126 | AA2: 5384.1357 | AB2: 4212.4385 | AC2: 107065.06 | AD2: =+SUMPRODUCT(AC2:AC4,C2:C4) -> 4166702
A3: 2026 | B3: 1 | C3: 20 | D3: Hábil | E3: 3554.4765 | F3: 2894.8443 | G3: 2360.7787 | H3: 2015.7464 | I3: 1960.4837 | J3: 2354.0223 | K3: 2811.4721 | L3: 4014.3453 | M3: 5724.6639 | N3: 6594.9933 | O3: 7303.1893 | P3: 8290.4465 | Q3: 8405.3837 | R3: 8288.0915 | S3: 8230.2361 | T3: 8080.6593 | U3: 7963.6105 | V3: 7448.5901 | W3: 8224.167 | X3: 9115.3639 | Y3: 8792.6934 | Z3: 7717.9754 | AA3: 6181.8572 | AB3: 4734.6307 | AC3: 143062.72
A4: 2026 | B4: 1 | C4: 5 | D4: Sábado | E4: 3324.9927 | F4: 2625.6047 | G4: 2261.514 | H4: 1949.6499 | I4: 1654.769 | J4: 1758.5466 | K4: 1871.7617 | L4: 3140.9481 | M4: 4932.3031 | N4: 5859.6888 | O4: 6680.6026 | P4: 7596.7138 | Q4: 8009.6581 | R4: 7895.8207 | S4: 7615.9551 | T4: 7390.9658 | U4: 7048.0783 | V4: 6846.3585 | W4: 7961.6813 | X4: 8881.6315 | Y4: 8527.084 | Z4: 7630.8781 | AA4: 6233.4657 | AB4: 4912.7715 | AC4: 132611.44
A5: 2026 | B5: 2 | C5: 4 | D5: Festivo | E5: 3981.6918 | F5: 3275.2529 | G5: 2748.4648 | H5: 2282.0927 | I5: 1666.4552 | J5: 1539.8202 | K5: 1813.1707 | L5: 3118.4516 | M5: 4588.6554 | N5: 5506.0067 | O5: 6090.416 | P5: 6824.1105 | Q5: 7435.1075 | R5: 7310.5979 | S5: 6655.5756 | T5: 6116.0513 | U5: 5837.7361 | V5: 5533.1604 | W5: 6753.2891 | X5: 8068.7136 | Y5: 8171.2729 | Z5: 7222.4043 | AA5: 5661.0142 | AB5: 4223.6012 | AC5: 122423.11 | AD5: =+SUMPRODUCT(AC5:AC7,C5:C7) -> 4120884.4
A6: 2026 | B6: 2 | C6: 20 | D6: Hábil | E6: 3419.974 | F6: 2853.0529 | G6: 2384.566 | H6: 2139.5607 | I6: 2094.993 | J6: 2859.0669 | K6: 3620.4027 | L6: 4481.4742 | M6: 6033.6386 | N6: 6798.1565 | O6: 7581.6241 | P6: 8590.8742 | Q6: 8648.5125 | R6: 8611.2485 | S6: 8986.53 | T6: 8952.3072 | U6: 8788.742 | V6: 8325.9646 | W6: 8892.22 | X6: 9980.6752 | Y6: 9538.9197 | Z6: 7730.711 | AA6: 6180.0468 | AB6: 4579.8583 | AC6: 152073.12
A7: 2026 | B7: 2 | C7: 4 | D7: Sábado | E7: 3758.8194 | F7: 3034.7636 | G7: 2562.6995 | H7: 1915.2654 | I7: 2071.0271 | J7: 2334.8436 | K7: 2700.0241 | L7: 4200.0351 | M7: 5574.0418 | N7: 6367.3833 | O7: 7382.8064 | P7: 8107.9439 | Q7: 8714.0658 | R7: 8543.3406 | S7: 8161.0022 | T7: 8198.847 | U7: 7998.0373 | V7: 7718.7217 | W7: 8463.5848 | X7: 9568.2738 | Y7: 9310.551 | Z7: 8337.6407 | AA7: 6937.8625 | AB7: 5470.8077 | AC7: 147432.39
A8: 2026 | B8: 3 | C8: 6 | D8: Festivo | E8: 3043.7496 | F8: 3285.9474 | G8: 2514.6548 | H8: 2155.6465 | I8: 2028.0201 | J8: 2067.3892 | K8: 2077.8047 | L8: 3070.7487 | M8: 4636.064 | N8: 5440.8192 | O8: 6147.9689 | P8: 7017.1765 | Q8: 7660.1254 | R8: 7322.7644 | S8: 4893.8854 | T8: 5939.2751 | U8: 5626.5105 | V8: 5483.6219 | W8: 6939.9727 | X8: 9212.9593 | Y8: 9312.4369 | Z8: 8591.6775 | AA8: 7267.1733 | AB8: 5642.7507 | AC8: 127379.14 | AD8: =+SUMPRODUCT(AC8:AC10,C8:C10) -> 4663890.8
A9: 2026 | B9: 3 | C9: 21 | D9: Hábil | E9: 3887.2575 | F9: 3200.429 | G9: 2706.4874 | H9: 2393.6843 | I9: 2268.6524 | J9: 2984.3771 | K9: 3762.6246 | L9: 4731.3206 | M9: 6358.5091 | N9: 7195.0473 | O9: 7812.2002 | P9: 8669.185 | Q9: 8681.2272 | R9: 8649.3973 | S9: 8739.2021 | T9: 8850.0596 | U9: 8848.087 | V9: 8292.0945 | W9: 9085.1395 | X9: 10183.022 | Y9: 9797.3167 | Z9: 8621.6098 | AA9: 6819.6522 | AB9: 5188.6077 | AC9: 157725.19
A10: 2026 | B10: 3 | C10: 4 | D10: Sábado | E10: 4087.9557 | F10: 3217.7579 | G10: 2747.095 | H10: 2454.2012 | I10: 2331.6434 | J10: 2458.4716 | K10: 2541.1581 | L10: 3788.9613 | M10: 6288.7973 | N10: 7206.3328 | O10: 7751.7627 | P10: 8504.4838 | Q10: 8763.1971 | R10: 8501.7549 | S10: 8283.4742 | T10: 8114.084 | U10: 7784.3191 | V10: 7513.1054 | W10: 8623.4447 | X10: 9632.2023 | Y10: 9336.8113 | Z10: 7099.7934 | AA10: 5682.7261 | AB10: 4133.1983 | AC10: 146846.73
A11: 2026 | B11: 4 | C11: 6 | D11: Festivo | E11: 3295.587 | F11: 2519.7151 | G11: 2163.3523 | H11: 1708.7226 | I11: 1580.6571 | J11: 1567.6905 | K11: 1576.3892 | L11: 2707.8696 | M11: 4261.3756 | N11: 5272.1971 | O11: 6003.2942 | P11: 6839.8573 | Q11: 7467.3934 | R11: 7266.4919 | S11: 6349.7292 | T11: 5819.9546 | U11: 5489.8615 | V11: 5471.1336 | W11: 7034.1433 | X11: 8213.8399 | Y11: 7903.7852 | Z11: 6985.5384 | AA11: 5421.8773 | AB11: 3959.2883 | AC11: 116879.74 | AD11: =+SUMPRODUCT(AC11:AC13,C11:C13) -> 4125328.2
A12: 2026 | B12: 4 | C12: 20 | D12: Hábil | E12: 2949.6345 | F12: 2215.4495 | G12: 1847.4648 | H12: 1535.1662 | I12: 1441.9752 | J12: 2169.2516 | K12: 2934.0929 | L12: 4094.5275 | M12: 5678.3364 | N12: 6433.5951 | O12: 6927.8383 | P12: 8020.1506 | Q12: 8074.9784 | R12: 8348.4156 | S12: 8876.2349 | T12: 9030.1107 | U12: 8789.9768 | V12: 8353.6675 | W12: 9125.4642 | X12: 9929.0425 | Y12: 9348.338 | Z12: 8078.5015 | AA12: 6339.8037 | AB12: 4269.5514 | AC12: 144811.57
A13: 2026 | B13: 4 | C13: 4 | D13: Sábado | E13: 3420.7339 | F13: 2778.08 | G13: 2215.9452 | H13: 1864.3387 | I13: 882.83167 | J13: 1936.7423 | K13: 2041.6874 | L13: 3535.3773 | M13: 5496.6353 | N13: 6510.515 | O13: 7143.8771 | P13: 8129.3388 | Q13: 8396.9423 | R13: 8106.3581 | S13: 7672.6348 | T13: 7084.3284 | U13: 6780.7653 | V13: 6710.9325 | W13: 7890.0009 | X13: 8490.1011 | Y13: 8182.6102 | Z13: 7145.3836 | AA13: 5605.4035 | AB13: 3933.0183 | AC13: 131954.58
A14: 2026 | B14: 5 | C14: 7 | D14: Festivo | E14: 4242.5333 | F14: 3340.8988 | G14: 2932.621 | H14: 2659.5508 | I14: 2468.229 | J14: 2543.7633 | K14: 2631.5765 | L14: 3937.1456 | M14: 5623.9345 | N14: 6735.6517 | O14: 7505.4023 | P14: 8337.4877 | Q14: 8861.5176 | R14: 8689.5859 | S14: 7928.6044 | T14: 7437.3608 | U14: 7007.4595 | V14: 7124.9051 | W14: 8507.9376 | X14: 9363.1347 | Y14: 9226.8087 | Z14: 8032.0366 | AA14: 6389.4506 | AB14: 5016.54 | AC14: 146544.14 | AD14: =+SUMPRODUCT(AC14:AC16,C14:C16) -> 4694989
A15: 2026 | B15: 5 | C15: 19 | D15: Hábil | E15: 3352.3766 | F15: 2711.9769 | G15: 2241.8626 | H15: 2016.0595 | I15: 1846.2587 | J15: 2533.5279 | K15: 3270.9655 | L15: 4483.8043 | M15: 5992.6532 | N15: 6940.9868 | O15: 7713.4889 | P15: 8645.4888 | Q15: 8843.7429 | R15: 8943.3414 | S15: 9125.1625 | T15: 9050.3039 | U15: 8934.046 | V15: 8585.6801 | W15: 9469.0279 | X15: 10214.03 | Y15: 9681.2787 | Z15: 8147.2387 | AA15: 6337.2154 | AB15: 4643.5632 | AC15: 153724.08
A16: 2026 | B16: 5 | C16: 5 | D16: Sábado | E16: 3682.4701 | F16: 2964.4443 | G16: 2507.4286 | H16: 2186.5242 | I16: 2077.7838 | J16: 2067.0518 | K16: 2352.6495 | L16: 4051.7276 | M16: 6097.5257 | N16: 7402.8168 | O16: 8472.6684 | P16: 8895.1445 | Q16: 9366.8827 | R16: 9119.3766 | S16: 8615.3794 | T16: 8342.6186 | U16: 7759.9078 | V16: 7738.895 | W16: 8097.364 | X16: 9292.2789 | Y16: 8894.5675 | Z16: 7867.4331 | AA16: 6531.6654 | AB16: 5299.9047 | AC16: 149684.51
A17: 2026 | B17: 6 | C17: 6 | D17: Festivo | E17: 3496.7475 | F17: 2877.2798 | G17: 2353.2234 | H17: 1945.8228 | I17: 869.751 | J17: 1495.5644 | K17: 1529.7122 | L17: 2743.587 | M17: 4239.3981 | N17: 5148.2759 | O17: 5690.0059 | P17: 6217.6838 | Q17: 6818.0812 | R17: 6512.8606 | S17: 5968.7229 | T17: 5416.2062 | U17: 5103.0546 | V17: 5474.1306 | W17: 6885.4434 | X17: 8049.1678 | Y17: 7759.4566 | Z17: 6613.9377 | AA17: 5432.5667 | AB17: 4161.0967 | AC17: 112801.78 | AD17: =+SUMPRODUCT(AC17:AC19,C17:C19) -> 4033377.8
A18: 2026 | B18: 6 | C18: 20 | D18: Hábil | E18: 2787.0521 | F18: 2208.769 | G18: 1703.7615 | H18: 1444.514 | I18: 1386.6073 | J18: 1829.2487 | K18: 2536.9872 | L18: 4162.3702 | M18: 6109.3994 | N18: 6903.3298 | O18: 7586.425 | P18: 8916.4469 | Q18: 9123.0992 | R18: 8702.248 | S18: 8476.5747 | T18: 8307.7895 | U18: 8058.0329 | V18: 7771.9503 | W18: 8406.5891 | X18: 9081.644 | Y18: 8489.2025 | Z18: 7156.853 | AA18: 5521.1199 | AB18: 3941.3002 | AC18: 140611.31
A19: 2026 | B19: 6 | C19: 4 | D19: Sábado | E19: 3316.251 | F19: 2746.4229 | G19: 2142.7735 | H19: 1826.1572 | I19: 1715.7727 | J19: 1894.4693 | K19: 2216.9405 | L19: 3688.704 | M19: 5637.8445 | N19: 6576.7296 | O19: 7282.0606 | P19: 8175.028 | Q19: 8222.3346 | R19: 7864.1387 | S19: 7415.5986 | T19: 6992.3816 | U19: 6967.1737 | V19: 7219.158 | W19: 8260.0255 | X19: 9066.3839 | Y19: 8680.996 | Z19: 7461.4805 | AA19: 6055.716 | AB19: 4660.6604 | AC19: 136085.2
A20: 2026 | B20: 7 | C20: 6 | D20: Festivo | E20: 3226.7132 | F20: 2609.5696 | G20: 2086.0175 | H20: 1770.6324 | I20: 1626.6937 | J20: 1777.2643 | K20: 1757.7717 | L20: 3078.5144 | M20: 4666.4132 | N20: 5841.028 | O20: 6515.8113 | P20: 7575.0465 | Q20: 8229.8972 | R20: 8038.1315 | S20: 7415.694 | T20: 7031.6081 | U20: 6736.6876 | V20: 6582.1507 | W20: 7491.4699 | X20: 8745.0713 | Y20: 8204.8437 | Z20: 6902.9699 | AA20: 5409.0594 | AB20: 3954.9185 | AC20: 127273.98 | AD20: =+SUMPRODUCT(AC20:AC22,C20:C22) -> 4425238.2
A21: 2026 | B21: 7 | C21: 21 | D21: Hábil | E21: 3175.267 | F21: 2586.6833 | G21: 2097.7725 | H21: 1759.4579 | I21: 1733.3783 | J21: 2408.1888 | K21: 3139.3883 | L21: 4434.0955 | M21: 5912.3169 | N21: 6787.969 | O21: 7725.6503 | P21: 8675.614 | Q21: 8720.7075 | R21: 8912.6361 | S21: 9102.9684 | T21: 8306.8506 | U21: 8008.0017 | V21: 8081.513 | W21: 8803.6661 | X21: 9890.0088 | Y21: 9294.2821 | Z21: 7805.2064 | AA21: 5767.9544 | AB21: 4068.9149 | AC21: 147198.49
A22: 2026 | B22: 7 | C22: 4 | D22: Sábado | E22: 2544.1781 | F22: 1837.3856 | G22: 1379.0144 | H22: 1032.3066 | I22: 1040.5786 | J22: 1233.7899 | K22: 1589.7596 | L22: 3219.4358 | M22: 5398.9314 | N22: 6836.1708 | O22: 7956.9249 | P22: 8963.3134 | Q22: 9550.6497 | R22: 9331.1281 | S22: 8929.4635 | T22: 8622.6799 | U22: 8299.1848 | V22: 7971.5976 | W22: 8634.8932 | X22: 9592.5455 | Y22: 9052.9552 | Z22: 8058.8157 | AA22: 6550.9441 | AB22: 4979.8605 | AC22: 142606.51
A23: 2026 | B23: 8 | C23: 7 | D23: Festivo | E23: 0 | F23: 0 | G23: 0 | H23: 0 | I23: 0 | J23: 0 | K23: 0 | L23: 0 | M23: 0 | N23: 0 | O23: 0 | P23: 0 | Q23: 0 | R23: 0 | S23: 0 | T23: 0 | U23: 0 | V23: 0 | W23: 0 | X23: 0 | Y23: 0 | Z23: 0 | AA23: 0 | AB23: 0 | AC23: 0 | AD23: =+SUMPRODUCT(AC23:AC25,C23:C25) -> 0
A24: 2026 | B24: 8 | C24: 19 | D24: Hábil | E24: 0 | F24: 0 | G24: 0 | H24: 0 | I24: 0 | J24: 0 | K24: 0 | L24: 0 | M24: 0 | N24: 0 | O24: 0 | P24: 0 | Q24: 0 | R24: 0 | S24: 0 | T24: 0 | U24: 0 | V24: 0 | W24: 0 | X24: 0 | Y24: 0 | Z24: 0 | AA24: 0 | AB24: 0 | AC24: 0
A25: 2026 | B25: 8 | C25: 5 | D25: Sábado | E25: 0 | F25: 0 | G25: 0 | H25: 0 | I25: 0 | J25: 0 | K25: 0 | L25: 0 | M25: 0 | N25: 0 | O25: 0 | P25: 0 | Q25: 0 | R25: 0 | S25: 0 | T25: 0 | U25: 0 | V25: 0 | W25: 0 | X25: 0 | Y25: 0 | Z25: 0 | AA25: 0 | AB25: 0 | AC25: 0
A26: 2026 | B26: 9 | C26: 4 | D26: Festivo | E26: 0 | F26: 0 | G26: 0 | H26: 0 | I26: 0 | J26: 0 | K26: 0 | L26: 0 | M26: 0 | N26: 0 | O26: 0 | P26: 0 | Q26: 0 | R26: 0 | S26: 0 | T26: 0 | U26: 0 | V26: 0 | W26: 0 | X26: 0 | Y26: 0 | Z26: 0 | AA26: 0 | AB26: 0 | AC26: 0 | AD26: =+SUMPRODUCT(AC26:AC28,C26:C28) -> 0
A27: 2026 | B27: 9 | C27: 22 | D27: Hábil | E27: 0 | F27: 0 | G27: 0 | H27: 0 | I27: 0 | J27: 0 | K27: 0 | L27: 0 | M27: 0 | N27: 0 | O27: 0 | P27: 0 | Q27: 0 | R27: 0 | S27: 0 | T27: 0 | U27: 0 | V27: 0 | W27: 0 | X27: 0 | Y27: 0 | Z27: 0 | AA27: 0 | AB27: 0 | AC27: 0
A28: 2026 | B28: 9 | C28: 4 | D28: Sábado | E28: 0 | F28: 0 | G28: 0 | H28: 0 | I28: 0 | J28: 0 | K28: 0 | L28: 0 | M28: 0 | N28: 0 | O28: 0 | P28: 0 | Q28: 0 | R28: 0 | S28: 0 | T28: 0 | U28: 0 | V28: 0 | W28: 0 | X28: 0 | Y28: 0 | Z28: 0 | AA28: 0 | AB28: 0 | AC28: 0
A29: 2026 | B29: 10 | C29: 5 | D29: Festivo | E29: 0 | F29: 0 | G29: 0 | H29: 0 | I29: 0 | J29: 0 | K29: 0 | L29: 0 | M29: 0 | N29: 0 | O29: 0 | P29: 0 | Q29: 0 | R29: 0 | S29: 0 | T29: 0 | U29: 0 | V29: 0 | W29: 0 | X29: 0 | Y29: 0 | Z29: 0 | AA29: 0 | AB29: 0 | AC29: 0 | AD29: =+SUMPRODUCT(AC29:AC31,C29:C31) -> 0
A30: 2026 | B30: 10 | C30: 21 | D30: Hábil | E30: 0 | F30: 0 | G30: 0 | H30: 0 | I30: 0 | J30: 0 | K30: 0 | L30: 0 | M30: 0 | N30: 0 | O30: 0 | P30: 0 | Q30: 0 | R30: 0 | S30: 0 | T30: 0 | U30: 0 | V30: 0 | W30: 0 | X30: 0 | Y30: 0 | Z30: 0 | AA30: 0 | AB30: 0 | AC30: 0
A31: 2026 | B31: 10 | C31: 5 | D31: Sábado | E31: 0 | F31: 0 | G31: 0 | H31: 0 | I31: 0 | J31: 0 | K31: 0 | L31: 0 | M31: 0 | N31: 0 | O31: 0 | P31: 0 | Q31: 0 | R31: 0 | S31: 0 | T31: 0 | U31: 0 | V31: 0 | W31: 0 | X31: 0 | Y31: 0 | Z31: 0 | AA31: 0 | AB31: 0 | AC31: 0
A32: 2026 | B32: 11 | C32: 7 | D32: Festivo | E32: 3113.7894 | F32: 2372.6581 | G32: 1766.4824 | H32: 1579.4036 | I32: 1370.1005 | J32: 1524.7243 | K32: 1683.9559 | L32: 3021.8528 | M32: 4723.7959 | N32: 5697.2286 | O32: 6383.7284 | P32: 7321.6981 | Q32: 7865.0977 | R32: 7613.1262 | S32: 6640.2264 | T32: 6116.7901 | U32: 5840.2224 | V32: 6140.4288 | W32: 8192.6519 | X32: 8287.9482 | Y32: 7841.4254 | Z32: 6667.9976 | AA32: 5148.8977 | AB32: 3688.3144 | AC32: 120602.54 | AD32: =+SUMPRODUCT(AC32:AC34,C32:C34) -> 4072572.2
A33: 2026 | B33: 11 | C33: 19 | D33: Hábil | E33: 2902.3608 | F33: 2236.221 | G33: 1830.196 | H33: 1481.4357 | I33: 1433.1717 | J33: 2080.5676 | K33: 3074.21 | L33: 4477.8611 | M33: 5965.5098 | N33: 7008.7311 | O33: 7686.2896 | P33: 8600.3968 | Q33: 8564.853 | R33: 8582.0554 | S33: 8423.4125 | T33: 8407.5312 | U33: 8151.1912 | V33: 7949.0319 | W33: 9308.5242 | X33: 9215.7889 | Y33: 8487.67 | Z33: 7115.0539 | AA33: 5411.3322 | AB33: 3851.9607 | AC33: 142245.36
A34: 2026 | B34: 11 | C34: 4 | D34: Sábado | E34: 2624.7841 | F34: 2017.8629 | G34: 1509.9547 | H34: 775.3193 | I34: 782.51624 | J34: 1397.3699 | K34: 1886.2053 | L34: 3396.4827 | M34: 5480.7824 | N34: 6577.9593 | O34: 7383.6113 | P34: 8163.9463 | Q34: 8506.7264 | R34: 8204.6074 | S34: 7767.6941 | T34: 7376.8831 | U34: 6899.0521 | V34: 7214.2412 | W34: 8967.9606 | X34: 8927.9449 | Y34: 8303.3039 | Z34: 7131.7514 | AA34: 5819.2203 | AB34: 4306.9623 | AC34: 131423.14
A35: 2026 | B35: 12 | C35: 6 | D35: Festivo | E35: 3915.3174 | F35: 3042.3495 | G35: 2493.8058 | H35: 2091.8877 | I35: 1862.277 | J35: 1872.6364 | K35: 2068.1522 | L35: 3115.9657 | M35: 4478.7353 | N35: 5436.3621 | O35: 6108.4835 | P35: 6786.4432 | Q35: 7333.8488 | R35: 7346.5459 | S35: 6768.8542 | T35: 6263.5221 | U35: 5961.2372 | V35: 6077.5099 | W35: 7711.4539 | X35: 8055.2744 | Y35: 7657.5348 | Z35: 6810.1334 | AA35: 5552.2166 | AB35: 4175.9093 | AC35: 122986.46 | AD35: =+SUMPRODUCT(AC35:AC37,C35:C37) -> 4410647.3
A36: 2026 | B36: 12 | C36: 21 | D36: Hábil | E36: 3520.7343 | F36: 2852.5905 | G36: 2350.5638 | H36: 2015.3999 | I36: 1955.3027 | J36: 2350.3173 | K36: 3038.7292 | L36: 4654.265 | M36: 5994.4399 | N36: 6582.4382 | O36: 8168.5711 | P36: 7968.8136 | Q36: 8448.8046 | R36: 8137.9128 | S36: 8069.9543 | T36: 8490.4501 | U36: 8248.7913 | V36: 8402.3736 | W36: 9717.7298 | X36: 9792.2238 | Y36: 9096.6279 | Z36: 7853.5308 | AA36: 6249.5726 | AB36: 4704.858 | AC36: 148665
A37: 2026 | B37: 12 | C37: 4 | D37: Sábado | E37: 3408.0603 | F37: 2614.6337 | G37: 2148.6254 | H37: 1734.8188 | I37: 1561.9077 | J37: 1688.6582 | K37: 2253.7817 | L37: 3589.4368 | M37: 5485.411 | N37: 6548.4477 | O37: 7252.4285 | P37: 7938.8174 | Q37: 8118.8801 | R37: 7915.642 | S37: 7619.4233 | T37: 7443.2891 | U37: 7250.8407 | V37: 7438.2059 | W37: 9036.1063 | X37: 9311.792 | Y37: 8566.2188 | Z37: 7508.9657 | AA37: 6305.7988 | AB37: 4950.7228 | AC37: 137690.91
A38: 2027 | B38: 1 | C38: 7 | D38: Festivo | E38: 3705.3628 | F38: 2992.8899 | G38: 2429.5789 | H38: 2097.0215 | I38: 1935.0631 | J38: 1938.7443 | K38: 1803.6194 | L38: 2564.831 | M38: 3703.5282 | N38: 4718.629 | O38: 5214.6206 | P38: 5890.9377 | Q38: 6397.1778 | R38: 6355.2647 | S38: 5685.8945 | T38: 5395.0246 | U38: 5158.0723 | V38: 5041.9575 | W38: 6664.1598 | X38: 7969.9039 | Y38: 7852.0767 | Z38: 6907.5899 | AA38: 5621.6132 | AB38: 4434.7806 | AC38: 112478.34 | AD38: =+SUMPRODUCT(AC38:AC40,C38:C40) -> 4309001.1
A39: 2027 | B39: 1 | C39: 19 | D39: Hábil | E39: 3768.3193 | F39: 3100.1663 | G39: 2559.2019 | H39: 2209.7127 | I39: 2153.7362 | J39: 2552.3582 | K39: 3015.7172 | L39: 4234.1286 | M39: 5966.5402 | N39: 6848.1121 | O39: 7565.4563 | P39: 8565.4664 | Q39: 8681.8882 | R39: 8563.0809 | S39: 8504.4781 | T39: 8352.9692 | U39: 8234.4085 | V39: 7712.7353 | W39: 8498.3307 | X39: 9401.0397 | Y39: 9074.2011 | Z39: 7985.6004 | AA39: 6429.6393 | AB39: 4963.7182 | AC39: 148941
A40: 2027 | B40: 1 | C40: 5 | D40: Sábado | E40: 3535.8712 | F40: 2827.4488 | G40: 2458.655 | H40: 2142.7624 | I40: 1844.0724 | J40: 1949.1904 | K40: 2063.868 | L40: 3349.4492 | M40: 5163.9441 | N40: 6103.3093 | O40: 6934.8273 | P40: 7862.7723 | Q40: 8281.0508 | R40: 8165.743 | S40: 7882.2622 | T40: 7654.3666 | U40: 7307.0499 | V40: 7102.7243 | W40: 8232.4543 | X40: 9164.288 | Y40: 8805.1607 | Z40: 7897.3779 | AA40: 6481.9145 | AB40: 5144.1602 | AC40: 138354.72
A41: 2027 | B41: 2 | C41: 4 | D41: Festivo | E41: 2636.9751 | F41: 1986.4765 | G41: 1501.4027 | H41: 1071.9609 | I41: 505.07347 | J41: 388.46613 | K41: 640.1711 | L41: 1842.0917 | M41: 3195.8755 | N41: 4040.5852 | O41: 4578.7173 | P41: 5254.3133 | Q41: 5816.9278 | R41: 5702.2776 | S41: 5099.1241 | T41: 4602.3226 | U41: 4346.0462 | V41: 4065.5887 | W41: 5189.1 | X41: 6400.3609 | Y41: 6494.799 | Z41: 5621.0677 | AA41: 4183.3182 | AB41: 2859.7286 | AC41: 88022.77 | AD41: =+SUMPRODUCT(AC41:AC43,C41:C43) -> 3102795.8
A42: 2027 | B42: 2 | C42: 20 | D42: Hábil | E42: 2119.7377 | F42: 1597.7089 | G42: 1166.3197 | H42: 940.71549 | I42: 899.67687 | J42: 1603.2467 | K42: 2304.2952 | L42: 3097.1816 | M42: 4526.4359 | N42: 5230.4145 | O42: 5951.8422 | P42: 6881.1735 | Q42: 6934.2477 | R42: 6899.9345 | S42: 7245.4989 | T42: 7213.9861 | U42: 7063.3729 | V42: 6637.2411 | W42: 7158.6569 | X42: 8160.9214 | Y42: 7754.1469 | Z42: 6089.1235 | AA42: 4661.2506 | AB42: 3187.775 | AC42: 115324.9
A43: 2027 | B43: 2 | C43: 4 | D43: Sábado | E43: 2431.7511 | F43: 1765.0306 | G43: 1330.3475 | H43: 734.18128 | I43: 877.60879 | J43: 1120.5347 | K43: 1456.7979 | L43: 2838.0286 | M43: 4103.2329 | N43: 4833.7526 | O43: 5768.7681 | P43: 6436.4847 | Q43: 6994.6101 | R43: 6837.4039 | S43: 6485.3415 | T43: 6520.1896 | U43: 6335.2812 | V43: 6078.0836 | W43: 6763.9638 | X43: 7781.1765 | Y43: 7543.8618 | Z43: 6647.9927 | AA43: 5359.0577 | AB43: 4008.1734 | AC43: 111051.65
A44: 2027 | B44: 3 | C44: 7 | D44: Festivo | E44: 2231.7141 | F44: 2461.6532 | G44: 1729.3988 | H44: 1388.5612 | I44: 1267.3945 | J44: 1304.771 | K44: 1314.6593 | L44: 2257.3466 | M44: 3743.4354 | N44: 4507.4588 | O44: 5178.8169 | P44: 6004.0306 | Q44: 6614.4374 | R44: 6294.1516 | S44: 3988.2074 | T44: 4980.6859 | U44: 4683.7515 | V44: 4548.0951 | W44: 5930.7344 | X44: 8088.6764 | Y44: 8183.1191 | Z44: 7498.8401 | AA44: 6241.3741 | AB44: 4699.1697 | AC44: 105140.48 | AD44: =+SUMPRODUCT(AC44:AC46,C44:C46) -> 3909486.4
A45: 2027 | B45: 3 | C45: 20 | D45: Hábil | E45: 3032.5288 | F45: 2380.4633 | G45: 1911.522 | H45: 1614.5511 | I45: 1495.8475 | J45: 2175.3467 | K45: 2914.204 | L45: 3833.8706 | M45: 5378.7008 | N45: 6172.8987 | O45: 6758.8152 | P45: 7572.4246 | Q45: 7583.8573 | R45: 7553.6384 | S45: 7638.8979 | T45: 7744.1444 | U45: 7742.2717 | V45: 7214.4201 | W45: 7967.3261 | X45: 9009.6403 | Y45: 8643.4573 | Z45: 7527.2574 | AA45: 5816.5038 | AB45: 4268.0126 | AC45: 133950.6
A46: 2027 | B46: 3 | C46: 4 | D46: Sábado | E46: 3223.0689 | F46: 2396.9151 | G46: 1950.0742 | H46: 1672.005 | I46: 1555.6502 | J46: 1676.0592 | K46: 1754.5606 | L46: 2939.2077 | M46: 5312.5175 | N46: 6183.6129 | O46: 6701.4366 | P46: 7416.0596 | Q46: 7661.6784 | R46: 7413.4688 | S46: 7206.2361 | T46: 7045.4194 | U46: 6732.3452 | V46: 6474.8586 | W46: 7528.9994 | X46: 8486.6999 | Y46: 8206.2598 | Z46: 6082.466 | AA46: 4737.1218 | AB46: 3266.0216 | AC46: 123622.74
A47: 2027 | B47: 4 | C47: 4 | D47: Festivo | E47: 2475.4362 | F47: 1738.6136 | G47: 1400.1864 | H47: 968.43814 | I47: 846.81812 | J47: 834.50409 | K47: 842.76499 | L47: 1917.2984 | M47: 3392.617 | N47: 4352.5643 | O47: 5046.8655 | P47: 5841.3247 | Q47: 6437.2771 | R47: 6246.487 | S47: 5375.8646 | T47: 4872.7533 | U47: 4559.2737 | V47: 4541.4883 | W47: 6025.8324 | X47: 7146.1553 | Y47: 6851.7055 | Z47: 5979.6737 | AA47: 4494.7111 | AB47: 3105.7337 | AC47: 95294.387 | AD47: =+SUMPRODUCT(AC47:AC49,C47:C49) -> 3499668.7
A48: 2027 | B48: 4 | C48: 22 | D48: Hábil | E48: 2146.8954 | F48: 1449.6616 | G48: 1100.1974 | H48: 803.61668 | I48: 715.11603 | J48: 1405.7889 | K48: 2132.136 | L48: 3234.1663 | M48: 4738.2627 | N48: 5455.5095 | O48: 5924.8776 | P48: 6962.2143 | Q48: 7014.2827 | R48: 7273.9579 | S48: 7775.2122 | T48: 7921.3435 | U48: 7693.2955 | V48: 7278.9454 | W48: 8011.8979 | X48: 8775.0324 | Y48: 8223.5546 | Z48: 7017.6284 | AA48: 5366.4386 | AB48: 3400.3814 | AC48: 121820.41
A49: 2027 | B49: 4 | C49: 4 | D49: Sábado | E49: 2594.2845 | F49: 1983.9751 | G49: 1450.1323 | H49: 1116.2221 | I49: 184.11395 | J49: 1184.9816 | K49: 1284.6449 | L49: 2703.1579 | M49: 4565.7065 | N49: 5528.5581 | O49: 6130.0433 | P49: 7065.9071 | Q49: 7320.0422 | R49: 7044.083 | S49: 6632.1889 | T49: 6073.4917 | U49: 5785.2068 | V49: 5718.8886 | W49: 6838.615 | X49: 7408.5123 | Y49: 7116.4974 | Z49: 6131.474 | AA49: 4669.0005 | AB49: 3080.7859 | AC49: 109610.51
A50: 2027 | B50: 5 | C50: 7 | D50: Festivo | E50: 3392.5054 | F50: 2535.32 | G50: 2147.1696 | H50: 1887.5613 | I50: 1705.6714 | J50: 1777.4819 | K50: 1860.9661 | L50: 3102.1729 | M50: 4705.8059 | N50: 5762.7173 | O50: 6494.5205 | P50: 7285.5855 | Q50: 7783.7816 | R50: 7620.3258 | S50: 6896.8595 | T50: 6429.8334 | U50: 6021.1254 | V50: 6132.7812 | W50: 7447.6325 | X50: 8260.6698 | Y50: 8131.0645 | Z50: 6995.1926 | AA50: 5433.5833 | AB50: 4128.3549 | AC50: 123938.68 | AD50: =+SUMPRODUCT(AC50:AC52,C50:C52) -> 3990561.1
A51: 2027 | B51: 5 | C51: 20 | D51: Hábil | E51: 2546.2319 | F51: 1937.4029 | G51: 1490.4645 | H51: 1275.7931 | I51: 1114.3631 | J51: 1767.7512 | K51: 2468.8343 | L51: 3621.8822 | M51: 5056.3474 | N51: 5957.9297 | O51: 6692.3488 | P51: 7578.4027 | Q51: 7766.8831 | R51: 7861.5716 | S51: 8034.4293 | T51: 7963.2611 | U51: 7852.7344 | V51: 7521.5425 | W51: 8361.3426 | X51: 9069.6175 | Y51: 8563.1299 | Z51: 7104.7154 | AA51: 5383.9232 | AB51: 3773.7653 | AC51: 130764.67
A52: 2027 | B52: 5 | C52: 4 | D52: Sábado | E52: 2860.0524 | F52: 2177.424 | G52: 1742.9385 | H52: 1437.8542 | I52: 1334.4745 | J52: 1324.2715 | K52: 1595.7897 | L52: 3211.1061 | M52: 5156.0498 | N52: 6396.9923 | O52: 7414.102 | P52: 7815.7508 | Q52: 8264.233 | R52: 8028.9286 | S52: 7549.7776 | T52: 7290.4634 | U52: 6736.4793 | V52: 6716.5024 | W52: 7057.2995 | X52: 8193.3071 | Y52: 7815.2022 | Z52: 6838.7037 | AA52: 5568.7872 | AB52: 4397.7502 | AC52: 126924.24
A53: 2027 | B53: 6 | C53: 6 | D53: Festivo | E53: 2662.0724 | F53: 2073.9475 | G53: 1576.4064 | H53: 1189.6188 | I53: 167.99231 | J53: 762.14188 | K53: 794.56188 | L53: 1947.0191 | M53: 3367.1476 | N53: 4230.0395 | O53: 4744.3599 | P53: 5245.3392 | Q53: 5815.3587 | R53: 5525.5812 | S53: 5008.9749 | T53: 4484.4135 | U53: 4187.1062 | V53: 4539.4071 | W53: 5879.3126 | X53: 6984.1569 | Y53: 6709.104 | Z53: 5621.5442 | AA53: 4499.9463 | AB53: 3292.8079 | AC53: 91308.36 | AD53: =+SUMPRODUCT(AC53:AC55,C53:C55) -> 3355721.8
A54: 2027 | B54: 6 | C54: 20 | D54: Hábil | E54: 1988.285 | F54: 1439.2609 | G54: 959.80488 | H54: 713.6744 | I54: 658.69753 | J54: 1078.9429 | K54: 1750.8724 | L54: 3294.017 | M54: 5142.5337 | N54: 5896.2941 | O54: 6544.8272 | P54: 7807.5548 | Q54: 8003.7512 | R54: 7604.1936 | S54: 7389.9386 | T54: 7229.6933 | U54: 6992.5734 | V54: 6720.9656 | W54: 7323.494 | X54: 7964.3936 | Y54: 7401.9274 | Z54: 6136.9899 | AA54: 4584.0189 | AB54: 3084.1323 | AC54: 117710.84
A55: 2027 | B55: 6 | C55: 4 | D55: Sábado | E55: 2490.7083 | F55: 1949.7115 | G55: 1376.6045 | H55: 1076.0079 | I55: 971.20838 | J55: 1140.8636 | K55: 1447.0189 | L55: 2844.3166 | M55: 4694.8377 | N55: 5586.2187 | O55: 6255.8625 | P55: 7103.649 | Q55: 7148.5621 | R55: 6808.4896 | S55: 6382.6439 | T55: 5980.8402 | U55: 5956.9077 | V55: 6196.1425 | W55: 7184.3459 | X55: 7949.9055 | Y55: 7584.0169 | Z55: 6426.2044 | AA55: 5091.5664 | AB55: 3767.0955 | AC55: 113413.73
A56: 2027 | B56: 7 | C56: 6 | D56: Festivo | E56: 2419.192 | F56: 1832.7606 | G56: 1335.263 | H56: 1035.573 | I56: 898.79743 | J56: 1041.8748 | K56: 1023.3523 | L56: 2278.3684 | M56: 3787.2455 | N56: 4903.4056 | O56: 5544.6085 | P56: 6551.1309 | Q56: 7173.393 | R56: 6991.1705 | S56: 6399.7085 | T56: 6034.7366 | U56: 5754.4928 | V56: 5607.6465 | W56: 6471.7134 | X56: 7662.9295 | Y56: 7149.5862 | Z56: 5912.5001 | AA56: 4492.934 | AB56: 3111.1583 | AC56: 105413.54 | AD56: =+SUMPRODUCT(AC56:AC58,C56:C58) -> 3719326.8
A57: 2027 | B57: 7 | C57: 20 | D57: Hábil | E57: 2370.3061 | F57: 1811.0132 | G57: 1346.433 | H57: 1024.9546 | I57: 1000.1729 | J57: 1641.4015 | K57: 2336.2129 | L57: 3566.4891 | M57: 4971.1469 | N57: 5803.2222 | O57: 6694.2399 | P57: 7596.9288 | Q57: 7639.7781 | R57: 7822.1554 | S57: 8003.0159 | T57: 7246.5168 | U57: 6962.5401 | V57: 7032.3931 | W57: 7718.6083 | X57: 8750.8893 | Y57: 8184.8089 | Z57: 6769.8369 | AA57: 4833.9686 | AB57: 3219.4816 | AC57: 124346.51
A58: 2027 | B58: 7 | C58: 5 | D58: Sábado | E58: 1770.6233 | F58: 1099.0042 | G58: 663.44382 | H58: 333.98998 | I58: 341.85032 | J58: 525.44642 | K58: 863.70137 | L58: 2412.2768 | M58: 4483.31 | N58: 5849.0253 | O58: 6914.0052 | P58: 7870.3108 | Q58: 8428.4184 | R58: 8219.8212 | S58: 7838.1454 | T58: 7546.6288 | U58: 7239.2325 | V58: 6927.9477 | W58: 7558.2344 | X58: 8468.2292 | Y58: 7955.4916 | Z58: 7010.8253 | AA58: 5577.9929 | AB58: 4085.0941 | AC58: 119983.05
A59: 2027 | B59: 8 | C59: 7 | D59: Festivo | E59: 0 | F59: 0 | G59: 0 | H59: 0 | I59: 0 | J59: 0 | K59: 0 | L59: 0 | M59: 0 | N59: 0 | O59: 0 | P59: 0 | Q59: 0 | R59: 0 | S59: 0 | T59: 0 | U59: 0 | V59: 0 | W59: 0 | X59: 0 | Y59: 0 | Z59: 0 | AA59: 0 | AB59: 0 | AC59: 0 | AD59: =+SUMPRODUCT(AC59:AC61,C59:C61) -> 0
A60: 2027 | B60: 8 | C60: 21 | D60: Hábil | E60: 0 | F60: 0 | G60: 0 | H60: 0 | I60: 0 | J60: 0 | K60: 0 | L60: 0 | M60: 0 | N60: 0 | O60: 0 | P60: 0 | Q60: 0 | R60: 0 | S60: 0 | T60: 0 | U60: 0 | V60: 0 | W60: 0 | X60: 0 | Y60: 0 | Z60: 0 | AA60: 0 | AB60: 0 | AC60: 0
A61: 2027 | B61: 8 | C61: 3 | D61: Sábado | E61: 0 | F61: 0 | G61: 0 | H61: 0 | I61: 0 | J61: 0 | K61: 0 | L61: 0 | M61: 0 | N61: 0 | O61: 0 | P61: 0 | Q61: 0 | R61: 0 | S61: 0 | T61: 0 | U61: 0 | V61: 0 | W61: 0 | X61: 0 | Y61: 0 | Z61: 0 | AA61: 0 | AB61: 0 | AC61: 0
A62: 2027 | B62: 9 | C62: 4 | D62: Festivo | E62: 0 | F62: 0 | G62: 0 | H62: 0 | I62: 0 | J62: 0 | K62: 0 | L62: 0 | M62: 0 | N62: 0 | O62: 0 | P62: 0 | Q62: 0 | R62: 0 | S62: 0 | T62: 0 | U62: 0 | V62: 0 | W62: 0 | X62: 0 | Y62: 0 | Z62: 0 | AA62: 0 | AB62: 0 | AC62: 0 | AD62: =+SUMPRODUCT(AC62:AC64,C62:C64) -> 0
A63: 2027 | B63: 9 | C63: 22 | D63: Hábil | E63: 0 | F63: 0 | G63: 0 | H63: 0 | I63: 0 | J63: 0 | K63: 0 | L63: 0 | M63: 0 | N63: 0 | O63: 0 | P63: 0 | Q63: 0 | R63: 0 | S63: 0 | T63: 0 | U63: 0 | V63: 0 | W63: 0 | X63: 0 | Y63: 0 | Z63: 0 | AA63: 0 | AB63: 0 | AC63: 0
A64: 2027 | B64: 9 | C64: 4 | D64: Sábado | E64: 0 | F64: 0 | G64: 0 | H64: 0 | I64: 0 | J64: 0 | K64: 0 | L64: 0 | M64: 0 | N64: 0 | O64: 0 | P64: 0 | Q64: 0 | R64: 0 | S64: 0 | T64: 0 | U64: 0 | V64: 0 | W64: 0 | X64: 0 | Y64: 0 | Z64: 0 | AA64: 0 | AB64: 0 | AC64: 0
A65: 2027 | B65: 10 | C65: 6 | D65: Festivo | E65: 0 | F65: 0 | G65: 0 | H65: 0 | I65: 0 | J65: 0 | K65: 0 | L65: 0 | M65: 0 | N65: 0 | O65: 0 | P65: 0 | Q65: 0 | R65: 0 | S65: 0 | T65: 0 | U65: 0 | V65: 0 | W65: 0 | X65: 0 | Y65: 0 | Z65: 0 | AA65: 0 | AB65: 0 | AC65: 0 | AD65: =+SUMPRODUCT(AC65:AC67,C65:C67) -> 0
A66: 2027 | B66: 10 | C66: 20 | D66: Hábil | E66: 0 | F66: 0 | G66: 0 | H66: 0 | I66: 0 | J66: 0 | K66: 0 | L66: 0 | M66: 0 | N66: 0 | O66: 0 | P66: 0 | Q66: 0 | R66: 0 | S66: 0 | T66: 0 | U66: 0 | V66: 0 | W66: 0 | X66: 0 | Y66: 0 | Z66: 0 | AA66: 0 | AB66: 0 | AC66: 0
A67: 2027 | B67: 10 | C67: 5 | D67: Sábado | E67: 0 | F67: 0 | G67: 0 | H67: 0 | I67: 0 | J67: 0 | K67: 0 | L67: 0 | M67: 0 | N67: 0 | O67: 0 | P67: 0 | Q67: 0 | R67: 0 | S67: 0 | T67: 0 | U67: 0 | V67: 0 | W67: 0 | X67: 0 | Y67: 0 | Z67: 0 | AA67: 0 | AB67: 0 | AC67: 0
A68: 2027 | B68: 11 | C68: 6 | D68: Festivo | E68: 2269.9576 | F68: 1567.6371 | G68: 993.20514 | H68: 815.92312 | I68: 617.5806 | J68: 764.10713 | K68: 915.00026 | L68: 2182.8354 | M68: 3795.6528 | N68: 4718.1097 | O68: 5368.6595 | P68: 6257.5105 | Q68: 6772.4539 | R68: 6533.6773 | S68: 5611.7255 | T68: 5115.7 | U68: 4853.6153 | V68: 5138.1008 | W68: 7082.855 | X68: 7173.1609 | Y68: 6750.0212 | Z68: 5638.0423 | AA68: 4198.4932 | AB68: 2814.3964 | AC68: 97948.421 | AD68: =+SUMPRODUCT(AC68:AC70,C68:C70) -> 3389657.3
A69: 2027 | B69: 11 | C69: 20 | D69: Hábil | E69: 2069.6009 | F69: 1438.3448 | G69: 1053.5823 | H69: 723.08547 | I69: 677.34893 | J69: 1290.8426 | K69: 2232.4509 | L69: 3562.5968 | M69: 4972.3417 | N69: 5960.9327 | O69: 6603.0094 | P69: 7469.2475 | Q69: 7435.5651 | R69: 7451.8666 | S69: 7301.5314 | T69: 7286.4817 | U69: 7043.5655 | V69: 6851.9927 | W69: 8140.2923 | X69: 8052.4134 | Y69: 7362.4239 | Z69: 6061.6876 | AA69: 4447.1848 | AB69: 2969.473 | AC69: 118457.86
A70: 2027 | B70: 11 | C70: 4 | D70: Sábado | E70: 1806.5601 | F70: 1231.4216 | G70: 750.11098 | H70: 53.94631 | I70: 60.766366 | J70: 643.42194 | K70: 1106.6585 | L70: 2537.8471 | M70: 4512.9982 | N70: 5552.7192 | O70: 6316.1815 | P70: 7055.6526 | Q70: 7380.4823 | R70: 7094.1844 | S70: 6680.151 | T70: 6309.8057 | U70: 5856.9972 | V70: 6155.6808 | W70: 7817.5631 | X70: 7779.6429 | Y70: 7187.7125 | Z70: 6077.5108 | AA70: 4833.713 | AB70: 3400.6475 | AC70: 108202.38
A71: 2027 | B71: 12 | C71: 6 | D71: Festivo | E71: 3428.0665 | F71: 2580.2447 | G71: 2047.5019 | H71: 1657.1612 | I71: 1434.1645 | J71: 1444.2255 | K71: 1634.1094 | L71: 2651.7403 | M71: 3975.2549 | N71: 4905.297 | O71: 5558.0578 | P71: 6216.4886 | Q71: 6748.126 | R71: 6760.4573 | S71: 6199.4063 | T71: 5708.6304 | U71: 5415.0529 | V71: 5527.9763 | W71: 7114.854 | X71: 7448.7707 | Y71: 7062.4881 | Z71: 6239.4964 | AA71: 5017.8143 | AB71: 3681.1519 | AC71: 110456.54 | AD71: =+SUMPRODUCT(AC71:AC73,C71:C73) -> 4015650.2
A72: 2027 | B72: 12 | C72: 22 | D72: Hábil | E72: 3044.8495 | F72: 2395.9518 | G72: 1908.386 | H72: 1582.8767 | I72: 1524.5106 | J72: 1908.1466 | K72: 2576.7287 | L72: 4145.7284 | M72: 5447.2992 | N72: 6018.36 | O72: 7558.8039 | P72: 7364.8005 | Q72: 7830.9651 | R72: 7529.0286 | S72: 7463.0278 | T72: 7871.411 | U72: 7636.7133 | V72: 7785.8716 | W72: 9063.3386 | X72: 9135.6867 | Y72: 8460.1277 | Z72: 7252.8384 | AA72: 5695.0827 | AB72: 4194.8641 | AC72: 135395.4
A73: 2027 | B73: 12 | C73: 3 | D73: Sábado | E73: 2935.421 | F73: 2164.8493 | G73: 1712.2645 | H73: 1310.3778 | I73: 1142.4475 | J73: 1265.5469 | K73: 1814.3918 | L73: 3111.5729 | M73: 4952.933 | N73: 5985.3486 | O73: 6669.0511 | P73: 7335.6683 | Q73: 7510.5442 | R73: 7313.1605 | S73: 7025.4745 | T73: 6854.4139 | U73: 6667.509 | V73: 6849.4771 | W73: 8401.3495 | X73: 8669.094 | Y73: 7944.9972 | Z73: 6918.1986 | AA73: 5749.6892 | AB73: 4433.6467 | AC73: 124737.43
A74: 2028 | B74: 1 | C74: 7 | D74: Festivo | E74: 4116.6556 | F74: 3386.6414 | G74: 2809.4614 | H74: 2468.7164 | I74: 2302.7704 | J74: 2306.5422 | K74: 2168.0905 | L74: 2948.0434 | M74: 4114.7758 | N74: 5154.8689 | O74: 5663.072 | P74: 6356.0403 | Q74: 6874.7442 | R74: 6831.7993 | S74: 6145.9489 | T74: 5847.9177 | U74: 5605.1315 | V74: 5486.1579 | W74: 7148.2995 | X74: 8486.1915 | Y74: 8365.4634 | Z74: 7397.7229 | AA74: 6080.0849 | AB74: 4864.032 | AC74: 122929.17 | AD74: =+SUMPRODUCT(AC74:AC76,C74:C76) -> 4664066
A75: 2028 | B75: 1 | C75: 20 | D75: Hábil | E75: 4181.1622 | F75: 3496.5589 | G75: 2942.2758 | H75: 2584.182 | I75: 2526.8273 | J75: 2935.2636 | K75: 3410.0307 | L75: 4658.4398 | M75: 6433.5042 | N75: 7336.7807 | O75: 8071.7862 | P75: 9096.417 | Q75: 9215.7052 | R75: 9093.9728 | S75: 9033.9272 | T75: 8878.6881 | U75: 8757.2082 | V75: 8222.6912 | W75: 9027.6284 | X75: 9952.5624 | Y75: 9617.6769 | Z75: 8502.2744 | AA75: 6908.005 | AB75: 5405.9922 | AC75: 160289.56
A76: 2028 | B76: 1 | C76: 4 | D76: Sábado | E76: 3942.991 | F76: 3217.1271 | G76: 2839.2533 | H76: 2515.5834 | I76: 2209.5395 | J76: 2317.2456 | K76: 2434.7466 | L76: 3751.9793 | M76: 5611.1478 | N76: 6573.6406 | O76: 7425.6308 | P76: 8376.4223 | Q76: 8804.999 | R76: 8686.8522 | S76: 8396.392 | T76: 8162.8855 | U76: 7807.0177 | V76: 7597.6616 | W76: 8755.206 | X76: 9709.9818 | Y76: 9342.0126 | Z76: 8411.8799 | AA76: 6961.5671 | AB76: 5590.8768 | AC76: 149442.64
A77: 2028 | B77: 2 | C77: 4 | D77: Festivo | E77: 3331.9934 | F77: 2652.5819 | G77: 2145.9481 | H77: 1697.4189 | I77: 1105.3349 | J77: 983.5447 | K77: 1246.4372 | L77: 2501.7797 | M77: 3915.7353 | N77: 4797.9899 | O77: 5360.0404 | P77: 6065.6647 | Q77: 6653.2857 | R77: 6533.5397 | S77: 5903.5777 | T77: 5384.6949 | U77: 5117.0278 | V77: 4824.1047 | W77: 5997.5528 | X77: 7262.6508 | Y77: 7361.2864 | Z77: 6448.7203 | AA77: 4947.067 | AB77: 3564.6476 | AC77: 105802.62 | AD77: =+SUMPRODUCT(AC77:AC79,C77:C79) -> 3763314.2
A78: 2028 | B78: 2 | C78: 21 | D78: Hábil | E78: 2791.7662 | F78: 2246.5348 | G78: 1795.9716 | H78: 1560.3399 | I78: 1517.4773 | J78: 2252.3187 | K78: 2984.5268 | L78: 3812.6548 | M78: 5305.4353 | N78: 6040.7036 | O78: 6794.1968 | P78: 7764.8341 | Q78: 7820.2673 | R78: 7784.429 | S78: 8145.3527 | T78: 8112.4392 | U78: 7955.1318 | V78: 7510.0597 | W78: 8054.6508 | X78: 9101.4631 | Y78: 8676.6086 | Z78: 6937.5797 | AA78: 5446.242 | AB78: 3907.2748 | AC78: 134318.26
A79: 2028 | B79: 2 | C79: 4 | D79: Sábado | E79: 3117.6478 | F79: 2421.2935 | G79: 1967.29 | H79: 1344.6259 | I79: 1494.4283 | J79: 1748.1516 | K79: 2099.3607 | L79: 3541.9832 | M79: 4863.4221 | N79: 5626.4113 | O79: 6602.9855 | P79: 7300.3802 | Q79: 7883.3126 | R79: 7719.1191 | S79: 7351.4086 | T79: 7387.8055 | U79: 7194.6785 | V79: 6926.0492 | W79: 7642.4147 | X79: 8704.8397 | Y79: 8456.977 | Z79: 7521.2891 | AA79: 6175.0646 | AB79: 4764.1375 | AC79: 129855.08
A80: 2028 | B80: 3 | C80: 5 | D80: Festivo | E80: 2658.5875 | F80: 2894.9708 | G80: 2142.1946 | H80: 1791.805 | I80: 1667.2426 | J80: 1705.6665 | K80: 1715.832 | L80: 2684.9384 | M80: 4212.6752 | N80: 4998.1107 | O80: 5688.2837 | P80: 6536.6243 | Q80: 7164.138 | R80: 6834.876 | S80: 4464.3071 | T80: 5484.6001 | U80: 5179.344 | V80: 5039.8858 | W80: 6461.274 | X80: 8679.693 | Y80: 8776.7824 | Z80: 8073.3263 | AA80: 6780.6194 | AB80: 5195.1943 | AC80: 116830.97 | AD80: =+SUMPRODUCT(AC80:AC82,C80:C82) -> 4349346.7
A81: 2028 | B81: 3 | C81: 22 | D81: Hábil | E81: 3481.8453 | F81: 2811.5054 | G81: 2329.4219 | H81: 2024.1283 | I81: 1902.098 | J81: 2600.6404 | K81: 3360.2044 | L81: 4305.6449 | M81: 5893.7695 | N81: 6710.225 | O81: 7312.5619 | P81: 8148.9731 | Q81: 8160.7262 | R81: 8129.6604 | S81: 8217.3093 | T81: 8325.5054 | U81: 8323.5802 | V81: 7780.9353 | W81: 8554.9417 | X81: 9626.4672 | Y81: 9250.0217 | Z81: 8102.54 | AA81: 6343.842 | AB81: 4751.9539 | AC81: 146448.5
A82: 2028 | B82: 3 | C82: 4 | D82: Sábado | E82: 3677.7253 | F82: 2828.4183 | G82: 2369.0546 | H82: 2083.1924 | I82: 1963.5768 | J82: 2087.3602 | K82: 2168.0617 | L82: 3385.9089 | M82: 5825.7313 | N82: 6721.2395 | O82: 7253.5754 | P82: 7988.2259 | Q82: 8240.7282 | R82: 7985.5625 | S82: 7772.522 | T82: 7607.1984 | U82: 7285.3501 | V82: 7020.6475 | W82: 8104.3308 | X82: 9088.8712 | Y82: 8800.5717 | Z82: 6617.2579 | AA82: 5234.21 | AB82: 3721.8818 | AC82: 135831.2
A83: 2028 | B83: 4 | C83: 7 | D83: Festivo | E83: 2969.2268 | F83: 2208.8937 | G83: 1859.668 | H83: 1414.1434 | I83: 1288.6427 | J83: 1275.9358 | K83: 1284.4603 | L83: 2393.2799 | M83: 3915.6731 | N83: 4906.2503 | O83: 5622.7053 | P83: 6442.5142 | Q83: 7057.4823 | R83: 6860.6044 | S83: 5962.2022 | T83: 5443.0375 | U83: 5119.5554 | V83: 5101.2026 | W83: 6632.9091 | X83: 7788.9794 | Y83: 7485.1343 | Z83: 6585.2777 | AA83: 5052.9328 | AB83: 3619.6358 | AC83: 108290.35 | AD83: =+SUMPRODUCT(AC83:AC85,C83:C85) -> 3815278.6
A84: 2028 | B84: 4 | C84: 18 | D84: Hábil | E84: 2630.2029 | F84: 1910.7218 | G84: 1550.1069 | H84: 1244.0628 | I84: 1152.7383 | J84: 1865.4491 | K84: 2614.9726 | L84: 3752.1665 | M84: 5304.2556 | N84: 6044.3884 | O84: 6528.7331 | P84: 7599.1691 | Q84: 7652.8989 | R84: 7920.8598 | S84: 8438.1082 | T84: 8588.9023 | U84: 8353.5777 | V84: 7926.0065 | W84: 8682.346 | X84: 9469.8307 | Y84: 8900.7563 | Z84: 7656.3514 | AA84: 5952.4754 | AB84: 3923.6851 | AC84: 135662.77
A85: 2028 | B85: 4 | C85: 5 | D85: Sábado | E85: 3091.8673 | F85: 2462.0842 | G85: 1911.2075 | H85: 1566.6429 | I85: 604.79299 | J85: 1637.5964 | K85: 1740.4397 | L85: 3204.2147 | M85: 5126.1936 | N85: 6119.7678 | O85: 6740.4452 | P85: 7706.1706 | Q85: 7968.4146 | R85: 7683.6501 | S85: 7258.6133 | T85: 6682.0892 | U85: 6384.6057 | V85: 6316.1714 | W85: 7471.626 | X85: 8059.7076 | Y85: 7758.3751 | Z85: 6741.9216 | AA85: 5232.7834 | AB85: 3593.892 | AC85: 123063.27
A86: 2028 | B86: 5 | C86: 6 | D86: Festivo | E86: 3838.0456 | F86: 2957.5623 | G86: 2558.8621 | H86: 2292.1978 | I86: 2105.3642 | J86: 2179.1265 | K86: 2264.8798 | L86: 3539.8219 | M86: 5187.0409 | N86: 6272.6786 | O86: 7024.3719 | P86: 7836.9376 | Q86: 8348.6744 | R86: 8180.776 | S86: 7437.6462 | T86: 6957.9266 | U86: 6538.1102 | V86: 6652.8007 | W86: 8003.389 | X86: 8838.5243 | Y86: 8705.3963 | Z86: 7538.652 | AA86: 5934.5989 | AB86: 4593.8951 | AC86: 135787.28 | AD86: =+SUMPRODUCT(AC86:AC88,C86:C88) -> 4368914.2
A87: 2028 | B87: 5 | C87: 21 | D87: Hábil | E87: 2968.7708 | F87: 2343.3941 | G87: 1884.3081 | H87: 1663.8021 | I87: 1497.9845 | J87: 2169.1313 | K87: 2889.2695 | L87: 4073.6567 | M87: 5547.1099 | N87: 6473.1968 | O87: 7227.577 | P87: 8137.7134 | Q87: 8331.3167 | R87: 8428.5787 | S87: 8606.1346 | T87: 8533.0321 | U87: 8419.5014 | V87: 8079.3078 | W87: 8941.9333 | X87: 9669.4587 | Y87: 9149.2051 | Z87: 7651.1516 | AA87: 5883.5891 | AB87: 4229.6679 | AC87: 142798.79
A88: 2028 | B88: 5 | C88: 4 | D88: Sábado | E88: 3291.1208 | F88: 2589.9389 | G88: 2143.6442 | H88: 1830.2679 | I88: 1724.0784 | J88: 1713.5981 | K88: 1992.496 | L88: 3651.7159 | M88: 5649.5222 | N88: 6924.1929 | O88: 7968.9471 | P88: 8381.5125 | Q88: 8842.1843 | R88: 8600.4844 | S88: 8108.3103 | T88: 7841.9481 | U88: 7272.907 | V88: 7252.3871 | W88: 7602.4469 | X88: 8769.3306 | Y88: 8380.9491 | Z88: 7377.9098 | AA88: 6073.4776 | AB88: 4870.6124 | AC88: 138853.98
A89: 2028 | B89: 6 | C89: 6 | D89: Festivo | E89: 3116.1069 | F89: 2510.9325 | G89: 1998.968 | H89: 1600.9677 | I89: 549.72481 | J89: 1161.0984 | K89: 1194.4583 | L89: 2380.3245 | M89: 3841.6218 | N89: 4729.5284 | O89: 5258.7587 | P89: 5774.2611 | Q89: 6360.8051 | R89: 6062.6271 | S89: 5531.0447 | T89: 4991.2765 | U89: 4685.3505 | V89: 5047.8644 | W89: 6426.613 | X89: 7563.4861 | Y89: 7280.4595 | Z89: 6161.372 | AA89: 5007.2596 | AB89: 3765.127 | AC89: 103000.04 | AD89: =+SUMPRODUCT(AC89:AC91,C89:C91) -> 3724343.2
A90: 2028 | B90: 6 | C90: 20 | D90: Hábil | E90: 2422.7867 | F90: 1857.8467 | G90: 1364.4916 | H90: 1111.2259 | I90: 1054.6553 | J90: 1487.0834 | K90: 2178.4917 | L90: 3766.3712 | M90: 5668.4753 | N90: 6444.0868 | O90: 7111.4205 | P90: 8410.7538 | Q90: 8612.6379 | R90: 8201.4973 | S90: 7981.0311 | T90: 7816.1404 | U90: 7572.1466 | V90: 7292.665 | W90: 7912.6604 | X90: 8572.1392 | Y90: 7993.3675 | Z90: 6691.7602 | AA90: 5093.7695 | AB90: 3550.402 | AC90: 130167.91
A91: 2028 | B91: 6 | C91: 4 | D91: Sábado | E91: 2939.775 | F91: 2383.095 | G91: 1793.374 | H91: 1484.0632 | I91: 1376.2257 | J91: 1550.7991 | K91: 1865.8297 | L91: 3303.6342 | M91: 5207.8008 | N91: 6125.0224 | O91: 6814.0788 | P91: 7686.4422 | Q91: 7732.6572 | R91: 7382.7262 | S91: 6944.5356 | T91: 6531.0838 | U91: 6506.4575 | V91: 6752.6276 | W91: 7769.4785 | X91: 8557.2312 | Y91: 8180.7357 | Z91: 6989.3588 | AA91: 5616.0305 | AB91: 4253.164 | AC91: 125746.23
A92: 2028 | B92: 7 | C92: 7 | D92: Festivo | E92: 2880.6741 | F92: 2276.6912 | G92: 1764.304 | H92: 1455.6446 | I92: 1314.7754 | J92: 1462.135 | K92: 1443.0581 | L92: 2735.6357 | M92: 4289.6721 | N92: 5439.2379 | O92: 6099.6313 | P92: 7136.278 | Q92: 7777.1638 | R92: 7589.4876 | S92: 6980.3237 | T92: 6604.4285 | U92: 6315.7973 | V92: 6164.5559 | W92: 7054.4836 | X92: 8281.3517 | Y92: 7752.6445 | Z92: 6478.5336 | AA92: 5016.4811 | AB92: 3593.3502 | AC92: 117906.34 | AD92: =+SUMPRODUCT(AC92:AC94,C92:C94) -> 4100617.1
A93: 2028 | B93: 7 | C93: 19 | D93: Hábil | E93: 2830.325 | F93: 2254.293 | G93: 1775.8083 | H93: 1444.7084 | I93: 1419.185 | J93: 2079.605 | K93: 2795.2114 | L93: 4062.3086 | M93: 5509.0065 | N93: 6365.9851 | O93: 7283.6702 | P93: 8213.3756 | Q93: 8257.5074 | R93: 8445.3431 | S93: 8631.6165 | T93: 7852.4761 | U93: 7560.0002 | V93: 7631.9439 | W93: 8338.6969 | X93: 9401.8731 | Y93: 8818.8504 | Z93: 7361.5297 | AA93: 5367.7226 | AB93: 3704.9156 | AC93: 137405.96
A94: 2028 | B94: 7 | C94: 5 | D94: Sábado | E94: 2212.6943 | F94: 1520.9743 | G94: 1072.3779 | H94: 733.06384 | I94: 741.15943 | J94: 930.25039 | K94: 1278.629 | L94: 2873.5519 | M94: 5006.5691 | N94: 6413.159 | O94: 7510.0127 | P94: 8494.9397 | Q94: 9069.7509 | R94: 8854.9106 | S94: 8461.8117 | T94: 8161.5703 | U94: 7844.9738 | V94: 7524.3726 | W94: 8173.5231 | X94: 9110.7533 | Y94: 8582.6699 | Z94: 7609.7306 | AA94: 6134.0148 | AB94: 4596.435 | AC94: 132911.9
A95: 2028 | B95: 8 | C95: 6 | D95: Festivo | E95: 3012.8998 | F95: 2384.6078 | G95: 1888.9147 | H95: 1589.3384 | I95: 1563.7746 | J95: 1664.8829 | K95: 1934.7884 | L95: 3238.6298 | M95: 4947.2032 | N95: 6013.0102 | O95: 6739.946 | P95: 7509.6821 | Q95: 7931.2521 | R95: 7466.6146 | S95: 6345.7229 | T95: 5970.167 | U95: 5980.3015 | V95: 5983.614 | W95: 7116.5481 | X95: 8205.9031 | Y95: 7651.7509 | Z95: 6367.1932 | AA95: 4777.9238 | AB95: 3506.3308 | AC95: 119791 | AD95: =+SUMPRODUCT(AC95:AC97,C95:C97) -> 4242356.2
A96: 2028 | B96: 8 | C96: 21 | D96: Hábil | E96: 2564.2302 | F96: 2056.25 | G96: 1664.1569 | H96: 1378.4425 | I96: 1381.6266 | J96: 2178.2252 | K96: 3116.9713 | L96: 4240.2276 | M96: 5891.6326 | N96: 6740.0637 | O96: 7694.9477 | P96: 8823.7155 | Q96: 8789.4209 | R96: 8912.4362 | S96: 9169.3853 | T96: 9086.4028 | U96: 8855.98 | V96: 8136.8807 | W96: 8613.1991 | X96: 9444.673 | Y96: 8724.7931 | Z96: 7248.6014 | AA96: 5165.5555 | AB96: 3557.7886 | AC96: 143435.61
A97: 2028 | B97: 8 | C97: 4 | D97: Sábado | E97: 1930.7563 | F97: 1778.1683 | G97: 1429.6803 | H97: 1075.4112 | I97: 1003.7584 | J97: 1177.3483 | K97: 1700.8289 | L97: 3319.7036 | M97: 5202.0666 | N97: 6362.8371 | O97: 7347.2992 | P97: 8531.988 | Q97: 8811.2505 | R97: 8481.5841 | S97: 7991.493 | T97: 7630.8367 | U97: 7231.0424 | V97: 7127.114 | W97: 8231.4714 | X97: 8502.1083 | Y97: 7728.4584 | Z97: 6437.7705 | AA97: 5048.0998 | AB97: 3784.5378 | AC97: 127865.61
A98: 2028 | B98: 9 | C98: 4 | D98: Festivo | E98: 2110.0137 | F98: 1479.83 | G98: 1001.8975 | H98: 699.39095 | I98: 564.20869 | J98: 638.52138 | K98: 845.26227 | L98: 2230.4838 | M98: 4117.1132 | N98: 4627.6864 | O98: 5231.7638 | P98: 5956.8559 | Q98: 6685.1343 | R98: 6461.8546 | S98: 6318.5779 | T98: 5682.5493 | U98: 5335.3232 | V98: 5325.588 | W98: 6885.6427 | X98: 7450.4266 | Y98: 5920.4989 | Z98: 4782.903 | AA98: 3538.0808 | AB98: 2475.5595 | AC98: 96365.167 | AD98: =+SUMPRODUCT(AC98:AC100,C98:C100) -> 3958090.5
A99: 2028 | B99: 9 | C99: 21 | D99: Hábil | E99: 2566.3606 | F99: 1987.7814 | G99: 1586.802 | H99: 1273.0565 | I99: 1208.886 | J99: 1981.9784 | K99: 2939.4826 | L99: 4164.1309 | M99: 5727.3738 | N99: 6422.8443 | O99: 7264.0128 | P99: 8534.2032 | Q99: 8645.5537 | R99: 8722.243 | S99: 8891.0078 | T99: 8814.0057 | U99: 8609.6352 | V99: 8102.4991 | W99: 8970.4843 | X99: 9561.6861 | Y99: 8953.7614 | Z99: 7554.8454 | AA99: 5667.4257 | AB99: 4001.0447 | AC99: 142151.1
A100: 2028 | B100: 9 | C100: 5 | D100: Sábado | E100: 2987.8359 | F100: 2246.4201 | G100: 1843.0415 | H100: 1448.9566 | I100: 1337.552 | J100: 1450.0963 | K100: 1965.8984 | L100: 3485.6471 | M100: 5346.4911 | N100: 6349.8693 | O100: 6674.852 | P100: 7540.2421 | Q100: 6110.0136 | R100: 7188.852 | S100: 6628.2368 | T100: 6332.0247 | U100: 5982.4724 | V100: 6121.4943 | W100: 7489.8006 | X100: 7821.4753 | Y100: 7217.6657 | Z100: 6145.6448 | AA100: 4527.3805 | AB100: 3249.3716 | AC100: 117491.33
...

Sheet Producto No. 3 Curva 2026-2035
A5: ANEXO No. 1. Oferta Producto No. 3 Curva (junio de 2026 a diciembre año 2035) Convocatoria Pública DISPAC S.A. E.S.P.
A8: PROPONENTE
A10: MES | B10: DEMANDA REQUERIDA DISPAC KWh | C10: DEMANDA PERIODO REQUERIDA DISPAC KWh | D10: PORCENTAJE (%) OFERTADO DE LA DEMANDA REQUERIDA | E10: DEMANDA OFERTADA KWh - MES | F10: DEMANDA PERIODO OFERTADA KWh | G10: PRECIO OFERTADO $ kWh (0.00)
A11: JUNIO DE 2026 | B11: =+'Despacho Horario Producto No. 3'!AB2 -> 1752241.1 | C11: =+SUM(B11:B17) -> 12562647 | E11: =+$D$11*B11 -> 0 | F11: =+SUM(E11:E17) -> 0
A12: JULIO DE 2026 | B12: =+'Despacho Horario Producto No. 3'!AB3 -> 1816398 | E12: =+$D$11*B12 -> 0
A13: AGOSTO DE 2026 | B13: =+'Despacho Horario Producto No. 3'!AB4 -> 1814297 | E13: =+$D$11*B13 -> 0
A14: SEPTIEMBRE DE 2026 | B14: =+'Despacho Horario Producto No. 3'!AB5 -> 1770367.8 | E14: =+$D$11*B14 -> 0
A15: OCTUBRE DE 2026 | B15: =+'Despacho Horario Producto No. 3'!AB6 -> 1808727.3 | E15: =+$D$11*B15 -> 0
A16: NOVIEMBRE DE 2026 | B16: =+'Despacho Horario Producto No. 3'!AB7 -> 1754745.6 | E16: =+$D$11*B16 -> 0
A17: DICIEMBRE DE 2026 | B17: =+'Despacho Horario Producto No. 3'!AB8 -> 1845870.6 | E17: =+$D$11*B17 -> 0
A18: ENERO DE 2027 | B18: =+'Despacho Horario Producto No. 3'!AB9 -> 1864971.9 | C18: =SUM(B18:B29) -> 21906724 | E18: =+$D$18*B18 -> 0 | F18: =SUM(E18:E29) -> 0
A19: FEBRERO DE 2027 | B19: =+'Despacho Horario Producto No. 3'!AB10 -> 1697293.2 | E19: =+$D$18*B19 -> 0
A20: MARZO DE 2027 | B20: =+'Despacho Horario Producto No. 3'!AB11 -> 1860913.9 | E20: =+$D$18*B20 -> 0
A21: ABRIL DE 2027 | B21: =+'Despacho Horario Producto No. 3'!AB12 -> 1798120.2 | E21: =+$D$18*B21 -> 0
A22: MAYO DE 2027 | B22: =+'Despacho Horario Producto No. 3'!AB13 -> 1861354 | E22: =+$D$18*B22 -> 0
A23: JUNIO DE 2027 | B23: =+'Despacho Horario Producto No. 3'!AB14 -> 1789118.5 | E23: =+$D$18*B23 -> 0
A24: JULIO DE 2027 | B24: =+'Despacho Horario Producto No. 3'!AB15 -> 1854369.5 | E24: =+$D$18*B24 -> 0
A25: AGOSTO DE 2027 | B25: =+'Despacho Horario Producto No. 3'!AB16 -> 1852159.3 | E25: =+$D$18*B25 -> 0
A26: SEPTIEMBRE DE 2027 | B26: =+'Despacho Horario Producto No. 3'!AB17 -> 1806857.2 | E26: =+$D$18*B26 -> 0
A27: OCTUBRE DE 2027 | B27: =+'Despacho Horario Producto No. 3'!AB18 -> 1846490.7 | E27: =+$D$18*B27 -> 0
A28: NOVIEMBRE DE 2027 | B28: =+'Despacho Horario Producto No. 3'!AB19 -> 1791306.1 | E28: =+$D$18*B28 -> 0
A29: DICIEMBRE DE 2027 | B29: =+'Despacho Horario Producto No. 3'!AB20 -> 1883769.6 | E29: =+$D$18*B29 -> 0
A30: ENERO DE 2028 | B30: =+'Despacho Horario Producto No. 3'!AB21 -> 1902739.3 | C30: =SUM(B30:B41) -> 22413439 | E30: =+$D$30*B30 -> 0 | F30: =SUM(E30:E41) -> 0
A31: FEBRERO DE 2028 | B31: =+'Despacho Horario Producto No. 3'!AB22 -> 1793344.4 | E31: =+$D$30*B31 -> 0
A32: MARZO DE 2028 | B32: =+'Despacho Horario Producto No. 3'!AB23 -> 1898745.8 | E32: =+$D$30*B32 -> 0
A33: ABRIL DE 2028 | B33: =+'Despacho Horario Producto No. 3'!AB24 -> 1834698.4 | E33: =+$D$30*B33 -> 0
A34: MAYO DE 2028 | B34: =+'Despacho Horario Producto No. 3'!AB25 -> 1899138.2 | E34: =+$D$30*B34 -> 0
A35: JUNIO DE 2028 | B35: =+'Despacho Horario Producto No. 3'!AB26 -> 1825676.8 | E35: =+$D$30*B35 -> 0
A36: JULIO DE 2028 | B36: =+'Despacho Horario Producto No. 3'!AB27 -> 1892139.7 | E36: =+$D$30*B36 -> 0
A37: AGOSTO DE 2028 | B37: =+'Despacho Horario Producto No. 3'!AB28 -> 1889924.1 | E37: =+$D$30*B37 -> 0
A38: SEPTIEMBRE DE 2028 | B38: =+'Despacho Horario Producto No. 3'!AB29 -> 1843396.4 | E38: =+$D$30*B38 -> 0
A39: OCTUBRE DE 2028 | B39: =+'Despacho Horario Producto No. 3'!AB30 -> 1884250.7 | E39: =+$D$30*B39 -> 0
A40: NOVIEMBRE DE 2028 | B40: =+'Despacho Horario Producto No. 3'!AB31 -> 1827848.7 | E40: =+$D$30*B40 -> 0
A41: DICIEMBRE DE 2028 | B41: =+'Despacho Horario Producto No. 3'!AB32 -> 1921536.3 | E41: =+$D$30*B41 -> 0
A42: ENERO DE 2029 | B42: =+'Despacho Horario Producto No. 3'!AB33 -> 1940499.5 | C42: =SUM(B42:B53) -> 22796204 | E42: =+$D$42*B42 -> 0 | F42: =SUM(E42:E53) -> 0
A43: FEBRERO DE 2029 | B43: =+'Despacho Horario Producto No. 3'!AB34 -> 1765615.8 | E43: =+$D$42*B43 -> 0
A44: MARZO DE 2029 | B44: =+'Despacho Horario Producto No. 3'!AB35 -> 1936509.1 | E44: =+$D$42*B44 -> 0
A45: ABRIL DE 2029 | B45: =+'Despacho Horario Producto No. 3'!AB36 -> 1871241.9 | E45: =+$D$42*B45 -> 0
A46: MAYO DE 2029 | B46: =+'Despacho Horario Producto No. 3'!AB37 -> 1936899.2 | E46: =+$D$42*B46 -> 0
A47: JUNIO DE 2029 | B47: =+'Despacho Horario Producto No. 3'!AB38 -> 1862219.3 | E47: =+$D$42*B47 -> 0
A48: JULIO DE 2029 | B48: =+'Despacho Horario Producto No. 3'!AB39 -> 1929899.9 | E48: =+$D$42*B48 -> 0
A49: AGOSTO DE 2029 | B49: =+'Despacho Horario Producto No. 3'!AB40 -> 1927684.2 | E49: =+$D$42*B49 -> 0
A50: SEPTIEMBRE DE 2029 | B50: =+'Despacho Horario Producto No. 3'!AB41 -> 1879938 | E50: =+$D$42*B50 -> 0
A51: OCTUBRE DE 2029 | B51: =+'Despacho Horario Producto No. 3'!AB42 -> 1922010.5 | E51: =+$D$42*B51 -> 0
A52: NOVIEMBRE DE 2029 | B52: =+'Despacho Horario Producto No. 3'!AB43 -> 1864390.5 | E52: =+$D$42*B52 -> 0
A53: DICIEMBRE DE 2029 | B53: =+'Despacho Horario Producto No. 3'!AB44 -> 1959296.4 | E53: =+$D$42*B53 -> 0
A54: ENERO DE 2030 | B54: =+'Despacho Horario Producto No. 3'!AB45 -> 1978259.3 | C54: =SUM(B54:B65) -> 23240796 | E54: =+$D$54*B54 -> 0 | F54: =SUM(E54:E65) -> 0
A55: FEBRERO DE 2030 | B55: =+'Despacho Horario Producto No. 3'!AB46 -> 1799721.6 | E55: =+$D$54*B55 -> 0
A56: MARZO DE 2030 | B56: =+'Despacho Horario Producto No. 3'!AB47 -> 1974269.1 | E56: =+$D$54*B56 -> 0
A57: ABRIL DE 2030 | B57: =+'Despacho Horario Producto No. 3'!AB48 -> 1907783.7 | E57: =+$D$54*B57 -> 0
A58: MAYO DE 2030 | B58: =+'Despacho Horario Producto No. 3'!AB49 -> 1974659 | E58: =+$D$54*B58 -> 0
A59: JUNIO DE 2030 | B59: =+'Despacho Horario Producto No. 3'!AB50 -> 1898761 | E59: =+$D$54*B59 -> 0
A60: JULIO DE 2030 | B60: =+'Despacho Horario Producto No. 3'!AB51 -> 1967659.7 | E60: =+$D$54*B60 -> 0
A61: AGOSTO DE 2030 | B61: =+'Despacho Horario Producto No. 3'!AB52 -> 1965444 | E61: =+$D$54*B61 -> 0
A62: SEPTIEMBRE DE 2030 | B62: =+'Despacho Horario Producto No. 3'!AB53 -> 1916479.7 | E62: =+$D$54*B62 -> 0
A63: OCTUBRE DE 2030 | B63: =+'Despacho Horario Producto No. 3'!AB54 -> 1959770.3 | E63: =+$D$54*B63 -> 0
A64: NOVIEMBRE DE 2030 | B64: =+'Despacho Horario Producto No. 3'!AB55 -> 1900932.2 | E64: =+$D$54*B64 -> 0
A65: DICIEMBRE DE 2030 | B65: =+'Despacho Horario Producto No. 3'!AB56 -> 1997056.2 | E65: =+$D$54*B65 -> 0
A66: ENERO DE 2031 | B66: =+'Despacho Horario Producto No. 3'!AB57 -> 2016019 | C66: =SUM(B66:B77) -> 23685387 | E66: =+$D$66*B66 -> 0 | F66: =SUM(E66:E77) -> 0
A67: FEBRERO DE 2031 | B67: =+'Despacho Horario Producto No. 3'!AB58 -> 1833827.3 | E67: =+$D$66*B67 -> 0
A68: MARZO DE 2031 | B68: =+'Despacho Horario Producto No. 3'!AB59 -> 2012028.8 | E68: =+$D$66*B68 -> 0
A69: ABRIL DE 2031 | B69: =+'Despacho Horario Producto No. 3'!AB60 -> 1944325.4 | E69: =+$D$66*B69 -> 0
A70: MAYO DE 2031 | B70: =+'Despacho Horario Producto No. 3'!AB61 -> 2012418.8 | E70: =+$D$66*B70 -> 0
A71: JUNIO DE 2031 | B71: =+'Despacho Horario Producto No. 3'!AB62 -> 1935302.8 | E71: =+$D$66*B71 -> 0
A72: JULIO DE 2031 | B72: =+'Despacho Horario Producto No. 3'!AB63 -> 2005419.5 | E72: =+$D$66*B72 -> 0
A73: AGOSTO DE 2031 | B73: =+'Despacho Horario Producto No. 3'!AB64 -> 2003203.7 | E73: =+$D$66*B73 -> 0
A74: SEPTIEMBRE DE 2031 | B74: =+'Despacho Horario Producto No. 3'!AB65 -> 1953021.4 | E74: =+$D$66*B74 -> 0
A75: OCTUBRE DE 2031 | B75: =+'Despacho Horario Producto No. 3'!AB66 -> 1997530 | E75: =+$D$66*B75 -> 0
A76: NOVIEMBRE DE 2031 | B76: =+'Despacho Horario Producto No. 3'!AB67 -> 1937473.9 | E76: =+$D$66*B76 -> 0
A77: DICIEMBRE DE 2031 | B77: =+'Despacho Horario Producto No. 3'!AB68 -> 2034815.9 | E77: =+$D$66*B77 -> 0
A78: ENERO DE 2032 | B78: =+'Despacho Horario Producto No. 3'!AB69 -> 2053778.8 | C78: =SUM(B78:B89) -> 24196689 | E78: =+$D$78*B78 -> 0 | F78: =SUM(E78:E89) -> 0
A79: FEBRERO DE 2032 | B79: =+'Despacho Horario Producto No. 3'!AB70 -> 1934644.8 | E79: =+$D$78*B79 -> 0
A80: MARZO DE 2032 | B80: =+'Despacho Horario Producto No. 3'!AB71 -> 2049788.6 | E80: =+$D$78*B80 -> 0
A81: ABRIL DE 2032 | B81: =+'Despacho Horario Producto No. 3'!AB72 -> 1980867.2 | E81: =+$D$78*B81 -> 0
A82: MAYO DE 2032 | B82: =+'Despacho Horario Producto No. 3'!AB73 -> 2050178.5 | E82: =+$D$78*B82 -> 0
A83: JUNIO DE 2032 | B83: =+'Despacho Horario Producto No. 3'!AB74 -> 1971844.5 | E83: =+$D$78*B83 -> 0
A84: JULIO DE 2032 | B84: =+'Despacho Horario Producto No. 3'!AB75 -> 2043179.3 | E84: =+$D$78*B84 -> 0
A85: AGOSTO DE 2032 | B85: =+'Despacho Horario Producto No. 3'!AB76 -> 2040963.5 | E85: =+$D$78*B85 -> 0
A86: SEPTIEMBRE DE 2032 | B86: =+'Despacho Horario Producto No. 3'!AB77 -> 1989563.1 | E86: =+$D$78*B86 -> 0
A87: OCTUBRE DE 2032 | B87: =+'Despacho Horario Producto No. 3'!AB78 -> 2035289.8 | E87: =+$D$78*B87 -> 0
A88: NOVIEMBRE DE 2032 | B88: =+'Despacho Horario Producto No. 3'!AB79 -> 1974015.6 | E88: =+$D$78*B88 -> 0
A89: DICIEMBRE DE 2032 | B89: =+'Despacho Horario Producto No. 3'!AB80 -> 2072575.7 | E89: =+$D$78*B89 -> 0
A90: ENERO DE 2033 | B90: =+'Despacho Horario Producto No. 3'!AB81 -> 2091538.6 | C90: =SUM(B90:B101) -> 24574568 | E90: =+$D$90*B90 -> 0 | F90: =SUM(E90:E101) -> 0
A91: FEBRERO DE 2033 | B91: =+'Despacho Horario Producto No. 3'!AB82 -> 1902038.5 | E91: =+$D$90*B91 -> 0
A92: MARZO DE 2033 | B92: =+'Despacho Horario Producto No. 3'!AB83 -> 2087548.4 | E92: =+$D$90*B92 -> 0
A93: ABRIL DE 2033 | B93: =+'Despacho Horario Producto No. 3'!AB84 -> 2017408.9 | E93: =+$D$90*B93 -> 0
A94: MAYO DE 2033 | B94: =+'Despacho Horario Producto No. 3'!AB85 -> 2087938.3 | E94: =+$D$90*B94 -> 0
A95: JUNIO DE 2033 | B95: =+'Despacho Horario Producto No. 3'!AB86 -> 2008386.2 | E95: =+$D$90*B95 -> 0
A96: JULIO DE 2033 | B96: =+'Despacho Horario Producto No. 3'!AB87 -> 2080939.1 | E96: =+$D$90*B96 -> 0
A97: AGOSTO DE 2033 | B97: =+'Despacho Horario Producto No. 3'!AB88 -> 2078723.3 | E97: =+$D$90*B97 -> 0
A98: SEPTIEMBRE DE 2033 | B98: =+'Despacho Horario Producto No. 3'!AB89 -> 2026104.8 | E98: =+$D$90*B98 -> 0
A99: OCTUBRE DE 2033 | B99: =+'Despacho Horario Producto No. 3'!AB90 -> 2073049.6 | E99: =+$D$90*B99 -> 0
A100: NOVIEMBRE DE 2033 | B100: =+'Despacho Horario Producto No. 3'!AB91 -> 2010557.4 | E100: =+$D$90*B100 -> 0
A101: DICIEMBRE DE 2033 | B101: =+'Despacho Horario Producto No. 3'!AB92 -> 2110335.5 | E101: =+$D$90*B101 -> 0
A102: ENERO DE 2034 | B102: =+'Despacho Horario Producto No. 3'!AB93 -> 2129298.4 | C102: =SUM(B102:B113) -> 25019159 | E102: =+$D$102*B102 -> 0 | F102: =SUM(E102:E113) -> 0
A103: FEBRERO DE 2034 | B103: =+'Despacho Horario Producto No. 3'!AB94 -> 1936144.1 | E103: =+$D$102*B103 -> 0
A104: MARZO DE 2034 | B104: =+'Despacho Horario Producto No. 3'!AB95 -> 2125308.2 | E104: =+$D$102*B104 -> 0
A105: ABRIL DE 2034 | B105: =+'Despacho Horario Producto No. 3'!AB96 -> 2053950.6 | E105: =+$D$102*B105 -> 0
A106: MAYO DE 2034 | B106: =+'Despacho Horario Producto No. 3'!AB97 -> 2125698.1 | E106: =+$D$102*B106 -> 0
A107: JUNIO DE 2034 | B107: =+'Despacho Horario Producto No. 3'!AB98 -> 2044927.9 | E107: =+$D$102*B107 -> 0
...

Sheet Despacho Horario Producto No. 3
A1: Año | B1: Mes | C1: Total Mes | D1: H1 | E1: H2 | F1: H3 | G1: H4 | H1: H5 | I1: H6 | J1: H7 | K1: H8 | L1: H9 | M1: H10 | N1: H11 | O1: H12 | P1: H13 | Q1: H14 | R1: H15 | S1: H16 | T1: H17 | U1: H18 | V1: H19 | W1: H20 | X1: H21 | Y1: H22 | Z1: H23 | AA1: H24 | AB1: kWh/mes
A2: =+YEAR(B2) -> 2026 | B2: 46174 | C2: 1752241.1 | D2: 0 | E2: 0 | F2: 0 | G2: 0 | H2: 0 | I2: 1.3751514 | J2: 221.84282 | K2: 2256.6262 | L2: 4960.2043 | M2: 6407.6538 | N2: 7181.2815 | O2: 7378.0394 | P2: 7318.0573 | Q2: 6945.3204 | R2: 6408.609 | S2: 5441.9307 | T2: 3261.8619 | U2: 624.5931 | V2: 0.64062085 | W2: 0 | X2: 0 | Y2: 0 | Z2: 0 | AA2: 0 | AB2: =SUM(D2:AA2)*_xlfn.DAYS(B3,B2) -> 1752241.1
A3: =+YEAR(B3) -> 2026 | B3: 46204 | C3: 1816398 | D3: 0 | E3: 0 | F3: 0 | G3: 0 | H3: 0 | I3: 1.3795176 | J3: 222.54718 | K3: 2263.7911 | L3: 4975.9532 | M3: 6427.9984 | N3: 7204.0824 | O3: 7401.465 | P3: 7341.2926 | Q3: 6967.3721 | R3: 6428.9567 | S3: 5459.2091 | T3: 3272.2185 | U3: 626.57622 | V3: 0.64265485 | W3: 0 | X3: 0 | Y3: 0 | Z3: 0 | AA3: 0 | AB3: =SUM(D3:AA3)*_xlfn.DAYS(B4,B3) -> 1816398
A4: =+YEAR(B4) -> 2026 | B4: 46235 | C4: 1814297 | D4: 0 | E4: 0 | F4: 0 | G4: 0 | H4: 0 | I4: 1.3779219 | J4: 222.28975 | K4: 2261.1725 | L4: 4970.1975 | M4: 6420.563 | N4: 7195.7493 | O4: 7392.9036 | P4: 7332.8007 | Q4: 6959.3128 | R4: 6421.5202 | S4: 5452.8943 | T4: 3268.4335 | U4: 625.85144 | V4: 0.64191148 | W4: 0 | X4: 0 | Y4: 0 | Z4: 0 | AA4: 0 | AB4: =SUM(D4:AA4)*_xlfn.DAYS(B5,B4) -> 1814297
A5: =+YEAR(B5) -> 2026 | B5: 46266 | C5: 1770367.8 | D5: 0 | E5: 0 | F5: 0 | G5: 0 | H5: 0 | I5: 1.3893772 | J5: 224.13775 | K5: 2279.9706 | L5: 5011.5169 | M5: 6473.94 | N5: 7255.5708 | O5: 7454.3641 | P5: 7393.7616 | Q5: 7017.1687 | R5: 6474.9052 | S5: 5498.2267 | T5: 3295.6054 | U5: 631.05443 | V5: 0.64724798 | W5: 0 | X5: 0 | Y5: 0 | Z5: 0 | AA5: 0 | AB5: =SUM(D5:AA5)*_xlfn.DAYS(B6,B5) -> 1770367.8
A6: =+YEAR(B6) -> 2026 | B6: 46296 | C6: 1808727.3 | D6: 0 | E6: 0 | F6: 0 | G6: 0 | H6: 0 | I6: 1.3736918 | J6: 221.60735 | K6: 2254.231 | L6: 4954.9395 | M6: 6400.8526 | N6: 7173.6592 | O6: 7370.2083 | P6: 7310.2899 | Q6: 6937.9486 | R6: 6401.8069 | S6: 5436.1546 | T6: 3258.3998 | U6: 623.93015 | V6: 0.63994089 | W6: 0 | X6: 0 | Y6: 0 | Z6: 0 | AA6: 0 | AB6: =SUM(D6:AA6)*_xlfn.DAYS(B7,B6) -> 1808727.3
A7: =+YEAR(B7) -> 2026 | B7: 46327 | C7: 1754745.6 | D7: 0 | E7: 0 | F7: 0 | G7: 0 | H7: 0 | I7: 1.377117 | J7: 222.1599 | K7: 2259.8516 | L7: 4967.2941 | M7: 6416.8124 | N7: 7191.5458 | O7: 7388.585 | P7: 7328.5172 | Q7: 6955.2475 | R7: 6417.769 | S7: 5449.709 | T7: 3266.5242 | U7: 625.48584 | V7: 0.6415365 | W7: 0 | X7: 0 | Y7: 0 | Z7: 0 | AA7: 0 | AB7: =SUM(D7:AA7)*_xlfn.DAYS(B8,B7) -> 1754745.6
A8: =+YEAR(B8) -> 2026 | B8: 46357 | C8: 1845870.6 | D8: 0 | E8: 0 | F8: 0 | G8: 0 | H8: 0 | I8: 1.4019014 | J8: 226.15819 | K8: 2300.5229 | L8: 5056.6922 | M8: 6532.2979 | N8: 7320.9745 | O8: 7521.5599 | P8: 7460.411 | Q8: 7080.4235 | R8: 6533.2718 | S8: 5547.7893 | T8: 3325.3129 | U8: 636.74293 | V8: 0.65308245 | W8: 0 | X8: 0 | Y8: 0 | Z8: 0 | AA8: 0 | AB8: =SUM(D8:AA8)*_xlfn.DAYS(B9,B8) -> 1845870.6
A9: =+YEAR(B9) -> 2027 | B9: 46388 | C9: 1864971.9 | D9: 0 | E9: 0 | F9: 0 | G9: 0 | H9: 0 | I9: 1.4164085 | J9: 228.49851 | K9: 2324.3291 | L9: 5109.0195 | M9: 6599.8951 | N9: 7396.7331 | O9: 7599.3941 | P9: 7537.6125 | Q9: 7153.6927 | R9: 6600.879 | S9: 5605.1986 | T9: 3359.7238 | U9: 643.33204 | V9: 0.65984065 | W9: 0 | X9: 0 | Y9: 0 | Z9: 0 | AA9: 0 | AB9: =SUM(D9:AA9)*_xlfn.DAYS(B10,B9) -> 1864971.9
A10: =+YEAR(B10) -> 2027 | B10: 46419 | C10: 1697293.2 | D10: 0 | E10: 0 | F10: 0 | G10: 0 | H10: 0 | I10: 1.4271735 | J10: 230.23514 | K10: 2341.9944 | L10: 5147.8491 | M10: 6650.0556 | N10: 7452.9497 | O10: 7657.1509 | P10: 7594.8998 | Q10: 7208.0622 | R10: 6651.047 | S10: 5647.7992 | T10: 3385.2583 | U10: 648.22148 | V10: 0.66485556 | W10: 0 | X10: 0 | Y10: 0 | Z10: 0 | AA10: 0 | AB10: =SUM(D10:AA10)*_xlfn.DAYS(B11,B10) -> 1697293.2
A11: =+YEAR(B11) -> 2027 | B11: 46447 | C11: 1860913.9 | D11: 0 | E11: 0 | F11: 0 | G11: 0 | H11: 0 | I11: 1.4133265 | J11: 228.00131 | K11: 2319.2716 | L11: 5097.9028 | M11: 6585.5344 | N11: 7380.6385 | O11: 7582.8585 | P11: 7521.2113 | Q11: 7138.127 | R11: 6586.5161 | S11: 5593.0022 | T11: 3352.4133 | U11: 641.93221 | V11: 0.6584049 | W11: 0 | X11: 0 | Y11: 0 | Z11: 0 | AA11: 0 | AB11: =SUM(D11:AA11)*_xlfn.DAYS(B12,B11) -> 1860913.9
A12: =+YEAR(B12) -> 2027 | B12: 46478 | C12: 1798120.2 | D12: 0 | E12: 0 | F12: 0 | G12: 0 | H12: 0 | I12: 1.4111571 | J12: 227.65134 | K12: 2315.7116 | L12: 5090.0778 | M12: 6575.4259 | N12: 7369.3095 | O12: 7571.2192 | P12: 7509.6666 | Q12: 7127.1703 | R12: 6576.4061 | S12: 5584.4172 | T12: 3347.2675 | U12: 640.94687 | V12: 0.65739427 | W12: 0 | X12: 0 | Y12: 0 | Z12: 0 | AA12: 0 | AB12: =SUM(D12:AA12)*_xlfn.DAYS(B13,B12) -> 1798120.2
A13: =+YEAR(B13) -> 2027 | B13: 46508 | C13: 1861354 | D13: 0 | E13: 0 | F13: 0 | G13: 0 | H13: 0 | I13: 1.4136608 | J13: 228.05524 | K13: 2319.8201 | L13: 5099.1085 | M13: 6587.0919 | N13: 7382.384 | O13: 7584.6519 | P13: 7522.9901 | Q13: 7139.8152 | R13: 6588.0739 | S13: 5594.325 | T13: 3353.2062 | U13: 642.08403 | V13: 0.65856061 | W13: 0 | X13: 0 | Y13: 0 | Z13: 0 | AA13: 0 | AB13: =SUM(D13:AA13)*_xlfn.DAYS(B14,B13) -> 1861354
... A116: =+YEAR(B116) -> 2035 | B116: 49644 | C116: 2185855 | D116: 0 | E116: 0 | F116: 0 | G116: 0 | H116: 0 | I116: 1.6601127 | J116: 267.81348 | K116: 2724.2482 | L116: 5988.0667 | M116: 7735.4591 | N116: 8669.3994 | O116: 8906.9298 | P116: 8834.5182 | Q116: 8384.542 | R116: 7736.6124 | S116: 6569.6173 | T116: 3937.7908 | U116: 754.02239 | V116: 0.77337144 | W116: 0 | X116: 0 | Y116: 0 | Z116: 0 | AA116: 0 | AB116: =SUM(D116:AA116)*_xlfn.DAYS(B117,B116) -> 2185855
B117: 49675 | C117: =+SUM(C2:C116) -> 2.2585936e+08 | AB117: =+SUM(AB2:AB116) -> 2.2585936e+08
